Workbook
Name APT_CONTR: '06. APONTAMENTO DIÁRIO'!$D$5:$D$504
Name APT_DATA: '06. APONTAMENTO DIÁRIO'!$A$5:$A$504
Name APT_EQUIPE: '06. APONTAMENTO DIÁRIO'!$E$5:$E$504
Name APT_HH: '06. APONTAMENTO DIÁRIO'!$I$5:$I$504
Name APT_KM: '06. APONTAMENTO DIÁRIO'!$P$5:$P$504
Name APT_PARADA: '06. APONTAMENTO DIÁRIO'!$AA$5:$AA$504
Name APT_PESSOAS: '06. APONTAMENTO DIÁRIO'!$F$5:$F$504
Name APT_RETRO: '06. APONTAMENTO DIÁRIO'!$J$5:$J$504
Name ATA_CONTR: '15. ATAS DE REUNIÃO'!$E$5:$E$204
Name ATA_DATA: '15. ATAS DE REUNIÃO'!$B$5:$B$304
Name ATA_NUM: '15. ATAS DE REUNIÃO'!$A$5:$A$304
Name ATA_PEND: '15. ATAS DE REUNIÃO'!$L$5:$L$304
Name ATA_PRAZO: '15. ATAS DE REUNIÃO'!$N$5:$N$304
Name ATA_PRIO: '15. ATAS DE REUNIÃO'!$O$5:$O$304
Name ATA_RESP: '15. ATAS DE REUNIÃO'!$M$5:$M$304
Name ATA_STATUS: '15. ATAS DE REUNIÃO'!$P$5:$P$304
Name ATA_TIPO: '15. ATAS DE REUNIÃO'!$D$5:$D$204
Name BEN_PESSOA: '01A. BANCO DE CUSTOS'!$C$35
Name CAD_BAIRRO: '03. CADASTRO DE SERVIÇOS'!$K$5:$K$604
Name CAD_CONTR: '03. CADASTRO DE SERVIÇOS'!$B$5:$B$604
Name CAD_DTEXEC: '03. CADASTRO DE SERVIÇOS'!$R$5:$R$604
Name CAD_DTSOL: '03. CADASTRO DE SERVIÇOS'!$D$5:$D$604
Name CAD_ID: '03. CADASTRO DE SERVIÇOS'!$A$5:$A$604
Name CAD_SITPZ: '03. CADASTRO DE SERVIÇOS'!$U$5:$U$604
Name CAD_STATUS: '03. CADASTRO DE SERVIÇOS'!$S$5:$S$604
Name CAD_TAB: '03. CADASTRO DE SERVIÇOS'!$A$5:$X$604
Name CAD_TIPO: '03. CADASTRO DE SERVIÇOS'!$H$5:$H$604
Name CAD_VLR: '03. CADASTRO DE SERVIÇOS'!$V$5:$V$604
Name ENC_FATOR: '01A. BANCO DE CUSTOS'!$C$34
Name EQP_ATIVO: '08. EQUIPE'!$U$5:$U$60
Name EQP_CONTR: '08. EQUIPE'!$B$5:$B$60
Name EQP_CUSTOMES: '08. EQUIPE'!$J$5:$J$60
Name EQP_EQUIPE: '08. EQUIPE'!$C$5:$C$60
Name EQP_NOMES: '08. EQUIPE'!$D$5:$D$60
Name FAT_BRUTO: '12. FATURAMENTO'!$C$5:$C$52
Name FAT_CONTR: '12. FATURAMENTO'!$B$5:$B$52
Name FAT_MES: '12. FATURAMENTO'!$A$5:$A$52
Name FAT_RESULT: '12. FATURAMENTO'!$R$5:$R$52
Name LK_ID: '16. LOOKAHEAD E RESTRIÇÕES'!$C$5:$C$404
Name LK_PEND: '16. LOOKAHEAD E RESTRIÇÕES'!$M$5:$M$404
Name LK_SEM: '16. LOOKAHEAD E RESTRIÇÕES'!$A$5:$A$404
Name LK_SIT: '16. LOOKAHEAD E RESTRIÇÕES'!$N$5:$N$404
Name LST_BAIRRO: '01. CONFIGURAÇÕES'!$M$44:$M$85
Name LST_CAUSA_NC: '01. CONFIGURAÇÕES'!$Z$44:$Z$70
Name LST_CLIMA: '01. CONFIGURAÇÕES'!$T$44:$T$60
Name LST_CONTRATO: '01. CONFIGURAÇÕES'!$A$44:$A$57
Name LST_DIA: '01. CONFIGURAÇÕES'!$Y$44:$Y$61
Name LST_EQUIPAMENTO: '01. CONFIGURAÇÕES'!$O$44:$O$69
Name LST_EQUIPE: '01. CONFIGURAÇÕES'!$B$44:$B$65
Name LST_FUNCAO: '01. CONFIGURAÇÕES'!$N$44:$N$68
Name LST_GRAVIDADE: '01. CONFIGURAÇÕES'!$W$44:$W$59
Name LST_MATERIAL: '01. CONFIGURAÇÕES'!$P$44:$P$84
Name LST_MOTIVO_NE: '01. CONFIGURAÇÕES'!$J$44:$J$70
Name LST_MOTIVO_PARADA: '01. CONFIGURAÇÕES'!$K$44:$K$65
Name LST_MOVIMENTO: '01. CONFIGURAÇÕES'!$Q$44:$Q$60
Name LST_PAVIMENTO: '01. CONFIGURAÇÕES'!$L$44:$L$62
Name LST_PRIORIDADE: '01. CONFIGURAÇÕES'!$C$44:$C$59
Name LST_RESTRICAO: '01. CONFIGURAÇÕES'!$AA$44:$AA$70
Name LST_SN: '01. CONFIGURAÇÕES'!$R$44:$R$57
Name LST_SNP: '01. CONFIGURAÇÕES'!$S$44:$S$59

Sheet GUIA RÁPIDO
B1: GUIA RÁPIDO — COMO PREENCHER CADA ABA
B2: A esteira: 03 CADASTRO > 04 PROGRAMAÇÃO > 05 ORDENS DE SERVIÇO > 09 MEDIÇÃO > 12 FATURAMENTO. O resto é apoio e registro.
B4: 00. LEIA-ME
B5: Aqui não se digita NADA. É só leitura.
B6: É o manual do arquivo.
B7: Esqueceu como preenche alguma aba?
B8: Lê a caixa amarela no canto de cada aba.
B10: 01. CONFIGURAÇÕES
B11: Mexe uma vez, no começo. Não é do dia a dia.
B12: C5 a C11 = nomes: empresa, responsável, os 2 contratos
B13: C12 = dia em que a operação começou
B14: C13 = mês que você quer ver nos relatórios
... B305: K da aba 04 nunca foi preenchida.

Sheet 00. LEIA-ME
A1: CONTROLE OPERACIONAL E FINANCEIRO — CONTRATO GLOBAL SABESP · WCR SANEAMENTO | H1: COMO PREENCHER ESTA ABA
A2: Bertioga / Guarujá e Santos · versão 2.0 · setembro de 2026 · leia o bloco A e o bloco C — o resto é consulta | H2: Aqui não se digita NADA. É só leitura.
H3: É o manual do arquivo.
B4: A · COMECE POR AQUI — EM UM MINUTO | H4: Esqueceu como preenche alguma aba?
B5: O que é isto | C5: Um controle que liga o chamado da SABESP ao dinheiro na conta. Uma linha por serviço, do cadastro até a nota fiscal paga. Nada é digitado duas vezes: o ID amarra tudo. | H5: Lê a caixa amarela no canto de cada aba.
B6: O que você digita | C6: Só o AZUL e os filtros AMARELOS. São 8 abas de digitação (03 a 12) e 3 de implantação (01, 01A, 01B). As outras se calculam sozinhas.
B7: O que ela faz sozinha | C7: ID do serviço, data-limite, status, aderência, homem-hora, custo da equipe, valor da OS, medição, imposto, previsão de recebimento, resultado, margem e todos os gráficos.
B8: A rota mínima do dia | C8: 03 CADASTRO → 04 PROGRAMAÇÃO → (campo) → 06 APONTAMENTO → 05 ORDENS DE SERVIÇO → 09 MEDIÇÃO. Fazendo só isso, o resumo, o faturamento e o dashboard aparecem prontos.
B9: A única regra | C9: Não digite em cima de célula PRETA ou VERDE e não apague linha. Fórmula apagada não volta sozinha — e ninguém percebe até o fechamento.
B11: B · CONVENÇÃO DE CORES — VALE PARA A PLANILHA INTEIRA
B12: AZUL | C12: Você digita. É campo de entrada.
B13: PRETO | C13: Fórmula da própria aba. Não apague.
B14: VERDE | C14: Vem de outra aba pelo ID. Não digite por cima.
B15: AMARELO | C15: Filtro ou parâmetro. Muda o que a aba mostra ou calcula.
B16: Na dúvida | C16: Clique na célula e olhe a barra de fórmulas. Se começar com "=", ela não é sua.
B18: C · MAPA DE PREENCHIMENTO — COLUNA POR COLUNA, ABA POR ABA
B19: ABA | C19: O QUE VOCÊ DIGITA — SÓ AS CÉLULAS AZUIS | D19: O QUE APARECE SOZINHO | E19: QUEM · QUANDO
B20: 01. CONFIGURAÇÕES | C20: C5 a C13 nomes, contratos e datas · C17 desconto do consórcio · C18 dia de fechamento · C19 defasagem do recebimento · C20 dias úteis · C21 jornada · C22 prazo padrão SABESP · C23 alerta de prazo · C33 margem-alvo | D20: Todas as listas suspensas que o sistema inteiro usa (contrato, equipe, tipo, bairro, pavimento, motivo, material, função). | E20: Gestão · implantação e reajuste
B21: 01A. BANCO DE CUSTOS | C21: Quantidade e valor unitário de cada item de estrutura (engenheiro, kits, carros, caminhões, alojamento, indiretos) e a fonte de cada um. | D21: Custo mensal por contrato, que vira a meta diária de cada equipe na aba 06. | E21: Gestão · implantação e reajuste
B22: 01B. CARTEIRA E TICKET | C22: Coluna E: o CÓD. PREÇO de cada tipo de serviço. Nada mais. | D22: Mix contado na aba 03, descrição e preço da aba 02, ticket apurado da carteira. | E22: Programação · uma vez, ao confirmar os códigos
B23: 02. TABELA DE PREÇOS | C23: Só a busca amarela no alto da aba. Digite uma palavra e a coluna BUSCA marca os itens. | D23: Os 511 itens contratuais das duas cidades. Aba de consulta. | E23: Ninguém edita
B24: 03. CADASTRO DE SERVIÇOS | C24: B contrato · C nº da OS SABESP · D data da solicitação · E prazo · G prioridade · H tipo de serviço · I a N endereço, nº, bairro, cidade, referência e pavimento · O descrição · W tratativa · X observação | D24: A ID (nasce ao escolher o contrato) · F data-limite · P equipe · Q data programada · R data de execução · S status · T dias em aberto · U situação do prazo · V valor medido | E24: Programador · diário, até as 10h
B25: 04. PROGRAMAÇÃO DIÁRIA | C25: A data · C equipe · D sequência · E ID do serviço · K horas previstas. Na volta do campo: L executou? · M data de execução · N motivo da não execução · O reprogramar para · R observação | D25: B contrato · F tipo · G endereço · H bairro · I prioridade · J data-limite · P status do item · Q aderência | E25: Programador 16h · Encarregado fim do turno
B26: 05. ORDENS DE SERVIÇO | C26: A ID do serviço · G equipe · H encarregado · I início · J conclusão · L profundidade · M extensão · N pavimento reposto · O foto antes · P foto depois · Q nº do RDO · V pendência | D26: B a F contrato, nº da OS, endereço, bairro e tipo · K dias · R nº de itens medidos · S valor da OS · T mês de medição · U status da OS | E26: Apontador · no dia da conclusão
B27: 06. APONTAMENTO DIÁRIO | C27: A data · D contrato · E equipe · F nº de pessoas · G e H horas normais e extras · J a O horas de retro, munck, caminhão HR, compressor, rompedor e bomba · P km · Z status do dia · AA motivo de parada · AB observação | D27: I homem-hora · Q e R serviços programados e executados · S aderência · T valor produzido · U meta do dia · V atingimento · W custo da equipe · X resultado · Y R$ por HH | E27: Encarregado · até as 8h do dia seguinte
B28: 07. MATERIAIS | C28: A data · B contrato · C movimento · D ID do serviço · E material · F unidade · G quantidade · J custo unitário · L responsável · M fornecedor · N NF · O material da SABESP? · P observação | D28: H entrada · I saída · K custo total · e o saldo por material no quadro ao lado. | E28: Almoxarife · a cada movimento
B29: 08. EQUIPE | C29: A matrícula · B contrato · C equipe · D nome · E função · F admissão · G salário · M a S validades de ASO, NR-06, NR-10, NR-18, NR-33, NR-35 e CNH · U ativo? | D29: H encargos · I benefícios · J, K e L custo por mês, por dia e por hora · T alerta de vencimento (vermelho vencido, amarelo a 30 dias) | E29: Administrativo + Segurança · admissão e reciclagem
B30: 09. MEDIÇÃO | C30: A nº do boletim · C ID do serviço · H CÓD. PREÇO · K quantidade · N status · O data de apresentação · P valor glosado · Q motivo da glosa · S reapresentar? · T observação | D30: B mês · D a G contrato, nº da OS, equipe e data · I descrição · J unidade · L preço unitário · M valor · R valor aprovado | E30: Técnico de medição · semanal
... B34: 13. RESUMO e 14. DASHBOARD | C34: Nada. São abas de leitura. | D34: KPIs do mês, série mensal, ranking de equipes, Pareto de motivos e os gráficos do contrato. | E34: Gestão · leitura
B36: D · AS QUATRO ABAS DE PARTIDA — VOCÊ MEXE UMA VEZ E VALE PARA O CONTRATO INTEIRO
B37: Estas quatro não são do dia a dia: são a base que faz todas as outras calcularem certo. Errou aqui, erra em tudo — e em silêncio.
B38: 01. CONFIGURAÇÕES — o painel de partida: quem é o contrato, com que regras ele corre e quais palavras a planilha aceita
B39: O que é | C39: Três coisas em uma aba: a identificação dos dois contratos (bloco A), os parâmetros que regem prazo, medição e caixa (bloco B), e as listas padronizadas (bloco D) que abastecem TODAS as caixas de seleção do arquivo.
B40: O que ela decide | C40: Dia de fechamento + defasagem = a data prevista de recebimento na aba 12. Prazo padrão SABESP = a data-limite e o alerta VENCIDO na aba 03. Dias úteis e jornada = o custo por dia e por hora na aba 08 e a meta diária na aba 06. Desconto do consórcio = o valor líquido na aba 12.
B41: O bloco C não se digita | C41: Custo mensal e ticket aparecem em verde: vêm das abas 01A e 01B. Digitar por cima quebra a rastreabilidade — é justamente o que essa versão tirou da planilha.
B42: Onde se erra | C42: Equipe, bairro, material, função ou motivo que não estiver na lista do bloco D simplesmente não aparece na caixa de seleção das outras abas. Para incluir, escreva na PRIMEIRA linha vazia da lista — a faixa nomeada já tem folga reservada.
B43: Quando mexer | C43: Na implantação; quando entra equipe, bairro ou material novo; e em reajuste de contrato.
B44: 01A. BANCO DE CUSTOS — a memória de cálculo do custo mensal — de onde sai a meta de cada equipe
B45: O que é | C45: O custo do contrato desmontado item a item: engenheiro, kits de equipe, carros, caminhões, alojamento e indiretos, cada linha com quantidade, valor unitário e a fonte declarada. Mais três blocos de base: encargos (58% sobre o salário), benefícios por pessoa e tributos sobre a medição (22%).
B46: O que ela decide | C46: O total desta aba é o custo mensal que aparece na aba 01, e é ele que gera a META R$ DO DIA de cada equipe na aba 06 e o CUSTO DO MÊS na aba 12 — ou seja, a margem do contrato sai daqui.
B47: A folha não é digitada | C47: A linha "Equipe de campo" vem somada da aba 08, pessoa a pessoa, com salário real, encargos e benefícios. Contratou ou demitiu? Mexe na 08, não aqui.
B48: Onde se erra | C48: Mudar o valor total no braço em vez de mudar a quantidade ou o preço unitário do item. O total é fórmula: some um item novo na lista, não sobrescreva o resultado.
B49: Quando mexer | C49: Quando muda quantidade (mais um carro, mais uma frente), preço contratado (locação, alojamento, diesel) ou os percentuais de encargo e tributo.
B50: 01B. CARTEIRA E TICKET — quanto vale, em média, um serviço — e é isso que vira meta de faturamento
B51: O que é | C51: A aba conta, tipo por tipo, quantos serviços existem hoje na aba 03 (o mix é contado, não estimado) e multiplica pelo preço do item correspondente na aba 02. O resultado é o ticket médio real da carteira de cada cidade.
B52: O que você faz aqui | C52: Só uma coisa: preencher a coluna E — o CÓD. PREÇO que representa cada tipo de serviço. Descrição e preço aparecem sozinhos ao lado, direto da tabela do contrato.
B53: Enquanto a coluna E estiver vazia | C53: O TICKET ADOTADO continua sendo o de referência herdado do fluxo de caixa (R$ 881,20 em Bertioga e R$ 1.338,83 em Santos). Preenchida, a planilha passa a usar o ticket apurado do contrato.
B54: Cuidado com o contrato | C54: O código tem que ser do mesmo contrato da linha: BER- no mix de Bertioga, SAN- no de Santos. Bertioga não tem itens de supressão (SUPR) nem de religação (RELIG) — esses só existem em Santos. Tipo sem código equivalente no contrato fica sem preço, e é para ficar mesmo.
B55: Para que serve o ticket | C55: É ele que transforma "quantos serviços" em "quanto de receita": alimenta a meta diária da equipe na aba 06 e a projeção de faturamento.
B56: 02. TABELA DE PREÇOS — o contrato em forma de tabela — aba de consulta, ninguém edita
B57: O que é | C57: Os 511 itens contratados das duas cidades — 212 de Bertioga/Guarujá e 299 de Santos — com grupo, item SABESP, descrição, unidade e preço unitário.
B58: A CHAVE é o que liga tudo | C58: Coluna A: prefixo do contrato (BER- ou SAN-) + o número do preço. É a CHAVE que a aba 09 usa para trazer descrição, unidade e preço. Por isso um código de Santos não funciona numa OS de Bertioga: são tabelas diferentes, com preços diferentes para o mesmo serviço.
B59: Como achar o item | C59: Digite uma palavra na célula amarela de busca (TRA, CAVALETE, LRP, ESGOTO...) e a coluna BUSCA marca 1 em tudo que bate. Filtre por essa coluna.
B60: Como ler a descrição | C60: LAG = ligação de água · TRA = troca de ramal de água · TCV = troca de cavalete · LESG = ligação de esgoto · TRE = troca de ramal de esgoto · SUPR = supressão · RELIG = religação · LRP e LPB = reposição de pavimento · ADC = adicional. Depois vem a condição: CORR = corretiva, PREV = preventiva, AVUL = avulsa, SUCES = sucessiva.
B61: Os dois sufixos que mudam o preço | C61: S/REP = sem reposição de pavimento · SF = sem fornecimento de material. A diferença entre a versão com e sem chega a 40% do valor do item — confirme com o consórcio qual se aplica ao seu escopo antes da primeira medição.
B62: Um serviço, vários itens | C62: A medição é por item, não por serviço: uma troca de ramal costuma gerar o TRA + a reposição LRP + algum ADC. Item esquecido é faturamento perdido.
B63: Nunca edite preço aqui | C63: Só muda com reajuste oficial — e quando mudar, muda o histórico inteiro do contrato junto.
B65: E · PASSO A PASSO DE UM SERVIÇO — DO CHAMADO DA SABESP AO DINHEIRO NA CONTA
B66: Exemplo: vazamento no ramal, Alameda Mauá 225, Boracéia. Siga as 8 etapas na ordem — cada uma é uma aba e leva menos de um minuto.
B67: 1 · CHEGOU O CHAMADO | C67: Aba 03, uma linha nova. Escolha o contrato (BERTIOGA) e o ID nasce sozinho: BER-0007. Digite o nº da OS da SABESP, a data da solicitação, o prazo, a prioridade, o tipo e o endereço. A DATA LIMITE aparece em F. Acabou. | E67: Programador · até as 10h
B68: 2 · PROGRAMAR O DIA | C68: Aba 04: data de amanhã, equipe, sequência e o ID BER-0007. Endereço, prioridade e data-limite vêm sozinhos — não redigite. Digite as horas previstas e imprima a aba: ela já sai formatada em paisagem para o encarregado levar. | E68: Programador · até as 16h
B69: 3 · O CAMPO EXECUTA | C69: A folha volta com EXECUTOU? = SIM ou NÃO. Se NÃO, escolha o MOTIVO na lista — sem motivo a linha fica vermelha e a aderência da equipe cai. Se for reprogramar, ponha a nova data na coluna O. | E69: Encarregado · fim do turno
B70: 4 · APONTAR O DIA | C70: Aba 06, uma linha por equipe por dia: pessoas, horas normais e extras, horas de cada máquina e km. É daqui que saem HH, custo do dia e R$ por HH. Aba 10: clima, atividades e visita da fiscalização. Houve chuva, quebra ou interferência? Lance na aba 11 HOJE — depois do mês não vale mais como pleito. | E70: Encarregado · até as 8h do dia seguinte
B71: 5 · ABRIR E FECHAR A OS | C71: Aba 05: digite o ID BER-0007 e contrato, endereço, bairro e tipo aparecem. Preencha equipe, encarregado, início, conclusão, profundidade, extensão, pavimento reposto e as duas fotos. Sem foto ou sem pavimento a OS fica PENDENTE e não entra no fechamento. | E71: Apontador · no dia da conclusão
B72: 6 · MEDIR POR ITEM | C72: Aba 09, uma linha por item de preço. Digite o nº do boletim, o ID e o CÓD. PREÇO — ache o código na aba 02 pela busca amarela. Descrição, unidade e preço vêm da tabela do contrato; de você, só a quantidade. Um serviço costuma render 2 ou 3 itens: o serviço, a reposição de pavimento e os adicionais. Item esquecido é faturamento perdido. | E72: Técnico de medição · semanal
B73: 7 · FECHAR O MÊS | C73: Confira a aba 13: produção, aderência, custo e margem. Na aba 12 o mês já está montado com a medição somada — digite só o nº e a data da NF. Imposto, desconto do consórcio, valor líquido e a data prevista de recebimento se calculam. | E73: Gestão · dia 1
B74: 8 · RECEBER | C74: Aba 12: data e valor recebido. Se vier menos que o previsto, a DIFERENÇA acende e o status vira EM ATRASO ou parcial. Lance a glosa de volta na aba 09 com o motivo e marque REAPRESENTAR — é assim que o dinheiro volta. | E74: Financeiro · na data do crédito
B76: F · ROTINA — O QUE OLHAR E QUANDO
B77: Todo dia, 8h | C77: Aba 06: o apontamento de ontem está completo? Aba 13: quantos serviços estão VENCIDOS?
B78: Todo dia, 16h | C78: Aba 04: programação de amanhã fechada, com o que está vencido em primeiro lugar.
B79: Toda segunda | C79: Aba 13, blocos C e D: qual equipe ficou abaixo da meta e qual motivo de não execução mais se repetiu.
B80: Toda sexta | C80: Aba 09: nenhuma OS concluída sem item de medição lançado. É a maior fonte de perda de receita.
B81: Dia 1 do mês | C81: Aba 12: fechar o mês anterior, emitir a NF e conferir a margem na aba 13.
B82: Dia 20 | C82: Aba 12: o crédito caiu? Se não, a linha já está EM ATRASO — cobre com o boletim aprovado em mãos.
B84: G · O QUE ACENDE VERMELHO — E O QUE FAZER
B85: ID não encontrado | C85: Você digitou na OS, na medição ou no material um ID que não existe na aba 03. Cadastre o serviço primeiro, ou corrija o ID.
B86: CÓDIGO NÃO ENCONTRADO | C86: Código fora da tabela do contrato. Procure na aba 02 pela busca amarela — e confira o contrato: código de Santos não existe em Bertioga.
B87: EXECUTOU? = NÃO sem motivo | C87: A linha fica vermelha até você escolher o motivo na lista. Sem motivo não há Pareto nem defesa de produtividade.
B88: Saída de material sem OS | C88: Material que saiu sem serviço vinculado é perda. Vincule o ID ou registre como perda na observação.
B89: VENCIDO / VENCE EM BREVE | C89: O prazo SABESP está estourando. Puxe o serviço para o topo da programação de amanhã.
B90: ASO ou NR vencido | C90: Vermelho = equipe barrada em campo, dia perdido inteiro. Amarelo = vence em 30 dias, agende a reciclagem agora.
B91: OS PENDENTE | C91: Falta foto ou falta o pavimento reposto. Complete antes do fechamento — é exatamente isso que a fiscalização glosa.
B92: Diferença no recebimento | C92: Veio menos que o previsto. Lance o valor glosado e o motivo na aba 09 e marque REAPRESENTAR.
B94: H · O QUE NUNCA FAZER
B95: Apagar linha | C95: Quebra as faixas nomeadas e o número para de somar. Para cancelar um serviço, use CANCELADO na coluna de tratativa da aba 03.
B96: Digitar sobre fórmula | C96: Célula preta ou verde sobrescrita para de calcular só naquela linha — e ninguém percebe até o fechamento não bater.
B97: Inventar valor fora da lista | C97: Equipe, bairro, material, função e motivo só existem se estiverem na aba 01. Item novo, cadastre na 01 primeiro.
B98: Redigitar endereço | C98: Na OS e na medição use o ID. É o que garante que programação, execução, material e medição falam do mesmo serviço.
B99: Medir sem OS concluída | C99: Item medido sem OS não tem evidência fotográfica. É o primeiro a ser glosado.
B100: Guardar ocorrência para depois | C100: Chuva, interferência e quebra só viram pleito se estiverem lançadas no dia, com hora e custo.
B102: I · IMPLANTAÇÃO — O QUE FALTA PREENCHER ANTES DE RODAR
B103: Aba 03 | C103: Equipe designada e nº da OS SABESP dos 22 serviços já importados de 02 a 09/09/2026.
B104: Aba 08 | C104: Data de admissão e as validades de ASO e NRs das 31 pessoas já cadastradas com salário real.
B105: Aba 01B | C105: O CÓD. PREÇO de cada tipo de serviço (coluna E). Enquanto estiver vazio, o ticket usa a referência do fluxo de caixa em vez do preço do contrato.
B106: Aba 01 | C106: Confirmar o prazo padrão da SABESP e o desconto do consórcio, se houver.
B107: Aba 09 | C107: Os itens de medição dos serviços que já foram concluídos — é o que falta para o primeiro boletim fechar.
B108: Já veio pronto | C108: 511 itens de preço das duas cidades, 31 pessoas com salário, encargos e benefícios reais, e a carteira de Bertioga com ID, bairro e tipo padronizados.
B110: J · DE ONDE VEM CADA NÚMERO
B111: Preços | C111: Abas PREÇOS BERTIOGA e PREÇOS SANTOS do FLUXO_CAIXA_PROJETADO_BERTIOGA_SANTOS_v4. Nenhum código foi presumido — a escolha do item é do técnico de medição.
B112: Custos e metas | C112: Aba 01A, item a item, com quantidade, valor unitário e fonte em cada linha. A folha vem da aba 08, pessoa a pessoa, com encargos e benefícios reais.
...

Sheet 01. CONFIGURAÇÕES
A1: CONFIGURAÇÕES — PARÂMETROS E LISTAS PADRONIZADAS | AB1: COMO PREENCHER ESTA ABA
A2: Painel de partida do contrato: identificação (A), os parâmetros que regem prazo, medição e caixa (B), e as listas que alimentam TODAS as caixas de seleção do arquivo (D). O bloco C não se digita — custo vem da aba 01A e ticket da 01B. Item novo em lista: escreva na PRIMEIRA linha vazia. AZUL = você edita · PRETO e VERDE = não edite. | AB2: Mexe uma vez, no começo. Não é do dia a dia.
AB3: C5 a C11 = nomes: empresa, responsável, os 2 contratos
A4: A · IDENTIFICAÇÃO | AB4: C12 = dia em que a operação começou
B5: Empresa executante | C5: WCR SANEAMENTO | AB5: C13 = mês que você quer ver nos relatórios
B6: Responsável pelo contrato | C6: Felipe Nery | AB6: C17 = % que o consórcio desconta (0 se não desconta)
B7: Coordenador de operações | C7: Ícaro Atila | AB7: C18 = dia que fecha a medição (30)
B8: Contrato 1 — nome curto | C8: BERTIOGA | AB8: C19 = dias que a SABESP demora pra pagar (20)
B9: Contrato 1 — descrição | C9: Manutenção Global GJ B — Bertioga / Guarujá (Consórcio) | AB9: C20 = dias úteis no mês (22)
B10: Contrato 2 — nome curto | C10: SANTOS | AB10: C21 = horas por dia (8,8)
B11: Contrato 2 — descrição | C11: Manutenção Global SA — Santos (Consórcio Global SA) | AB11: C22 = prazo padrão da SABESP em dias (5)
B12: Início da operação | C12: 46265 | AB12: C23 = dias antes de acender o alerta (2)
B13: Mês de referência atual | C13: 46266 | AB13: C33 e D33 = margem que você quer ganhar (0,20 = 20%)
AB14: Da linha 44 pra baixo = as listas dos menus.
A15: B · PARÂMETROS FINANCEIROS E DE MEDIÇÃO | AB15: Item novo: escreve na 1a linha vazia da coluna.
B16: Imposto sobre a nota (%) | C16: ='01A. BANCO DE CUSTOS'!$C$47 -> 0.22 | D16: Fórmula — vem da aba 01A, bloco D, tributo a tributo. | AB16: Só o que está AZUL é seu. Preto e verde é fórmula.
B17: Desconto do consórcio (%) | C17: 0 | D17: Se o consórcio retiver percentual da medição. 0 = não retém.
B18: Dia de fechamento da medição | C18: 30 | D18: Último dia do mês. Depois desta data o serviço entra no mês seguinte.
B19: Defasagem de recebimento (dias) | C19: 20 | D19: Da data de fechamento até o crédito em conta.
B20: Dias úteis por mês | C20: 22 | D20: Base do custo/dia e das metas diárias.
B21: Jornada normal (h/dia) | C21: 8.8 | D21: Base do cálculo de produtividade R$/hh.
B22: Prazo padrão SABESP (dias) | C22: 5 | D22: Usado quando o prazo não vem informado na solicitação.
B23: Alerta de prazo — dias antes | C23: 2 | D23: A partir de quantos dias do vencimento o serviço fica AMARELO.
B24: Nº de equipes — BERTIOGA | C24: =SUMPRODUCT((COUNTIFS(EQP_CONTR,"BERTIOGA",EQP_ATIVO,"SIM",EQP_EQUIPE,{"BER-A";"BER-B";"BER-C";"BER-D"})>0)*1) -> 4 | D24: Fórmula — conta quantas equipes têm pelo menos uma pessoa ativa na aba 08.
B25: Nº de equipes — SANTOS | C25: =SUMPRODUCT((COUNTIFS(EQP_CONTR,"SANTOS",EQP_ATIVO,"SIM",EQP_EQUIPE,{"SAN-A";"SAN-B";"SAN-C";"SAN-D"})>0)*1) -> 4 | D25: Fórmula — conta quantas equipes têm pelo menos uma pessoa ativa na aba 08.
A27: C · CUSTOS E METAS POR CONTRATO (custos vindos de FLUXO_CAIXA_PROJETADO_BERTIOGA_SANTOS_v4)
B28: PARÂMETRO | C28: BERTIOGA | D28: SANTOS | E28: UN | F28: OBSERVAÇÃO
B29: Custo mensal total do contrato | C29: ='01A. BANCO DE CUSTOS'!$E$16 -> 230982.81 | D29: ='01A. BANCO DE CUSTOS'!$E$30 -> 273163.84 | E29: R$/mês | F29: Fórmula — vem da aba 01A, item a item (estrutura + quadro nominal ativo da aba 08).
B30: Custo por dia útil | C30: =C29/$C$20 -> 10499.219 | D30: =D29/$C$20 -> 12416.538 | E30: R$/dia | F30: Fórmula: custo mensal ÷ dias úteis.
B31: Custo por equipe por dia | C31: =C30/$C$24 -> 2624.8047 | D31: =D30/$C$25 -> 3104.1345 | E31: R$/dia | F31: Fórmula: custo/dia ÷ nº de equipes.
B32: Ticket médio por serviço | C32: ='01B. CARTEIRA E TICKET'!$H$34 -> 317.49648 | D32: ='01B. CARTEIRA E TICKET'!$H$66 -> 1338.83 | E32: R$/serviço | F32: Fórmula — vem da aba 01B, apurado do mix real da carteira ou, na falta dos códigos, do ticket de referência do fluxo de caixa.
B33: Margem-alvo do cenário adotado | C33: 0.2 | D33: 0.2 | E33: % | F33: Cenário ÓTIMA do fluxo de caixa (aba PREMISSAS). É decisão comercial — por isso continua azul.
B34: Meta de medição bruta no mês | C34: =C29*(1+C33)/(1-$C$16) -> 355358.17 | D34: =D29*(1+D33)/(1-$C$16) -> 420252.06 | E34: R$/mês | F34: Fórmula: custo × (1+margem) ÷ (1−imposto).
B35: Meta de serviços no mês | C35: =C34/C32 -> 1119.2507 | D35: =D34/D32 -> 313.89501 | E35: serv./mês | F35: Fórmula: meta R$ ÷ ticket médio.
B36: Meta de serviços por dia útil | C36: =C35/$C$20 -> 50.875033 | D36: =D35/$C$20 -> 14.267955 | E36: serv./dia | F36: Base: dias ÚTEIS (22). No fluxo de caixa a base é 30 dias corridos — por isso lá aparece 13,8 e 10,3.
B37: Meta de serviços por equipe/dia | C37: =C36/$C$24 -> 12.718758 | D37: =D36/$C$25 -> 3.5669888 | E37: serv./dia | F37: É a meta que o encarregado cobra em campo.
B38: Meta de R$ por equipe/dia | C38: =C34/$C$20/$C$24 -> 4038.161 | D38: =D34/$C$20/$C$25 -> 4775.5916 | E38: R$/dia | F38: É a meta que a gestão cobra na reunião semanal.
B39: Produção mínima de equilíbrio (serv./dia) | C39: =C29/(1-$C$16)/C32/$C$20 -> 42.395861 | D39: =D29/(1-$C$16)/D32/$C$20 -> 11.889963 | E39: serv./dia | F39: Abaixo disso o contrato dá prejuízo.
A41: D · LISTAS PADRONIZADAS (alimentam todas as caixas de seleção — acrescente na primeira linha vazia)
A43: CONTRATO | B43: EQUIPE | C43: PRIORIDADE | D43: TIPO | E43: STATUS_CAD | F43: STATUS_PROG | G43: STATUS_OS | H43: STATUS_MED | I43: STATUS_FAT | J43: MOTIVO_NE | K43: MOTIVO_PARADA | L43: PAVIMENTO | M43: BAIRRO | N43: FUNCAO | O43: EQUIPAMENTO | P43: MATERIAL | Q43: MOVIMENTO | R43: SN | S43: SNP | T43: CLIMA | U43: SOLO | V43: TIPO_OCOR | W43: GRAVIDADE | X43: STATUS_OC | Y43: DIA | Z43: CAUSA_NC | AA43: RESTRICAO
A44: BERTIOGA | B44: BER-A | C44: EMERGENCIAL | D44: Vazamento de água não visível — rede | E44: CADASTRADO | F44: PROGRAMADO | G44: ABERTA | H44: A MEDIR | I44: A FATURAR | J44: Falta de material | K44: SEM PARADA | L44: ASFALTO | M44: Centro | N44: Encarregado de Obras | O44: Retroescavadeira | P44: Tubo PVC DEFOFO | Q44: ENTRADA | R44: SIM | S44: SIM | T44: BOM | U44: SECO | V44: Acidente / incidente | W44: BAIXA | X44: ABERTA | Y44: NORMAL | Z44: Falta de material | AA44: Material
A45: SANTOS | B45: BER-B | C45: URGENTE | D45: Vazamento de água não visível — ramal | E45: PROGRAMADO | F45: EXECUTADO | G45: EM EXECUÇÃO | H45: MEDIDA | I45: NF EMITIDA | J45: Falta de equipamento | K45: Chuva | L45: CONCRETO | M45: Boracéia | N45: Líder de Equipe | O45: Caminhão 3/4 + Munck | P45: Tubo PVC PBA | Q45: SAÍDA | R45: NÃO | S45: NÃO | T45: NUBLADO | U45: ÚMIDO | V45: Quase acidente | W45: MÉDIA | X45: EM TRATATIVA | Y45: SÁBADO | Z45: Falta de equipamento | AA45: Equipamento
B46: BER-C | C46: NORMAL | D46: Vazamento de água visível — rede | E46: EM EXECUÇÃO | F46: NÃO EXECUTADO | G46: AGUARDANDO MATERIAL | H46: APRESENTADA | I46: APRESENTADA | J46: Equipe deslocada para emergência | K46: Quebra de equipamento | L46: PARALELEPÍPEDO | M46: Jardim Vicente de Carvalho | N46: Encanador | O46: Caminhão HR | P46: Tubo PEAD | Q46: DEVOLUÇÃO | S46: PARCIAL | T46: CHUVA FRACA | U46: ENCHARCADO | V46: Interferência de outra concessionária | W46: ALTA | X46: RESOLVIDA | Y46: DOMINGO | Z46: Falta de mão de obra | AA46: Mão de obra
B47: BER-D | C47: PROGRAMÁVEL | D47: Vazamento de água visível — ramal | E47: EXECUTADO | F47: REPROGRAMADO | G47: AGUARDANDO PAVIMENTO | H47: APROVADA | I47: APROVADA | J47: Chuva | K47: Falta de material | L47: BLOQUETE | M47: Albatroz II | N47: Encanador Motorizado | O47: Caminhão basculante | P47: Tubo PVC esgoto | Q47: PERDA / QUEBRA | S47: NÃO SE APLICA | T47: CHUVA FORTE | U47: LENÇOL FREÁTICO ALTO | V47: Reclamação de morador | W47: CRÍTICA | X47: CANCELADA | Y47: FERIADO | Z47: Falta de frente liberada | AA47: OS / projeto
B48: SAN-A | D48: Vazamento pé do cavalete | E48: PENDENTE | F48: CANCELADO | G48: CONCLUÍDA | H48: GLOSADA | I48: RECEBIDA | J48: Endereço não localizado | K48: Falta de efetivo | L48: PASSEIO / CALÇADA | M48: Ana Paula | N48: Pedreiro | O48: Compressor | P48: Colar de tomada | Q48: TRANSFERÊNCIA | T48: IMPRATICÁVEL | V48: Retrabalho | Y48: PLANTÃO | Z48: OS não emitida pela SABESP | AA48: Licença / via
B49: SAN-B | D49: Vazamento no ferrule | E49: CANCELADO | G49: MEDIDA | H49: REAPRESENTADA | I49: RECEBIDA PARCIAL | J49: Sem acesso / imóvel fechado | K49: Acidente / incidente | L49: TERRA / SAIBRO | M49: Rio da Praia | N49: Pedreiro Motorizado | O49: Rompedor pneumático | P49: Ferrule | V49: Quebra de equipamento | Y49: PARADO | Z49: Licença / liberação da via | AA49: Acesso ao local
B50: SAN-C | D50: Troca de ramal de água | E50: DEVOLVIDO À SABESP | G50: CANCELADA | H50: PAGA | I50: EM ATRASO | J50: Interferência de outra concessionária | K50: Sem frente de serviço | L50: SEM PAVIMENTO | M50: Vista Linda | N50: Operador de Retroescavadeira | O50: Martelete elétrico | P50: T de serviço | V50: Falta de material | Z50: Chuva / clima | AA50: Informação técnica
B51: SAN-D | D51: Troca de cavalete | J51: Vazamento não localizado | K51: Feriado | M51: Indaiá | N51: Ajudante Geral | O51: Bomba de esgotamento | P51: Curva / joelho | V51: Chuva | Z51: Retrabalho por qualidade | AA51: Financeiro
B52: APOIO | D52: Execução de ligação de água | J52: Necessita corte de asfalto / licença | K52: Deslocamento longo | M52: Maitinga | N52: Programador(a) | O52: Gerador | P52: Luva de correr | V52: Notificação da fiscalização | Z52: Mudança de prioridade da SABESP | AA52: Fiscalização
B53: TERCEIRO | D53: Supressão de ligação de água | J53: Trânsito / evento na via | K53: Outro | M53: Costa do Sol | N53: Engenheiro | O53: Serra de disco / clipper | P53: Adaptador | V53: Dano a terceiros | Z53: Interferência de terceiros
D54: Religação de água | J54: Serviço já executado por terceiro | M54: Riviera | N54: Técnico de Segurança | O54: Máquina de solda PEAD | P54: Registro esfera | V54: Vazamento de terceiro | Z54: Programação mal dimensionada
D55: Substituição de hidrômetro | J55: Ordem cancelada pela SABESP | M55: São Lourenço | N55: Motorista | O55: Detector de vazamento (geofone) | P55: Registro de gaveta | V55: Outro | Z55: Quebra de veículo
D56: Troca de registro / TMD | J56: Falta de efetivo | M56: Guaratuba | N56: Almoxarife | O56: Kit sinalização | P56: Cavalete completo | Z56: Outro
D57: Conserto de rede de água | J57: Quebra de veículo | M57: Chácaras | O57: Van de equipe | P57: Hidrômetro
D58: Execução de ligação de esgoto | J58: Outro | M58: Vicente de Carvalho | P58: Caixa de proteção
D59: Troca de ramal de esgoto | M59: Enseada | P59: Tê / cruzeta FoFo
D60: Desobstrução de rede de esgoto | M60: Pitangueiras | P60: Abraçadeira de reparo
D61: Conserto de rede de esgoto | M61: Jardim Santa Maria | P61: Areia
D62: Construção de PI / PV | M62: Perequê | P62: Pedrisco
D63: Recuperação de PI / PV | M63: Gonzaga | P63: Brita
D64: Reposição de pavimento | M64: Ponta da Praia | P64: Cimento
D65: Remanejamento de rede | M65: Embaré | P65: Concreto usinado
D66: Travessia | M66: Aparecida | P66: CBUQ / massa asfáltica
D67: Vistoria / levantamento | M67: Boqueirão | P67: Emulsão asfáltica
D68: Outro | M68: Campo Grande | P68: Anel de PI/PV
M69: Marapé | P69: Tampão FoFo
M70: Vila Belmiro | P70: Fita zebrada
M71: Zona Noroeste | P71: Cone de sinalização
M72: Areia Branca | P72: Outro
M73: Outro

Sheet 01A. BANCO DE CUSTOS
A1: BANCO DE CUSTOS, ENCARGOS E TRIBUTOS — ITEM A ITEM | K1: COMO PREENCHER ESTA ABA
A2: É daqui que sai o custo mensal de cada contrato — e, por consequência, a meta diária de cada equipe (aba 06) e a margem (aba 12). Cada linha tem quantidade, valor unitário e fonte declarada. A folha não é digitada: vem somada da aba 08, pessoa a pessoa. Nada é digitado na aba 01 — o total daqui é que alimenta o bloco C de lá. AZUL = quantidade e preço contratados · VERDE = vem da aba 08. | K2: Daqui sai o custo do mês e a meta de cada equipe.
K3: Mexe só quando o preço de verdade mudar.
A4: CUSTO MENSAL — BERTIOGA | K4: C = quantos você tem (2 caminhões, escreve 2)
B5: ITEM | C5: QTD | D5: VALOR UNIT. | E5: TOTAL / MÊS | F5: FONTE | K5: D = quanto custa CADA UM por mês
B6: Engenheiro residente | C6: 1 | D6: 13000 | E6: =C6*D6 -> 13000 | F6: Salário + encargos — praticado pela WCR nos dois contratos | K6: F = de onde saiu o preço (contrato, cotação, aluguel)
B7: Kit de ferramentas por equipe | C7: 4 | D7: 7200 | E7: =C7*D7 -> 28800 | F7: Locação mensal — 1 kit por equipe | K7: C34 = fator de encargos sobre o salário (0,58)
B8: Carro do engenheiro | C8: 1 | D8: 3400 | E8: =C8*D8 -> 3400 | F8: Locação mensal | K8: C35 = benefícios por pessoa por mês
B9: Carro do encarregado | C9: 1 | D9: 3500 | E9: =C9*D9 -> 3500 | F9: Locação mensal | K9: C40 a C46 = as alíquotas dos impostos
B10: Caminhão 3/4 com munck | C10: 1 | D10: 25000 | E10: =C10*D10 -> 25000 | F10: Locação mensal com operador | K10: Linha 15 e 29 (folha) NÃO se digita:
B11: Caminhão tipo HR | C11: 3 | D11: 6500 | E11: =C11*D11 -> 19500 | F11: Locação mensal — 1 por equipe de campo | K11: vem somada da aba 08. EQUIPE, pessoa por pessoa.
B12: Alojamento | C12: 1 | D12: 13500 | E12: =C12*D12 -> 13500 | F12: Casa da equipe em Bertioga
B13: Equipamentos leves | C13: 1 | D13: 12900 | E13: =C13*D13 -> 12900 | F13: Compressor, rompedor, bombas, geofone, serra e sinalização
B14: Custos indiretos | C14: 1 | D14: 20000 | E14: =C14*D14 -> 20000 | F14: Administração de contrato, contabilidade, seguros, EPI e telefonia
B15: Equipe de campo — folha, encargos e benefícios | C15: =COUNTIFS(EQP_CONTR,"BERTIOGA",EQP_ATIVO,"SIM") -> 14 | D15: =IF(C15=0,0,E15/C15) -> 6527.3436 | E15: =SUMIFS(EQP_CUSTOMES,EQP_CONTR,"BERTIOGA",EQP_ATIVO,"SIM") -> 91382.81 | F15: Soma do quadro nominal ativo da aba 08. EQUIPE — salário + encargos + benefícios, pessoa a pessoa.
B16: TOTAL MENSAL — BERTIOGA | E16: =SUM(E6:E15) -> 230982.81 | F16: Fluxo Trimestral Obra · FLUXO_CAIXA_PROJETADO_BERTIOGA_SANTOS_v4 — abas CUSTOS BERTIOGA e CUSTOS SANTOS
A18: CUSTO MENSAL — SANTOS
B19: ITEM | C19: QTD | D19: VALOR UNIT. | E19: TOTAL / MÊS | F19: FONTE
B20: Engenheiro residente | C20: 1 | D20: 13000 | E20: =C20*D20 -> 13000 | F20: Salário + encargos — praticado pela WCR nos dois contratos
B21: Kit de ferramentas por equipe | C21: 4 | D21: 7200 | E21: =C21*D21 -> 28800 | F21: Locação mensal — 1 kit por equipe
B22: Carro do engenheiro | C22: 1 | D22: 3400 | E22: =C22*D22 -> 3400 | F22: Locação mensal
B23: Carro do encarregado | C23: 1 | D23: 3400 | E23: =C23*D23 -> 3400 | F23: Locação mensal
B24: Caminhão 3/4 com munck | C24: 2 | D24: 25000 | E24: =C24*D24 -> 50000 | F24: Locação mensal com operador
B25: Caminhão tipo HR | C25: 2 | D25: 6000 | E25: =C25*D25 -> 12000 | F25: Locação mensal
B26: Alojamento | C26: 1 | D26: 6000 | E26: =C26*D26 -> 6000 | F26: Casa da equipe em Santos
B27: Equipamentos leves | C27: 1 | D27: 12900 | E27: =C27*D27 -> 12900 | F27: Compressor, rompedor, bombas, geofone, serra e sinalização
B28: Custos indiretos | C28: 1 | D28: 20000 | E28: =C28*D28 -> 20000 | F28: Administração de contrato, contabilidade, seguros, EPI e telefonia
B29: Equipe de campo — folha, encargos e benefícios | C29: =COUNTIFS(EQP_CONTR,"SANTOS",EQP_ATIVO,"SIM") -> 16 | D29: =IF(C29=0,0,E29/C29) -> 7728.99 | E29: =SUMIFS(EQP_CUSTOMES,EQP_CONTR,"SANTOS",EQP_ATIVO,"SIM") -> 123663.84 | F29: Soma do quadro nominal ativo da aba 08. EQUIPE — salário + encargos + benefícios, pessoa a pessoa.
B30: TOTAL MENSAL — SANTOS | E30: =SUM(E20:E29) -> 273163.84 | F30: Fluxo Trimestral Obra · FLUXO_CAIXA_PROJETADO_BERTIOGA_SANTOS_v4 — abas CUSTOS BERTIOGA e CUSTOS SANTOS
A32: C · ENCARGOS E BENEFÍCIOS — BASE DA FOLHA
B33: PARÂMETRO | C33: VALOR | D33: UN | E33: MEMÓRIA DE CÁLCULO | F33: FONTE
B34: Fator de encargos sobre o salário | C34: 0.58 | D34: % | E34: INSS patronal, RAT, FGTS, 13º, férias + 1/3, rescisão e repouso. Apurado da própria folha: encargos ÷ salário dá 58,0% para todos os 31 colaboradores das duas cidades. | F34: Folha real — CUSTOS BERTIOGA e CUSTOS SANTOS do FLUXO_CAIXA v4
B35: Benefícios por pessoa | C35: 1904.32 | D35: R$/mês | E35: Vale-refeição + vale-alimentação + vale-transporte. Valor único na folha das duas cidades. | F35: Folha real — CUSTOS BERTIOGA e CUSTOS SANTOS do FLUXO_CAIXA v4
B36: Conferência — folha original das duas cidades | C36: 226754.32 | D36: R$/mês | E36: =IF(ABS(C36-(SUMIFS(EQP_CUSTOMES,EQP_ATIVO,"SIM")))<50,"Confere — diferença só de arredondamento por pessoa","⚠ divergência: revise o fator de encargos") -> ⚠ divergência: revise o fator de encargos | F36: Soma de folha + encargos + benefícios das 31 pessoas, como estava no fluxo de caixa
A38: D · TRIBUTOS SOBRE A MEDIÇÃO — Lucro Presumido, serviço
B39: TRIBUTO | C39: ALÍQUOTA | D39: UN | E39: MEMÓRIA DE CÁLCULO | F39: FONTE
B40: PIS | C40: 0.0065 | D40: % | E40: Regime cumulativo do Lucro Presumido | F40: Lei 9.718/98
B41: COFINS | C41: 0.03 | D41: % | E41: Regime cumulativo do Lucro Presumido | F41: Lei 9.718/98
B42: IRPJ | C42: 0.048 | D42: % | E42: 15% sobre a presunção de 32% para serviço | F42: RIR/2018
B43: Adicional de IRPJ | C43: 0.01 | D43: % | E43: 10% sobre o excedente de R$ 20 mil/mês — provisão | F43: RIR/2018
B44: CSLL | C44: 0.0288 | D44: % | E44: 9% sobre a presunção de 32% para serviço | F44: Lei 7.689/88
B45: ISS | C45: 0.05 | D45: % | E45: Alíquota-teto adotada por prudência. Bertioga, Guarujá e Santos cobram entre 2% e 5% sobre manutenção — ajuste por município se for menor. | F45: Códigos tributários municipais · LC 116/2003 art. 8º
B46: Retenção de INSS sobre cessão de mão de obra | C46: 0.0467 | D46: % | E46: Retenção de 11% líquida da compensação, ajustada para fechar a carga de 22% adotada no fluxo de caixa | F46: IN RFB 971/2009
B47: TOTAL DE TRIBUTOS SOBRE A MEDIÇÃO | C47: =SUM(C40:C46) -> 0.22 | D47: % | E47: Soma das alíquotas acima. É este total que a aba 01 usa. | F47: derivado

Sheet 01B. CARTEIRA E TICKET
A1: CARTEIRA E TICKET MÉDIO — DE ONDE SAI O R$ POR SERVIÇO | L1: COMO PREENCHER ESTA ABA
A2: O mix não é chutado: cada linha conta, na aba 03, quantos serviços daquele tipo existem hoje. Você preenche só a coluna E — o CÓD. PREÇO que representa o tipo — e o ticket passa a ser apurado da tabela do contrato em vez de herdado do fluxo de caixa. O código tem que ser do mesmo contrato da linha: Bertioga não tem SUPR nem RELIG. Tipo sem item equivalente no contrato fica sem preço, e é para ficar mesmo. | L2: Só a coluna E é sua. O resto é fórmula.
L3: E = o CÓD. PREÇO daquele tipo de serviço
A4: MIX DA CARTEIRA — BERTIOGA | L4: exemplo: BER-72000053
B5: TIPO DE SERVIÇO | C5: Nº NA CARTEIRA | D5: % DO MIX | E5: CÓD. PREÇO (CHAVE) | F5: DESCRIÇÃO DO ITEM | G5: PREÇO UNIT. | H5: CONTRIBUIÇÃO | I5: MEMÓRIA DE CÁLCULO | L5: Pega o código na aba 02. TABELA DE PREÇOS.
B6: Vazamento de água não visível — rede | C6: =COUNTIFS(CAD_TIPO,$B6,CAD_CONTR,"BERTIOGA") -> 8 | D6: =IF(COUNTIFS(CAD_CONTR,"BERTIOGA")=0,"",C6/COUNTIFS(CAD_CONTR,"BERTIOGA")) -> 0.14814815 | E6: BER-72000053 | F6: =IFERROR(IF($E6="","",VLOOKUP($E6,PRE_TAB,5,FALSE)),"CÓDIGO NÃO ENCONTRADO") -> LAG ATE 32MM TA AVUL S/REP SF | G6: =IFERROR(IF($E6="","",VLOOKUP($E6,PRE_TAB,8,FALSE)),"") -> 787.5 | H6: =IF(OR($D6="",$G6=""),0,$D6*$G6) -> 116.66667 | I6: nº deste tipo ÷ total do contrato, na aba 03 · preço do item na aba 02 | L6: O código tem que ser do MESMO contrato da linha:
B7: Vazamento de água não visível — ramal | C7: =COUNTIFS(CAD_TIPO,$B7,CAD_CONTR,"BERTIOGA") -> 5 | D7: =IF(COUNTIFS(CAD_CONTR,"BERTIOGA")=0,"",C7/COUNTIFS(CAD_CONTR,"BERTIOGA")) -> 0.092592593 | E7: BER-72000053 | F7: =IFERROR(IF($E7="","",VLOOKUP($E7,PRE_TAB,5,FALSE)),"CÓDIGO NÃO ENCONTRADO") -> LAG ATE 32MM TA AVUL S/REP SF | G7: =IFERROR(IF($E7="","",VLOOKUP($E7,PRE_TAB,8,FALSE)),"") -> 787.5 | H7: =IF(OR($D7="",$G7=""),0,$D7*$G7) -> 72.916667 | I7: nº deste tipo ÷ total do contrato, na aba 03 · preço do item na aba 02 | L7: BER- com BER-, SAN- com SAN-.
B8: Vazamento de água visível — rede | C8: =COUNTIFS(CAD_TIPO,$B8,CAD_CONTR,"BERTIOGA") -> 0 | D8: =IF(COUNTIFS(CAD_CONTR,"BERTIOGA")=0,"",C8/COUNTIFS(CAD_CONTR,"BERTIOGA")) -> 0 | F8: =IFERROR(IF($E8="","",VLOOKUP($E8,PRE_TAB,5,FALSE)),"CÓDIGO NÃO ENCONTRADO") | G8: =IFERROR(IF($E8="","",VLOOKUP($E8,PRE_TAB,8,FALSE)),"") | H8: =IF(OR($D8="",$G8=""),0,$D8*$G8) -> 0 | I8: nº deste tipo ÷ total do contrato, na aba 03 · preço do item na aba 02 | L8: Tipo que não existe no contrato fica sem preço mesmo.
B9: Vazamento de água visível — ramal | C9: =COUNTIFS(CAD_TIPO,$B9,CAD_CONTR,"BERTIOGA") -> 0 | D9: =IF(COUNTIFS(CAD_CONTR,"BERTIOGA")=0,"",C9/COUNTIFS(CAD_CONTR,"BERTIOGA")) -> 0 | F9: =IFERROR(IF($E9="","",VLOOKUP($E9,PRE_TAB,5,FALSE)),"CÓDIGO NÃO ENCONTRADO") | G9: =IFERROR(IF($E9="","",VLOOKUP($E9,PRE_TAB,8,FALSE)),"") | H9: =IF(OR($D9="",$G9=""),0,$D9*$G9) -> 0 | I9: nº deste tipo ÷ total do contrato, na aba 03 · preço do item na aba 02
B10: Vazamento pé do cavalete | C10: =COUNTIFS(CAD_TIPO,$B10,CAD_CONTR,"BERTIOGA") -> 7 | D10: =IF(COUNTIFS(CAD_CONTR,"BERTIOGA")=0,"",C10/COUNTIFS(CAD_CONTR,"BERTIOGA")) -> 0.12962963 | E10: BER-72000226 | F10: =IFERROR(IF($E10="","",VLOOKUP($E10,PRE_TAB,5,FALSE)),"CÓDIGO NÃO ENCONTRADO") -> TCV SF | G10: =IFERROR(IF($E10="","",VLOOKUP($E10,PRE_TAB,8,FALSE)),"") -> 301.47 | H10: =IF(OR($D10="",$G10=""),0,$D10*$G10) -> 39.079444 | I10: nº deste tipo ÷ total do contrato, na aba 03 · preço do item na aba 02
B11: Vazamento no ferrule | C11: =COUNTIFS(CAD_TIPO,$B11,CAD_CONTR,"BERTIOGA") -> 2 | D11: =IF(COUNTIFS(CAD_CONTR,"BERTIOGA")=0,"",C11/COUNTIFS(CAD_CONTR,"BERTIOGA")) -> 0.037037037 | E11: BER-72000897 | F11: =IFERROR(IF($E11="","",VLOOKUP($E11,PRE_TAB,5,FALSE)),"CÓDIGO NÃO ENCONTRADO") -> ADC SUBST TMD AG SF | G11: =IFERROR(IF($E11="","",VLOOKUP($E11,PRE_TAB,8,FALSE)),"") -> 43.3 | H11: =IF(OR($D11="",$G11=""),0,$D11*$G11) -> 1.6037037 | I11: nº deste tipo ÷ total do contrato, na aba 03 · preço do item na aba 02
B12: Troca de ramal de água | C12: =COUNTIFS(CAD_TIPO,$B12,CAD_CONTR,"BERTIOGA") -> 6 | D12: =IF(COUNTIFS(CAD_CONTR,"BERTIOGA")=0,"",C12/COUNTIFS(CAD_CONTR,"BERTIOGA")) -> 0.11111111 | E12: BER-72000044 | F12: =IFERROR(IF($E12="","",VLOOKUP($E12,PRE_TAB,5,FALSE)),"CÓDIGO NÃO ENCONTRADO") -> TRA ATE 32MM CORR TA S/REP SF | G12: =IFERROR(IF($E12="","",VLOOKUP($E12,PRE_TAB,8,FALSE)),"") -> 785.07 | H12: =IF(OR($D12="",$G12=""),0,$D12*$G12) -> 87.23 | I12: nº deste tipo ÷ total do contrato, na aba 03 · preço do item na aba 02
B13: Troca de cavalete | C13: =COUNTIFS(CAD_TIPO,$B13,CAD_CONTR,"BERTIOGA") -> 0 | D13: =IF(COUNTIFS(CAD_CONTR,"BERTIOGA")=0,"",C13/COUNTIFS(CAD_CONTR,"BERTIOGA")) -> 0 | F13: =IFERROR(IF($E13="","",VLOOKUP($E13,PRE_TAB,5,FALSE)),"CÓDIGO NÃO ENCONTRADO") | G13: =IFERROR(IF($E13="","",VLOOKUP($E13,PRE_TAB,8,FALSE)),"") | H13: =IF(OR($D13="",$G13=""),0,$D13*$G13) -> 0 | I13: nº deste tipo ÷ total do contrato, na aba 03 · preço do item na aba 02
B14: Execução de ligação de água | C14: =COUNTIFS(CAD_TIPO,$B14,CAD_CONTR,"BERTIOGA") -> 0 | D14: =IF(COUNTIFS(CAD_CONTR,"BERTIOGA")=0,"",C14/COUNTIFS(CAD_CONTR,"BERTIOGA")) -> 0 | F14: =IFERROR(IF($E14="","",VLOOKUP($E14,PRE_TAB,5,FALSE)),"CÓDIGO NÃO ENCONTRADO") | G14: =IFERROR(IF($E14="","",VLOOKUP($E14,PRE_TAB,8,FALSE)),"") | H14: =IF(OR($D14="",$G14=""),0,$D14*$G14) -> 0 | I14: nº deste tipo ÷ total do contrato, na aba 03 · preço do item na aba 02
B15: Supressão de ligação de água | C15: =COUNTIFS(CAD_TIPO,$B15,CAD_CONTR,"BERTIOGA") -> 0 | D15: =IF(COUNTIFS(CAD_CONTR,"BERTIOGA")=0,"",C15/COUNTIFS(CAD_CONTR,"BERTIOGA")) -> 0 | F15: =IFERROR(IF($E15="","",VLOOKUP($E15,PRE_TAB,5,FALSE)),"CÓDIGO NÃO ENCONTRADO") | G15: =IFERROR(IF($E15="","",VLOOKUP($E15,PRE_TAB,8,FALSE)),"") | H15: =IF(OR($D15="",$G15=""),0,$D15*$G15) -> 0 | I15: nº deste tipo ÷ total do contrato, na aba 03 · preço do item na aba 02
B16: Religação de água | C16: =COUNTIFS(CAD_TIPO,$B16,CAD_CONTR,"BERTIOGA") -> 0 | D16: =IF(COUNTIFS(CAD_CONTR,"BERTIOGA")=0,"",C16/COUNTIFS(CAD_CONTR,"BERTIOGA")) -> 0 | F16: =IFERROR(IF($E16="","",VLOOKUP($E16,PRE_TAB,5,FALSE)),"CÓDIGO NÃO ENCONTRADO") | G16: =IFERROR(IF($E16="","",VLOOKUP($E16,PRE_TAB,8,FALSE)),"") | H16: =IF(OR($D16="",$G16=""),0,$D16*$G16) -> 0 | I16: nº deste tipo ÷ total do contrato, na aba 03 · preço do item na aba 02
B17: Substituição de hidrômetro | C17: =COUNTIFS(CAD_TIPO,$B17,CAD_CONTR,"BERTIOGA") -> 0 | D17: =IF(COUNTIFS(CAD_CONTR,"BERTIOGA")=0,"",C17/COUNTIFS(CAD_CONTR,"BERTIOGA")) -> 0 | F17: =IFERROR(IF($E17="","",VLOOKUP($E17,PRE_TAB,5,FALSE)),"CÓDIGO NÃO ENCONTRADO") | G17: =IFERROR(IF($E17="","",VLOOKUP($E17,PRE_TAB,8,FALSE)),"") | H17: =IF(OR($D17="",$G17=""),0,$D17*$G17) -> 0 | I17: nº deste tipo ÷ total do contrato, na aba 03 · preço do item na aba 02
B18: Troca de registro / TMD | C18: =COUNTIFS(CAD_TIPO,$B18,CAD_CONTR,"BERTIOGA") -> 0 | D18: =IF(COUNTIFS(CAD_CONTR,"BERTIOGA")=0,"",C18/COUNTIFS(CAD_CONTR,"BERTIOGA")) -> 0 | F18: =IFERROR(IF($E18="","",VLOOKUP($E18,PRE_TAB,5,FALSE)),"CÓDIGO NÃO ENCONTRADO") | G18: =IFERROR(IF($E18="","",VLOOKUP($E18,PRE_TAB,8,FALSE)),"") | H18: =IF(OR($D18="",$G18=""),0,$D18*$G18) -> 0 | I18: nº deste tipo ÷ total do contrato, na aba 03 · preço do item na aba 02
B19: Conserto de rede de água | C19: =COUNTIFS(CAD_TIPO,$B19,CAD_CONTR,"BERTIOGA") -> 0 | D19: =IF(COUNTIFS(CAD_CONTR,"BERTIOGA")=0,"",C19/COUNTIFS(CAD_CONTR,"BERTIOGA")) -> 0 | F19: =IFERROR(IF($E19="","",VLOOKUP($E19,PRE_TAB,5,FALSE)),"CÓDIGO NÃO ENCONTRADO") | G19: =IFERROR(IF($E19="","",VLOOKUP($E19,PRE_TAB,8,FALSE)),"") | H19: =IF(OR($D19="",$G19=""),0,$D19*$G19) -> 0 | I19: nº deste tipo ÷ total do contrato, na aba 03 · preço do item na aba 02
B20: Execução de ligação de esgoto | C20: =COUNTIFS(CAD_TIPO,$B20,CAD_CONTR,"BERTIOGA") -> 0 | D20: =IF(COUNTIFS(CAD_CONTR,"BERTIOGA")=0,"",C20/COUNTIFS(CAD_CONTR,"BERTIOGA")) -> 0 | F20: =IFERROR(IF($E20="","",VLOOKUP($E20,PRE_TAB,5,FALSE)),"CÓDIGO NÃO ENCONTRADO") | G20: =IFERROR(IF($E20="","",VLOOKUP($E20,PRE_TAB,8,FALSE)),"") | H20: =IF(OR($D20="",$G20=""),0,$D20*$G20) -> 0 | I20: nº deste tipo ÷ total do contrato, na aba 03 · preço do item na aba 02
B21: Troca de ramal de esgoto | C21: =COUNTIFS(CAD_TIPO,$B21,CAD_CONTR,"BERTIOGA") -> 0 | D21: =IF(COUNTIFS(CAD_CONTR,"BERTIOGA")=0,"",C21/COUNTIFS(CAD_CONTR,"BERTIOGA")) -> 0 | F21: =IFERROR(IF($E21="","",VLOOKUP($E21,PRE_TAB,5,FALSE)),"CÓDIGO NÃO ENCONTRADO") | G21: =IFERROR(IF($E21="","",VLOOKUP($E21,PRE_TAB,8,FALSE)),"") | H21: =IF(OR($D21="",$G21=""),0,$D21*$G21) -> 0 | I21: nº deste tipo ÷ total do contrato, na aba 03 · preço do item na aba 02
B22: Desobstrução de rede de esgoto | C22: =COUNTIFS(CAD_TIPO,$B22,CAD_CONTR,"BERTIOGA") -> 0 | D22: =IF(COUNTIFS(CAD_CONTR,"BERTIOGA")=0,"",C22/COUNTIFS(CAD_CONTR,"BERTIOGA")) -> 0 | F22: =IFERROR(IF($E22="","",VLOOKUP($E22,PRE_TAB,5,FALSE)),"CÓDIGO NÃO ENCONTRADO") | G22: =IFERROR(IF($E22="","",VLOOKUP($E22,PRE_TAB,8,FALSE)),"") | H22: =IF(OR($D22="",$G22=""),0,$D22*$G22) -> 0 | I22: nº deste tipo ÷ total do contrato, na aba 03 · preço do item na aba 02
B23: Conserto de rede de esgoto | C23: =COUNTIFS(CAD_TIPO,$B23,CAD_CONTR,"BERTIOGA") -> 0 | D23: =IF(COUNTIFS(CAD_CONTR,"BERTIOGA")=0,"",C23/COUNTIFS(CAD_CONTR,"BERTIOGA")) -> 0 | F23: =IFERROR(IF($E23="","",VLOOKUP($E23,PRE_TAB,5,FALSE)),"CÓDIGO NÃO ENCONTRADO") | G23: =IFERROR(IF($E23="","",VLOOKUP($E23,PRE_TAB,8,FALSE)),"") | H23: =IF(OR($D23="",$G23=""),0,$D23*$G23) -> 0 | I23: nº deste tipo ÷ total do contrato, na aba 03 · preço do item na aba 02
B24: Construção de PI / PV | C24: =COUNTIFS(CAD_TIPO,$B24,CAD_CONTR,"BERTIOGA") -> 0 | D24: =IF(COUNTIFS(CAD_CONTR,"BERTIOGA")=0,"",C24/COUNTIFS(CAD_CONTR,"BERTIOGA")) -> 0 | F24: =IFERROR(IF($E24="","",VLOOKUP($E24,PRE_TAB,5,FALSE)),"CÓDIGO NÃO ENCONTRADO") | G24: =IFERROR(IF($E24="","",VLOOKUP($E24,PRE_TAB,8,FALSE)),"") | H24: =IF(OR($D24="",$G24=""),0,$D24*$G24) -> 0 | I24: nº deste tipo ÷ total do contrato, na aba 03 · preço do item na aba 02
... B30: Outro | C30: =COUNTIFS(CAD_TIPO,$B30,CAD_CONTR,"BERTIOGA") -> 0 | D30: =IF(COUNTIFS(CAD_CONTR,"BERTIOGA")=0,"",C30/COUNTIFS(CAD_CONTR,"BERTIOGA")) -> 0 | F30: =IFERROR(IF($E30="","",VLOOKUP($E30,PRE_TAB,5,FALSE)),"CÓDIGO NÃO ENCONTRADO") | G30: =IFERROR(IF($E30="","",VLOOKUP($E30,PRE_TAB,8,FALSE)),"") | H30: =IF(OR($D30="",$G30=""),0,$D30*$G30) -> 0 | I30: nº deste tipo ÷ total do contrato, na aba 03 · preço do item na aba 02
B31: TOTAL DA CARTEIRA | C31: =SUM(C6:C30) -> 28 | D31: =SUM(D6:D30) -> 0.51851852 | H31: =SUM(H6:H30) -> 317.49648
B32: Ticket apurado da carteira | H32: =H31 -> 317.49648 | I32: Soma das contribuições: % do mix × preço do item. Fica zero enquanto os códigos de preço não forem preenchidos.
B33: Ticket de referência | H33: 881.2 | I33: Média adotada no Fluxo Trimestral Obra — aba PREMISSAS do FLUXO_CAIXA v4
B34: TICKET ADOTADO | H34: =IF(H32>0,H32,H33) -> 317.49648 | I34: Usa o apurado assim que houver códigos preenchidos; até lá, o de referência. É este valor que alimenta a aba 01.
A36: MIX DA CARTEIRA — SANTOS
B37: TIPO DE SERVIÇO | C37: Nº NA CARTEIRA | D37: % DO MIX | E37: CÓD. PREÇO (CHAVE) | F37: DESCRIÇÃO DO ITEM | G37: PREÇO UNIT. | H37: CONTRIBUIÇÃO | I37: MEMÓRIA DE CÁLCULO
B38: Vazamento de água não visível — rede | C38: =COUNTIFS(CAD_TIPO,$B38,CAD_CONTR,"SANTOS") -> 0 | D38: =IF(COUNTIFS(CAD_CONTR,"SANTOS")=0,"",C38/COUNTIFS(CAD_CONTR,"SANTOS")) | F38: =IFERROR(IF($E38="","",VLOOKUP($E38,PRE_TAB,5,FALSE)),"CÓDIGO NÃO ENCONTRADO") | G38: =IFERROR(IF($E38="","",VLOOKUP($E38,PRE_TAB,8,FALSE)),"") | H38: =IF(OR($D38="",$G38=""),0,$D38*$G38) -> 0 | I38: nº deste tipo ÷ total do contrato, na aba 03 · preço do item na aba 02
B39: Vazamento de água não visível — ramal | C39: =COUNTIFS(CAD_TIPO,$B39,CAD_CONTR,"SANTOS") -> 0 | D39: =IF(COUNTIFS(CAD_CONTR,"SANTOS")=0,"",C39/COUNTIFS(CAD_CONTR,"SANTOS")) | F39: =IFERROR(IF($E39="","",VLOOKUP($E39,PRE_TAB,5,FALSE)),"CÓDIGO NÃO ENCONTRADO") | G39: =IFERROR(IF($E39="","",VLOOKUP($E39,PRE_TAB,8,FALSE)),"") | H39: =IF(OR($D39="",$G39=""),0,$D39*$G39) -> 0 | I39: nº deste tipo ÷ total do contrato, na aba 03 · preço do item na aba 02
B40: Vazamento de água visível — rede | C40: =COUNTIFS(CAD_TIPO,$B40,CAD_CONTR,"SANTOS") -> 0 | D40: =IF(COUNTIFS(CAD_CONTR,"SANTOS")=0,"",C40/COUNTIFS(CAD_CONTR,"SANTOS")) | F40: =IFERROR(IF($E40="","",VLOOKUP($E40,PRE_TAB,5,FALSE)),"CÓDIGO NÃO ENCONTRADO") | G40: =IFERROR(IF($E40="","",VLOOKUP($E40,PRE_TAB,8,FALSE)),"") | H40: =IF(OR($D40="",$G40=""),0,$D40*$G40) -> 0 | I40: nº deste tipo ÷ total do contrato, na aba 03 · preço do item na aba 02
B41: Vazamento de água visível — ramal | C41: =COUNTIFS(CAD_TIPO,$B41,CAD_CONTR,"SANTOS") -> 0 | D41: =IF(COUNTIFS(CAD_CONTR,"SANTOS")=0,"",C41/COUNTIFS(CAD_CONTR,"SANTOS")) | F41: =IFERROR(IF($E41="","",VLOOKUP($E41,PRE_TAB,5,FALSE)),"CÓDIGO NÃO ENCONTRADO") | G41: =IFERROR(IF($E41="","",VLOOKUP($E41,PRE_TAB,8,FALSE)),"") | H41: =IF(OR($D41="",$G41=""),0,$D41*$G41) -> 0 | I41: nº deste tipo ÷ total do contrato, na aba 03 · preço do item na aba 02
B42: Vazamento pé do cavalete | C42: =COUNTIFS(CAD_TIPO,$B42,CAD_CONTR,"SANTOS") -> 0 | D42: =IF(COUNTIFS(CAD_CONTR,"SANTOS")=0,"",C42/COUNTIFS(CAD_CONTR,"SANTOS")) | F42: =IFERROR(IF($E42="","",VLOOKUP($E42,PRE_TAB,5,FALSE)),"CÓDIGO NÃO ENCONTRADO") | G42: =IFERROR(IF($E42="","",VLOOKUP($E42,PRE_TAB,8,FALSE)),"") | H42: =IF(OR($D42="",$G42=""),0,$D42*$G42) -> 0 | I42: nº deste tipo ÷ total do contrato, na aba 03 · preço do item na aba 02
B43: Vazamento no ferrule | C43: =COUNTIFS(CAD_TIPO,$B43,CAD_CONTR,"SANTOS") -> 0 | D43: =IF(COUNTIFS(CAD_CONTR,"SANTOS")=0,"",C43/COUNTIFS(CAD_CONTR,"SANTOS")) | F43: =IFERROR(IF($E43="","",VLOOKUP($E43,PRE_TAB,5,FALSE)),"CÓDIGO NÃO ENCONTRADO") | G43: =IFERROR(IF($E43="","",VLOOKUP($E43,PRE_TAB,8,FALSE)),"") | H43: =IF(OR($D43="",$G43=""),0,$D43*$G43) -> 0 | I43: nº deste tipo ÷ total do contrato, na aba 03 · preço do item na aba 02
B44: Troca de ramal de água | C44: =COUNTIFS(CAD_TIPO,$B44,CAD_CONTR,"SANTOS") -> 0 | D44: =IF(COUNTIFS(CAD_CONTR,"SANTOS")=0,"",C44/COUNTIFS(CAD_CONTR,"SANTOS")) | F44: =IFERROR(IF($E44="","",VLOOKUP($E44,PRE_TAB,5,FALSE)),"CÓDIGO NÃO ENCONTRADO") | G44: =IFERROR(IF($E44="","",VLOOKUP($E44,PRE_TAB,8,FALSE)),"") | H44: =IF(OR($D44="",$G44=""),0,$D44*$G44) -> 0 | I44: nº deste tipo ÷ total do contrato, na aba 03 · preço do item na aba 02
B45: Troca de cavalete | C45: =COUNTIFS(CAD_TIPO,$B45,CAD_CONTR,"SANTOS") -> 0 | D45: =IF(COUNTIFS(CAD_CONTR,"SANTOS")=0,"",C45/COUNTIFS(CAD_CONTR,"SANTOS")) | F45: =IFERROR(IF($E45="","",VLOOKUP($E45,PRE_TAB,5,FALSE)),"CÓDIGO NÃO ENCONTRADO") | G45: =IFERROR(IF($E45="","",VLOOKUP($E45,PRE_TAB,8,FALSE)),"") | H45: =IF(OR($D45="",$G45=""),0,$D45*$G45) -> 0 | I45: nº deste tipo ÷ total do contrato, na aba 03 · preço do item na aba 02
B46: Execução de ligação de água | C46: =COUNTIFS(CAD_TIPO,$B46,CAD_CONTR,"SANTOS") -> 0 | D46: =IF(COUNTIFS(CAD_CONTR,"SANTOS")=0,"",C46/COUNTIFS(CAD_CONTR,"SANTOS")) | F46: =IFERROR(IF($E46="","",VLOOKUP($E46,PRE_TAB,5,FALSE)),"CÓDIGO NÃO ENCONTRADO") | G46: =IFERROR(IF($E46="","",VLOOKUP($E46,PRE_TAB,8,FALSE)),"") | H46: =IF(OR($D46="",$G46=""),0,$D46*$G46) -> 0 | I46: nº deste tipo ÷ total do contrato, na aba 03 · preço do item na aba 02
B47: Supressão de ligação de água | C47: =COUNTIFS(CAD_TIPO,$B47,CAD_CONTR,"SANTOS") -> 0 | D47: =IF(COUNTIFS(CAD_CONTR,"SANTOS")=0,"",C47/COUNTIFS(CAD_CONTR,"SANTOS")) | F47: =IFERROR(IF($E47="","",VLOOKUP($E47,PRE_TAB,5,FALSE)),"CÓDIGO NÃO ENCONTRADO") | G47: =IFERROR(IF($E47="","",VLOOKUP($E47,PRE_TAB,8,FALSE)),"") | H47: =IF(OR($D47="",$G47=""),0,$D47*$G47) -> 0 | I47: nº deste tipo ÷ total do contrato, na aba 03 · preço do item na aba 02
B48: Religação de água | C48: =COUNTIFS(CAD_TIPO,$B48,CAD_CONTR,"SANTOS") -> 0 | D48: =IF(COUNTIFS(CAD_CONTR,"SANTOS")=0,"",C48/COUNTIFS(CAD_CONTR,"SANTOS")) | F48: =IFERROR(IF($E48="","",VLOOKUP($E48,PRE_TAB,5,FALSE)),"CÓDIGO NÃO ENCONTRADO") | G48: =IFERROR(IF($E48="","",VLOOKUP($E48,PRE_TAB,8,FALSE)),"") | H48: =IF(OR($D48="",$G48=""),0,$D48*$G48) -> 0 | I48: nº deste tipo ÷ total do contrato, na aba 03 · preço do item na aba 02
B49: Substituição de hidrômetro | C49: =COUNTIFS(CAD_TIPO,$B49,CAD_CONTR,"SANTOS") -> 0 | D49: =IF(COUNTIFS(CAD_CONTR,"SANTOS")=0,"",C49/COUNTIFS(CAD_CONTR,"SANTOS")) | F49: =IFERROR(IF($E49="","",VLOOKUP($E49,PRE_TAB,5,FALSE)),"CÓDIGO NÃO ENCONTRADO") | G49: =IFERROR(IF($E49="","",VLOOKUP($E49,PRE_TAB,8,FALSE)),"") | H49: =IF(OR($D49="",$G49=""),0,$D49*$G49) -> 0 | I49: nº deste tipo ÷ total do contrato, na aba 03 · preço do item na aba 02
... B62: Outro | C62: =COUNTIFS(CAD_TIPO,$B62,CAD_CONTR,"SANTOS") -> 0 | D62: =IF(COUNTIFS(CAD_CONTR,"SANTOS")=0,"",C62/COUNTIFS(CAD_CONTR,"SANTOS")) | F62: =IFERROR(IF($E62="","",VLOOKUP($E62,PRE_TAB,5,FALSE)),"CÓDIGO NÃO ENCONTRADO") | G62: =IFERROR(IF($E62="","",VLOOKUP($E62,PRE_TAB,8,FALSE)),"") | H62: =IF(OR($D62="",$G62=""),0,$D62*$G62) -> 0 | I62: nº deste tipo ÷ total do contrato, na aba 03 · preço do item na aba 02
B63: TOTAL DA CARTEIRA | C63: =SUM(C38:C62) -> 0 | D63: =SUM(D38:D62) -> 0 | H63: =SUM(H38:H62) -> 0
B64: Ticket apurado da carteira | H64: =H63 -> 0 | I64: Soma das contribuições: % do mix × preço do item. Fica zero enquanto os códigos de preço não forem preenchidos.
B65: Ticket de referência | H65: 1338.83 | I65: Média ponderada água/esgoto — aba PREMISSAS do FLUXO_CAIXA v4
B66: TICKET ADOTADO | H66: =IF(H64>0,H64,H65) -> 1338.83 | I66: Usa o apurado assim que houver códigos preenchidos; até lá, o de referência. É este valor que alimenta a aba 01.

Sheet 02. TABELA DE PREÇOS
A1: TABELA DE PREÇOS DOS CONTRATOS — BERTIOGA/GUARUJÁ E SANTOS | O1: COMO PREENCHER ESTA ABA
A2: 511 itens contratados — 212 de Bertioga/Guarujá e 299 de Santos. Aba de consulta: ninguém edita, preço só muda em reajuste oficial. A CHAVE (coluna A) = prefixo do contrato + nº do preço, e é ela que a aba 09 usa para trazer descrição, unidade e preço — por isso um código SAN- não vale numa OS de Bertioga. Busque por palavra na célula amarela; o dicionário dos códigos está no rodapé da aba. | J2: BUSCAR: | L2: ◀ digite parte da descrição ou o nº do preço e filtre a coluna BUSCA por "1" | O2: Aba de consulta. NÃO digita nada.
O3: São os 511 preços que a SABESP paga.
A4: CHAVE | B4: CONTRATO | C4: GRUPO | D4: ITEM SABESP | E4: DESCRIÇÃO DO SERVIÇO | F4: N. PREÇO | G4: UN | H4: R$ UNIT. | I4: BUSCA | O4: Só muda em reajuste oficial do contrato.
A5: BER-72000033 | B5: BERTIOGA | C5: EXECUÇÃO DE LIGAÇÃO DE ÁGUA SUCESSIVA | E5: LAG PA SUCES S/REP SF | F5: 72000033 | G5: un | H5: 60.95 | I5: =IF($K$2="","",IF(ISNUMBER(SEARCH($K$2,$E5&$F5)),1,"")) | O5: PARA ACHAR UM SERVIÇO:
A6: BER-72000034 | B6: BERTIOGA | C6: EXECUÇÃO DE LIGAÇÃO DE ÁGUA SUCESSIVA | E6: LAG TA SUCES S/REP SF | F6: 72000034 | G6: un | H6: 151.81 | I6: =IF($K$2="","",IF(ISNUMBER(SEARCH($K$2,$E6&$F6)),1,"")) | O6: 1) digite parte do nome na célula amarela (J2)
A7: BER-72000035 | B7: BERTIOGA | C7: EXECUÇÃO DE LIGAÇÃO DE ÁGUA SUCESSIVA | E7: LAG EX SUCES S/REP SF | F7: 72000035 | G7: un | H7: 202.39 | I7: =IF($K$2="","",IF(ISNUMBER(SEARCH($K$2,$E7&$F7)),1,"")) | O7: 2) filtre a coluna BUSCA por "1"
A8: BER-72000036 | B8: BERTIOGA | C8: EXECUÇÃO DE LIGAÇÃO DE ÁGUA SUCESSIVA | E8: LAG TO SUCES S/REP SF | F8: 72000036 | G8: un | H8: 282.67 | I8: =IF($K$2="","",IF(ISNUMBER(SEARCH($K$2,$E8&$F8)),1,"")) | O8: A CHAVE da coluna A é o que as outras abas usam.
A9: BER-72000037 | B9: BERTIOGA | C9: EXECUÇÃO DE LIGAÇÃO DE ÁGUA SUCESSIVA | E9: LAG PO SUCES S/REP SF | F9: 72000037 | G9: un | H9: 338.9 | I9: =IF($K$2="","",IF(ISNUMBER(SEARCH($K$2,$E9&$F9)),1,""))
A10: BER-72000229 | B10: BERTIOGA | C10: EXECUÇÃO DE LIGAÇÃO DE ÁGUA SUCESSIVA | E10: ADC INST CV SF | F10: 72000229 | G10: un | H10: 193.79 | I10: =IF($K$2="","",IF(ISNUMBER(SEARCH($K$2,$E10&$F10)),1,""))
A11: BER-72000057 | B11: BERTIOGA | C11: EXECUÇÃO DE LIGAÇÃO DE ÁGUA SUCESSIVA | E11: LAG PA SUCES S/REP | F11: 72000057 | G11: un | H11: 436.78 | I11: =IF($K$2="","",IF(ISNUMBER(SEARCH($K$2,$E11&$F11)),1,""))
A12: BER-72000058 | B12: BERTIOGA | C12: EXECUÇÃO DE LIGAÇÃO DE ÁGUA SUCESSIVA | E12: LAG TA SUCES S/REP | F12: 72000058 | G12: un | H12: 500.87 | I12: =IF($K$2="","",IF(ISNUMBER(SEARCH($K$2,$E12&$F12)),1,""))
A13: BER-72000059 | B13: BERTIOGA | C13: EXECUÇÃO DE LIGAÇÃO DE ÁGUA SUCESSIVA | E13: LAG EX SUCES S/REP | F13: 72000059 | G13: un | H13: 637.5 | I13: =IF($K$2="","",IF(ISNUMBER(SEARCH($K$2,$E13&$F13)),1,""))
A14: BER-72000060 | B14: BERTIOGA | C14: EXECUÇÃO DE LIGAÇÃO DE ÁGUA SUCESSIVA | E14: LAG TO SUCES S/REP | F14: 72000060 | G14: un | H14: 654.59 | I14: =IF($K$2="","",IF(ISNUMBER(SEARCH($K$2,$E14&$F14)),1,""))
A15: BER-72000061 | B15: BERTIOGA | C15: EXECUÇÃO DE LIGAÇÃO DE ÁGUA SUCESSIVA | E15: LAG PO SUCES S/REP | F15: 72000061 | G15: un | H15: 704.59 | I15: =IF($K$2="","",IF(ISNUMBER(SEARCH($K$2,$E15&$F15)),1,""))
A16: BER-72000224 | B16: BERTIOGA | C16: EXECUÇÃO DE LIGAÇÃO DE ÁGUA SUCESSIVA | E16: ADC INST CV | F16: 72000224 | G16: un | H16: 311.39 | I16: =IF($K$2="","",IF(ISNUMBER(SEARCH($K$2,$E16&$F16)),1,""))
A17: BER-72000101 | B17: BERTIOGA | C17: EXECUÇÃO DE LIGAÇÃO DE ÁGUA SUCESSIVA | E17: LRP CIM LAG SUCES | F17: 72000101 | G17: un | H17: 139.9 | I17: =IF($K$2="","",IF(ISNUMBER(SEARCH($K$2,$E17&$F17)),1,""))
A18: BER-72000102 | B18: BERTIOGA | C18: EXECUÇÃO DE LIGAÇÃO DE ÁGUA SUCESSIVA | E18: LRP ESP LAG SUCES | F18: 72000102 | G18: un | H18: 242.97 | I18: =IF($K$2="","",IF(ISNUMBER(SEARCH($K$2,$E18&$F18)),1,""))
A19: BER-72001180 | B19: BERTIOGA | C19: EXECUÇÃO DE LIGAÇÃO DE ÁGUA SUCESSIVA | E19: LPB TA LAG SUCES COMPX C | F19: 72001180 | G19: un | H19: 41.96 | I19: =IF($K$2="","",IF(ISNUMBER(SEARCH($K$2,$E19&$F19)),1,""))
A20: BER-72001082 | B20: BERTIOGA | C20: EXECUÇÃO DE LIGAÇÃO DE ÁGUA SUCESSIVA | E20: LPB EX LAG SUCES COMPX C | F20: 72001082 | G20: un | H20: 78.11 | I20: =IF($K$2="","",IF(ISNUMBER(SEARCH($K$2,$E20&$F20)),1,""))
... A216: BER-72001222 | B216: BERTIOGA | C216: EXECUÇÃO DE TROCA DE LIGAÇÃO DE ESGOTO | E216: LPB DE 3 A 4M TO TRE COMPX C | F216: 72001222 | G216: un | H216: 1365.8 | I216: =IF($K$2="","",IF(ISNUMBER(SEARCH($K$2,$E216&$F216)),1,""))
A217: SAN-72000759 | B217: SANTOS | C217: SERVIÇOS DE ESGOTO | D217: 2090501 | E217: CONST PI ATE 2M S/REP | F217: 72000759 | G217: un | H217: 1597.75 | I217: =IF($K$2="","",IF(ISNUMBER(SEARCH($K$2,$E217&$F217)),1,""))
A218: SAN-72000759 | B218: SANTOS | C218: SERVIÇOS DE ESGOTO | D218: 2220501 | E218: CONST PI ATE 2M S/REP | F218: 72000759 | G218: un | H218: 1597.75 | I218: =IF($K$2="","",IF(ISNUMBER(SEARCH($K$2,$E218&$F218)),1,""))
A219: SAN-72000760 | B219: SANTOS | C219: SERVIÇOS DE ESGOTO | D219: 2090502 | E219: CONST PI DE 2 A 3M S/REP | F219: 72000760 | G219: un | H219: 1762.75 | I219: =IF($K$2="","",IF(ISNUMBER(SEARCH($K$2,$E219&$F219)),1,""))
A220: SAN-72000760 | B220: SANTOS | C220: SERVIÇOS DE ESGOTO | D220: 2220502 | E220: CONST PI DE 2 A 3M S/REP | F220: 72000760 | G220: un | H220: 1762.75 | I220: =IF($K$2="","",IF(ISNUMBER(SEARCH($K$2,$E220&$F220)),1,""))
A221: SAN-72000748 | B221: SANTOS | C221: SERVIÇOS DE ESGOTO | D221: 2090508 | E221: CPV DIAM = 1,20M - DE 2 A 3M - S/REP | F221: 72000748 | G221: un | H221: 2992.75 | I221: =IF($K$2="","",IF(ISNUMBER(SEARCH($K$2,$E221&$F221)),1,""))
A222: SAN-72000748 | B222: SANTOS | C222: SERVIÇOS DE ESGOTO | D222: 2220508 | E222: CPV DIAM = 1,20M - DE 2 A 3M - S/REP | F222: 72000748 | G222: un | H222: 2992.75 | I222: =IF($K$2="","",IF(ISNUMBER(SEARCH($K$2,$E222&$F222)),1,""))
A223: SAN-72000749 | B223: SANTOS | C223: SERVIÇOS DE ESGOTO | D223: 2090509 | E223: CPV DIAM = 1,20M - DE 3 A 4M - S/REP | F223: 72000749 | G223: un | H223: 3712.75 | I223: =IF($K$2="","",IF(ISNUMBER(SEARCH($K$2,$E223&$F223)),1,""))
A224: SAN-72000749 | B224: SANTOS | C224: SERVIÇOS DE ESGOTO | D224: 2220509 | E224: CPV DIAM = 1,20M - DE 3 A 4M - S/REP | F224: 72000749 | G224: un | H224: 3712.75 | I224: =IF($K$2="","",IF(ISNUMBER(SEARCH($K$2,$E224&$F224)),1,""))
A225: SAN-72000750 | B225: SANTOS | C225: SERVIÇOS DE ESGOTO | D225: 2090510 | E225: CPV DIAM = 1,20M - DE 4 A 5M - S/REP | F225: 72000750 | G225: un | H225: 4297.75 | I225: =IF($K$2="","",IF(ISNUMBER(SEARCH($K$2,$E225&$F225)),1,""))
A226: SAN-72000750 | B226: SANTOS | C226: SERVIÇOS DE ESGOTO | D226: 2220510 | E226: CPV DIAM = 1,20M - DE 4 A 5M - S/REP | F226: 72000750 | G226: un | H226: 4297.75 | I226: =IF($K$2="","",IF(ISNUMBER(SEARCH($K$2,$E226&$F226)),1,""))
A227: SAN-72000747 | B227: SANTOS | C227: SERVIÇOS DE ESGOTO | D227: 2090507 | E227: CPV DIAM = 1,20M - PROF ATE 2M S/REP | F227: 72000747 | G227: un | H227: 2097.75 | I227: =IF($K$2="","",IF(ISNUMBER(SEARCH($K$2,$E227&$F227)),1,""))
A228: SAN-72000747 | B228: SANTOS | C228: SERVIÇOS DE ESGOTO | D228: 2220507 | E228: CPV DIAM = 1,20M - PROF ATE 2M S/REP | F228: 72000747 | G228: un | H228: 2097.75 | I228: =IF($K$2="","",IF(ISNUMBER(SEARCH($K$2,$E228&$F228)),1,""))
... A515: SAN-72000238 | B515: SANTOS | C515: SERVIÇOS DE ÁGUA | D515: 1030301 | E515: SUPR TMD AG S/REP SF | F515: 72000238 | G515: un | H515: 427.95 | I515: =IF($K$2="","",IF(ISNUMBER(SEARCH($K$2,$E515&$F515)),1,""))
A518: COMO ESCOLHER O ITEM — DICIONÁRIO DOS CÓDIGOS E O QUE CADA CONTRATO TEM
A519: SERVIÇO DE CAMPO | C519: ONDE PROCURAR NA TABELA | E519: COMO ESCOLHER O ITEM CERTO | G519: EXISTE EM
A520: Nova ligação de água | C520: Grupos EXECUÇÃO DE LIGAÇÃO DE ÁGUA AVULSA e SUCESSIVA — prefixo LAG | E520: AVULSA = endereço isolado. SUCESSIVA = várias na mesma rua no mesmo dia, e custa menos. Confira o diâmetro e o tipo de piso na descrição. | G520: Os dois contratos
A521: Troca de ramal de água | C521: EXECUÇÃO DE TROCA DE LIGAÇÃO DE ÁGUA — prefixo TRA | E521: CORR = corretiva (o vazamento já aconteceu). PREV = preventiva (programada). É este o item de vazamento no ramal: a SABESP paga a troca, não o diagnóstico. | G521: Os dois contratos
A522: Serviço no cavalete | C522: EXECUÇÃO DE SERVIÇOS GERAIS EM CAVALETE — TCV, SUBST CV, ADC TCV | E522: TCV = troca do cavalete. ADC = adicional por cavalete a mais no mesmo endereço. SUBST CV POR UMA = troca por caixa padrão. | G522: Os dois contratos
A523: Ligação e troca de esgoto | C523: LESG (ligação) e TRE (troca de ramal), avulsa ou sucessiva | E523: O preço muda por faixa de profundidade (até 2 m, de 2 a 3 m, de 3 a 4 m) e pelo material. Confira a profundidade anotada na OS. | G523: Os dois contratos
A524: Supressão e religação | C524: SUPR e RELIG, dentro do grupo SERVIÇOS DE ÁGUA | E524: A tabela de Bertioga/Guarujá não tem nenhum item de supressão nem de religação. Se aparecer esse serviço em Bertioga, pare e trate com o consórcio antes de executar. | G524: SÓ SANTOS
A525: Reposição de pavimento | C525: LRP e LPB, dentro do mesmo grupo do serviço | E525: LRP CIM = cimento, LRP ESP = especial (asfalto), LPB = lastro/base por complexidade. É SEMPRE item separado, somado ao serviço. | G525: Os dois contratos
A526: Adicionais | C526: Prefixo ADC | E526: Segundo cavalete no mesmo endereço, instalação de caixa, substituição de TMD. Item pequeno e o mais esquecido na medição. | G526: Os dois contratos
A528: O QUE A TABELA NÃO TEM — E POR QUÊ
A529: Não existe item de preço para vazamento de rede, conserto de rede, ferrule, hidrômetro, desobstrução de esgoto, travessia, remanejamento nem vistoria — em nenhum dos dois contratos. A SABESP não paga pelo diagnóstico ("vazamento"), paga pela ação executada: ligação, troca de ramal, cavalete, supressão ou religação. Serviço que não se encaixa em nenhuma dessas ações não tem código: trate com o consórcio antes de executar, sob pena de fazer de graça.
A531: ATENÇÃO — antes da primeira medição, confirme com o consórcio qual sufixo se aplica ao seu escopo: S/REP (sem reposição de pavimento) × com reposição, e SF (sem fornecimento de material) × com fornecimento. A diferença entre um e outro chega a 40% do preço do item.

Sheet 03. CADASTRO DE SERVIÇOS
A1: CADASTRO DE SERVIÇOS — CARTEIRA DE DEMANDAS RECEBIDAS DA SABESP | AA1: COMO PREENCHER ESTA ABA
A2: Porta de entrada de TODO serviço. Nada é programado, executado ou medido sem estar aqui. AZUL = digite · PRETO = fórmula (não apague). | AA2: Chegou pedido da SABESP? Abre 1 linha aqui. SEMPRE.
AA3: Nada é programado nem medido sem estar aqui.
A4: ID | B4: CONTRATO | C4: Nº OS SABESP | D4: DATA DA SOLICITAÇÃO | E4: PRAZO (dias) | F4: DATA LIMITE | G4: PRIORIDADE | H4: TIPO DE SERVIÇO | I4: ENDEREÇO | J4: Nº | K4: BAIRRO | L4: CIDADE | M4: PONTO DE REFERÊNCIA | N4: PAVIMENTO | O4: DESCRIÇÃO DA SOLICITAÇÃO | P4: EQUIPE DESIGNADA | Q4: DATA PROGRAMADA | R4: DATA DE EXECUÇÃO | S4: STATUS | T4: DIAS EM ABERTO | U4: SITUAÇÃO DO PRAZO | V4: VALOR MEDIDO | W4: TRATATIVA MANUAL | X4: OBSERVAÇÃO | AA4: B = BERTIOGA ou SANTOS (menu)
A5: =IF($B5="","",LEFT($B5,3)&"-"&TEXT(ROW()-4,"0000")) -> BER-0001 | B5: BERTIOGA | D5: 46267 | E5: 5 | F5: =IF($D5="","",$D5+IF($E5="",'01. CONFIGURAÇÕES'!$C$22,$E5)) -> 46272 | G5: URGENTE | H5: Vazamento de água não visível — rede | I5: Alameda Maua | J5: 225 | K5: Boracéia | L5: Bertioga | M5: Sede | O5: Vazamento de água não visível rede | P5: =IFERROR(IF($A5="","",IF(COUNTIFS(OS_ID,$A5)>0,INDEX(OS_EQUIPE,MATCH($A5,OS_ID,0)),IF(COUNTIFS(PROG_ID,$A5)>0,INDEX(PROG_EQUIPE,MATCH($A5,PROG_ID,0)),""))),"") -> 0 | Q5: =IF($A5="","",IFERROR(IF(INDEX(PROG_DATA,MATCH($A5,PROG_ID,0))=0,"",INDEX(PROG_DATA,MATCH($A5,PROG_ID,0))),"")) -> 46273 | R5: =IF($A5="","",IFERROR(IF(INDEX(OS_FIM,MATCH($A5,OS_ID,0))=0,"",INDEX(OS_FIM,MATCH($A5,OS_ID,0))),"")) -> 46273 | S5: =IF($A5="","",IF($W5<>"",$W5,IF($V5>0,"MEDIDO",IF($R5<>"","EXECUTADO",IF(COUNTIFS(OS_ID,$A5)>0,"EM EXECUÇÃO",IF($Q5<>"","PROGRAMADO","CADASTRADO")))))) -> EXECUTADO | T5: =IF($A5="","",IF($R5<>"",$R5-$D5,TODAY()-$D5)) -> 6 | U5: =IF(OR($A5="",$F5=""),"",IF($R5<>"",IF($R5<=$F5,"NO PRAZO","FORA DO PRAZO"),IF(TODAY()>$F5,"VENCIDO",IF($F5-TODAY()<='01. CONFIGURAÇÕES'!$C$23,"VENCE EM BREVE","EM DIA")))) -> FORA DO PRAZO | V5: =IF($A5="","",SUMIFS(MED_VLR,MED_ID,$A5)) -> 0 | AA5: C = nº da OS que a SABESP passou
A6: =IF($B6="","",LEFT($B6,3)&"-"&TEXT(ROW()-4,"0000")) -> BER-0002 | B6: BERTIOGA | D6: 46267 | E6: 5 | F6: =IF($D6="","",$D6+IF($E6="",'01. CONFIGURAÇÕES'!$C$22,$E6)) -> 46272 | G6: URGENTE | H6: Vazamento de água não visível — rede | I6: Rua Francisco Chaves | J6: 2267 | K6: Jardim Vicente de Carvalho | L6: Bertioga | M6: B | O6: Vazamento de água não visível rede | P6: =IFERROR(IF($A6="","",IF(COUNTIFS(OS_ID,$A6)>0,INDEX(OS_EQUIPE,MATCH($A6,OS_ID,0)),IF(COUNTIFS(PROG_ID,$A6)>0,INDEX(PROG_EQUIPE,MATCH($A6,PROG_ID,0)),""))),"") -> 0 | Q6: =IF($A6="","",IFERROR(IF(INDEX(PROG_DATA,MATCH($A6,PROG_ID,0))=0,"",INDEX(PROG_DATA,MATCH($A6,PROG_ID,0))),"")) -> 46268 | R6: =IF($A6="","",IFERROR(IF(INDEX(OS_FIM,MATCH($A6,OS_ID,0))=0,"",INDEX(OS_FIM,MATCH($A6,OS_ID,0))),"")) -> 46268 | S6: =IF($A6="","",IF($W6<>"",$W6,IF($V6>0,"MEDIDO",IF($R6<>"","EXECUTADO",IF(COUNTIFS(OS_ID,$A6)>0,"EM EXECUÇÃO",IF($Q6<>"","PROGRAMADO","CADASTRADO")))))) -> MEDIDO | T6: =IF($A6="","",IF($R6<>"",$R6-$D6,TODAY()-$D6)) -> 1 | U6: =IF(OR($A6="",$F6=""),"",IF($R6<>"",IF($R6<=$F6,"NO PRAZO","FORA DO PRAZO"),IF(TODAY()>$F6,"VENCIDO",IF($F6-TODAY()<='01. CONFIGURAÇÕES'!$C$23,"VENCE EM BREVE","EM DIA")))) -> NO PRAZO | V6: =IF($A6="","",SUMIFS(MED_VLR,MED_ID,$A6)) -> 924.97 | AA6: D = data em que a SABESP pediu
A7: =IF($B7="","",LEFT($B7,3)&"-"&TEXT(ROW()-4,"0000")) -> BER-0003 | B7: BERTIOGA | D7: 46267 | E7: 5 | F7: =IF($D7="","",$D7+IF($E7="",'01. CONFIGURAÇÕES'!$C$22,$E7)) -> 46272 | G7: NORMAL | H7: Troca de ramal de água | I7: Alameda Agapanthos | J7: 66 | K7: Boracéia | L7: Bertioga | M7: L.10 Q.G | O7: Trocar ramal de água - vaz não visível | P7: =IFERROR(IF($A7="","",IF(COUNTIFS(OS_ID,$A7)>0,INDEX(OS_EQUIPE,MATCH($A7,OS_ID,0)),IF(COUNTIFS(PROG_ID,$A7)>0,INDEX(PROG_EQUIPE,MATCH($A7,PROG_ID,0)),""))),"") -> 0 | Q7: =IF($A7="","",IFERROR(IF(INDEX(PROG_DATA,MATCH($A7,PROG_ID,0))=0,"",INDEX(PROG_DATA,MATCH($A7,PROG_ID,0))),"")) -> 46268 | R7: =IF($A7="","",IFERROR(IF(INDEX(OS_FIM,MATCH($A7,OS_ID,0))=0,"",INDEX(OS_FIM,MATCH($A7,OS_ID,0))),"")) -> 46268 | S7: =IF($A7="","",IF($W7<>"",$W7,IF($V7>0,"MEDIDO",IF($R7<>"","EXECUTADO",IF(COUNTIFS(OS_ID,$A7)>0,"EM EXECUÇÃO",IF($Q7<>"","PROGRAMADO","CADASTRADO")))))) -> MEDIDO | T7: =IF($A7="","",IF($R7<>"",$R7-$D7,TODAY()-$D7)) -> 1 | U7: =IF(OR($A7="",$F7=""),"",IF($R7<>"",IF($R7<=$F7,"NO PRAZO","FORA DO PRAZO"),IF(TODAY()>$F7,"VENCIDO",IF($F7-TODAY()<='01. CONFIGURAÇÕES'!$C$23,"VENCE EM BREVE","EM DIA")))) -> NO PRAZO | V7: =IF($A7="","",SUMIFS(MED_VLR,MED_ID,$A7)) -> 785.07 | AA7: E = prazo em dias (5 se não falaram nada)
A8: =IF($B8="","",LEFT($B8,3)&"-"&TEXT(ROW()-4,"0000")) -> BER-0004 | B8: BERTIOGA | D8: 46267 | E8: 5 | F8: =IF($D8="","",$D8+IF($E8="",'01. CONFIGURAÇÕES'!$C$22,$E8)) -> 46272 | G8: URGENTE | H8: Vazamento de água não visível — ramal | I8: Alameda Paranapiacaba | J8: 600 | K8: Boracéia | L8: Bertioga | M8: Q.23 L.7 | O8: Vazamento de água não visível ramal | P8: =IFERROR(IF($A8="","",IF(COUNTIFS(OS_ID,$A8)>0,INDEX(OS_EQUIPE,MATCH($A8,OS_ID,0)),IF(COUNTIFS(PROG_ID,$A8)>0,INDEX(PROG_EQUIPE,MATCH($A8,PROG_ID,0)),""))),"") -> 0 | Q8: =IF($A8="","",IFERROR(IF(INDEX(PROG_DATA,MATCH($A8,PROG_ID,0))=0,"",INDEX(PROG_DATA,MATCH($A8,PROG_ID,0))),"")) -> 46268 | R8: =IF($A8="","",IFERROR(IF(INDEX(OS_FIM,MATCH($A8,OS_ID,0))=0,"",INDEX(OS_FIM,MATCH($A8,OS_ID,0))),"")) -> 46268 | S8: =IF($A8="","",IF($W8<>"",$W8,IF($V8>0,"MEDIDO",IF($R8<>"","EXECUTADO",IF(COUNTIFS(OS_ID,$A8)>0,"EM EXECUÇÃO",IF($Q8<>"","PROGRAMADO","CADASTRADO")))))) -> MEDIDO | T8: =IF($A8="","",IF($R8<>"",$R8-$D8,TODAY()-$D8)) -> 1 | U8: =IF(OR($A8="",$F8=""),"",IF($R8<>"",IF($R8<=$F8,"NO PRAZO","FORA DO PRAZO"),IF(TODAY()>$F8,"VENCIDO",IF($F8-TODAY()<='01. CONFIGURAÇÕES'!$C$23,"VENCE EM BREVE","EM DIA")))) -> NO PRAZO | V8: =IF($A8="","",SUMIFS(MED_VLR,MED_ID,$A8)) -> 785.07 | X8: Foi localizado um gato na mangueira da Sabesp, porem foi retirado | AA8: G = URGENTE ou NORMAL (menu)
A9: =IF($B9="","",LEFT($B9,3)&"-"&TEXT(ROW()-4,"0000")) -> BER-0005 | B9: BERTIOGA | D9: 46267 | E9: 5 | F9: =IF($D9="","",$D9+IF($E9="",'01. CONFIGURAÇÕES'!$C$22,$E9)) -> 46272 | G9: URGENTE | H9: Vazamento de água não visível — ramal | I9: Alameda Rio Grande da Serra | J9: 455 | K9: Boracéia | L9: Bertioga | M9: ANT N.687 | O9: Vazamento de água não visível ramal | P9: =IFERROR(IF($A9="","",IF(COUNTIFS(OS_ID,$A9)>0,INDEX(OS_EQUIPE,MATCH($A9,OS_ID,0)),IF(COUNTIFS(PROG_ID,$A9)>0,INDEX(PROG_EQUIPE,MATCH($A9,PROG_ID,0)),""))),"") -> 0 | Q9: =IF($A9="","",IFERROR(IF(INDEX(PROG_DATA,MATCH($A9,PROG_ID,0))=0,"",INDEX(PROG_DATA,MATCH($A9,PROG_ID,0))),"")) -> 46268 | R9: =IF($A9="","",IFERROR(IF(INDEX(OS_FIM,MATCH($A9,OS_ID,0))=0,"",INDEX(OS_FIM,MATCH($A9,OS_ID,0))),"")) -> 46268 | S9: =IF($A9="","",IF($W9<>"",$W9,IF($V9>0,"MEDIDO",IF($R9<>"","EXECUTADO",IF(COUNTIFS(OS_ID,$A9)>0,"EM EXECUÇÃO",IF($Q9<>"","PROGRAMADO","CADASTRADO")))))) -> MEDIDO | T9: =IF($A9="","",IF($R9<>"",$R9-$D9,TODAY()-$D9)) -> 1 | U9: =IF(OR($A9="",$F9=""),"",IF($R9<>"",IF($R9<=$F9,"NO PRAZO","FORA DO PRAZO"),IF(TODAY()>$F9,"VENCIDO",IF($F9-TODAY()<='01. CONFIGURAÇÕES'!$C$23,"VENCE EM BREVE","EM DIA")))) -> NO PRAZO | V9: =IF($A9="","",SUMIFS(MED_VLR,MED_ID,$A9)) -> 1086.54 | AA9: H = tipo de serviço (menu)
A10: =IF($B10="","",LEFT($B10,3)&"-"&TEXT(ROW()-4,"0000")) -> BER-0006 | B10: BERTIOGA | D10: 46267 | E10: 5 | F10: =IF($D10="","",$D10+IF($E10="",'01. CONFIGURAÇÕES'!$C$22,$E10)) -> 46272 | G10: NORMAL | H10: Troca de ramal de água | I10: Rua Prolongada Oswaldo Cruz | J10: 27 | K10: Jardim Vicente de Carvalho | L10: Bertioga | M10: Casa 2 | O10: Trocar ramal de água - vaz não visível | P10: =IFERROR(IF($A10="","",IF(COUNTIFS(OS_ID,$A10)>0,INDEX(OS_EQUIPE,MATCH($A10,OS_ID,0)),IF(COUNTIFS(PROG_ID,$A10)>0,INDEX(PROG_EQUIPE,MATCH($A10,PROG_ID,0)),""))),"") -> 0 | Q10: =IF($A10="","",IFERROR(IF(INDEX(PROG_DATA,MATCH($A10,PROG_ID,0))=0,"",INDEX(PROG_DATA,MATCH($A10,PROG_ID,0))),"")) -> 46268 | R10: =IF($A10="","",IFERROR(IF(INDEX(OS_FIM,MATCH($A10,OS_ID,0))=0,"",INDEX(OS_FIM,MATCH($A10,OS_ID,0))),"")) -> 46268 | S10: =IF($A10="","",IF($W10<>"",$W10,IF($V10>0,"MEDIDO",IF($R10<>"","EXECUTADO",IF(COUNTIFS(OS_ID,$A10)>0,"EM EXECUÇÃO",IF($Q10<>"","PROGRAMADO","CADASTRADO")))))) -> MEDIDO | T10: =IF($A10="","",IF($R10<>"",$R10-$D10,TODAY()-$D10)) -> 1 | U10: =IF(OR($A10="",$F10=""),"",IF($R10<>"",IF($R10<=$F10,"NO PRAZO","FORA DO PRAZO"),IF(TODAY()>$F10,"VENCIDO",IF($F10-TODAY()<='01. CONFIGURAÇÕES'!$C$23,"VENCE EM BREVE","EM DIA")))) -> NO PRAZO | V10: =IF($A10="","",SUMIFS(MED_VLR,MED_ID,$A10)) -> 924.97 | AA10: I = rua J = número K = bairro (menu)
A11: =IF($B11="","",LEFT($B11,3)&"-"&TEXT(ROW()-4,"0000")) -> BER-0007 | B11: BERTIOGA | D11: 46267 | E11: 5 | F11: =IF($D11="","",$D11+IF($E11="",'01. CONFIGURAÇÕES'!$C$22,$E11)) -> 46272 | G11: NORMAL | H11: Troca de ramal de água | I11: Rua Prolongada Oswaldo Cruz | J11: 391 | K11: Jardim Vicente de Carvalho | L11: Bertioga | M11: Q.F L.5 | O11: Trocar ramal de água - vaz não visível | P11: =IFERROR(IF($A11="","",IF(COUNTIFS(OS_ID,$A11)>0,INDEX(OS_EQUIPE,MATCH($A11,OS_ID,0)),IF(COUNTIFS(PROG_ID,$A11)>0,INDEX(PROG_EQUIPE,MATCH($A11,PROG_ID,0)),""))),"") -> 0 | Q11: =IF($A11="","",IFERROR(IF(INDEX(PROG_DATA,MATCH($A11,PROG_ID,0))=0,"",INDEX(PROG_DATA,MATCH($A11,PROG_ID,0))),"")) -> 46267 | R11: =IF($A11="","",IFERROR(IF(INDEX(OS_FIM,MATCH($A11,OS_ID,0))=0,"",INDEX(OS_FIM,MATCH($A11,OS_ID,0))),"")) -> 46268 | S11: =IF($A11="","",IF($W11<>"",$W11,IF($V11>0,"MEDIDO",IF($R11<>"","EXECUTADO",IF(COUNTIFS(OS_ID,$A11)>0,"EM EXECUÇÃO",IF($Q11<>"","PROGRAMADO","CADASTRADO")))))) -> MEDIDO | T11: =IF($A11="","",IF($R11<>"",$R11-$D11,TODAY()-$D11)) -> 1 | U11: =IF(OR($A11="",$F11=""),"",IF($R11<>"",IF($R11<=$F11,"NO PRAZO","FORA DO PRAZO"),IF(TODAY()>$F11,"VENCIDO",IF($F11-TODAY()<='01. CONFIGURAÇÕES'!$C$23,"VENCE EM BREVE","EM DIA")))) -> NO PRAZO | V11: =IF($A11="","",SUMIFS(MED_VLR,MED_ID,$A11)) -> 1871.61 | AA11: L = cidade M = ponto de referência
A12: =IF($B12="","",LEFT($B12,3)&"-"&TEXT(ROW()-4,"0000")) -> BER-0008 | B12: BERTIOGA | D12: 46267 | E12: 5 | F12: =IF($D12="","",$D12+IF($E12="",'01. CONFIGURAÇÕES'!$C$22,$E12)) -> 46272 | G12: URGENTE | H12: Vazamento de água não visível — ramal | I12: Alameda Paranapiacaba | J12: 930 | K12: Boracéia | L12: Bertioga | M12: ANT N.1128 | O12: Vazamento de água não visível ramal | P12: =IFERROR(IF($A12="","",IF(COUNTIFS(OS_ID,$A12)>0,INDEX(OS_EQUIPE,MATCH($A12,OS_ID,0)),IF(COUNTIFS(PROG_ID,$A12)>0,INDEX(PROG_EQUIPE,MATCH($A12,PROG_ID,0)),""))),"") -> 0 | Q12: =IF($A12="","",IFERROR(IF(INDEX(PROG_DATA,MATCH($A12,PROG_ID,0))=0,"",INDEX(PROG_DATA,MATCH($A12,PROG_ID,0))),"")) -> 46267 | R12: =IF($A12="","",IFERROR(IF(INDEX(OS_FIM,MATCH($A12,OS_ID,0))=0,"",INDEX(OS_FIM,MATCH($A12,OS_ID,0))),"")) -> 46268 | S12: =IF($A12="","",IF($W12<>"",$W12,IF($V12>0,"MEDIDO",IF($R12<>"","EXECUTADO",IF(COUNTIFS(OS_ID,$A12)>0,"EM EXECUÇÃO",IF($Q12<>"","PROGRAMADO","CADASTRADO")))))) -> MEDIDO | T12: =IF($A12="","",IF($R12<>"",$R12-$D12,TODAY()-$D12)) -> 1 | U12: =IF(OR($A12="",$F12=""),"",IF($R12<>"",IF($R12<=$F12,"NO PRAZO","FORA DO PRAZO"),IF(TODAY()>$F12,"VENCIDO",IF($F12-TODAY()<='01. CONFIGURAÇÕES'!$C$23,"VENCE EM BREVE","EM DIA")))) -> NO PRAZO | V12: =IF($A12="","",SUMIFS(MED_VLR,MED_ID,$A12)) -> 820.98 | AA12: N = piso: asfalto, calçada, terra (menu)
A13: =IF($B13="","",LEFT($B13,3)&"-"&TEXT(ROW()-4,"0000")) -> BER-0009 | B13: BERTIOGA | D13: 46267 | E13: 5 | F13: =IF($D13="","",$D13+IF($E13="",'01. CONFIGURAÇÕES'!$C$22,$E13)) -> 46272 | G13: URGENTE | H13: Vazamento de água não visível — ramal | I13: Rua dos Anjos Antiga Projetada 1B | J13: 57 | K13: Jardim Vicente de Carvalho | L13: Bertioga | M13: JD Vicente de Carvalho | O13: Vazamento de água não visível ramal | P13: =IFERROR(IF($A13="","",IF(COUNTIFS(OS_ID,$A13)>0,INDEX(OS_EQUIPE,MATCH($A13,OS_ID,0)),IF(COUNTIFS(PROG_ID,$A13)>0,INDEX(PROG_EQUIPE,MATCH($A13,PROG_ID,0)),""))),"") -> 0 | Q13: =IF($A13="","",IFERROR(IF(INDEX(PROG_DATA,MATCH($A13,PROG_ID,0))=0,"",INDEX(PROG_DATA,MATCH($A13,PROG_ID,0))),"")) -> 46269 | R13: =IF($A13="","",IFERROR(IF(INDEX(OS_FIM,MATCH($A13,OS_ID,0))=0,"",INDEX(OS_FIM,MATCH($A13,OS_ID,0))),"")) -> 46269 | S13: =IF($A13="","",IF($W13<>"",$W13,IF($V13>0,"MEDIDO",IF($R13<>"","EXECUTADO",IF(COUNTIFS(OS_ID,$A13)>0,"EM EXECUÇÃO",IF($Q13<>"","PROGRAMADO","CADASTRADO")))))) -> MEDIDO | T13: =IF($A13="","",IF($R13<>"",$R13-$D13,TODAY()-$D13)) -> 2 | U13: =IF(OR($A13="",$F13=""),"",IF($R13<>"",IF($R13<=$F13,"NO PRAZO","FORA DO PRAZO"),IF(TODAY()>$F13,"VENCIDO",IF($F13-TODAY()<='01. CONFIGURAÇÕES'!$C$23,"VENCE EM BREVE","EM DIA")))) -> NO PRAZO | V13: =IF($A13="","",SUMIFS(MED_VLR,MED_ID,$A13)) -> 924.97 | AA13: O = o que a SABESP pediu, com suas palavras
A14: =IF($B14="","",LEFT($B14,3)&"-"&TEXT(ROW()-4,"0000")) -> BER-0010 | B14: BERTIOGA | D14: 46268 | E14: 5 | F14: =IF($D14="","",$D14+IF($E14="",'01. CONFIGURAÇÕES'!$C$22,$E14)) -> 46273 | G14: NORMAL | H14: Troca de ramal de água | I14: Alameda Paranapiacaba | J14: 930 | K14: Boracéia | L14: Bertioga | M14: Casa 2 | O14: Trocar ramal de água - vaz não visível | P14: =IFERROR(IF($A14="","",IF(COUNTIFS(OS_ID,$A14)>0,INDEX(OS_EQUIPE,MATCH($A14,OS_ID,0)),IF(COUNTIFS(PROG_ID,$A14)>0,INDEX(PROG_EQUIPE,MATCH($A14,PROG_ID,0)),""))),"") -> 0 | Q14: =IF($A14="","",IFERROR(IF(INDEX(PROG_DATA,MATCH($A14,PROG_ID,0))=0,"",INDEX(PROG_DATA,MATCH($A14,PROG_ID,0))),"")) -> 46269 | R14: =IF($A14="","",IFERROR(IF(INDEX(OS_FIM,MATCH($A14,OS_ID,0))=0,"",INDEX(OS_FIM,MATCH($A14,OS_ID,0))),"")) -> 46269 | S14: =IF($A14="","",IF($W14<>"",$W14,IF($V14>0,"MEDIDO",IF($R14<>"","EXECUTADO",IF(COUNTIFS(OS_ID,$A14)>0,"EM EXECUÇÃO",IF($Q14<>"","PROGRAMADO","CADASTRADO")))))) -> MEDIDO | T14: =IF($A14="","",IF($R14<>"",$R14-$D14,TODAY()-$D14)) -> 1 | U14: =IF(OR($A14="",$F14=""),"",IF($R14<>"",IF($R14<=$F14,"NO PRAZO","FORA DO PRAZO"),IF(TODAY()>$F14,"VENCIDO",IF($F14-TODAY()<='01. CONFIGURAÇÕES'!$C$23,"VENCE EM BREVE","EM DIA")))) -> NO PRAZO | V14: =IF($A14="","",SUMIFS(MED_VLR,MED_ID,$A14)) -> 785.07 | AA14: X = observação, se tiver
A15: =IF($B15="","",LEFT($B15,3)&"-"&TEXT(ROW()-4,"0000")) -> BER-0011 | B15: BERTIOGA | D15: 46268 | E15: 5 | F15: =IF($D15="","",$D15+IF($E15="",'01. CONFIGURAÇÕES'!$C$22,$E15)) -> 46273 | G15: NORMAL | H15: Troca de ramal de água | I15: Alameda Paranapiacaba | J15: 930 | K15: Boracéia | L15: Bertioga | M15: Casa 3 | O15: Trocar ramal de água - vaz não visível | P15: =IFERROR(IF($A15="","",IF(COUNTIFS(OS_ID,$A15)>0,INDEX(OS_EQUIPE,MATCH($A15,OS_ID,0)),IF(COUNTIFS(PROG_ID,$A15)>0,INDEX(PROG_EQUIPE,MATCH($A15,PROG_ID,0)),""))),"") -> 0 | Q15: =IF($A15="","",IFERROR(IF(INDEX(PROG_DATA,MATCH($A15,PROG_ID,0))=0,"",INDEX(PROG_DATA,MATCH($A15,PROG_ID,0))),"")) -> 46269 | R15: =IF($A15="","",IFERROR(IF(INDEX(OS_FIM,MATCH($A15,OS_ID,0))=0,"",INDEX(OS_FIM,MATCH($A15,OS_ID,0))),"")) -> 46269 | S15: =IF($A15="","",IF($W15<>"",$W15,IF($V15>0,"MEDIDO",IF($R15<>"","EXECUTADO",IF(COUNTIFS(OS_ID,$A15)>0,"EM EXECUÇÃO",IF($Q15<>"","PROGRAMADO","CADASTRADO")))))) -> MEDIDO | T15: =IF($A15="","",IF($R15<>"",$R15-$D15,TODAY()-$D15)) -> 1 | U15: =IF(OR($A15="",$F15=""),"",IF($R15<>"",IF($R15<=$F15,"NO PRAZO","FORA DO PRAZO"),IF(TODAY()>$F15,"VENCIDO",IF($F15-TODAY()<='01. CONFIGURAÇÕES'!$C$23,"VENCE EM BREVE","EM DIA")))) -> NO PRAZO | V15: =IF($A15="","",SUMIFS(MED_VLR,MED_ID,$A15)) -> 785.07 | AA15: De P até V é fórmula: preenche sozinho quando você
A16: =IF($B16="","",LEFT($B16,3)&"-"&TEXT(ROW()-4,"0000")) -> BER-0012 | B16: BERTIOGA | D16: 46268 | E16: 5 | F16: =IF($D16="","",$D16+IF($E16="",'01. CONFIGURAÇÕES'!$C$22,$E16)) -> 46273 | G16: URGENTE | H16: Vazamento de água não visível — rede | I16: Avenida Tupi Guarani | J16: 960 | K16: Boracéia | L16: Bertioga | M16: ANT. 535 | O16: Vazamento de água não visível rede | P16: =IFERROR(IF($A16="","",IF(COUNTIFS(OS_ID,$A16)>0,INDEX(OS_EQUIPE,MATCH($A16,OS_ID,0)),IF(COUNTIFS(PROG_ID,$A16)>0,INDEX(PROG_EQUIPE,MATCH($A16,PROG_ID,0)),""))),"") -> 0 | Q16: =IF($A16="","",IFERROR(IF(INDEX(PROG_DATA,MATCH($A16,PROG_ID,0))=0,"",INDEX(PROG_DATA,MATCH($A16,PROG_ID,0))),"")) -> 46269 | R16: =IF($A16="","",IFERROR(IF(INDEX(OS_FIM,MATCH($A16,OS_ID,0))=0,"",INDEX(OS_FIM,MATCH($A16,OS_ID,0))),"")) -> 46269 | S16: =IF($A16="","",IF($W16<>"",$W16,IF($V16>0,"MEDIDO",IF($R16<>"","EXECUTADO",IF(COUNTIFS(OS_ID,$A16)>0,"EM EXECUÇÃO",IF($Q16<>"","PROGRAMADO","CADASTRADO")))))) -> MEDIDO | T16: =IF($A16="","",IF($R16<>"",$R16-$D16,TODAY()-$D16)) -> 1 | U16: =IF(OR($A16="",$F16=""),"",IF($R16<>"",IF($R16<=$F16,"NO PRAZO","FORA DO PRAZO"),IF(TODAY()>$F16,"VENCIDO",IF($F16-TODAY()<='01. CONFIGURAÇÕES'!$C$23,"VENCE EM BREVE","EM DIA")))) -> NO PRAZO | V16: =IF($A16="","",SUMIFS(MED_VLR,MED_ID,$A16)) -> 820.98 | AA16: programar (aba 04), executar (05) e medir (09).
A17: =IF($B17="","",LEFT($B17,3)&"-"&TEXT(ROW()-4,"0000")) -> BER-0013 | B17: BERTIOGA | D17: 46273 | E17: 5 | F17: =IF($D17="","",$D17+IF($E17="",'01. CONFIGURAÇÕES'!$C$22,$E17)) -> 46278 | G17: NORMAL | H17: Troca de ramal de água | I17: Rua Seis | J17: 239 | K17: Albatroz II | L17: Bertioga | M17: Albartroz II | O17: Trocar ramal de água - vaz não visível | P17: =IFERROR(IF($A17="","",IF(COUNTIFS(OS_ID,$A17)>0,INDEX(OS_EQUIPE,MATCH($A17,OS_ID,0)),IF(COUNTIFS(PROG_ID,$A17)>0,INDEX(PROG_EQUIPE,MATCH($A17,PROG_ID,0)),""))),"") -> 0 | Q17: =IF($A17="","",IFERROR(IF(INDEX(PROG_DATA,MATCH($A17,PROG_ID,0))=0,"",INDEX(PROG_DATA,MATCH($A17,PROG_ID,0))),"")) -> 46273 | R17: =IF($A17="","",IFERROR(IF(INDEX(OS_FIM,MATCH($A17,OS_ID,0))=0,"",INDEX(OS_FIM,MATCH($A17,OS_ID,0))),"")) -> 46273 | S17: =IF($A17="","",IF($W17<>"",$W17,IF($V17>0,"MEDIDO",IF($R17<>"","EXECUTADO",IF(COUNTIFS(OS_ID,$A17)>0,"EM EXECUÇÃO",IF($Q17<>"","PROGRAMADO","CADASTRADO")))))) -> MEDIDO | T17: =IF($A17="","",IF($R17<>"",$R17-$D17,TODAY()-$D17)) -> 0 | U17: =IF(OR($A17="",$F17=""),"",IF($R17<>"",IF($R17<=$F17,"NO PRAZO","FORA DO PRAZO"),IF(TODAY()>$F17,"VENCIDO",IF($F17-TODAY()<='01. CONFIGURAÇÕES'!$C$23,"VENCE EM BREVE","EM DIA")))) -> NO PRAZO | V17: =IF($A17="","",SUMIFS(MED_VLR,MED_ID,$A17)) -> 785.07
A18: =IF($B18="","",LEFT($B18,3)&"-"&TEXT(ROW()-4,"0000")) -> BER-0014 | B18: BERTIOGA | D18: 46273 | E18: 5 | F18: =IF($D18="","",$D18+IF($E18="",'01. CONFIGURAÇÕES'!$C$22,$E18)) -> 46278 | G18: URGENTE | H18: Vazamento pé do cavalete | I18: Rua Seis | J18: 14 | K18: Albatroz II | L18: Bertioga | M18: Albartroz II | O18: Vazamento pé do cavalete - não visível | P18: =IFERROR(IF($A18="","",IF(COUNTIFS(OS_ID,$A18)>0,INDEX(OS_EQUIPE,MATCH($A18,OS_ID,0)),IF(COUNTIFS(PROG_ID,$A18)>0,INDEX(PROG_EQUIPE,MATCH($A18,PROG_ID,0)),""))),"") -> 0 | Q18: =IF($A18="","",IFERROR(IF(INDEX(PROG_DATA,MATCH($A18,PROG_ID,0))=0,"",INDEX(PROG_DATA,MATCH($A18,PROG_ID,0))),"")) -> 46273 | R18: =IF($A18="","",IFERROR(IF(INDEX(OS_FIM,MATCH($A18,OS_ID,0))=0,"",INDEX(OS_FIM,MATCH($A18,OS_ID,0))),"")) -> 46273 | S18: =IF($A18="","",IF($W18<>"",$W18,IF($V18>0,"MEDIDO",IF($R18<>"","EXECUTADO",IF(COUNTIFS(OS_ID,$A18)>0,"EM EXECUÇÃO",IF($Q18<>"","PROGRAMADO","CADASTRADO")))))) -> MEDIDO | T18: =IF($A18="","",IF($R18<>"",$R18-$D18,TODAY()-$D18)) -> 0 | U18: =IF(OR($A18="",$F18=""),"",IF($R18<>"",IF($R18<=$F18,"NO PRAZO","FORA DO PRAZO"),IF(TODAY()>$F18,"VENCIDO",IF($F18-TODAY()<='01. CONFIGURAÇÕES'!$C$23,"VENCE EM BREVE","EM DIA")))) -> NO PRAZO | V18: =IF($A18="","",SUMIFS(MED_VLR,MED_ID,$A18)) -> 785.07
A19: =IF($B19="","",LEFT($B19,3)&"-"&TEXT(ROW()-4,"0000")) -> BER-0015 | B19: BERTIOGA | D19: 46273 | E19: 5 | F19: =IF($D19="","",$D19+IF($E19="",'01. CONFIGURAÇÕES'!$C$22,$E19)) -> 46278 | G19: URGENTE | H19: Vazamento no ferrule | I19: Rua C | K19: Ana Paula | L19: Bertioga | M19: Ana Paula, 1134 | O19: Vazamento no ferrule não visível | P19: =IFERROR(IF($A19="","",IF(COUNTIFS(OS_ID,$A19)>0,INDEX(OS_EQUIPE,MATCH($A19,OS_ID,0)),IF(COUNTIFS(PROG_ID,$A19)>0,INDEX(PROG_EQUIPE,MATCH($A19,PROG_ID,0)),""))),"") -> 0 | Q19: =IF($A19="","",IFERROR(IF(INDEX(PROG_DATA,MATCH($A19,PROG_ID,0))=0,"",INDEX(PROG_DATA,MATCH($A19,PROG_ID,0))),"")) -> 46273 | R19: =IF($A19="","",IFERROR(IF(INDEX(OS_FIM,MATCH($A19,OS_ID,0))=0,"",INDEX(OS_FIM,MATCH($A19,OS_ID,0))),"")) -> 46273 | S19: =IF($A19="","",IF($W19<>"",$W19,IF($V19>0,"MEDIDO",IF($R19<>"","EXECUTADO",IF(COUNTIFS(OS_ID,$A19)>0,"EM EXECUÇÃO",IF($Q19<>"","PROGRAMADO","CADASTRADO")))))) -> MEDIDO | T19: =IF($A19="","",IF($R19<>"",$R19-$D19,TODAY()-$D19)) -> 0 | U19: =IF(OR($A19="",$F19=""),"",IF($R19<>"",IF($R19<=$F19,"NO PRAZO","FORA DO PRAZO"),IF(TODAY()>$F19,"VENCIDO",IF($F19-TODAY()<='01. CONFIGURAÇÕES'!$C$23,"VENCE EM BREVE","EM DIA")))) -> NO PRAZO | V19: =IF($A19="","",SUMIFS(MED_VLR,MED_ID,$A19)) -> 785.07
A20: =IF($B20="","",LEFT($B20,3)&"-"&TEXT(ROW()-4,"0000")) -> BER-0016 | B20: BERTIOGA | D20: 46273 | E20: 5 | F20: =IF($D20="","",$D20+IF($E20="",'01. CONFIGURAÇÕES'!$C$22,$E20)) -> 46278 | G20: URGENTE | H20: Vazamento de água não visível — ramal | I20: Rua Aprovada 101 | J20: 21 | K20: Ana Paula | L20: Bertioga | M20: Ana Paula | O20: Vazamento no ramal não visível | P20: =IFERROR(IF($A20="","",IF(COUNTIFS(OS_ID,$A20)>0,INDEX(OS_EQUIPE,MATCH($A20,OS_ID,0)),IF(COUNTIFS(PROG_ID,$A20)>0,INDEX(PROG_EQUIPE,MATCH($A20,PROG_ID,0)),""))),"") -> 0 | Q20: =IF($A20="","",IFERROR(IF(INDEX(PROG_DATA,MATCH($A20,PROG_ID,0))=0,"",INDEX(PROG_DATA,MATCH($A20,PROG_ID,0))),"")) -> 46273 | R20: =IF($A20="","",IFERROR(IF(INDEX(OS_FIM,MATCH($A20,OS_ID,0))=0,"",INDEX(OS_FIM,MATCH($A20,OS_ID,0))),"")) -> 46276 | S20: =IF($A20="","",IF($W20<>"",$W20,IF($V20>0,"MEDIDO",IF($R20<>"","EXECUTADO",IF(COUNTIFS(OS_ID,$A20)>0,"EM EXECUÇÃO",IF($Q20<>"","PROGRAMADO","CADASTRADO")))))) -> MEDIDO | T20: =IF($A20="","",IF($R20<>"",$R20-$D20,TODAY()-$D20)) -> 3 | U20: =IF(OR($A20="",$F20=""),"",IF($R20<>"",IF($R20<=$F20,"NO PRAZO","FORA DO PRAZO"),IF(TODAY()>$F20,"VENCIDO",IF($F20-TODAY()<='01. CONFIGURAÇÕES'!$C$23,"VENCE EM BREVE","EM DIA")))) -> NO PRAZO | V20: =IF($A20="","",SUMIFS(MED_VLR,MED_ID,$A20)) -> 785.07
A21: =IF($B21="","",LEFT($B21,3)&"-"&TEXT(ROW()-4,"0000")) -> BER-0017 | B21: BERTIOGA | D21: 46273 | E21: 5 | F21: =IF($D21="","",$D21+IF($E21="",'01. CONFIGURAÇÕES'!$C$22,$E21)) -> 46278 | G21: URGENTE | H21: Vazamento pé do cavalete | I21: Rua Manoel Gajo | J21: 1426 | K21: Centro | L21: Bertioga | M21: Centro | O21: Vazamento pé do cavalete - não visível | P21: =IFERROR(IF($A21="","",IF(COUNTIFS(OS_ID,$A21)>0,INDEX(OS_EQUIPE,MATCH($A21,OS_ID,0)),IF(COUNTIFS(PROG_ID,$A21)>0,INDEX(PROG_EQUIPE,MATCH($A21,PROG_ID,0)),""))),"") -> 0 | Q21: =IF($A21="","",IFERROR(IF(INDEX(PROG_DATA,MATCH($A21,PROG_ID,0))=0,"",INDEX(PROG_DATA,MATCH($A21,PROG_ID,0))),"")) -> 46274 | R21: =IF($A21="","",IFERROR(IF(INDEX(OS_FIM,MATCH($A21,OS_ID,0))=0,"",INDEX(OS_FIM,MATCH($A21,OS_ID,0))),"")) -> 46274 | S21: =IF($A21="","",IF($W21<>"",$W21,IF($V21>0,"MEDIDO",IF($R21<>"","EXECUTADO",IF(COUNTIFS(OS_ID,$A21)>0,"EM EXECUÇÃO",IF($Q21<>"","PROGRAMADO","CADASTRADO")))))) -> MEDIDO | T21: =IF($A21="","",IF($R21<>"",$R21-$D21,TODAY()-$D21)) -> 1 | U21: =IF(OR($A21="",$F21=""),"",IF($R21<>"",IF($R21<=$F21,"NO PRAZO","FORA DO PRAZO"),IF(TODAY()>$F21,"VENCIDO",IF($F21-TODAY()<='01. CONFIGURAÇÕES'!$C$23,"VENCE EM BREVE","EM DIA")))) -> NO PRAZO | V21: =IF($A21="","",SUMIFS(MED_VLR,MED_ID,$A21)) -> 301.47
A22: =IF($B22="","",LEFT($B22,3)&"-"&TEXT(ROW()-4,"0000")) -> BER-0018 | B22: BERTIOGA | D22: 46273 | E22: 5 | F22: =IF($D22="","",$D22+IF($E22="",'01. CONFIGURAÇÕES'!$C$22,$E22)) -> 46278 | G22: URGENTE | H22: Vazamento pé do cavalete | I22: Rua Oswaldo de Salles Pereira | J22: 2623 | K22: Centro | L22: Bertioga | M22: Centro | O22: Vazamento pé do cavalete - não visível | P22: =IFERROR(IF($A22="","",IF(COUNTIFS(OS_ID,$A22)>0,INDEX(OS_EQUIPE,MATCH($A22,OS_ID,0)),IF(COUNTIFS(PROG_ID,$A22)>0,INDEX(PROG_EQUIPE,MATCH($A22,PROG_ID,0)),""))),"") -> 0 | Q22: =IF($A22="","",IFERROR(IF(INDEX(PROG_DATA,MATCH($A22,PROG_ID,0))=0,"",INDEX(PROG_DATA,MATCH($A22,PROG_ID,0))),"")) -> 46274 | R22: =IF($A22="","",IFERROR(IF(INDEX(OS_FIM,MATCH($A22,OS_ID,0))=0,"",INDEX(OS_FIM,MATCH($A22,OS_ID,0))),"")) -> 46274 | S22: =IF($A22="","",IF($W22<>"",$W22,IF($V22>0,"MEDIDO",IF($R22<>"","EXECUTADO",IF(COUNTIFS(OS_ID,$A22)>0,"EM EXECUÇÃO",IF($Q22<>"","PROGRAMADO","CADASTRADO")))))) -> MEDIDO | T22: =IF($A22="","",IF($R22<>"",$R22-$D22,TODAY()-$D22)) -> 1 | U22: =IF(OR($A22="",$F22=""),"",IF($R22<>"",IF($R22<=$F22,"NO PRAZO","FORA DO PRAZO"),IF(TODAY()>$F22,"VENCIDO",IF($F22-TODAY()<='01. CONFIGURAÇÕES'!$C$23,"VENCE EM BREVE","EM DIA")))) -> NO PRAZO | V22: =IF($A22="","",SUMIFS(MED_VLR,MED_ID,$A22)) -> 301.47
A23: =IF($B23="","",LEFT($B23,3)&"-"&TEXT(ROW()-4,"0000")) -> BER-0019 | B23: BERTIOGA | D23: 46273 | E23: 5 | F23: =IF($D23="","",$D23+IF($E23="",'01. CONFIGURAÇÕES'!$C$22,$E23)) -> 46278 | G23: URGENTE | H23: Vazamento no ferrule | I23: Rua Samuel Alves Levino | J23: 318 | K23: Rio da Praia | L23: Bertioga | M23: Rio da Praia | O23: Vazamento no ferrule não visível | P23: =IFERROR(IF($A23="","",IF(COUNTIFS(OS_ID,$A23)>0,INDEX(OS_EQUIPE,MATCH($A23,OS_ID,0)),IF(COUNTIFS(PROG_ID,$A23)>0,INDEX(PROG_EQUIPE,MATCH($A23,PROG_ID,0)),""))),"") -> 0 | Q23: =IF($A23="","",IFERROR(IF(INDEX(PROG_DATA,MATCH($A23,PROG_ID,0))=0,"",INDEX(PROG_DATA,MATCH($A23,PROG_ID,0))),"")) -> 46273 | R23: =IF($A23="","",IFERROR(IF(INDEX(OS_FIM,MATCH($A23,OS_ID,0))=0,"",INDEX(OS_FIM,MATCH($A23,OS_ID,0))),"")) -> 46276 | S23: =IF($A23="","",IF($W23<>"",$W23,IF($V23>0,"MEDIDO",IF($R23<>"","EXECUTADO",IF(COUNTIFS(OS_ID,$A23)>0,"EM EXECUÇÃO",IF($Q23<>"","PROGRAMADO","CADASTRADO")))))) -> MEDIDO | T23: =IF($A23="","",IF($R23<>"",$R23-$D23,TODAY()-$D23)) -> 3 | U23: =IF(OR($A23="",$F23=""),"",IF($R23<>"",IF($R23<=$F23,"NO PRAZO","FORA DO PRAZO"),IF(TODAY()>$F23,"VENCIDO",IF($F23-TODAY()<='01. CONFIGURAÇÕES'!$C$23,"VENCE EM BREVE","EM DIA")))) -> NO PRAZO | V23: =IF($A23="","",SUMIFS(MED_VLR,MED_ID,$A23)) -> 1992.97
A24: =IF($B24="","",LEFT($B24,3)&"-"&TEXT(ROW()-4,"0000")) -> BER-0020 | B24: BERTIOGA | D24: 46273 | E24: 5 | F24: =IF($D24="","",$D24+IF($E24="",'01. CONFIGURAÇÕES'!$C$22,$E24)) -> 46278 | G24: URGENTE | H24: Vazamento pé do cavalete | I24: Rua Renata Pereira Costa | J24: 9 | K24: Rio da Praia | L24: Bertioga | M24: Rio da Praia | O24: Vazamento pé do cavalete - não visível | P24: =IFERROR(IF($A24="","",IF(COUNTIFS(OS_ID,$A24)>0,INDEX(OS_EQUIPE,MATCH($A24,OS_ID,0)),IF(COUNTIFS(PROG_ID,$A24)>0,INDEX(PROG_EQUIPE,MATCH($A24,PROG_ID,0)),""))),"") -> 0 | Q24: =IF($A24="","",IFERROR(IF(INDEX(PROG_DATA,MATCH($A24,PROG_ID,0))=0,"",INDEX(PROG_DATA,MATCH($A24,PROG_ID,0))),"")) -> 46273 | R24: =IF($A24="","",IFERROR(IF(INDEX(OS_FIM,MATCH($A24,OS_ID,0))=0,"",INDEX(OS_FIM,MATCH($A24,OS_ID,0))),"")) -> 46276 | S24: =IF($A24="","",IF($W24<>"",$W24,IF($V24>0,"MEDIDO",IF($R24<>"","EXECUTADO",IF(COUNTIFS(OS_ID,$A24)>0,"EM EXECUÇÃO",IF($Q24<>"","PROGRAMADO","CADASTRADO")))))) -> EXECUTADO | T24: =IF($A24="","",IF($R24<>"",$R24-$D24,TODAY()-$D24)) -> 3 | U24: =IF(OR($A24="",$F24=""),"",IF($R24<>"",IF($R24<=$F24,"NO PRAZO","FORA DO PRAZO"),IF(TODAY()>$F24,"VENCIDO",IF($F24-TODAY()<='01. CONFIGURAÇÕES'!$C$23,"VENCE EM BREVE","EM DIA")))) -> NO PRAZO | V24: =IF($A24="","",SUMIFS(MED_VLR,MED_ID,$A24)) -> 0
A25: =IF($B25="","",LEFT($B25,3)&"-"&TEXT(ROW()-4,"0000")) -> BER-0021 | B25: BERTIOGA | D25: 46273 | E25: 5 | F25: =IF($D25="","",$D25+IF($E25="",'01. CONFIGURAÇÕES'!$C$22,$E25)) -> 46278 | G25: URGENTE | H25: Vazamento pé do cavalete | I25: Rua Jair Miranda (antiga rua 5) | J25: 45 | K25: Albatroz II | L25: Bertioga | M25: Albatroz II | O25: Vazamento pé do cavalete - não visível | P25: =IFERROR(IF($A25="","",IF(COUNTIFS(OS_ID,$A25)>0,INDEX(OS_EQUIPE,MATCH($A25,OS_ID,0)),IF(COUNTIFS(PROG_ID,$A25)>0,INDEX(PROG_EQUIPE,MATCH($A25,PROG_ID,0)),""))),"") -> 0 | Q25: =IF($A25="","",IFERROR(IF(INDEX(PROG_DATA,MATCH($A25,PROG_ID,0))=0,"",INDEX(PROG_DATA,MATCH($A25,PROG_ID,0))),"")) -> 46273 | R25: =IF($A25="","",IFERROR(IF(INDEX(OS_FIM,MATCH($A25,OS_ID,0))=0,"",INDEX(OS_FIM,MATCH($A25,OS_ID,0))),"")) | S25: =IF($A25="","",IF($W25<>"",$W25,IF($V25>0,"MEDIDO",IF($R25<>"","EXECUTADO",IF(COUNTIFS(OS_ID,$A25)>0,"EM EXECUÇÃO",IF($Q25<>"","PROGRAMADO","CADASTRADO")))))) -> EM EXECUÇÃO | T25: =IF($A25="","",IF($R25<>"",$R25-$D25,TODAY()-$D25)) -> 8 | U25: =IF(OR($A25="",$F25=""),"",IF($R25<>"",IF($R25<=$F25,"NO PRAZO","FORA DO PRAZO"),IF(TODAY()>$F25,"VENCIDO",IF($F25-TODAY()<='01. CONFIGURAÇÕES'!$C$23,"VENCE EM BREVE","EM DIA")))) -> VENCIDO | V25: =IF($A25="","",SUMIFS(MED_VLR,MED_ID,$A25)) -> 0
A26: =IF($B26="","",LEFT($B26,3)&"-"&TEXT(ROW()-4,"0000")) -> BER-0022 | B26: BERTIOGA | D26: 46273 | E26: 5 | F26: =IF($D26="","",$D26+IF($E26="",'01. CONFIGURAÇÕES'!$C$22,$E26)) -> 46278 | G26: URGENTE | H26: Vazamento pé do cavalete | I26: Rua Professor José Benevenuto Madureira | J26: 425 | K26: Rio da Praia | L26: Bertioga | M26: Rio da Praia | O26: Vazamento pé do cavalete - não visível | P26: =IFERROR(IF($A26="","",IF(COUNTIFS(OS_ID,$A26)>0,INDEX(OS_EQUIPE,MATCH($A26,OS_ID,0)),IF(COUNTIFS(PROG_ID,$A26)>0,INDEX(PROG_EQUIPE,MATCH($A26,PROG_ID,0)),""))),"") -> 0 | Q26: =IF($A26="","",IFERROR(IF(INDEX(PROG_DATA,MATCH($A26,PROG_ID,0))=0,"",INDEX(PROG_DATA,MATCH($A26,PROG_ID,0))),"")) -> 46273 | R26: =IF($A26="","",IFERROR(IF(INDEX(OS_FIM,MATCH($A26,OS_ID,0))=0,"",INDEX(OS_FIM,MATCH($A26,OS_ID,0))),"")) | S26: =IF($A26="","",IF($W26<>"",$W26,IF($V26>0,"MEDIDO",IF($R26<>"","EXECUTADO",IF(COUNTIFS(OS_ID,$A26)>0,"EM EXECUÇÃO",IF($Q26<>"","PROGRAMADO","CADASTRADO")))))) -> EM EXECUÇÃO | T26: =IF($A26="","",IF($R26<>"",$R26-$D26,TODAY()-$D26)) -> 8 | U26: =IF(OR($A26="",$F26=""),"",IF($R26<>"",IF($R26<=$F26,"NO PRAZO","FORA DO PRAZO"),IF(TODAY()>$F26,"VENCIDO",IF($F26-TODAY()<='01. CONFIGURAÇÕES'!$C$23,"VENCE EM BREVE","EM DIA")))) -> VENCIDO | V26: =IF($A26="","",SUMIFS(MED_VLR,MED_ID,$A26)) -> 0
A27: =IF($B27="","",LEFT($B27,3)&"-"&TEXT(ROW()-4,"0000")) -> BER-0023 | B27: BERTIOGA | D27: 46276 | E27: 5 | F27: =IF($D27="","",$D27+IF($E27="",'01. CONFIGURAÇÕES'!$C$22,$E27)) -> 46281 | G27: NORMAL | H27: Vazamento de água não visível — rede | I27: Rua aprovada 101 | J27: 01 | K27: Ana Paula | L27: Bertioga | M27: Ana Paula | O27: Vazamento não visível | P27: =IFERROR(IF($A27="","",IF(COUNTIFS(OS_ID,$A27)>0,INDEX(OS_EQUIPE,MATCH($A27,OS_ID,0)),IF(COUNTIFS(PROG_ID,$A27)>0,INDEX(PROG_EQUIPE,MATCH($A27,PROG_ID,0)),""))),"") -> 0 | Q27: =IF($A27="","",IFERROR(IF(INDEX(PROG_DATA,MATCH($A27,PROG_ID,0))=0,"",INDEX(PROG_DATA,MATCH($A27,PROG_ID,0))),"")) -> 46276 | R27: =IF($A27="","",IFERROR(IF(INDEX(OS_FIM,MATCH($A27,OS_ID,0))=0,"",INDEX(OS_FIM,MATCH($A27,OS_ID,0))),"")) -> 46276 | S27: =IF($A27="","",IF($W27<>"",$W27,IF($V27>0,"MEDIDO",IF($R27<>"","EXECUTADO",IF(COUNTIFS(OS_ID,$A27)>0,"EM EXECUÇÃO",IF($Q27<>"","PROGRAMADO","CADASTRADO")))))) -> MEDIDO | T27: =IF($A27="","",IF($R27<>"",$R27-$D27,TODAY()-$D27)) -> 0 | U27: =IF(OR($A27="",$F27=""),"",IF($R27<>"",IF($R27<=$F27,"NO PRAZO","FORA DO PRAZO"),IF(TODAY()>$F27,"VENCIDO",IF($F27-TODAY()<='01. CONFIGURAÇÕES'!$C$23,"VENCE EM BREVE","EM DIA")))) -> NO PRAZO | V27: =IF($A27="","",SUMIFS(MED_VLR,MED_ID,$A27)) -> 785.07
A28: =IF($B28="","",LEFT($B28,3)&"-"&TEXT(ROW()-4,"0000")) -> BER-0024 | B28: BERTIOGA | D28: 46279 | E28: 5 | F28: =IF($D28="","",$D28+IF($E28="",'01. CONFIGURAÇÕES'!$C$22,$E28)) -> 46284 | G28: NORMAL | H28: Vazamento no ramal não visível | I28: Avenida Sabino Abdala | J28: 85 | K28: Indaia | L28: Bertioga | M28: Indaia | O28: Vazamento no ramal não visível | P28: =IFERROR(IF($A28="","",IF(COUNTIFS(OS_ID,$A28)>0,INDEX(OS_EQUIPE,MATCH($A28,OS_ID,0)),IF(COUNTIFS(PROG_ID,$A28)>0,INDEX(PROG_EQUIPE,MATCH($A28,PROG_ID,0)),""))),"") -> 0 | Q28: =IF($A28="","",IFERROR(IF(INDEX(PROG_DATA,MATCH($A28,PROG_ID,0))=0,"",INDEX(PROG_DATA,MATCH($A28,PROG_ID,0))),"")) -> 46279 | R28: =IF($A28="","",IFERROR(IF(INDEX(OS_FIM,MATCH($A28,OS_ID,0))=0,"",INDEX(OS_FIM,MATCH($A28,OS_ID,0))),"")) -> 46279 | S28: =IF($A28="","",IF($W28<>"",$W28,IF($V28>0,"MEDIDO",IF($R28<>"","EXECUTADO",IF(COUNTIFS(OS_ID,$A28)>0,"EM EXECUÇÃO",IF($Q28<>"","PROGRAMADO","CADASTRADO")))))) -> MEDIDO | T28: =IF($A28="","",IF($R28<>"",$R28-$D28,TODAY()-$D28)) -> 0 | U28: =IF(OR($A28="",$F28=""),"",IF($R28<>"",IF($R28<=$F28,"NO PRAZO","FORA DO PRAZO"),IF(TODAY()>$F28,"VENCIDO",IF($F28-TODAY()<='01. CONFIGURAÇÕES'!$C$23,"VENCE EM BREVE","EM DIA")))) -> NO PRAZO | V28: =IF($A28="","",SUMIFS(MED_VLR,MED_ID,$A28)) -> 2813.95
A29: =IF($B29="","",LEFT($B29,3)&"-"&TEXT(ROW()-4,"0000")) -> BER-0025 | B29: BERTIOGA | D29: 46279 | E29: 5 | F29: =IF($D29="","",$D29+IF($E29="",'01. CONFIGURAÇÕES'!$C$22,$E29)) -> 46284 | G29: NORMAL | H29: Vazamento pé do cavalete | I29: Rua Luiz Alonso Peres | J29: 131 | K29: Indaia | L29: Bertioga | M29: Indaia | O29: Vazamento pé do cavalete | P29: =IFERROR(IF($A29="","",IF(COUNTIFS(OS_ID,$A29)>0,INDEX(OS_EQUIPE,MATCH($A29,OS_ID,0)),IF(COUNTIFS(PROG_ID,$A29)>0,INDEX(PROG_EQUIPE,MATCH($A29,PROG_ID,0)),""))),"") -> 0 | Q29: =IF($A29="","",IFERROR(IF(INDEX(PROG_DATA,MATCH($A29,PROG_ID,0))=0,"",INDEX(PROG_DATA,MATCH($A29,PROG_ID,0))),"")) -> 46279 | R29: =IF($A29="","",IFERROR(IF(INDEX(OS_FIM,MATCH($A29,OS_ID,0))=0,"",INDEX(OS_FIM,MATCH($A29,OS_ID,0))),"")) -> 46280 | S29: =IF($A29="","",IF($W29<>"",$W29,IF($V29>0,"MEDIDO",IF($R29<>"","EXECUTADO",IF(COUNTIFS(OS_ID,$A29)>0,"EM EXECUÇÃO",IF($Q29<>"","PROGRAMADO","CADASTRADO")))))) -> MEDIDO | T29: =IF($A29="","",IF($R29<>"",$R29-$D29,TODAY()-$D29)) -> 1 | U29: =IF(OR($A29="",$F29=""),"",IF($R29<>"",IF($R29<=$F29,"NO PRAZO","FORA DO PRAZO"),IF(TODAY()>$F29,"VENCIDO",IF($F29-TODAY()<='01. CONFIGURAÇÕES'!$C$23,"VENCE EM BREVE","EM DIA")))) -> NO PRAZO | V29: =IF($A29="","",SUMIFS(MED_VLR,MED_ID,$A29)) -> 820.98
A30: =IF($B30="","",LEFT($B30,3)&"-"&TEXT(ROW()-4,"0000")) -> BER-0026 | B30: BERTIOGA | D30: 46279 | E30: 5 | F30: =IF($D30="","",$D30+IF($E30="",'01. CONFIGURAÇÕES'!$C$22,$E30)) -> 46284 | G30: NORMAL | H30: Vazamento no ramal não visível | I30: Avenida Sabino Abdala | J30: 261 | K30: Indaia | L30: Bertioga | M30: Indaia | O30: Vazamento no ramal não visível | P30: =IFERROR(IF($A30="","",IF(COUNTIFS(OS_ID,$A30)>0,INDEX(OS_EQUIPE,MATCH($A30,OS_ID,0)),IF(COUNTIFS(PROG_ID,$A30)>0,INDEX(PROG_EQUIPE,MATCH($A30,PROG_ID,0)),""))),"") -> 0 | Q30: =IF($A30="","",IFERROR(IF(INDEX(PROG_DATA,MATCH($A30,PROG_ID,0))=0,"",INDEX(PROG_DATA,MATCH($A30,PROG_ID,0))),"")) -> 46279 | R30: 46280 | S30: =IF($A30="","",IF($W30<>"",$W30,IF($V30>0,"MEDIDO",IF($R30<>"","EXECUTADO",IF(COUNTIFS(OS_ID,$A30)>0,"EM EXECUÇÃO",IF($Q30<>"","PROGRAMADO","CADASTRADO")))))) -> MEDIDO | T30: =IF($A30="","",IF($R30<>"",$R30-$D30,TODAY()-$D30)) -> 1 | U30: =IF(OR($A30="",$F30=""),"",IF($R30<>"",IF($R30<=$F30,"NO PRAZO","FORA DO PRAZO"),IF(TODAY()>$F30,"VENCIDO",IF($F30-TODAY()<='01. CONFIGURAÇÕES'!$C$23,"VENCE EM BREVE","EM DIA")))) -> NO PRAZO | V30: =IF($A30="","",SUMIFS(MED_VLR,MED_ID,$A30)) -> 2434.34
A31: =IF($B31="","",LEFT($B31,3)&"-"&TEXT(ROW()-4,"0000")) -> BER-0027 | B31: BERTIOGA | D31: 46279 | E31: 5 | F31: =IF($D31="","",$D31+IF($E31="",'01. CONFIGURAÇÕES'!$C$22,$E31)) -> 46284 | G31: NORMAL | H31: Vazamento no ramal não visível | I31: Avenida Sabino Abdala | J31: 51 | K31: Indaia | L31: Bertioga | M31: Indaia | O31: Vazamento no ramal não visível | P31: =IFERROR(IF($A31="","",IF(COUNTIFS(OS_ID,$A31)>0,INDEX(OS_EQUIPE,MATCH($A31,OS_ID,0)),IF(COUNTIFS(PROG_ID,$A31)>0,INDEX(PROG_EQUIPE,MATCH($A31,PROG_ID,0)),""))),"") -> 0 | Q31: =IF($A31="","",IFERROR(IF(INDEX(PROG_DATA,MATCH($A31,PROG_ID,0))=0,"",INDEX(PROG_DATA,MATCH($A31,PROG_ID,0))),"")) -> 46279 | R31: =IF($A31="","",IFERROR(IF(INDEX(OS_FIM,MATCH($A31,OS_ID,0))=0,"",INDEX(OS_FIM,MATCH($A31,OS_ID,0))),"")) -> 46280 | S31: =IF($A31="","",IF($W31<>"",$W31,IF($V31>0,"MEDIDO",IF($R31<>"","EXECUTADO",IF(COUNTIFS(OS_ID,$A31)>0,"EM EXECUÇÃO",IF($Q31<>"","PROGRAMADO","CADASTRADO")))))) -> MEDIDO | T31: =IF($A31="","",IF($R31<>"",$R31-$D31,TODAY()-$D31)) -> 1 | U31: =IF(OR($A31="",$F31=""),"",IF($R31<>"",IF($R31<=$F31,"NO PRAZO","FORA DO PRAZO"),IF(TODAY()>$F31,"VENCIDO",IF($F31-TODAY()<='01. CONFIGURAÇÕES'!$C$23,"VENCE EM BREVE","EM DIA")))) -> NO PRAZO | V31: =IF($A31="","",SUMIFS(MED_VLR,MED_ID,$A31)) -> 2132.87
A32: =IF($B32="","",LEFT($B32,3)&"-"&TEXT(ROW()-4,"0000")) -> BER-0028 | B32: BERTIOGA | D32: 46279 | E32: 5 | F32: =IF($D32="","",$D32+IF($E32="",'01. CONFIGURAÇÕES'!$C$22,$E32)) -> 46284 | G32: NORMAL | H32: Vazamento cavalete não visível | I32: Rua Augusto Ribeiro Pacheco | J32: 146 | K32: Jardim Raphael | L32: Bertioga | M32: Jardim Raphael | O32: Vazamento cavalete não visível | P32: =IFERROR(IF($A32="","",IF(COUNTIFS(OS_ID,$A32)>0,INDEX(OS_EQUIPE,MATCH($A32,OS_ID,0)),IF(COUNTIFS(PROG_ID,$A32)>0,INDEX(PROG_EQUIPE,MATCH($A32,PROG_ID,0)),""))),"") -> 0 | Q32: =IF($A32="","",IFERROR(IF(INDEX(PROG_DATA,MATCH($A32,PROG_ID,0))=0,"",INDEX(PROG_DATA,MATCH($A32,PROG_ID,0))),"")) -> 46279 | R32: =IF($A32="","",IFERROR(IF(INDEX(OS_FIM,MATCH($A32,OS_ID,0))=0,"",INDEX(OS_FIM,MATCH($A32,OS_ID,0))),"")) | S32: =IF($A32="","",IF($W32<>"",$W32,IF($V32>0,"MEDIDO",IF($R32<>"","EXECUTADO",IF(COUNTIFS(OS_ID,$A32)>0,"EM EXECUÇÃO",IF($Q32<>"","PROGRAMADO","CADASTRADO")))))) -> EM EXECUÇÃO | T32: =IF($A32="","",IF($R32<>"",$R32-$D32,TODAY()-$D32)) -> 2 | U32: =IF(OR($A32="",$F32=""),"",IF($R32<>"",IF($R32<=$F32,"NO PRAZO","FORA DO PRAZO"),IF(TODAY()>$F32,"VENCIDO",IF($F32-TODAY()<='01. CONFIGURAÇÕES'!$C$23,"VENCE EM BREVE","EM DIA")))) -> EM DIA | V32: =IF($A32="","",SUMIFS(MED_VLR,MED_ID,$A32)) -> 0
A33: =IF($B33="","",LEFT($B33,3)&"-"&TEXT(ROW()-4,"0000")) -> BER-0029 | B33: BERTIOGA | D33: 46279 | E33: 5 | F33: =IF($D33="","",$D33+IF($E33="",'01. CONFIGURAÇÕES'!$C$22,$E33)) -> 46284 | G33: NORMAL | H33: Vazamento no ramal não visível | I33: Rua Cardeal Emile Biayenda | J33: 697 | K33: Rio da Praia | L33: Bertioga | M33: Rio da Praia | O33: Vazamento no ramal não visível | P33: =IFERROR(IF($A33="","",IF(COUNTIFS(OS_ID,$A33)>0,INDEX(OS_EQUIPE,MATCH($A33,OS_ID,0)),IF(COUNTIFS(PROG_ID,$A33)>0,INDEX(PROG_EQUIPE,MATCH($A33,PROG_ID,0)),""))),"") -> 0 | Q33: =IF($A33="","",IFERROR(IF(INDEX(PROG_DATA,MATCH($A33,PROG_ID,0))=0,"",INDEX(PROG_DATA,MATCH($A33,PROG_ID,0))),"")) -> 46279 | R33: =IF($A33="","",IFERROR(IF(INDEX(OS_FIM,MATCH($A33,OS_ID,0))=0,"",INDEX(OS_FIM,MATCH($A33,OS_ID,0))),"")) -> 46280 | S33: =IF($A33="","",IF($W33<>"",$W33,IF($V33>0,"MEDIDO",IF($R33<>"","EXECUTADO",IF(COUNTIFS(OS_ID,$A33)>0,"EM EXECUÇÃO",IF($Q33<>"","PROGRAMADO","CADASTRADO")))))) -> MEDIDO | T33: =IF($A33="","",IF($R33<>"",$R33-$D33,TODAY()-$D33)) -> 1 | U33: =IF(OR($A33="",$F33=""),"",IF($R33<>"",IF($R33<=$F33,"NO PRAZO","FORA DO PRAZO"),IF(TODAY()>$F33,"VENCIDO",IF($F33-TODAY()<='01. CONFIGURAÇÕES'!$C$23,"VENCE EM BREVE","EM DIA")))) -> NO PRAZO | V33: =IF($A33="","",SUMIFS(MED_VLR,MED_ID,$A33)) -> 2132.87
A34: =IF($B34="","",LEFT($B34,3)&"-"&TEXT(ROW()-4,"0000")) -> BER-0030 | B34: BERTIOGA | D34: 46281 | E34: 3 | F34: =IF($D34="","",$D34+IF($E34="",'01. CONFIGURAÇÕES'!$C$22,$E34)) -> 46284 | G34: URGENTE | H34: Vazamento de água não visível — rede | I34: Rua Maria Lídia Rego Lima | J34: 280 | K34: Vicente de Carvalho | L34: Guarujá | P34: =IFERROR(IF($A34="","",IF(COUNTIFS(OS_ID,$A34)>0,INDEX(OS_EQUIPE,MATCH($A34,OS_ID,0)),IF(COUNTIFS(PROG_ID,$A34)>0,INDEX(PROG_EQUIPE,MATCH($A34,PROG_ID,0)),""))),"") -> 0 | Q34: =IF($A34="","",IFERROR(IF(INDEX(PROG_DATA,MATCH($A34,PROG_ID,0))=0,"",INDEX(PROG_DATA,MATCH($A34,PROG_ID,0))),"")) -> 46281 | R34: =IF($A34="","",IFERROR(IF(INDEX(OS_FIM,MATCH($A34,OS_ID,0))=0,"",INDEX(OS_FIM,MATCH($A34,OS_ID,0))),"")) | S34: =IF($A34="","",IF($W34<>"",$W34,IF($V34>0,"MEDIDO",IF($R34<>"","EXECUTADO",IF(COUNTIFS(OS_ID,$A34)>0,"EM EXECUÇÃO",IF($Q34<>"","PROGRAMADO","CADASTRADO")))))) -> EM EXECUÇÃO | T34: =IF($A34="","",IF($R34<>"",$R34-$D34,TODAY()-$D34)) -> 0 | U34: =IF(OR($A34="",$F34=""),"",IF($R34<>"",IF($R34<=$F34,"NO PRAZO","FORA DO PRAZO"),IF(TODAY()>$F34,"VENCIDO",IF($F34-TODAY()<='01. CONFIGURAÇÕES'!$C$23,"VENCE EM BREVE","EM DIA")))) -> EM DIA | V34: =IF($A34="","",SUMIFS(MED_VLR,MED_ID,$A34)) -> 0
A35: =IF($B35="","",LEFT($B35,3)&"-"&TEXT(ROW()-4,"0000")) -> BER-0031 | B35: BERTIOGA | D35: 46281 | E35: 3 | F35: =IF($D35="","",$D35+IF($E35="",'01. CONFIGURAÇÕES'!$C$22,$E35)) -> 46284 | G35: URGENTE | H35: Vazamento no ramal não visível | I35: Rua Espírito Santo | J35: 407 | K35: Vicente de Carvalho | L35: Guarujá | O35: Vazamento no cavalete e troca de ramal | P35: =IFERROR(IF($A35="","",IF(COUNTIFS(OS_ID,$A35)>0,INDEX(OS_EQUIPE,MATCH($A35,OS_ID,0)),IF(COUNTIFS(PROG_ID,$A35)>0,INDEX(PROG_EQUIPE,MATCH($A35,PROG_ID,0)),""))),"") -> 0 | Q35: =IF($A35="","",IFERROR(IF(INDEX(PROG_DATA,MATCH($A35,PROG_ID,0))=0,"",INDEX(PROG_DATA,MATCH($A35,PROG_ID,0))),"")) -> 46281 | R35: =IF($A35="","",IFERROR(IF(INDEX(OS_FIM,MATCH($A35,OS_ID,0))=0,"",INDEX(OS_FIM,MATCH($A35,OS_ID,0))),"")) -> 46281 | S35: =IF($A35="","",IF($W35<>"",$W35,IF($V35>0,"MEDIDO",IF($R35<>"","EXECUTADO",IF(COUNTIFS(OS_ID,$A35)>0,"EM EXECUÇÃO",IF($Q35<>"","PROGRAMADO","CADASTRADO")))))) -> MEDIDO | T35: =IF($A35="","",IF($R35<>"",$R35-$D35,TODAY()-$D35)) -> 0 | U35: =IF(OR($A35="",$F35=""),"",IF($R35<>"",IF($R35<=$F35,"NO PRAZO","FORA DO PRAZO"),IF(TODAY()>$F35,"VENCIDO",IF($F35-TODAY()<='01. CONFIGURAÇÕES'!$C$23,"VENCE EM BREVE","EM DIA")))) -> NO PRAZO | V35: =IF($A35="","",SUMIFS(MED_VLR,MED_ID,$A35)) -> 1226.44
A36: =IF($B36="","",LEFT($B36,3)&"-"&TEXT(ROW()-4,"0000")) -> BER-0032 | B36: BERTIOGA | D36: 46281 | E36: 3 | F36: =IF($D36="","",$D36+IF($E36="",'01. CONFIGURAÇÕES'!$C$22,$E36)) -> 46284 | G36: URGENTE | H36: Vazamento cavalete não visível | I36: Rua Espírito Santo | J36: 260 | K36: Vicente de Carvalho | L36: Guarujá | O36: Vazamento no cavalete e troca de ramal | P36: =IFERROR(IF($A36="","",IF(COUNTIFS(OS_ID,$A36)>0,INDEX(OS_EQUIPE,MATCH($A36,OS_ID,0)),IF(COUNTIFS(PROG_ID,$A36)>0,INDEX(PROG_EQUIPE,MATCH($A36,PROG_ID,0)),""))),"") -> 0 | Q36: =IF($A36="","",IFERROR(IF(INDEX(PROG_DATA,MATCH($A36,PROG_ID,0))=0,"",INDEX(PROG_DATA,MATCH($A36,PROG_ID,0))),"")) -> 46281 | R36: 46281 | S36: =IF($A36="","",IF($W36<>"",$W36,IF($V36>0,"MEDIDO",IF($R36<>"","EXECUTADO",IF(COUNTIFS(OS_ID,$A36)>0,"EM EXECUÇÃO",IF($Q36<>"","PROGRAMADO","CADASTRADO")))))) -> MEDIDO | T36: =IF($A36="","",IF($R36<>"",$R36-$D36,TODAY()-$D36)) -> 0 | U36: =IF(OR($A36="",$F36=""),"",IF($R36<>"",IF($R36<=$F36,"NO PRAZO","FORA DO PRAZO"),IF(TODAY()>$F36,"VENCIDO",IF($F36-TODAY()<='01. CONFIGURAÇÕES'!$C$23,"VENCE EM BREVE","EM DIA")))) -> NO PRAZO | V36: =IF($A36="","",SUMIFS(MED_VLR,MED_ID,$A36)) -> 6659.14
A37: =IF($B37="","",LEFT($B37,3)&"-"&TEXT(ROW()-4,"0000")) -> BER-0033 | B37: BERTIOGA | D37: 46281 | E37: 3 | F37: =IF($D37="","",$D37+IF($E37="",'01. CONFIGURAÇÕES'!$C$22,$E37)) -> 46284 | G37: URGENTE | H37: Vazamento no ramal não visível | I37: Rua Mario Silveira | J37: 356 | K37: Vicente de Carvalho | L37: Guarujá | P37: =IFERROR(IF($A37="","",IF(COUNTIFS(OS_ID,$A37)>0,INDEX(OS_EQUIPE,MATCH($A37,OS_ID,0)),IF(COUNTIFS(PROG_ID,$A37)>0,INDEX(PROG_EQUIPE,MATCH($A37,PROG_ID,0)),""))),"") -> 0 | Q37: =IF($A37="","",IFERROR(IF(INDEX(PROG_DATA,MATCH($A37,PROG_ID,0))=0,"",INDEX(PROG_DATA,MATCH($A37,PROG_ID,0))),"")) -> 46281 | R37: =IF($A37="","",IFERROR(IF(INDEX(OS_FIM,MATCH($A37,OS_ID,0))=0,"",INDEX(OS_FIM,MATCH($A37,OS_ID,0))),"")) | S37: =IF($A37="","",IF($W37<>"",$W37,IF($V37>0,"MEDIDO",IF($R37<>"","EXECUTADO",IF(COUNTIFS(OS_ID,$A37)>0,"EM EXECUÇÃO",IF($Q37<>"","PROGRAMADO","CADASTRADO")))))) -> EM EXECUÇÃO | T37: =IF($A37="","",IF($R37<>"",$R37-$D37,TODAY()-$D37)) -> 0 | U37: =IF(OR($A37="",$F37=""),"",IF($R37<>"",IF($R37<=$F37,"NO PRAZO","FORA DO PRAZO"),IF(TODAY()>$F37,"VENCIDO",IF($F37-TODAY()<='01. CONFIGURAÇÕES'!$C$23,"VENCE EM BREVE","EM DIA")))) -> EM DIA | V37: =IF($A37="","",SUMIFS(MED_VLR,MED_ID,$A37)) -> 0
A38: =IF($B38="","",LEFT($B38,3)&"-"&TEXT(ROW()-4,"0000")) -> BER-0034 | B38: BERTIOGA | D38: 46281 | E38: 3 | F38: =IF($D38="","",$D38+IF($E38="",'01. CONFIGURAÇÕES'!$C$22,$E38)) -> 46284 | G38: URGENTE | H38: Vazamento no ramal não visível | I38: Rua Mario Silveira | J38: 295 | K38: Vicente de Carvalho | L38: Guarujá | P38: =IFERROR(IF($A38="","",IF(COUNTIFS(OS_ID,$A38)>0,INDEX(OS_EQUIPE,MATCH($A38,OS_ID,0)),IF(COUNTIFS(PROG_ID,$A38)>0,INDEX(PROG_EQUIPE,MATCH($A38,PROG_ID,0)),""))),"") -> 0 | Q38: =IF($A38="","",IFERROR(IF(INDEX(PROG_DATA,MATCH($A38,PROG_ID,0))=0,"",INDEX(PROG_DATA,MATCH($A38,PROG_ID,0))),"")) -> 46281 | R38: =IF($A38="","",IFERROR(IF(INDEX(OS_FIM,MATCH($A38,OS_ID,0))=0,"",INDEX(OS_FIM,MATCH($A38,OS_ID,0))),"")) | S38: =IF($A38="","",IF($W38<>"",$W38,IF($V38>0,"MEDIDO",IF($R38<>"","EXECUTADO",IF(COUNTIFS(OS_ID,$A38)>0,"EM EXECUÇÃO",IF($Q38<>"","PROGRAMADO","CADASTRADO")))))) -> EM EXECUÇÃO | T38: =IF($A38="","",IF($R38<>"",$R38-$D38,TODAY()-$D38)) -> 0 | U38: =IF(OR($A38="",$F38=""),"",IF($R38<>"",IF($R38<=$F38,"NO PRAZO","FORA DO PRAZO"),IF(TODAY()>$F38,"VENCIDO",IF($F38-TODAY()<='01. CONFIGURAÇÕES'!$C$23,"VENCE EM BREVE","EM DIA")))) -> EM DIA | V38: =IF($A38="","",SUMIFS(MED_VLR,MED_ID,$A38)) -> 0
A39: =IF($B39="","",LEFT($B39,3)&"-"&TEXT(ROW()-4,"0000")) -> BER-0035 | B39: BERTIOGA | D39: 46281 | E39: 3 | F39: =IF($D39="","",$D39+IF($E39="",'01. CONFIGURAÇÕES'!$C$22,$E39)) -> 46284 | G39: URGENTE | H39: Vazamento no ramal não visível | I39: Rua Tambaú | J39: 470 | K39: Vicente de Carvalho | L39: Guarujá | P39: =IFERROR(IF($A39="","",IF(COUNTIFS(OS_ID,$A39)>0,INDEX(OS_EQUIPE,MATCH($A39,OS_ID,0)),IF(COUNTIFS(PROG_ID,$A39)>0,INDEX(PROG_EQUIPE,MATCH($A39,PROG_ID,0)),""))),"") -> 0 | Q39: =IF($A39="","",IFERROR(IF(INDEX(PROG_DATA,MATCH($A39,PROG_ID,0))=0,"",INDEX(PROG_DATA,MATCH($A39,PROG_ID,0))),"")) -> 46281 | R39: =IF($A39="","",IFERROR(IF(INDEX(OS_FIM,MATCH($A39,OS_ID,0))=0,"",INDEX(OS_FIM,MATCH($A39,OS_ID,0))),"")) | S39: =IF($A39="","",IF($W39<>"",$W39,IF($V39>0,"MEDIDO",IF($R39<>"","EXECUTADO",IF(COUNTIFS(OS_ID,$A39)>0,"EM EXECUÇÃO",IF($Q39<>"","PROGRAMADO","CADASTRADO")))))) -> EM EXECUÇÃO | T39: =IF($A39="","",IF($R39<>"",$R39-$D39,TODAY()-$D39)) -> 0 | U39: =IF(OR($A39="",$F39=""),"",IF($R39<>"",IF($R39<=$F39,"NO PRAZO","FORA DO PRAZO"),IF(TODAY()>$F39,"VENCIDO",IF($F39-TODAY()<='01. CONFIGURAÇÕES'!$C$23,"VENCE EM BREVE","EM DIA")))) -> EM DIA | V39: =IF($A39="","",SUMIFS(MED_VLR,MED_ID,$A39)) -> 0
A40: =IF($B40="","",LEFT($B40,3)&"-"&TEXT(ROW()-4,"0000")) -> BER-0036 | B40: BERTIOGA | D40: 46281 | E40: 3 | F40: =IF($D40="","",$D40+IF($E40="",'01. CONFIGURAÇÕES'!$C$22,$E40)) -> 46284 | G40: URGENTE | H40: Vazamento de água não visível — rede | I40: Cazil Frazon | J40: 432 | K40: Vicente de Carvalho | L40: Guarujá | P40: =IFERROR(IF($A40="","",IF(COUNTIFS(OS_ID,$A40)>0,INDEX(OS_EQUIPE,MATCH($A40,OS_ID,0)),IF(COUNTIFS(PROG_ID,$A40)>0,INDEX(PROG_EQUIPE,MATCH($A40,PROG_ID,0)),""))),"") -> 0 | Q40: =IF($A40="","",IFERROR(IF(INDEX(PROG_DATA,MATCH($A40,PROG_ID,0))=0,"",INDEX(PROG_DATA,MATCH($A40,PROG_ID,0))),"")) -> 46281 | R40: =IF($A40="","",IFERROR(IF(INDEX(OS_FIM,MATCH($A40,OS_ID,0))=0,"",INDEX(OS_FIM,MATCH($A40,OS_ID,0))),"")) | S40: =IF($A40="","",IF($W40<>"",$W40,IF($V40>0,"MEDIDO",IF($R40<>"","EXECUTADO",IF(COUNTIFS(OS_ID,$A40)>0,"EM EXECUÇÃO",IF($Q40<>"","PROGRAMADO","CADASTRADO")))))) -> EM EXECUÇÃO | T40: =IF($A40="","",IF($R40<>"",$R40-$D40,TODAY()-$D40)) -> 0 | U40: =IF(OR($A40="",$F40=""),"",IF($R40<>"",IF($R40<=$F40,"NO PRAZO","FORA DO PRAZO"),IF(TODAY()>$F40,"VENCIDO",IF($F40-TODAY()<='01. CONFIGURAÇÕES'!$C$23,"VENCE EM BREVE","EM DIA")))) -> EM DIA | V40: =IF($A40="","",SUMIFS(MED_VLR,MED_ID,$A40)) -> 0
A41: =IF($B41="","",LEFT($B41,3)&"-"&TEXT(ROW()-4,"0000")) -> BER-0037 | B41: BERTIOGA | D41: 46281 | E41: 3 | F41: =IF($D41="","",$D41+IF($E41="",'01. CONFIGURAÇÕES'!$C$22,$E41)) -> 46284 | G41: URGENTE | H41: Vazamento de água não visível — rede | I41: Rua Clemente da Mata Amorim | J41: 28 | K41: Jardim Progresso | L41: Guarujá | P41: =IFERROR(IF($A41="","",IF(COUNTIFS(OS_ID,$A41)>0,INDEX(OS_EQUIPE,MATCH($A41,OS_ID,0)),IF(COUNTIFS(PROG_ID,$A41)>0,INDEX(PROG_EQUIPE,MATCH($A41,PROG_ID,0)),""))),"") -> 0 | Q41: =IF($A41="","",IFERROR(IF(INDEX(PROG_DATA,MATCH($A41,PROG_ID,0))=0,"",INDEX(PROG_DATA,MATCH($A41,PROG_ID,0))),"")) -> 46281 | R41: =IF($A41="","",IFERROR(IF(INDEX(OS_FIM,MATCH($A41,OS_ID,0))=0,"",INDEX(OS_FIM,MATCH($A41,OS_ID,0))),"")) | S41: =IF($A41="","",IF($W41<>"",$W41,IF($V41>0,"MEDIDO",IF($R41<>"","EXECUTADO",IF(COUNTIFS(OS_ID,$A41)>0,"EM EXECUÇÃO",IF($Q41<>"","PROGRAMADO","CADASTRADO")))))) -> EM EXECUÇÃO | T41: =IF($A41="","",IF($R41<>"",$R41-$D41,TODAY()-$D41)) -> 0 | U41: =IF(OR($A41="",$F41=""),"",IF($R41<>"",IF($R41<=$F41,"NO PRAZO","FORA DO PRAZO"),IF(TODAY()>$F41,"VENCIDO",IF($F41-TODAY()<='01. CONFIGURAÇÕES'!$C$23,"VENCE EM BREVE","EM DIA")))) -> EM DIA | V41: =IF($A41="","",SUMIFS(MED_VLR,MED_ID,$A41)) -> 0
A42: =IF($B42="","",LEFT($B42,3)&"-"&TEXT(ROW()-4,"0000")) -> BER-0038 | B42: BERTIOGA | D42: 46281 | E42: 3 | F42: =IF($D42="","",$D42+IF($E42="",'01. CONFIGURAÇÕES'!$C$22,$E42)) -> 46284 | G42: URGENTE | H42: Vazamento no ramal não visível | I42: Rua Clemente da Mata Amorim | J42: 77A | K42: Jardim Progresso | L42: Guarujá | P42: =IFERROR(IF($A42="","",IF(COUNTIFS(OS_ID,$A42)>0,INDEX(OS_EQUIPE,MATCH($A42,OS_ID,0)),IF(COUNTIFS(PROG_ID,$A42)>0,INDEX(PROG_EQUIPE,MATCH($A42,PROG_ID,0)),""))),"") -> 0 | Q42: =IF($A42="","",IFERROR(IF(INDEX(PROG_DATA,MATCH($A42,PROG_ID,0))=0,"",INDEX(PROG_DATA,MATCH($A42,PROG_ID,0))),"")) -> 46281 | R42: =IF($A42="","",IFERROR(IF(INDEX(OS_FIM,MATCH($A42,OS_ID,0))=0,"",INDEX(OS_FIM,MATCH($A42,OS_ID,0))),"")) | S42: =IF($A42="","",IF($W42<>"",$W42,IF($V42>0,"MEDIDO",IF($R42<>"","EXECUTADO",IF(COUNTIFS(OS_ID,$A42)>0,"EM EXECUÇÃO",IF($Q42<>"","PROGRAMADO","CADASTRADO")))))) -> EM EXECUÇÃO | T42: =IF($A42="","",IF($R42<>"",$R42-$D42,TODAY()-$D42)) -> 0 | U42: =IF(OR($A42="",$F42=""),"",IF($R42<>"",IF($R42<=$F42,"NO PRAZO","FORA DO PRAZO"),IF(TODAY()>$F42,"VENCIDO",IF($F42-TODAY()<='01. CONFIGURAÇÕES'!$C$23,"VENCE EM BREVE","EM DIA")))) -> EM DIA | V42: =IF($A42="","",SUMIFS(MED_VLR,MED_ID,$A42)) -> 0
A43: =IF($B43="","",LEFT($B43,3)&"-"&TEXT(ROW()-4,"0000")) -> BER-0039 | B43: BERTIOGA | D43: 46281 | E43: 3 | F43: =IF($D43="","",$D43+IF($E43="",'01. CONFIGURAÇÕES'!$C$22,$E43)) -> 46284 | G43: URGENTE | H43: Vazamento cavalete não visível | I43: Rua Adão Pereira da Silva | J43: 35 | K43: Jardim Progresso | L43: Guarujá | P43: =IFERROR(IF($A43="","",IF(COUNTIFS(OS_ID,$A43)>0,INDEX(OS_EQUIPE,MATCH($A43,OS_ID,0)),IF(COUNTIFS(PROG_ID,$A43)>0,INDEX(PROG_EQUIPE,MATCH($A43,PROG_ID,0)),""))),"") -> 0 | Q43: =IF($A43="","",IFERROR(IF(INDEX(PROG_DATA,MATCH($A43,PROG_ID,0))=0,"",INDEX(PROG_DATA,MATCH($A43,PROG_ID,0))),"")) -> 46281 | R43: =IF($A43="","",IFERROR(IF(INDEX(OS_FIM,MATCH($A43,OS_ID,0))=0,"",INDEX(OS_FIM,MATCH($A43,OS_ID,0))),"")) | S43: =IF($A43="","",IF($W43<>"",$W43,IF($V43>0,"MEDIDO",IF($R43<>"","EXECUTADO",IF(COUNTIFS(OS_ID,$A43)>0,"EM EXECUÇÃO",IF($Q43<>"","PROGRAMADO","CADASTRADO")))))) -> EM EXECUÇÃO | T43: =IF($A43="","",IF($R43<>"",$R43-$D43,TODAY()-$D43)) -> 0 | U43: =IF(OR($A43="",$F43=""),"",IF($R43<>"",IF($R43<=$F43,"NO PRAZO","FORA DO PRAZO"),IF(TODAY()>$F43,"VENCIDO",IF($F43-TODAY()<='01. CONFIGURAÇÕES'!$C$23,"VENCE EM BREVE","EM DIA")))) -> EM DIA | V43: =IF($A43="","",SUMIFS(MED_VLR,MED_ID,$A43)) -> 0
A44: =IF($B44="","",LEFT($B44,3)&"-"&TEXT(ROW()-4,"0000")) -> BER-0040 | B44: BERTIOGA | D44: 46281 | E44: 3 | F44: =IF($D44="","",$D44+IF($E44="",'01. CONFIGURAÇÕES'!$C$22,$E44)) -> 46284 | G44: URGENTE | H44: Vazamento no ramal não visível | I44: Rua Manoel Romero Rodrigues | J44: 18 | K44: Jardim Progresso | L44: Guarujá | P44: =IFERROR(IF($A44="","",IF(COUNTIFS(OS_ID,$A44)>0,INDEX(OS_EQUIPE,MATCH($A44,OS_ID,0)),IF(COUNTIFS(PROG_ID,$A44)>0,INDEX(PROG_EQUIPE,MATCH($A44,PROG_ID,0)),""))),"") -> 0 | Q44: =IF($A44="","",IFERROR(IF(INDEX(PROG_DATA,MATCH($A44,PROG_ID,0))=0,"",INDEX(PROG_DATA,MATCH($A44,PROG_ID,0))),"")) -> 46281 | R44: =IF($A44="","",IFERROR(IF(INDEX(OS_FIM,MATCH($A44,OS_ID,0))=0,"",INDEX(OS_FIM,MATCH($A44,OS_ID,0))),"")) | S44: =IF($A44="","",IF($W44<>"",$W44,IF($V44>0,"MEDIDO",IF($R44<>"","EXECUTADO",IF(COUNTIFS(OS_ID,$A44)>0,"EM EXECUÇÃO",IF($Q44<>"","PROGRAMADO","CADASTRADO")))))) -> EM EXECUÇÃO | T44: =IF($A44="","",IF($R44<>"",$R44-$D44,TODAY()-$D44)) -> 0 | U44: =IF(OR($A44="",$F44=""),"",IF($R44<>"",IF($R44<=$F44,"NO PRAZO","FORA DO PRAZO"),IF(TODAY()>$F44,"VENCIDO",IF($F44-TODAY()<='01. CONFIGURAÇÕES'!$C$23,"VENCE EM BREVE","EM DIA")))) -> EM DIA | V44: =IF($A44="","",SUMIFS(MED_VLR,MED_ID,$A44)) -> 0
A45: =IF($B45="","",LEFT($B45,3)&"-"&TEXT(ROW()-4,"0000")) -> BER-0041 | B45: BERTIOGA | D45: 46281 | E45: 3 | F45: =IF($D45="","",$D45+IF($E45="",'01. CONFIGURAÇÕES'!$C$22,$E45)) -> 46284 | G45: URGENTE | H45: Vazamento no ramal não visível | I45: Rua Manoel Romero Rodrigues | J45: 118 | K45: Jardim Progresso | L45: Guarujá | P45: =IFERROR(IF($A45="","",IF(COUNTIFS(OS_ID,$A45)>0,INDEX(OS_EQUIPE,MATCH($A45,OS_ID,0)),IF(COUNTIFS(PROG_ID,$A45)>0,INDEX(PROG_EQUIPE,MATCH($A45,PROG_ID,0)),""))),"") -> 0 | Q45: =IF($A45="","",IFERROR(IF(INDEX(PROG_DATA,MATCH($A45,PROG_ID,0))=0,"",INDEX(PROG_DATA,MATCH($A45,PROG_ID,0))),"")) -> 46281 | R45: =IF($A45="","",IFERROR(IF(INDEX(OS_FIM,MATCH($A45,OS_ID,0))=0,"",INDEX(OS_FIM,MATCH($A45,OS_ID,0))),"")) | S45: =IF($A45="","",IF($W45<>"",$W45,IF($V45>0,"MEDIDO",IF($R45<>"","EXECUTADO",IF(COUNTIFS(OS_ID,$A45)>0,"EM EXECUÇÃO",IF($Q45<>"","PROGRAMADO","CADASTRADO")))))) -> EM EXECUÇÃO | T45: =IF($A45="","",IF($R45<>"",$R45-$D45,TODAY()-$D45)) -> 0 | U45: =IF(OR($A45="",$F45=""),"",IF($R45<>"",IF($R45<=$F45,"NO PRAZO","FORA DO PRAZO"),IF(TODAY()>$F45,"VENCIDO",IF($F45-TODAY()<='01. CONFIGURAÇÕES'!$C$23,"VENCE EM BREVE","EM DIA")))) -> EM DIA | V45: =IF($A45="","",SUMIFS(MED_VLR,MED_ID,$A45)) -> 0
A46: =IF($B46="","",LEFT($B46,3)&"-"&TEXT(ROW()-4,"0000")) -> BER-0042 | B46: BERTIOGA | D46: 46281 | E46: 3 | F46: =IF($D46="","",$D46+IF($E46="",'01. CONFIGURAÇÕES'!$C$22,$E46)) -> 46284 | G46: URGENTE | H46: Vazamento de água não visível — rede | I46: Rua Dickson Rodrigues | J46: 39 | K46: Jardim Progresso | L46: Guarujá | P46: =IFERROR(IF($A46="","",IF(COUNTIFS(OS_ID,$A46)>0,INDEX(OS_EQUIPE,MATCH($A46,OS_ID,0)),IF(COUNTIFS(PROG_ID,$A46)>0,INDEX(PROG_EQUIPE,MATCH($A46,PROG_ID,0)),""))),"") -> 0 | Q46: =IF($A46="","",IFERROR(IF(INDEX(PROG_DATA,MATCH($A46,PROG_ID,0))=0,"",INDEX(PROG_DATA,MATCH($A46,PROG_ID,0))),"")) -> 46281 | R46: =IF($A46="","",IFERROR(IF(INDEX(OS_FIM,MATCH($A46,OS_ID,0))=0,"",INDEX(OS_FIM,MATCH($A46,OS_ID,0))),"")) | S46: =IF($A46="","",IF($W46<>"",$W46,IF($V46>0,"MEDIDO",IF($R46<>"","EXECUTADO",IF(COUNTIFS(OS_ID,$A46)>0,"EM EXECUÇÃO",IF($Q46<>"","PROGRAMADO","CADASTRADO")))))) -> EM EXECUÇÃO | T46: =IF($A46="","",IF($R46<>"",$R46-$D46,TODAY()-$D46)) -> 0 | U46: =IF(OR($A46="",$F46=""),"",IF($R46<>"",IF($R46<=$F46,"NO PRAZO","FORA DO PRAZO"),IF(TODAY()>$F46,"VENCIDO",IF($F46-TODAY()<='01. CONFIGURAÇÕES'!$C$23,"VENCE EM BREVE","EM DIA")))) -> EM DIA | V46: =IF($A46="","",SUMIFS(MED_VLR,MED_ID,$A46)) -> 0
A47: =IF($B47="","",LEFT($B47,3)&"-"&TEXT(ROW()-4,"0000")) -> BER-0043 | B47: BERTIOGA | D47: 46281 | E47: 3 | F47: =IF($D47="","",$D47+IF($E47="",'01. CONFIGURAÇÕES'!$C$22,$E47)) -> 46284 | G47: URGENTE | H47: Vazamento no ramal não visível | I47: Rua Coronel João Akui | J47: 38 | K47: Jardim Progresso | L47: Guarujá | P47: =IFERROR(IF($A47="","",IF(COUNTIFS(OS_ID,$A47)>0,INDEX(OS_EQUIPE,MATCH($A47,OS_ID,0)),IF(COUNTIFS(PROG_ID,$A47)>0,INDEX(PROG_EQUIPE,MATCH($A47,PROG_ID,0)),""))),"") -> 0 | Q47: =IF($A47="","",IFERROR(IF(INDEX(PROG_DATA,MATCH($A47,PROG_ID,0))=0,"",INDEX(PROG_DATA,MATCH($A47,PROG_ID,0))),"")) -> 46281 | R47: =IF($A47="","",IFERROR(IF(INDEX(OS_FIM,MATCH($A47,OS_ID,0))=0,"",INDEX(OS_FIM,MATCH($A47,OS_ID,0))),"")) | S47: =IF($A47="","",IF($W47<>"",$W47,IF($V47>0,"MEDIDO",IF($R47<>"","EXECUTADO",IF(COUNTIFS(OS_ID,$A47)>0,"EM EXECUÇÃO",IF($Q47<>"","PROGRAMADO","CADASTRADO")))))) -> EM EXECUÇÃO | T47: =IF($A47="","",IF($R47<>"",$R47-$D47,TODAY()-$D47)) -> 0 | U47: =IF(OR($A47="",$F47=""),"",IF($R47<>"",IF($R47<=$F47,"NO PRAZO","FORA DO PRAZO"),IF(TODAY()>$F47,"VENCIDO",IF($F47-TODAY()<='01. CONFIGURAÇÕES'!$C$23,"VENCE EM BREVE","EM DIA")))) -> EM DIA | V47: =IF($A47="","",SUMIFS(MED_VLR,MED_ID,$A47)) -> 0
A48: =IF($B48="","",LEFT($B48,3)&"-"&TEXT(ROW()-4,"0000")) -> BER-0044 | B48: BERTIOGA | D48: 46281 | E48: 3 | F48: =IF($D48="","",$D48+IF($E48="",'01. CONFIGURAÇÕES'!$C$22,$E48)) -> 46284 | G48: URGENTE | H48: Vazamento no ramal não visível | I48: Rua Miguel Seiad | J48: 930 | L48: Bertioga | O48: Vazamento no ramal não visível | P48: =IFERROR(IF($A48="","",IF(COUNTIFS(OS_ID,$A48)>0,INDEX(OS_EQUIPE,MATCH($A48,OS_ID,0)),IF(COUNTIFS(PROG_ID,$A48)>0,INDEX(PROG_EQUIPE,MATCH($A48,PROG_ID,0)),""))),"") -> 0 | Q48: =IF($A48="","",IFERROR(IF(INDEX(PROG_DATA,MATCH($A48,PROG_ID,0))=0,"",INDEX(PROG_DATA,MATCH($A48,PROG_ID,0))),"")) -> 46281 | R48: =IF($A48="","",IFERROR(IF(INDEX(OS_FIM,MATCH($A48,OS_ID,0))=0,"",INDEX(OS_FIM,MATCH($A48,OS_ID,0))),"")) -> 46281 | S48: =IF($A48="","",IF($W48<>"",$W48,IF($V48>0,"MEDIDO",IF($R48<>"","EXECUTADO",IF(COUNTIFS(OS_ID,$A48)>0,"EM EXECUÇÃO",IF($Q48<>"","PROGRAMADO","CADASTRADO")))))) -> MEDIDO | T48: =IF($A48="","",IF($R48<>"",$R48-$D48,TODAY()-$D48)) -> 0 | U48: =IF(OR($A48="",$F48=""),"",IF($R48<>"",IF($R48<=$F48,"NO PRAZO","FORA DO PRAZO"),IF(TODAY()>$F48,"VENCIDO",IF($F48-TODAY()<='01. CONFIGURAÇÕES'!$C$23,"VENCE EM BREVE","EM DIA")))) -> NO PRAZO | V48: =IF($A48="","",SUMIFS(MED_VLR,MED_ID,$A48)) -> 2132.87
A49: =IF($B49="","",LEFT($B49,3)&"-"&TEXT(ROW()-4,"0000")) -> BER-0045 | B49: BERTIOGA | F49: =IF($D49="","",$D49+IF($E49="",'01. CONFIGURAÇÕES'!$C$22,$E49)) | P49: =IFERROR(IF($A49="","",IF(COUNTIFS(OS_ID,$A49)>0,INDEX(OS_EQUIPE,MATCH($A49,OS_ID,0)),IF(COUNTIFS(PROG_ID,$A49)>0,INDEX(PROG_EQUIPE,MATCH($A49,PROG_ID,0)),""))),"") | Q49: =IF($A49="","",IFERROR(IF(INDEX(PROG_DATA,MATCH($A49,PROG_ID,0))=0,"",INDEX(PROG_DATA,MATCH($A49,PROG_ID,0))),"")) | R49: =IF($A49="","",IFERROR(IF(INDEX(OS_FIM,MATCH($A49,OS_ID,0))=0,"",INDEX(OS_FIM,MATCH($A49,OS_ID,0))),"")) | S49: =IF($A49="","",IF($W49<>"",$W49,IF($V49>0,"MEDIDO",IF($R49<>"","EXECUTADO",IF(COUNTIFS(OS_ID,$A49)>0,"EM EXECUÇÃO",IF($Q49<>"","PROGRAMADO","CADASTRADO")))))) -> CADASTRADO | T49: =IF($A49="","",IF($R49<>"",$R49-$D49,TODAY()-$D49)) -> 46281 | U49: =IF(OR($A49="",$F49=""),"",IF($R49<>"",IF($R49<=$F49,"NO PRAZO","FORA DO PRAZO"),IF(TODAY()>$F49,"VENCIDO",IF($F49-TODAY()<='01. CONFIGURAÇÕES'!$C$23,"VENCE EM BREVE","EM DIA")))) | V49: =IF($A49="","",SUMIFS(MED_VLR,MED_ID,$A49)) -> 0
A50: =IF($B50="","",LEFT($B50,3)&"-"&TEXT(ROW()-4,"0000")) -> BER-0046 | B50: BERTIOGA | F50: =IF($D50="","",$D50+IF($E50="",'01. CONFIGURAÇÕES'!$C$22,$E50)) | P50: =IFERROR(IF($A50="","",IF(COUNTIFS(OS_ID,$A50)>0,INDEX(OS_EQUIPE,MATCH($A50,OS_ID,0)),IF(COUNTIFS(PROG_ID,$A50)>0,INDEX(PROG_EQUIPE,MATCH($A50,PROG_ID,0)),""))),"") | Q50: =IF($A50="","",IFERROR(IF(INDEX(PROG_DATA,MATCH($A50,PROG_ID,0))=0,"",INDEX(PROG_DATA,MATCH($A50,PROG_ID,0))),"")) | R50: =IF($A50="","",IFERROR(IF(INDEX(OS_FIM,MATCH($A50,OS_ID,0))=0,"",INDEX(OS_FIM,MATCH($A50,OS_ID,0))),"")) | S50: =IF($A50="","",IF($W50<>"",$W50,IF($V50>0,"MEDIDO",IF($R50<>"","EXECUTADO",IF(COUNTIFS(OS_ID,$A50)>0,"EM EXECUÇÃO",IF($Q50<>"","PROGRAMADO","CADASTRADO")))))) -> CADASTRADO | T50: =IF($A50="","",IF($R50<>"",$R50-$D50,TODAY()-$D50)) -> 46281 | U50: =IF(OR($A50="",$F50=""),"",IF($R50<>"",IF($R50<=$F50,"NO PRAZO","FORA DO PRAZO"),IF(TODAY()>$F50,"VENCIDO",IF($F50-TODAY()<='01. CONFIGURAÇÕES'!$C$23,"VENCE EM BREVE","EM DIA")))) | V50: =IF($A50="","",SUMIFS(MED_VLR,MED_ID,$A50)) -> 0
A51: =IF($B51="","",LEFT($B51,3)&"-"&TEXT(ROW()-4,"0000")) -> BER-0047 | B51: BERTIOGA | F51: =IF($D51="","",$D51+IF($E51="",'01. CONFIGURAÇÕES'!$C$22,$E51)) | P51: =IFERROR(IF($A51="","",IF(COUNTIFS(OS_ID,$A51)>0,INDEX(OS_EQUIPE,MATCH($A51,OS_ID,0)),IF(COUNTIFS(PROG_ID,$A51)>0,INDEX(PROG_EQUIPE,MATCH($A51,PROG_ID,0)),""))),"") | Q51: =IF($A51="","",IFERROR(IF(INDEX(PROG_DATA,MATCH($A51,PROG_ID,0))=0,"",INDEX(PROG_DATA,MATCH($A51,PROG_ID,0))),"")) | R51: =IF($A51="","",IFERROR(IF(INDEX(OS_FIM,MATCH($A51,OS_ID,0))=0,"",INDEX(OS_FIM,MATCH($A51,OS_ID,0))),"")) | S51: =IF($A51="","",IF($W51<>"",$W51,IF($V51>0,"MEDIDO",IF($R51<>"","EXECUTADO",IF(COUNTIFS(OS_ID,$A51)>0,"EM EXECUÇÃO",IF($Q51<>"","PROGRAMADO","CADASTRADO")))))) -> CADASTRADO | T51: =IF($A51="","",IF($R51<>"",$R51-$D51,TODAY()-$D51)) -> 46281 | U51: =IF(OR($A51="",$F51=""),"",IF($R51<>"",IF($R51<=$F51,"NO PRAZO","FORA DO PRAZO"),IF(TODAY()>$F51,"VENCIDO",IF($F51-TODAY()<='01. CONFIGURAÇÕES'!$C$23,"VENCE EM BREVE","EM DIA")))) | V51: =IF($A51="","",SUMIFS(MED_VLR,MED_ID,$A51)) -> 0
A52: =IF($B52="","",LEFT($B52,3)&"-"&TEXT(ROW()-4,"0000")) -> BER-0048 | B52: BERTIOGA | F52: =IF($D52="","",$D52+IF($E52="",'01. CONFIGURAÇÕES'!$C$22,$E52)) | P52: =IFERROR(IF($A52="","",IF(COUNTIFS(OS_ID,$A52)>0,INDEX(OS_EQUIPE,MATCH($A52,OS_ID,0)),IF(COUNTIFS(PROG_ID,$A52)>0,INDEX(PROG_EQUIPE,MATCH($A52,PROG_ID,0)),""))),"") | Q52: =IF($A52="","",IFERROR(IF(INDEX(PROG_DATA,MATCH($A52,PROG_ID,0))=0,"",INDEX(PROG_DATA,MATCH($A52,PROG_ID,0))),"")) | R52: =IF($A52="","",IFERROR(IF(INDEX(OS_FIM,MATCH($A52,OS_ID,0))=0,"",INDEX(OS_FIM,MATCH($A52,OS_ID,0))),"")) | S52: =IF($A52="","",IF($W52<>"",$W52,IF($V52>0,"MEDIDO",IF($R52<>"","EXECUTADO",IF(COUNTIFS(OS_ID,$A52)>0,"EM EXECUÇÃO",IF($Q52<>"","PROGRAMADO","CADASTRADO")))))) -> CADASTRADO | T52: =IF($A52="","",IF($R52<>"",$R52-$D52,TODAY()-$D52)) -> 46281 | U52: =IF(OR($A52="",$F52=""),"",IF($R52<>"",IF($R52<=$F52,"NO PRAZO","FORA DO PRAZO"),IF(TODAY()>$F52,"VENCIDO",IF($F52-TODAY()<='01. CONFIGURAÇÕES'!$C$23,"VENCE EM BREVE","EM DIA")))) | V52: =IF($A52="","",SUMIFS(MED_VLR,MED_ID,$A52)) -> 0
A53: =IF($B53="","",LEFT($B53,3)&"-"&TEXT(ROW()-4,"0000")) -> BER-0049 | B53: BERTIOGA | F53: =IF($D53="","",$D53+IF($E53="",'01. CONFIGURAÇÕES'!$C$22,$E53)) | P53: =IFERROR(IF($A53="","",IF(COUNTIFS(OS_ID,$A53)>0,INDEX(OS_EQUIPE,MATCH($A53,OS_ID,0)),IF(COUNTIFS(PROG_ID,$A53)>0,INDEX(PROG_EQUIPE,MATCH($A53,PROG_ID,0)),""))),"") | Q53: =IF($A53="","",IFERROR(IF(INDEX(PROG_DATA,MATCH($A53,PROG_ID,0))=0,"",INDEX(PROG_DATA,MATCH($A53,PROG_ID,0))),"")) | R53: =IF($A53="","",IFERROR(IF(INDEX(OS_FIM,MATCH($A53,OS_ID,0))=0,"",INDEX(OS_FIM,MATCH($A53,OS_ID,0))),"")) | S53: =IF($A53="","",IF($W53<>"",$W53,IF($V53>0,"MEDIDO",IF($R53<>"","EXECUTADO",IF(COUNTIFS(OS_ID,$A53)>0,"EM EXECUÇÃO",IF($Q53<>"","PROGRAMADO","CADASTRADO")))))) -> CADASTRADO | T53: =IF($A53="","",IF($R53<>"",$R53-$D53,TODAY()-$D53)) -> 46281 | U53: =IF(OR($A53="",$F53=""),"",IF($R53<>"",IF($R53<=$F53,"NO PRAZO","FORA DO PRAZO"),IF(TODAY()>$F53,"VENCIDO",IF($F53-TODAY()<='01. CONFIGURAÇÕES'!$C$23,"VENCE EM BREVE","EM DIA")))) | V53: =IF($A53="","",SUMIFS(MED_VLR,MED_ID,$A53)) -> 0
A54: =IF($B54="","",LEFT($B54,3)&"-"&TEXT(ROW()-4,"0000")) -> BER-0050 | B54: BERTIOGA | F54: =IF($D54="","",$D54+IF($E54="",'01. CONFIGURAÇÕES'!$C$22,$E54)) | P54: =IFERROR(IF($A54="","",IF(COUNTIFS(OS_ID,$A54)>0,INDEX(OS_EQUIPE,MATCH($A54,OS_ID,0)),IF(COUNTIFS(PROG_ID,$A54)>0,INDEX(PROG_EQUIPE,MATCH($A54,PROG_ID,0)),""))),"") | Q54: =IF($A54="","",IFERROR(IF(INDEX(PROG_DATA,MATCH($A54,PROG_ID,0))=0,"",INDEX(PROG_DATA,MATCH($A54,PROG_ID,0))),"")) | R54: =IF($A54="","",IFERROR(IF(INDEX(OS_FIM,MATCH($A54,OS_ID,0))=0,"",INDEX(OS_FIM,MATCH($A54,OS_ID,0))),"")) | S54: =IF($A54="","",IF($W54<>"",$W54,IF($V54>0,"MEDIDO",IF($R54<>"","EXECUTADO",IF(COUNTIFS(OS_ID,$A54)>0,"EM EXECUÇÃO",IF($Q54<>"","PROGRAMADO","CADASTRADO")))))) -> CADASTRADO | T54: =IF($A54="","",IF($R54<>"",$R54-$D54,TODAY()-$D54)) -> 46281 | U54: =IF(OR($A54="",$F54=""),"",IF($R54<>"",IF($R54<=$F54,"NO PRAZO","FORA DO PRAZO"),IF(TODAY()>$F54,"VENCIDO",IF($F54-TODAY()<='01. CONFIGURAÇÕES'!$C$23,"VENCE EM BREVE","EM DIA")))) | V54: =IF($A54="","",SUMIFS(MED_VLR,MED_ID,$A54)) -> 0
A55: =IF($B55="","",LEFT($B55,3)&"-"&TEXT(ROW()-4,"0000")) -> BER-0051 | B55: BERTIOGA | F55: =IF($D55="","",$D55+IF($E55="",'01. CONFIGURAÇÕES'!$C$22,$E55)) | P55: =IFERROR(IF($A55="","",IF(COUNTIFS(OS_ID,$A55)>0,INDEX(OS_EQUIPE,MATCH($A55,OS_ID,0)),IF(COUNTIFS(PROG_ID,$A55)>0,INDEX(PROG_EQUIPE,MATCH($A55,PROG_ID,0)),""))),"") | Q55: =IF($A55="","",IFERROR(IF(INDEX(PROG_DATA,MATCH($A55,PROG_ID,0))=0,"",INDEX(PROG_DATA,MATCH($A55,PROG_ID,0))),"")) | R55: =IF($A55="","",IFERROR(IF(INDEX(OS_FIM,MATCH($A55,OS_ID,0))=0,"",INDEX(OS_FIM,MATCH($A55,OS_ID,0))),"")) | S55: =IF($A55="","",IF($W55<>"",$W55,IF($V55>0,"MEDIDO",IF($R55<>"","EXECUTADO",IF(COUNTIFS(OS_ID,$A55)>0,"EM EXECUÇÃO",IF($Q55<>"","PROGRAMADO","CADASTRADO")))))) -> CADASTRADO | T55: =IF($A55="","",IF($R55<>"",$R55-$D55,TODAY()-$D55)) -> 46281 | U55: =IF(OR($A55="",$F55=""),"",IF($R55<>"",IF($R55<=$F55,"NO PRAZO","FORA DO PRAZO"),IF(TODAY()>$F55,"VENCIDO",IF($F55-TODAY()<='01. CONFIGURAÇÕES'!$C$23,"VENCE EM BREVE","EM DIA")))) | V55: =IF($A55="","",SUMIFS(MED_VLR,MED_ID,$A55)) -> 0
A56: =IF($B56="","",LEFT($B56,3)&"-"&TEXT(ROW()-4,"0000")) -> BER-0052 | B56: BERTIOGA | F56: =IF($D56="","",$D56+IF($E56="",'01. CONFIGURAÇÕES'!$C$22,$E56)) | P56: =IFERROR(IF($A56="","",IF(COUNTIFS(OS_ID,$A56)>0,INDEX(OS_EQUIPE,MATCH($A56,OS_ID,0)),IF(COUNTIFS(PROG_ID,$A56)>0,INDEX(PROG_EQUIPE,MATCH($A56,PROG_ID,0)),""))),"") | Q56: =IF($A56="","",IFERROR(IF(INDEX(PROG_DATA,MATCH($A56,PROG_ID,0))=0,"",INDEX(PROG_DATA,MATCH($A56,PROG_ID,0))),"")) | R56: =IF($A56="","",IFERROR(IF(INDEX(OS_FIM,MATCH($A56,OS_ID,0))=0,"",INDEX(OS_FIM,MATCH($A56,OS_ID,0))),"")) | S56: =IF($A56="","",IF($W56<>"",$W56,IF($V56>0,"MEDIDO",IF($R56<>"","EXECUTADO",IF(COUNTIFS(OS_ID,$A56)>0,"EM EXECUÇÃO",IF($Q56<>"","PROGRAMADO","CADASTRADO")))))) -> CADASTRADO | T56: =IF($A56="","",IF($R56<>"",$R56-$D56,TODAY()-$D56)) -> 46281 | U56: =IF(OR($A56="",$F56=""),"",IF($R56<>"",IF($R56<=$F56,"NO PRAZO","FORA DO PRAZO"),IF(TODAY()>$F56,"VENCIDO",IF($F56-TODAY()<='01. CONFIGURAÇÕES'!$C$23,"VENCE EM BREVE","EM DIA")))) | V56: =IF($A56="","",SUMIFS(MED_VLR,MED_ID,$A56)) -> 0
A57: =IF($B57="","",LEFT($B57,3)&"-"&TEXT(ROW()-4,"0000")) -> BER-0053 | B57: BERTIOGA | F57: =IF($D57="","",$D57+IF($E57="",'01. CONFIGURAÇÕES'!$C$22,$E57)) | P57: =IFERROR(IF($A57="","",IF(COUNTIFS(OS_ID,$A57)>0,INDEX(OS_EQUIPE,MATCH($A57,OS_ID,0)),IF(COUNTIFS(PROG_ID,$A57)>0,INDEX(PROG_EQUIPE,MATCH($A57,PROG_ID,0)),""))),"") | Q57: =IF($A57="","",IFERROR(IF(INDEX(PROG_DATA,MATCH($A57,PROG_ID,0))=0,"",INDEX(PROG_DATA,MATCH($A57,PROG_ID,0))),"")) | R57: =IF($A57="","",IFERROR(IF(INDEX(OS_FIM,MATCH($A57,OS_ID,0))=0,"",INDEX(OS_FIM,MATCH($A57,OS_ID,0))),"")) | S57: =IF($A57="","",IF($W57<>"",$W57,IF($V57>0,"MEDIDO",IF($R57<>"","EXECUTADO",IF(COUNTIFS(OS_ID,$A57)>0,"EM EXECUÇÃO",IF($Q57<>"","PROGRAMADO","CADASTRADO")))))) -> CADASTRADO | T57: =IF($A57="","",IF($R57<>"",$R57-$D57,TODAY()-$D57)) -> 46281 | U57: =IF(OR($A57="",$F57=""),"",IF($R57<>"",IF($R57<=$F57,"NO PRAZO","FORA DO PRAZO"),IF(TODAY()>$F57,"VENCIDO",IF($F57-TODAY()<='01. CONFIGURAÇÕES'!$C$23,"VENCE EM BREVE","EM DIA")))) | V57: =IF($A57="","",SUMIFS(MED_VLR,MED_ID,$A57)) -> 0
A58: =IF($B58="","",LEFT($B58,3)&"-"&TEXT(ROW()-4,"0000")) -> BER-0054 | B58: BERTIOGA | F58: =IF($D58="","",$D58+IF($E58="",'01. CONFIGURAÇÕES'!$C$22,$E58)) | P58: =IFERROR(IF($A58="","",IF(COUNTIFS(OS_ID,$A58)>0,INDEX(OS_EQUIPE,MATCH($A58,OS_ID,0)),IF(COUNTIFS(PROG_ID,$A58)>0,INDEX(PROG_EQUIPE,MATCH($A58,PROG_ID,0)),""))),"") | Q58: =IF($A58="","",IFERROR(IF(INDEX(PROG_DATA,MATCH($A58,PROG_ID,0))=0,"",INDEX(PROG_DATA,MATCH($A58,PROG_ID,0))),"")) | R58: =IF($A58="","",IFERROR(IF(INDEX(OS_FIM,MATCH($A58,OS_ID,0))=0,"",INDEX(OS_FIM,MATCH($A58,OS_ID,0))),"")) | S58: =IF($A58="","",IF($W58<>"",$W58,IF($V58>0,"MEDIDO",IF($R58<>"","EXECUTADO",IF(COUNTIFS(OS_ID,$A58)>0,"EM EXECUÇÃO",IF($Q58<>"","PROGRAMADO","CADASTRADO")))))) -> CADASTRADO | T58: =IF($A58="","",IF($R58<>"",$R58-$D58,TODAY()-$D58)) -> 46281 | U58: =IF(OR($A58="",$F58=""),"",IF($R58<>"",IF($R58<=$F58,"NO PRAZO","FORA DO PRAZO"),IF(TODAY()>$F58,"VENCIDO",IF($F58-TODAY()<='01. CONFIGURAÇÕES'!$C$23,"VENCE EM BREVE","EM DIA")))) | V58: =IF($A58="","",SUMIFS(MED_VLR,MED_ID,$A58)) -> 0
A59: =IF($B59="","",LEFT($B59,3)&"-"&TEXT(ROW()-4,"0000")) | F59: =IF($D59="","",$D59+IF($E59="",'01. CONFIGURAÇÕES'!$C$22,$E59)) | P59: =IFERROR(IF($A59="","",IF(COUNTIFS(OS_ID,$A59)>0,INDEX(OS_EQUIPE,MATCH($A59,OS_ID,0)),IF(COUNTIFS(PROG_ID,$A59)>0,INDEX(PROG_EQUIPE,MATCH($A59,PROG_ID,0)),""))),"") | Q59: =IF($A59="","",IFERROR(IF(INDEX(PROG_DATA,MATCH($A59,PROG_ID,0))=0,"",INDEX(PROG_DATA,MATCH($A59,PROG_ID,0))),"")) | R59: =IF($A59="","",IFERROR(IF(INDEX(OS_FIM,MATCH($A59,OS_ID,0))=0,"",INDEX(OS_FIM,MATCH($A59,OS_ID,0))),"")) | S59: =IF($A59="","",IF($W59<>"",$W59,IF($V59>0,"MEDIDO",IF($R59<>"","EXECUTADO",IF(COUNTIFS(OS_ID,$A59)>0,"EM EXECUÇÃO",IF($Q59<>"","PROGRAMADO","CADASTRADO")))))) | T59: =IF($A59="","",IF($R59<>"",$R59-$D59,TODAY()-$D59)) | U59: =IF(OR($A59="",$F59=""),"",IF($R59<>"",IF($R59<=$F59,"NO PRAZO","FORA DO PRAZO"),IF(TODAY()>$F59,"VENCIDO",IF($F59-TODAY()<='01. CONFIGURAÇÕES'!$C$23,"VENCE EM BREVE","EM DIA")))) | V59: =IF($A59="","",SUMIFS(MED_VLR,MED_ID,$A59))
A60: =IF($B60="","",LEFT($B60,3)&"-"&TEXT(ROW()-4,"0000")) | F60: =IF($D60="","",$D60+IF($E60="",'01. CONFIGURAÇÕES'!$C$22,$E60)) | P60: =IFERROR(IF($A60="","",IF(COUNTIFS(OS_ID,$A60)>0,INDEX(OS_EQUIPE,MATCH($A60,OS_ID,0)),IF(COUNTIFS(PROG_ID,$A60)>0,INDEX(PROG_EQUIPE,MATCH($A60,PROG_ID,0)),""))),"") | Q60: =IF($A60="","",IFERROR(IF(INDEX(PROG_DATA,MATCH($A60,PROG_ID,0))=0,"",INDEX(PROG_DATA,MATCH($A60,PROG_ID,0))),"")) | R60: =IF($A60="","",IFERROR(IF(INDEX(OS_FIM,MATCH($A60,OS_ID,0))=0,"",INDEX(OS_FIM,MATCH($A60,OS_ID,0))),"")) | S60: =IF($A60="","",IF($W60<>"",$W60,IF($V60>0,"MEDIDO",IF($R60<>"","EXECUTADO",IF(COUNTIFS(OS_ID,$A60)>0,"EM EXECUÇÃO",IF($Q60<>"","PROGRAMADO","CADASTRADO")))))) | T60: =IF($A60="","",IF($R60<>"",$R60-$D60,TODAY()-$D60)) | U60: =IF(OR($A60="",$F60=""),"",IF($R60<>"",IF($R60<=$F60,"NO PRAZO","FORA DO PRAZO"),IF(TODAY()>$F60,"VENCIDO",IF($F60-TODAY()<='01. CONFIGURAÇÕES'!$C$23,"VENCE EM BREVE","EM DIA")))) | V60: =IF($A60="","",SUMIFS(MED_VLR,MED_ID,$A60))
A61: =IF($B61="","",LEFT($B61,3)&"-"&TEXT(ROW()-4,"0000")) | F61: =IF($D61="","",$D61+IF($E61="",'01. CONFIGURAÇÕES'!$C$22,$E61)) | P61: =IFERROR(IF($A61="","",IF(COUNTIFS(OS_ID,$A61)>0,INDEX(OS_EQUIPE,MATCH($A61,OS_ID,0)),IF(COUNTIFS(PROG_ID,$A61)>0,INDEX(PROG_EQUIPE,MATCH($A61,PROG_ID,0)),""))),"") | Q61: =IF($A61="","",IFERROR(IF(INDEX(PROG_DATA,MATCH($A61,PROG_ID,0))=0,"",INDEX(PROG_DATA,MATCH($A61,PROG_ID,0))),"")) | R61: =IF($A61="","",IFERROR(IF(INDEX(OS_FIM,MATCH($A61,OS_ID,0))=0,"",INDEX(OS_FIM,MATCH($A61,OS_ID,0))),"")) | S61: =IF($A61="","",IF($W61<>"",$W61,IF($V61>0,"MEDIDO",IF($R61<>"","EXECUTADO",IF(COUNTIFS(OS_ID,$A61)>0,"EM EXECUÇÃO",IF($Q61<>"","PROGRAMADO","CADASTRADO")))))) | T61: =IF($A61="","",IF($R61<>"",$R61-$D61,TODAY()-$D61)) | U61: =IF(OR($A61="",$F61=""),"",IF($R61<>"",IF($R61<=$F61,"NO PRAZO","FORA DO PRAZO"),IF(TODAY()>$F61,"VENCIDO",IF($F61-TODAY()<='01. CONFIGURAÇÕES'!$C$23,"VENCE EM BREVE","EM DIA")))) | V61: =IF($A61="","",SUMIFS(MED_VLR,MED_ID,$A61))
A62: =IF($B62="","",LEFT($B62,3)&"-"&TEXT(ROW()-4,"0000")) | F62: =IF($D62="","",$D62+IF($E62="",'01. CONFIGURAÇÕES'!$C$22,$E62)) | P62: =IFERROR(IF($A62="","",IF(COUNTIFS(OS_ID,$A62)>0,INDEX(OS_EQUIPE,MATCH($A62,OS_ID,0)),IF(COUNTIFS(PROG_ID,$A62)>0,INDEX(PROG_EQUIPE,MATCH($A62,PROG_ID,0)),""))),"") | Q62: =IF($A62="","",IFERROR(IF(INDEX(PROG_DATA,MATCH($A62,PROG_ID,0))=0,"",INDEX(PROG_DATA,MATCH($A62,PROG_ID,0))),"")) | R62: =IF($A62="","",IFERROR(IF(INDEX(OS_FIM,MATCH($A62,OS_ID,0))=0,"",INDEX(OS_FIM,MATCH($A62,OS_ID,0))),"")) | S62: =IF($A62="","",IF($W62<>"",$W62,IF($V62>0,"MEDIDO",IF($R62<>"","EXECUTADO",IF(COUNTIFS(OS_ID,$A62)>0,"EM EXECUÇÃO",IF($Q62<>"","PROGRAMADO","CADASTRADO")))))) | T62: =IF($A62="","",IF($R62<>"",$R62-$D62,TODAY()-$D62)) | U62: =IF(OR($A62="",$F62=""),"",IF($R62<>"",IF($R62<=$F62,"NO PRAZO","FORA DO PRAZO"),IF(TODAY()>$F62,"VENCIDO",IF($F62-TODAY()<='01. CONFIGURAÇÕES'!$C$23,"VENCE EM BREVE","EM DIA")))) | V62: =IF($A62="","",SUMIFS(MED_VLR,MED_ID,$A62))
A63: =IF($B63="","",LEFT($B63,3)&"-"&TEXT(ROW()-4,"0000")) | F63: =IF($D63="","",$D63+IF($E63="",'01. CONFIGURAÇÕES'!$C$22,$E63)) | P63: =IFERROR(IF($A63="","",IF(COUNTIFS(OS_ID,$A63)>0,INDEX(OS_EQUIPE,MATCH($A63,OS_ID,0)),IF(COUNTIFS(PROG_ID,$A63)>0,INDEX(PROG_EQUIPE,MATCH($A63,PROG_ID,0)),""))),"") | Q63: =IF($A63="","",IFERROR(IF(INDEX(PROG_DATA,MATCH($A63,PROG_ID,0))=0,"",INDEX(PROG_DATA,MATCH($A63,PROG_ID,0))),"")) | R63: =IF($A63="","",IFERROR(IF(INDEX(OS_FIM,MATCH($A63,OS_ID,0))=0,"",INDEX(OS_FIM,MATCH($A63,OS_ID,0))),"")) | S63: =IF($A63="","",IF($W63<>"",$W63,IF($V63>0,"MEDIDO",IF($R63<>"","EXECUTADO",IF(COUNTIFS(OS_ID,$A63)>0,"EM EXECUÇÃO",IF($Q63<>"","PROGRAMADO","CADASTRADO")))))) | T63: =IF($A63="","",IF($R63<>"",$R63-$D63,TODAY()-$D63)) | U63: =IF(OR($A63="",$F63=""),"",IF($R63<>"",IF($R63<=$F63,"NO PRAZO","FORA DO PRAZO"),IF(TODAY()>$F63,"VENCIDO",IF($F63-TODAY()<='01. CONFIGURAÇÕES'!$C$23,"VENCE EM BREVE","EM DIA")))) | V63: =IF($A63="","",SUMIFS(MED_VLR,MED_ID,$A63))
A64: =IF($B64="","",LEFT($B64,3)&"-"&TEXT(ROW()-4,"0000")) | F64: =IF($D64="","",$D64+IF($E64="",'01. CONFIGURAÇÕES'!$C$22,$E64)) | P64: =IFERROR(IF($A64="","",IF(COUNTIFS(OS_ID,$A64)>0,INDEX(OS_EQUIPE,MATCH($A64,OS_ID,0)),IF(COUNTIFS(PROG_ID,$A64)>0,INDEX(PROG_EQUIPE,MATCH($A64,PROG_ID,0)),""))),"") | Q64: =IF($A64="","",IFERROR(IF(INDEX(PROG_DATA,MATCH($A64,PROG_ID,0))=0,"",INDEX(PROG_DATA,MATCH($A64,PROG_ID,0))),"")) | R64: =IF($A64="","",IFERROR(IF(INDEX(OS_FIM,MATCH($A64,OS_ID,0))=0,"",INDEX(OS_FIM,MATCH($A64,OS_ID,0))),"")) | S64: =IF($A64="","",IF($W64<>"",$W64,IF($V64>0,"MEDIDO",IF($R64<>"","EXECUTADO",IF(COUNTIFS(OS_ID,$A64)>0,"EM EXECUÇÃO",IF($Q64<>"","PROGRAMADO","CADASTRADO")))))) | T64: =IF($A64="","",IF($R64<>"",$R64-$D64,TODAY()-$D64)) | U64: =IF(OR($A64="",$F64=""),"",IF($R64<>"",IF($R64<=$F64,"NO PRAZO","FORA DO PRAZO"),IF(TODAY()>$F64,"VENCIDO",IF($F64-TODAY()<='01. CONFIGURAÇÕES'!$C$23,"VENCE EM BREVE","EM DIA")))) | V64: =IF($A64="","",SUMIFS(MED_VLR,MED_ID,$A64))
A65: =IF($B65="","",LEFT($B65,3)&"-"&TEXT(ROW()-4,"0000")) | F65: =IF($D65="","",$D65+IF($E65="",'01. CONFIGURAÇÕES'!$C$22,$E65)) | P65: =IFERROR(IF($A65="","",IF(COUNTIFS(OS_ID,$A65)>0,INDEX(OS_EQUIPE,MATCH($A65,OS_ID,0)),IF(COUNTIFS(PROG_ID,$A65)>0,INDEX(PROG_EQUIPE,MATCH($A65,PROG_ID,0)),""))),"") | Q65: =IF($A65="","",IFERROR(IF(INDEX(PROG_DATA,MATCH($A65,PROG_ID,0))=0,"",INDEX(PROG_DATA,MATCH($A65,PROG_ID,0))),"")) | R65: =IF($A65="","",IFERROR(IF(INDEX(OS_FIM,MATCH($A65,OS_ID,0))=0,"",INDEX(OS_FIM,MATCH($A65,OS_ID,0))),"")) | S65: =IF($A65="","",IF($W65<>"",$W65,IF($V65>0,"MEDIDO",IF($R65<>"","EXECUTADO",IF(COUNTIFS(OS_ID,$A65)>0,"EM EXECUÇÃO",IF($Q65<>"","PROGRAMADO","CADASTRADO")))))) | T65: =IF($A65="","",IF($R65<>"",$R65-$D65,TODAY()-$D65)) | U65: =IF(OR($A65="",$F65=""),"",IF($R65<>"",IF($R65<=$F65,"NO PRAZO","FORA DO PRAZO"),IF(TODAY()>$F65,"VENCIDO",IF($F65-TODAY()<='01. CONFIGURAÇÕES'!$C$23,"VENCE EM BREVE","EM DIA")))) | V65: =IF($A65="","",SUMIFS(MED_VLR,MED_ID,$A65))
A66: =IF($B66="","",LEFT($B66,3)&"-"&TEXT(ROW()-4,"0000")) | F66: =IF($D66="","",$D66+IF($E66="",'01. CONFIGURAÇÕES'!$C$22,$E66)) | P66: =IFERROR(IF($A66="","",IF(COUNTIFS(OS_ID,$A66)>0,INDEX(OS_EQUIPE,MATCH($A66,OS_ID,0)),IF(COUNTIFS(PROG_ID,$A66)>0,INDEX(PROG_EQUIPE,MATCH($A66,PROG_ID,0)),""))),"") | Q66: =IF($A66="","",IFERROR(IF(INDEX(PROG_DATA,MATCH($A66,PROG_ID,0))=0,"",INDEX(PROG_DATA,MATCH($A66,PROG_ID,0))),"")) | R66: =IF($A66="","",IFERROR(IF(INDEX(OS_FIM,MATCH($A66,OS_ID,0))=0,"",INDEX(OS_FIM,MATCH($A66,OS_ID,0))),"")) | S66: =IF($A66="","",IF($W66<>"",$W66,IF($V66>0,"MEDIDO",IF($R66<>"","EXECUTADO",IF(COUNTIFS(OS_ID,$A66)>0,"EM EXECUÇÃO",IF($Q66<>"","PROGRAMADO","CADASTRADO")))))) | T66: =IF($A66="","",IF($R66<>"",$R66-$D66,TODAY()-$D66)) | U66: =IF(OR($A66="",$F66=""),"",IF($R66<>"",IF($R66<=$F66,"NO PRAZO","FORA DO PRAZO"),IF(TODAY()>$F66,"VENCIDO",IF($F66-TODAY()<='01. CONFIGURAÇÕES'!$C$23,"VENCE EM BREVE","EM DIA")))) | V66: =IF($A66="","",SUMIFS(MED_VLR,MED_ID,$A66))
A67: =IF($B67="","",LEFT($B67,3)&"-"&TEXT(ROW()-4,"0000")) | F67: =IF($D67="","",$D67+IF($E67="",'01. CONFIGURAÇÕES'!$C$22,$E67)) | P67: =IFERROR(IF($A67="","",IF(COUNTIFS(OS_ID,$A67)>0,INDEX(OS_EQUIPE,MATCH($A67,OS_ID,0)),IF(COUNTIFS(PROG_ID,$A67)>0,INDEX(PROG_EQUIPE,MATCH($A67,PROG_ID,0)),""))),"") | Q67: =IF($A67="","",IFERROR(IF(INDEX(PROG_DATA,MATCH($A67,PROG_ID,0))=0,"",INDEX(PROG_DATA,MATCH($A67,PROG_ID,0))),"")) | R67: =IF($A67="","",IFERROR(IF(INDEX(OS_FIM,MATCH($A67,OS_ID,0))=0,"",INDEX(OS_FIM,MATCH($A67,OS_ID,0))),"")) | S67: =IF($A67="","",IF($W67<>"",$W67,IF($V67>0,"MEDIDO",IF($R67<>"","EXECUTADO",IF(COUNTIFS(OS_ID,$A67)>0,"EM EXECUÇÃO",IF($Q67<>"","PROGRAMADO","CADASTRADO")))))) | T67: =IF($A67="","",IF($R67<>"",$R67-$D67,TODAY()-$D67)) | U67: =IF(OR($A67="",$F67=""),"",IF($R67<>"",IF($R67<=$F67,"NO PRAZO","FORA DO PRAZO"),IF(TODAY()>$F67,"VENCIDO",IF($F67-TODAY()<='01. CONFIGURAÇÕES'!$C$23,"VENCE EM BREVE","EM DIA")))) | V67: =IF($A67="","",SUMIFS(MED_VLR,MED_ID,$A67))
A68: =IF($B68="","",LEFT($B68,3)&"-"&TEXT(ROW()-4,"0000")) | F68: =IF($D68="","",$D68+IF($E68="",'01. CONFIGURAÇÕES'!$C$22,$E68)) | P68: =IFERROR(IF($A68="","",IF(COUNTIFS(OS_ID,$A68)>0,INDEX(OS_EQUIPE,MATCH($A68,OS_ID,0)),IF(COUNTIFS(PROG_ID,$A68)>0,INDEX(PROG_EQUIPE,MATCH($A68,PROG_ID,0)),""))),"") | Q68: =IF($A68="","",IFERROR(IF(INDEX(PROG_DATA,MATCH($A68,PROG_ID,0))=0,"",INDEX(PROG_DATA,MATCH($A68,PROG_ID,0))),"")) | R68: =IF($A68="","",IFERROR(IF(INDEX(OS_FIM,MATCH($A68,OS_ID,0))=0,"",INDEX(OS_FIM,MATCH($A68,OS_ID,0))),"")) | S68: =IF($A68="","",IF($W68<>"",$W68,IF($V68>0,"MEDIDO",IF($R68<>"","EXECUTADO",IF(COUNTIFS(OS_ID,$A68)>0,"EM EXECUÇÃO",IF($Q68<>"","PROGRAMADO","CADASTRADO")))))) | T68: =IF($A68="","",IF($R68<>"",$R68-$D68,TODAY()-$D68)) | U68: =IF(OR($A68="",$F68=""),"",IF($R68<>"",IF($R68<=$F68,"NO PRAZO","FORA DO PRAZO"),IF(TODAY()>$F68,"VENCIDO",IF($F68-TODAY()<='01. CONFIGURAÇÕES'!$C$23,"VENCE EM BREVE","EM DIA")))) | V68: =IF($A68="","",SUMIFS(MED_VLR,MED_ID,$A68))
A69: =IF($B69="","",LEFT($B69,3)&"-"&TEXT(ROW()-4,"0000")) | F69: =IF($D69="","",$D69+IF($E69="",'01. CONFIGURAÇÕES'!$C$22,$E69)) | P69: =IFERROR(IF($A69="","",IF(COUNTIFS(OS_ID,$A69)>0,INDEX(OS_EQUIPE,MATCH($A69,OS_ID,0)),IF(COUNTIFS(PROG_ID,$A69)>0,INDEX(PROG_EQUIPE,MATCH($A69,PROG_ID,0)),""))),"") | Q69: =IF($A69="","",IFERROR(IF(INDEX(PROG_DATA,MATCH($A69,PROG_ID,0))=0,"",INDEX(PROG_DATA,MATCH($A69,PROG_ID,0))),"")) | R69: =IF($A69="","",IFERROR(IF(INDEX(OS_FIM,MATCH($A69,OS_ID,0))=0,"",INDEX(OS_FIM,MATCH($A69,OS_ID,0))),"")) | S69: =IF($A69="","",IF($W69<>"",$W69,IF($V69>0,"MEDIDO",IF($R69<>"","EXECUTADO",IF(COUNTIFS(OS_ID,$A69)>0,"EM EXECUÇÃO",IF($Q69<>"","PROGRAMADO","CADASTRADO")))))) | T69: =IF($A69="","",IF($R69<>"",$R69-$D69,TODAY()-$D69)) | U69: =IF(OR($A69="",$F69=""),"",IF($R69<>"",IF($R69<=$F69,"NO PRAZO","FORA DO PRAZO"),IF(TODAY()>$F69,"VENCIDO",IF($F69-TODAY()<='01. CONFIGURAÇÕES'!$C$23,"VENCE EM BREVE","EM DIA")))) | V69: =IF($A69="","",SUMIFS(MED_VLR,MED_ID,$A69))
A70: =IF($B70="","",LEFT($B70,3)&"-"&TEXT(ROW()-4,"0000")) | F70: =IF($D70="","",$D70+IF($E70="",'01. CONFIGURAÇÕES'!$C$22,$E70)) | P70: =IFERROR(IF($A70="","",IF(COUNTIFS(OS_ID,$A70)>0,INDEX(OS_EQUIPE,MATCH($A70,OS_ID,0)),IF(COUNTIFS(PROG_ID,$A70)>0,INDEX(PROG_EQUIPE,MATCH($A70,PROG_ID,0)),""))),"") | Q70: =IF($A70="","",IFERROR(IF(INDEX(PROG_DATA,MATCH($A70,PROG_ID,0))=0,"",INDEX(PROG_DATA,MATCH($A70,PROG_ID,0))),"")) | R70: =IF($A70="","",IFERROR(IF(INDEX(OS_FIM,MATCH($A70,OS_ID,0))=0,"",INDEX(OS_FIM,MATCH($A70,OS_ID,0))),"")) | S70: =IF($A70="","",IF($W70<>"",$W70,IF($V70>0,"MEDIDO",IF($R70<>"","EXECUTADO",IF(COUNTIFS(OS_ID,$A70)>0,"EM EXECUÇÃO",IF($Q70<>"","PROGRAMADO","CADASTRADO")))))) | T70: =IF($A70="","",IF($R70<>"",$R70-$D70,TODAY()-$D70)) | U70: =IF(OR($A70="",$F70=""),"",IF($R70<>"",IF($R70<=$F70,"NO PRAZO","FORA DO PRAZO"),IF(TODAY()>$F70,"VENCIDO",IF($F70-TODAY()<='01. CONFIGURAÇÕES'!$C$23,"VENCE EM BREVE","EM DIA")))) | V70: =IF($A70="","",SUMIFS(MED_VLR,MED_ID,$A70))
... A604: =IF($B604="","",LEFT($B604,3)&"-"&TEXT(ROW()-4,"0000")) | F604: =IF($D604="","",$D604+IF($E604="",'01. CONFIGURAÇÕES'!$C$22,$E604)) | P604: =IFERROR(IF($A604="","",IF(COUNTIFS(OS_ID,$A604)>0,INDEX(OS_EQUIPE,MATCH($A604,OS_ID,0)),IF(COUNTIFS(PROG_ID,$A604)>0,INDEX(PROG_EQUIPE,MATCH($A604,PROG_ID,0)),""))),"") | Q604: =IF($A604="","",IFERROR(IF(INDEX(PROG_DATA,MATCH($A604,PROG_ID,0))=0,"",INDEX(PROG_DATA,MATCH($A604,PROG_ID,0))),"")) | R604: =IF($A604="","",IFERROR(IF(INDEX(OS_FIM,MATCH($A604,OS_ID,0))=0,"",INDEX(OS_FIM,MATCH($A604,OS_ID,0))),"")) | S604: =IF($A604="","",IF($W604<>"",$W604,IF($V604>0,"MEDIDO",IF($R604<>"","EXECUTADO",IF(COUNTIFS(OS_ID,$A604)>0,"EM EXECUÇÃO",IF($Q604<>"","PROGRAMADO","CADASTRADO")))))) | T604: =IF($A604="","",IF($R604<>"",$R604-$D604,TODAY()-$D604)) | U604: =IF(OR($A604="",$F604=""),"",IF($R604<>"",IF($R604<=$F604,"NO PRAZO","FORA DO PRAZO"),IF(TODAY()>$F604,"VENCIDO",IF($F604-TODAY()<='01. CONFIGURAÇÕES'!$C$23,"VENCE EM BREVE","EM DIA")))) | V604: =IF($A604="","",SUMIFS(MED_VLR,MED_ID,$A604))

Sheet 04. PROGRAMAÇÃO DIÁRIA
A1: PROGRAMAÇÃO DIÁRIA — DISTRIBUIÇÃO DOS SERVIÇOS POR EQUIPE E POR DIA | U1: COMO PREENCHER ESTA ABA
A2: O programador monta o dia seguinte até as 16h. O encarregado devolve esta folha preenchida no fim do dia (EXECUTOU? / MOTIVO). Cada linha = um serviço para uma equipe em um dia. | U2: 1 linha = 1 serviço, pra 1 equipe, em 1 dia.
U3: NA VÉSPERA, ATÉ AS 16h:
A4: DATA | B4: CONTRATO | C4: EQUIPE | D4: SEQ | E4: ID DO SERVIÇO | F4: TIPO DE SERVIÇO | G4: ENDEREÇO | H4: BAIRRO | I4: PRIORIDADE | J4: DATA LIMITE | K4: H PREVISTAS | L4: EXECUTOU? | M4: DATA DE EXECUÇÃO | N4: MOTIVO DA NÃO EXECUÇÃO | O4: REPROGRAMAR PARA | P4: STATUS DO ITEM | Q4: ADERÊNCIA | R4: OBSERVAÇÃO | U4: A = data em que vai executar
A5: 46273 | B5: =IFERROR(IF($E5="","",VLOOKUP($E5,CAD_TAB,2,FALSE)),"") -> BERTIOGA | D5: 1 | E5: BER-0001 | F5: =IFERROR(IF($E5="","",VLOOKUP($E5,CAD_TAB,8,FALSE)),"") -> Vazamento de água não visível — rede | G5: =IFERROR(IF($E5="","",VLOOKUP($E5,CAD_TAB,9,FALSE)),"") -> Alameda Maua | H5: =IFERROR(IF($E5="","",VLOOKUP($E5,CAD_TAB,11,FALSE)),"") -> Boracéia | I5: =IFERROR(IF($E5="","",VLOOKUP($E5,CAD_TAB,7,FALSE)),"") -> URGENTE | J5: =IFERROR(IF($E5="","",VLOOKUP($E5,CAD_TAB,6,FALSE)),"") -> 46272 | L5: SIM | M5: 46273 | N5: Chuva | P5: =IF($E5="","",IF($L5="SIM","EXECUTADO",IF($O5<>"","REPROGRAMADO",IF($L5="NÃO","NÃO EXECUTADO","PROGRAMADO")))) -> EXECUTADO | Q5: =IF($E5="","",IF($L5="SIM",IF($M5=$A5,"NO DIA","FORA DO DIA"),"")) -> NO DIA | U5: C = equipe: BER-A, BER-B... (menu)
A6: 46268 | B6: =IFERROR(IF($E6="","",VLOOKUP($E6,CAD_TAB,2,FALSE)),"") -> BERTIOGA | D6: 2 | E6: BER-0002 | F6: =IFERROR(IF($E6="","",VLOOKUP($E6,CAD_TAB,8,FALSE)),"") -> Vazamento de água não visível — rede | G6: =IFERROR(IF($E6="","",VLOOKUP($E6,CAD_TAB,9,FALSE)),"") -> Rua Francisco Chaves | H6: =IFERROR(IF($E6="","",VLOOKUP($E6,CAD_TAB,11,FALSE)),"") -> Jardim Vicente de Carvalho | I6: =IFERROR(IF($E6="","",VLOOKUP($E6,CAD_TAB,7,FALSE)),"") -> URGENTE | J6: =IFERROR(IF($E6="","",VLOOKUP($E6,CAD_TAB,6,FALSE)),"") -> 46272 | L6: SIM | M6: 46268 | P6: =IF($E6="","",IF($L6="SIM","EXECUTADO",IF($O6<>"","REPROGRAMADO",IF($L6="NÃO","NÃO EXECUTADO","PROGRAMADO")))) -> EXECUTADO | Q6: =IF($E6="","",IF($L6="SIM",IF($M6=$A6,"NO DIA","FORA DO DIA"),"")) -> NO DIA | U6: D = ordem do serviço no dia: 1, 2, 3...
A7: 46268 | B7: =IFERROR(IF($E7="","",VLOOKUP($E7,CAD_TAB,2,FALSE)),"") -> BERTIOGA | D7: 3 | E7: BER-0003 | F7: =IFERROR(IF($E7="","",VLOOKUP($E7,CAD_TAB,8,FALSE)),"") -> Troca de ramal de água | G7: =IFERROR(IF($E7="","",VLOOKUP($E7,CAD_TAB,9,FALSE)),"") -> Alameda Agapanthos | H7: =IFERROR(IF($E7="","",VLOOKUP($E7,CAD_TAB,11,FALSE)),"") -> Boracéia | I7: =IFERROR(IF($E7="","",VLOOKUP($E7,CAD_TAB,7,FALSE)),"") -> NORMAL | J7: =IFERROR(IF($E7="","",VLOOKUP($E7,CAD_TAB,6,FALSE)),"") -> 46272 | L7: SIM | M7: 46268 | P7: =IF($E7="","",IF($L7="SIM","EXECUTADO",IF($O7<>"","REPROGRAMADO",IF($L7="NÃO","NÃO EXECUTADO","PROGRAMADO")))) -> EXECUTADO | Q7: =IF($E7="","",IF($L7="SIM",IF($M7=$A7,"NO DIA","FORA DO DIA"),"")) -> NO DIA | U7: E = ID do serviço (BER-0001), copiado da aba 03
A8: 46268 | B8: =IFERROR(IF($E8="","",VLOOKUP($E8,CAD_TAB,2,FALSE)),"") -> BERTIOGA | D8: 4 | E8: BER-0004 | F8: =IFERROR(IF($E8="","",VLOOKUP($E8,CAD_TAB,8,FALSE)),"") -> Vazamento de água não visível — ramal | G8: =IFERROR(IF($E8="","",VLOOKUP($E8,CAD_TAB,9,FALSE)),"") -> Alameda Paranapiacaba | H8: =IFERROR(IF($E8="","",VLOOKUP($E8,CAD_TAB,11,FALSE)),"") -> Boracéia | I8: =IFERROR(IF($E8="","",VLOOKUP($E8,CAD_TAB,7,FALSE)),"") -> URGENTE | J8: =IFERROR(IF($E8="","",VLOOKUP($E8,CAD_TAB,6,FALSE)),"") -> 46272 | L8: SIM | M8: 46268 | P8: =IF($E8="","",IF($L8="SIM","EXECUTADO",IF($O8<>"","REPROGRAMADO",IF($L8="NÃO","NÃO EXECUTADO","PROGRAMADO")))) -> EXECUTADO | Q8: =IF($E8="","",IF($L8="SIM",IF($M8=$A8,"NO DIA","FORA DO DIA"),"")) -> NO DIA | U8: endereço e tipo aparecem sozinhos
A9: 46268 | B9: =IFERROR(IF($E9="","",VLOOKUP($E9,CAD_TAB,2,FALSE)),"") -> BERTIOGA | D9: 5 | E9: BER-0005 | F9: =IFERROR(IF($E9="","",VLOOKUP($E9,CAD_TAB,8,FALSE)),"") -> Vazamento de água não visível — ramal | G9: =IFERROR(IF($E9="","",VLOOKUP($E9,CAD_TAB,9,FALSE)),"") -> Alameda Rio Grande da Serra | H9: =IFERROR(IF($E9="","",VLOOKUP($E9,CAD_TAB,11,FALSE)),"") -> Boracéia | I9: =IFERROR(IF($E9="","",VLOOKUP($E9,CAD_TAB,7,FALSE)),"") -> URGENTE | J9: =IFERROR(IF($E9="","",VLOOKUP($E9,CAD_TAB,6,FALSE)),"") -> 46272 | L9: SIM | M9: 46268 | P9: =IF($E9="","",IF($L9="SIM","EXECUTADO",IF($O9<>"","REPROGRAMADO",IF($L9="NÃO","NÃO EXECUTADO","PROGRAMADO")))) -> EXECUTADO | Q9: =IF($E9="","",IF($L9="SIM",IF($M9=$A9,"NO DIA","FORA DO DIA"),"")) -> NO DIA | U9: K = quantas horas acha que vai levar
A10: 46268 | B10: =IFERROR(IF($E10="","",VLOOKUP($E10,CAD_TAB,2,FALSE)),"") -> BERTIOGA | D10: 6 | E10: BER-0006 | F10: =IFERROR(IF($E10="","",VLOOKUP($E10,CAD_TAB,8,FALSE)),"") -> Troca de ramal de água | G10: =IFERROR(IF($E10="","",VLOOKUP($E10,CAD_TAB,9,FALSE)),"") -> Rua Prolongada Oswaldo Cruz | H10: =IFERROR(IF($E10="","",VLOOKUP($E10,CAD_TAB,11,FALSE)),"") -> Jardim Vicente de Carvalho | I10: =IFERROR(IF($E10="","",VLOOKUP($E10,CAD_TAB,7,FALSE)),"") -> NORMAL | J10: =IFERROR(IF($E10="","",VLOOKUP($E10,CAD_TAB,6,FALSE)),"") -> 46272 | L10: SIM | M10: 46268 | P10: =IF($E10="","",IF($L10="SIM","EXECUTADO",IF($O10<>"","REPROGRAMADO",IF($L10="NÃO","NÃO EXECUTADO","PROGRAMADO")))) -> EXECUTADO | Q10: =IF($E10="","",IF($L10="SIM",IF($M10=$A10,"NO DIA","FORA DO DIA"),"")) -> NO DIA | U10: NO FIM DO DIA, O ENCARREGADO DEVOLVE:
A11: 46267 | B11: =IFERROR(IF($E11="","",VLOOKUP($E11,CAD_TAB,2,FALSE)),"") -> BERTIOGA | D11: 7 | E11: BER-0007 | F11: =IFERROR(IF($E11="","",VLOOKUP($E11,CAD_TAB,8,FALSE)),"") -> Troca de ramal de água | G11: =IFERROR(IF($E11="","",VLOOKUP($E11,CAD_TAB,9,FALSE)),"") -> Rua Prolongada Oswaldo Cruz | H11: =IFERROR(IF($E11="","",VLOOKUP($E11,CAD_TAB,11,FALSE)),"") -> Jardim Vicente de Carvalho | I11: =IFERROR(IF($E11="","",VLOOKUP($E11,CAD_TAB,7,FALSE)),"") -> NORMAL | J11: =IFERROR(IF($E11="","",VLOOKUP($E11,CAD_TAB,6,FALSE)),"") -> 46272 | L11: SIM | M11: 46276 | P11: =IF($E11="","",IF($L11="SIM","EXECUTADO",IF($O11<>"","REPROGRAMADO",IF($L11="NÃO","NÃO EXECUTADO","PROGRAMADO")))) -> EXECUTADO | Q11: =IF($E11="","",IF($L11="SIM",IF($M11=$A11,"NO DIA","FORA DO DIA"),"")) -> FORA DO DIA | U11: L = EXECUTOU? SIM ou NÃO (menu)
A12: 46267 | B12: =IFERROR(IF($E12="","",VLOOKUP($E12,CAD_TAB,2,FALSE)),"") -> BERTIOGA | D12: 8 | E12: BER-0008 | F12: =IFERROR(IF($E12="","",VLOOKUP($E12,CAD_TAB,8,FALSE)),"") -> Vazamento de água não visível — ramal | G12: =IFERROR(IF($E12="","",VLOOKUP($E12,CAD_TAB,9,FALSE)),"") -> Alameda Paranapiacaba | H12: =IFERROR(IF($E12="","",VLOOKUP($E12,CAD_TAB,11,FALSE)),"") -> Boracéia | I12: =IFERROR(IF($E12="","",VLOOKUP($E12,CAD_TAB,7,FALSE)),"") -> URGENTE | J12: =IFERROR(IF($E12="","",VLOOKUP($E12,CAD_TAB,6,FALSE)),"") -> 46272 | L12: SIM | M12: 46269 | P12: =IF($E12="","",IF($L12="SIM","EXECUTADO",IF($O12<>"","REPROGRAMADO",IF($L12="NÃO","NÃO EXECUTADO","PROGRAMADO")))) -> EXECUTADO | Q12: =IF($E12="","",IF($L12="SIM",IF($M12=$A12,"NO DIA","FORA DO DIA"),"")) -> FORA DO DIA | U12: M = data em que executou
A13: 46269 | B13: =IFERROR(IF($E13="","",VLOOKUP($E13,CAD_TAB,2,FALSE)),"") -> BERTIOGA | D13: 9 | E13: BER-0009 | F13: =IFERROR(IF($E13="","",VLOOKUP($E13,CAD_TAB,8,FALSE)),"") -> Vazamento de água não visível — ramal | G13: =IFERROR(IF($E13="","",VLOOKUP($E13,CAD_TAB,9,FALSE)),"") -> Rua dos Anjos Antiga Projetada 1B | H13: =IFERROR(IF($E13="","",VLOOKUP($E13,CAD_TAB,11,FALSE)),"") -> Jardim Vicente de Carvalho | I13: =IFERROR(IF($E13="","",VLOOKUP($E13,CAD_TAB,7,FALSE)),"") -> URGENTE | J13: =IFERROR(IF($E13="","",VLOOKUP($E13,CAD_TAB,6,FALSE)),"") -> 46272 | L13: SIM | M13: 46269 | P13: =IF($E13="","",IF($L13="SIM","EXECUTADO",IF($O13<>"","REPROGRAMADO",IF($L13="NÃO","NÃO EXECUTADO","PROGRAMADO")))) -> EXECUTADO | Q13: =IF($E13="","",IF($L13="SIM",IF($M13=$A13,"NO DIA","FORA DO DIA"),"")) -> NO DIA | U13: N = se foi NÃO, o motivo (menu)
A14: 46269 | B14: =IFERROR(IF($E14="","",VLOOKUP($E14,CAD_TAB,2,FALSE)),"") -> BERTIOGA | D14: 10 | E14: BER-0010 | F14: =IFERROR(IF($E14="","",VLOOKUP($E14,CAD_TAB,8,FALSE)),"") -> Troca de ramal de água | G14: =IFERROR(IF($E14="","",VLOOKUP($E14,CAD_TAB,9,FALSE)),"") -> Alameda Paranapiacaba | H14: =IFERROR(IF($E14="","",VLOOKUP($E14,CAD_TAB,11,FALSE)),"") -> Boracéia | I14: =IFERROR(IF($E14="","",VLOOKUP($E14,CAD_TAB,7,FALSE)),"") -> NORMAL | J14: =IFERROR(IF($E14="","",VLOOKUP($E14,CAD_TAB,6,FALSE)),"") -> 46273 | L14: SIM | M14: 46269 | P14: =IF($E14="","",IF($L14="SIM","EXECUTADO",IF($O14<>"","REPROGRAMADO",IF($L14="NÃO","NÃO EXECUTADO","PROGRAMADO")))) -> EXECUTADO | Q14: =IF($E14="","",IF($L14="SIM",IF($M14=$A14,"NO DIA","FORA DO DIA"),"")) -> NO DIA | U14: O = pra que dia vai remarcar
A15: 46269 | B15: =IFERROR(IF($E15="","",VLOOKUP($E15,CAD_TAB,2,FALSE)),"") -> BERTIOGA | D15: 11 | E15: BER-0011 | F15: =IFERROR(IF($E15="","",VLOOKUP($E15,CAD_TAB,8,FALSE)),"") -> Troca de ramal de água | G15: =IFERROR(IF($E15="","",VLOOKUP($E15,CAD_TAB,9,FALSE)),"") -> Alameda Paranapiacaba | H15: =IFERROR(IF($E15="","",VLOOKUP($E15,CAD_TAB,11,FALSE)),"") -> Boracéia | I15: =IFERROR(IF($E15="","",VLOOKUP($E15,CAD_TAB,7,FALSE)),"") -> NORMAL | J15: =IFERROR(IF($E15="","",VLOOKUP($E15,CAD_TAB,6,FALSE)),"") -> 46273 | L15: SIM | M15: 46269 | P15: =IF($E15="","",IF($L15="SIM","EXECUTADO",IF($O15<>"","REPROGRAMADO",IF($L15="NÃO","NÃO EXECUTADO","PROGRAMADO")))) -> EXECUTADO | Q15: =IF($E15="","",IF($L15="SIM",IF($M15=$A15,"NO DIA","FORA DO DIA"),"")) -> NO DIA | U15: R = observação
A16: 46269 | B16: =IFERROR(IF($E16="","",VLOOKUP($E16,CAD_TAB,2,FALSE)),"") -> BERTIOGA | D16: 12 | E16: BER-0012 | F16: =IFERROR(IF($E16="","",VLOOKUP($E16,CAD_TAB,8,FALSE)),"") -> Vazamento de água não visível — rede | G16: =IFERROR(IF($E16="","",VLOOKUP($E16,CAD_TAB,9,FALSE)),"") -> Avenida Tupi Guarani | H16: =IFERROR(IF($E16="","",VLOOKUP($E16,CAD_TAB,11,FALSE)),"") -> Boracéia | I16: =IFERROR(IF($E16="","",VLOOKUP($E16,CAD_TAB,7,FALSE)),"") -> URGENTE | J16: =IFERROR(IF($E16="","",VLOOKUP($E16,CAD_TAB,6,FALSE)),"") -> 46273 | L16: SIM | M16: 46269 | P16: =IF($E16="","",IF($L16="SIM","EXECUTADO",IF($O16<>"","REPROGRAMADO",IF($L16="NÃO","NÃO EXECUTADO","PROGRAMADO")))) -> EXECUTADO | Q16: =IF($E16="","",IF($L16="SIM",IF($M16=$A16,"NO DIA","FORA DO DIA"),"")) -> NO DIA
A17: 46273 | B17: =IFERROR(IF($E17="","",VLOOKUP($E17,CAD_TAB,2,FALSE)),"") -> BERTIOGA | D17: 13 | E17: BER-0013 | F17: =IFERROR(IF($E17="","",VLOOKUP($E17,CAD_TAB,8,FALSE)),"") -> Troca de ramal de água | G17: =IFERROR(IF($E17="","",VLOOKUP($E17,CAD_TAB,9,FALSE)),"") -> Rua Seis | H17: =IFERROR(IF($E17="","",VLOOKUP($E17,CAD_TAB,11,FALSE)),"") -> Albatroz II | I17: =IFERROR(IF($E17="","",VLOOKUP($E17,CAD_TAB,7,FALSE)),"") -> NORMAL | J17: =IFERROR(IF($E17="","",VLOOKUP($E17,CAD_TAB,6,FALSE)),"") -> 46278 | L17: SIM | M17: 46273 | P17: =IF($E17="","",IF($L17="SIM","EXECUTADO",IF($O17<>"","REPROGRAMADO",IF($L17="NÃO","NÃO EXECUTADO","PROGRAMADO")))) -> EXECUTADO | Q17: =IF($E17="","",IF($L17="SIM",IF($M17=$A17,"NO DIA","FORA DO DIA"),"")) -> NO DIA
A18: 46273 | B18: =IFERROR(IF($E18="","",VLOOKUP($E18,CAD_TAB,2,FALSE)),"") -> BERTIOGA | D18: 14 | E18: BER-0014 | F18: =IFERROR(IF($E18="","",VLOOKUP($E18,CAD_TAB,8,FALSE)),"") -> Vazamento pé do cavalete | G18: =IFERROR(IF($E18="","",VLOOKUP($E18,CAD_TAB,9,FALSE)),"") -> Rua Seis | H18: =IFERROR(IF($E18="","",VLOOKUP($E18,CAD_TAB,11,FALSE)),"") -> Albatroz II | I18: =IFERROR(IF($E18="","",VLOOKUP($E18,CAD_TAB,7,FALSE)),"") -> URGENTE | J18: =IFERROR(IF($E18="","",VLOOKUP($E18,CAD_TAB,6,FALSE)),"") -> 46278 | L18: SIM | M18: 46273 | P18: =IF($E18="","",IF($L18="SIM","EXECUTADO",IF($O18<>"","REPROGRAMADO",IF($L18="NÃO","NÃO EXECUTADO","PROGRAMADO")))) -> EXECUTADO | Q18: =IF($E18="","",IF($L18="SIM",IF($M18=$A18,"NO DIA","FORA DO DIA"),"")) -> NO DIA
A19: 46273 | B19: =IFERROR(IF($E19="","",VLOOKUP($E19,CAD_TAB,2,FALSE)),"") -> BERTIOGA | D19: 15 | E19: BER-0015 | F19: =IFERROR(IF($E19="","",VLOOKUP($E19,CAD_TAB,8,FALSE)),"") -> Vazamento no ferrule | G19: =IFERROR(IF($E19="","",VLOOKUP($E19,CAD_TAB,9,FALSE)),"") -> Rua C | H19: =IFERROR(IF($E19="","",VLOOKUP($E19,CAD_TAB,11,FALSE)),"") -> Ana Paula | I19: =IFERROR(IF($E19="","",VLOOKUP($E19,CAD_TAB,7,FALSE)),"") -> URGENTE | J19: =IFERROR(IF($E19="","",VLOOKUP($E19,CAD_TAB,6,FALSE)),"") -> 46278 | L19: SIM | M19: 46273 | P19: =IF($E19="","",IF($L19="SIM","EXECUTADO",IF($O19<>"","REPROGRAMADO",IF($L19="NÃO","NÃO EXECUTADO","PROGRAMADO")))) -> EXECUTADO | Q19: =IF($E19="","",IF($L19="SIM",IF($M19=$A19,"NO DIA","FORA DO DIA"),"")) -> NO DIA
A20: 46273 | B20: =IFERROR(IF($E20="","",VLOOKUP($E20,CAD_TAB,2,FALSE)),"") -> BERTIOGA | D20: 16 | E20: BER-0016 | F20: =IFERROR(IF($E20="","",VLOOKUP($E20,CAD_TAB,8,FALSE)),"") -> Vazamento de água não visível — ramal | G20: =IFERROR(IF($E20="","",VLOOKUP($E20,CAD_TAB,9,FALSE)),"") -> Rua Aprovada 101 | H20: =IFERROR(IF($E20="","",VLOOKUP($E20,CAD_TAB,11,FALSE)),"") -> Ana Paula | I20: =IFERROR(IF($E20="","",VLOOKUP($E20,CAD_TAB,7,FALSE)),"") -> URGENTE | J20: =IFERROR(IF($E20="","",VLOOKUP($E20,CAD_TAB,6,FALSE)),"") -> 46278 | L20: SIM | M20: 46276 | P20: =IF($E20="","",IF($L20="SIM","EXECUTADO",IF($O20<>"","REPROGRAMADO",IF($L20="NÃO","NÃO EXECUTADO","PROGRAMADO")))) -> EXECUTADO | Q20: =IF($E20="","",IF($L20="SIM",IF($M20=$A20,"NO DIA","FORA DO DIA"),"")) -> FORA DO DIA
A21: 46274 | B21: =IFERROR(IF($E21="","",VLOOKUP($E21,CAD_TAB,2,FALSE)),"") -> BERTIOGA | D21: 17 | E21: BER-0017 | F21: =IFERROR(IF($E21="","",VLOOKUP($E21,CAD_TAB,8,FALSE)),"") -> Vazamento pé do cavalete | G21: =IFERROR(IF($E21="","",VLOOKUP($E21,CAD_TAB,9,FALSE)),"") -> Rua Manoel Gajo | H21: =IFERROR(IF($E21="","",VLOOKUP($E21,CAD_TAB,11,FALSE)),"") -> Centro | I21: =IFERROR(IF($E21="","",VLOOKUP($E21,CAD_TAB,7,FALSE)),"") -> URGENTE | J21: =IFERROR(IF($E21="","",VLOOKUP($E21,CAD_TAB,6,FALSE)),"") -> 46278 | L21: SIM | M21: 46274 | P21: =IF($E21="","",IF($L21="SIM","EXECUTADO",IF($O21<>"","REPROGRAMADO",IF($L21="NÃO","NÃO EXECUTADO","PROGRAMADO")))) -> EXECUTADO | Q21: =IF($E21="","",IF($L21="SIM",IF($M21=$A21,"NO DIA","FORA DO DIA"),"")) -> NO DIA
A22: 46274 | B22: =IFERROR(IF($E22="","",VLOOKUP($E22,CAD_TAB,2,FALSE)),"") -> BERTIOGA | D22: 18 | E22: BER-0018 | F22: =IFERROR(IF($E22="","",VLOOKUP($E22,CAD_TAB,8,FALSE)),"") -> Vazamento pé do cavalete | G22: =IFERROR(IF($E22="","",VLOOKUP($E22,CAD_TAB,9,FALSE)),"") -> Rua Oswaldo de Salles Pereira | H22: =IFERROR(IF($E22="","",VLOOKUP($E22,CAD_TAB,11,FALSE)),"") -> Centro | I22: =IFERROR(IF($E22="","",VLOOKUP($E22,CAD_TAB,7,FALSE)),"") -> URGENTE | J22: =IFERROR(IF($E22="","",VLOOKUP($E22,CAD_TAB,6,FALSE)),"") -> 46278 | L22: SIM | M22: 46274 | P22: =IF($E22="","",IF($L22="SIM","EXECUTADO",IF($O22<>"","REPROGRAMADO",IF($L22="NÃO","NÃO EXECUTADO","PROGRAMADO")))) -> EXECUTADO | Q22: =IF($E22="","",IF($L22="SIM",IF($M22=$A22,"NO DIA","FORA DO DIA"),"")) -> NO DIA
A23: 46273 | B23: =IFERROR(IF($E23="","",VLOOKUP($E23,CAD_TAB,2,FALSE)),"") -> BERTIOGA | D23: 19 | E23: BER-0019 | F23: =IFERROR(IF($E23="","",VLOOKUP($E23,CAD_TAB,8,FALSE)),"") -> Vazamento no ferrule | G23: =IFERROR(IF($E23="","",VLOOKUP($E23,CAD_TAB,9,FALSE)),"") -> Rua Samuel Alves Levino | H23: =IFERROR(IF($E23="","",VLOOKUP($E23,CAD_TAB,11,FALSE)),"") -> Rio da Praia | I23: =IFERROR(IF($E23="","",VLOOKUP($E23,CAD_TAB,7,FALSE)),"") -> URGENTE | J23: =IFERROR(IF($E23="","",VLOOKUP($E23,CAD_TAB,6,FALSE)),"") -> 46278 | L23: SIM | M23: 46276 | P23: =IF($E23="","",IF($L23="SIM","EXECUTADO",IF($O23<>"","REPROGRAMADO",IF($L23="NÃO","NÃO EXECUTADO","PROGRAMADO")))) -> EXECUTADO | Q23: =IF($E23="","",IF($L23="SIM",IF($M23=$A23,"NO DIA","FORA DO DIA"),"")) -> FORA DO DIA
A24: 46273 | B24: =IFERROR(IF($E24="","",VLOOKUP($E24,CAD_TAB,2,FALSE)),"") -> BERTIOGA | D24: 20 | E24: BER-0020 | F24: =IFERROR(IF($E24="","",VLOOKUP($E24,CAD_TAB,8,FALSE)),"") -> Vazamento pé do cavalete | G24: =IFERROR(IF($E24="","",VLOOKUP($E24,CAD_TAB,9,FALSE)),"") -> Rua Renata Pereira Costa | H24: =IFERROR(IF($E24="","",VLOOKUP($E24,CAD_TAB,11,FALSE)),"") -> Rio da Praia | I24: =IFERROR(IF($E24="","",VLOOKUP($E24,CAD_TAB,7,FALSE)),"") -> URGENTE | J24: =IFERROR(IF($E24="","",VLOOKUP($E24,CAD_TAB,6,FALSE)),"") -> 46278 | L24: SIM | M24: 46276 | P24: =IF($E24="","",IF($L24="SIM","EXECUTADO",IF($O24<>"","REPROGRAMADO",IF($L24="NÃO","NÃO EXECUTADO","PROGRAMADO")))) -> EXECUTADO | Q24: =IF($E24="","",IF($L24="SIM",IF($M24=$A24,"NO DIA","FORA DO DIA"),"")) -> FORA DO DIA
A25: 46273 | B25: =IFERROR(IF($E25="","",VLOOKUP($E25,CAD_TAB,2,FALSE)),"") -> BERTIOGA | D25: 21 | E25: BER-0021 | F25: =IFERROR(IF($E25="","",VLOOKUP($E25,CAD_TAB,8,FALSE)),"") -> Vazamento pé do cavalete | G25: =IFERROR(IF($E25="","",VLOOKUP($E25,CAD_TAB,9,FALSE)),"") -> Rua Jair Miranda (antiga rua 5) | H25: =IFERROR(IF($E25="","",VLOOKUP($E25,CAD_TAB,11,FALSE)),"") -> Albatroz II | I25: =IFERROR(IF($E25="","",VLOOKUP($E25,CAD_TAB,7,FALSE)),"") -> URGENTE | J25: =IFERROR(IF($E25="","",VLOOKUP($E25,CAD_TAB,6,FALSE)),"") -> 46278 | L25: NÃO | N25: Chuva | P25: =IF($E25="","",IF($L25="SIM","EXECUTADO",IF($O25<>"","REPROGRAMADO",IF($L25="NÃO","NÃO EXECUTADO","PROGRAMADO")))) -> NÃO EXECUTADO | Q25: =IF($E25="","",IF($L25="SIM",IF($M25=$A25,"NO DIA","FORA DO DIA"),""))
A26: 46273 | B26: =IFERROR(IF($E26="","",VLOOKUP($E26,CAD_TAB,2,FALSE)),"") -> BERTIOGA | D26: 22 | E26: BER-0022 | F26: =IFERROR(IF($E26="","",VLOOKUP($E26,CAD_TAB,8,FALSE)),"") -> Vazamento pé do cavalete | G26: =IFERROR(IF($E26="","",VLOOKUP($E26,CAD_TAB,9,FALSE)),"") -> Rua Professor José Benevenuto Madureira | H26: =IFERROR(IF($E26="","",VLOOKUP($E26,CAD_TAB,11,FALSE)),"") -> Rio da Praia | I26: =IFERROR(IF($E26="","",VLOOKUP($E26,CAD_TAB,7,FALSE)),"") -> URGENTE | J26: =IFERROR(IF($E26="","",VLOOKUP($E26,CAD_TAB,6,FALSE)),"") -> 46278 | L26: NÃO | N26: Chuva | P26: =IF($E26="","",IF($L26="SIM","EXECUTADO",IF($O26<>"","REPROGRAMADO",IF($L26="NÃO","NÃO EXECUTADO","PROGRAMADO")))) -> NÃO EXECUTADO | Q26: =IF($E26="","",IF($L26="SIM",IF($M26=$A26,"NO DIA","FORA DO DIA"),""))
A27: 46276 | B27: =IFERROR(IF($E27="","",VLOOKUP($E27,CAD_TAB,2,FALSE)),"") -> BERTIOGA | D27: 23 | E27: BER-0023 | F27: =IFERROR(IF($E27="","",VLOOKUP($E27,CAD_TAB,8,FALSE)),"") -> Vazamento de água não visível — rede | G27: =IFERROR(IF($E27="","",VLOOKUP($E27,CAD_TAB,9,FALSE)),"") -> Rua aprovada 101 | H27: =IFERROR(IF($E27="","",VLOOKUP($E27,CAD_TAB,11,FALSE)),"") -> Ana Paula | I27: =IFERROR(IF($E27="","",VLOOKUP($E27,CAD_TAB,7,FALSE)),"") -> NORMAL | J27: =IFERROR(IF($E27="","",VLOOKUP($E27,CAD_TAB,6,FALSE)),"") -> 46281 | L27: SIM | M27: 46276 | P27: =IF($E27="","",IF($L27="SIM","EXECUTADO",IF($O27<>"","REPROGRAMADO",IF($L27="NÃO","NÃO EXECUTADO","PROGRAMADO")))) -> EXECUTADO | Q27: =IF($E27="","",IF($L27="SIM",IF($M27=$A27,"NO DIA","FORA DO DIA"),"")) -> NO DIA
A28: 46279 | B28: =IFERROR(IF($E28="","",VLOOKUP($E28,CAD_TAB,2,FALSE)),"") -> BERTIOGA | D28: 24 | E28: BER-0024 | F28: =IFERROR(IF($E28="","",VLOOKUP($E28,CAD_TAB,8,FALSE)),"") -> Vazamento no ramal não visível | G28: =IFERROR(IF($E28="","",VLOOKUP($E28,CAD_TAB,9,FALSE)),"") -> Avenida Sabino Abdala | H28: =IFERROR(IF($E28="","",VLOOKUP($E28,CAD_TAB,11,FALSE)),"") -> Indaia | I28: =IFERROR(IF($E28="","",VLOOKUP($E28,CAD_TAB,7,FALSE)),"") -> NORMAL | J28: =IFERROR(IF($E28="","",VLOOKUP($E28,CAD_TAB,6,FALSE)),"") -> 46284 | L28: SIM | M28: 46279 | P28: =IF($E28="","",IF($L28="SIM","EXECUTADO",IF($O28<>"","REPROGRAMADO",IF($L28="NÃO","NÃO EXECUTADO","PROGRAMADO")))) -> EXECUTADO | Q28: =IF($E28="","",IF($L28="SIM",IF($M28=$A28,"NO DIA","FORA DO DIA"),"")) -> NO DIA
A29: 46279 | B29: =IFERROR(IF($E29="","",VLOOKUP($E29,CAD_TAB,2,FALSE)),"") -> BERTIOGA | D29: 25 | E29: BER-0025 | F29: =IFERROR(IF($E29="","",VLOOKUP($E29,CAD_TAB,8,FALSE)),"") -> Vazamento pé do cavalete | G29: =IFERROR(IF($E29="","",VLOOKUP($E29,CAD_TAB,9,FALSE)),"") -> Rua Luiz Alonso Peres | H29: =IFERROR(IF($E29="","",VLOOKUP($E29,CAD_TAB,11,FALSE)),"") -> Indaia | I29: =IFERROR(IF($E29="","",VLOOKUP($E29,CAD_TAB,7,FALSE)),"") -> NORMAL | J29: =IFERROR(IF($E29="","",VLOOKUP($E29,CAD_TAB,6,FALSE)),"") -> 46284 | L29: SIM | M29: 46280 | P29: =IF($E29="","",IF($L29="SIM","EXECUTADO",IF($O29<>"","REPROGRAMADO",IF($L29="NÃO","NÃO EXECUTADO","PROGRAMADO")))) -> EXECUTADO | Q29: =IF($E29="","",IF($L29="SIM",IF($M29=$A29,"NO DIA","FORA DO DIA"),"")) -> FORA DO DIA
A30: 46279 | B30: =IFERROR(IF($E30="","",VLOOKUP($E30,CAD_TAB,2,FALSE)),"") -> BERTIOGA | D30: 26 | E30: BER-0026 | F30: =IFERROR(IF($E30="","",VLOOKUP($E30,CAD_TAB,8,FALSE)),"") -> Vazamento no ramal não visível | G30: =IFERROR(IF($E30="","",VLOOKUP($E30,CAD_TAB,9,FALSE)),"") -> Avenida Sabino Abdala | H30: =IFERROR(IF($E30="","",VLOOKUP($E30,CAD_TAB,11,FALSE)),"") -> Indaia | I30: =IFERROR(IF($E30="","",VLOOKUP($E30,CAD_TAB,7,FALSE)),"") -> NORMAL | J30: =IFERROR(IF($E30="","",VLOOKUP($E30,CAD_TAB,6,FALSE)),"") -> 46284 | L30: SIM | M30: 46280 | P30: =IF($E30="","",IF($L30="SIM","EXECUTADO",IF($O30<>"","REPROGRAMADO",IF($L30="NÃO","NÃO EXECUTADO","PROGRAMADO")))) -> EXECUTADO | Q30: =IF($E30="","",IF($L30="SIM",IF($M30=$A30,"NO DIA","FORA DO DIA"),"")) -> FORA DO DIA
A31: 46279 | B31: =IFERROR(IF($E31="","",VLOOKUP($E31,CAD_TAB,2,FALSE)),"") -> BERTIOGA | D31: 27 | E31: BER-0027 | F31: =IFERROR(IF($E31="","",VLOOKUP($E31,CAD_TAB,8,FALSE)),"") -> Vazamento no ramal não visível | G31: =IFERROR(IF($E31="","",VLOOKUP($E31,CAD_TAB,9,FALSE)),"") -> Avenida Sabino Abdala | H31: =IFERROR(IF($E31="","",VLOOKUP($E31,CAD_TAB,11,FALSE)),"") -> Indaia | I31: =IFERROR(IF($E31="","",VLOOKUP($E31,CAD_TAB,7,FALSE)),"") -> NORMAL | J31: =IFERROR(IF($E31="","",VLOOKUP($E31,CAD_TAB,6,FALSE)),"") -> 46284 | L31: SIM | M31: 46280 | P31: =IF($E31="","",IF($L31="SIM","EXECUTADO",IF($O31<>"","REPROGRAMADO",IF($L31="NÃO","NÃO EXECUTADO","PROGRAMADO")))) -> EXECUTADO | Q31: =IF($E31="","",IF($L31="SIM",IF($M31=$A31,"NO DIA","FORA DO DIA"),"")) -> FORA DO DIA
A32: 46279 | B32: =IFERROR(IF($E32="","",VLOOKUP($E32,CAD_TAB,2,FALSE)),"") -> BERTIOGA | D32: 28 | E32: BER-0028 | F32: =IFERROR(IF($E32="","",VLOOKUP($E32,CAD_TAB,8,FALSE)),"") -> Vazamento cavalete não visível | G32: =IFERROR(IF($E32="","",VLOOKUP($E32,CAD_TAB,9,FALSE)),"") -> Rua Augusto Ribeiro Pacheco | H32: =IFERROR(IF($E32="","",VLOOKUP($E32,CAD_TAB,11,FALSE)),"") -> Jardim Raphael | I32: =IFERROR(IF($E32="","",VLOOKUP($E32,CAD_TAB,7,FALSE)),"") -> NORMAL | J32: =IFERROR(IF($E32="","",VLOOKUP($E32,CAD_TAB,6,FALSE)),"") -> 46284 | L32: NÃO | P32: =IF($E32="","",IF($L32="SIM","EXECUTADO",IF($O32<>"","REPROGRAMADO",IF($L32="NÃO","NÃO EXECUTADO","PROGRAMADO")))) -> NÃO EXECUTADO | Q32: =IF($E32="","",IF($L32="SIM",IF($M32=$A32,"NO DIA","FORA DO DIA"),""))
A33: 46279 | B33: =IFERROR(IF($E33="","",VLOOKUP($E33,CAD_TAB,2,FALSE)),"") -> BERTIOGA | D33: 29 | E33: BER-0029 | F33: =IFERROR(IF($E33="","",VLOOKUP($E33,CAD_TAB,8,FALSE)),"") -> Vazamento no ramal não visível | G33: =IFERROR(IF($E33="","",VLOOKUP($E33,CAD_TAB,9,FALSE)),"") -> Rua Cardeal Emile Biayenda | H33: =IFERROR(IF($E33="","",VLOOKUP($E33,CAD_TAB,11,FALSE)),"") -> Rio da Praia | I33: =IFERROR(IF($E33="","",VLOOKUP($E33,CAD_TAB,7,FALSE)),"") -> NORMAL | J33: =IFERROR(IF($E33="","",VLOOKUP($E33,CAD_TAB,6,FALSE)),"") -> 46284 | L33: SIM | M33: 46280 | P33: =IF($E33="","",IF($L33="SIM","EXECUTADO",IF($O33<>"","REPROGRAMADO",IF($L33="NÃO","NÃO EXECUTADO","PROGRAMADO")))) -> EXECUTADO | Q33: =IF($E33="","",IF($L33="SIM",IF($M33=$A33,"NO DIA","FORA DO DIA"),"")) -> FORA DO DIA
A34: 46281 | B34: =IFERROR(IF($E34="","",VLOOKUP($E34,CAD_TAB,2,FALSE)),"") -> BERTIOGA | D34: 30 | E34: BER-0030 | F34: =IFERROR(IF($E34="","",VLOOKUP($E34,CAD_TAB,8,FALSE)),"") -> Vazamento de água não visível — rede | G34: =IFERROR(IF($E34="","",VLOOKUP($E34,CAD_TAB,9,FALSE)),"") -> Rua Maria Lídia Rego Lima | H34: =IFERROR(IF($E34="","",VLOOKUP($E34,CAD_TAB,11,FALSE)),"") -> Vicente de Carvalho | I34: =IFERROR(IF($E34="","",VLOOKUP($E34,CAD_TAB,7,FALSE)),"") -> URGENTE | J34: =IFERROR(IF($E34="","",VLOOKUP($E34,CAD_TAB,6,FALSE)),"") -> 46284 | P34: =IF($E34="","",IF($L34="SIM","EXECUTADO",IF($O34<>"","REPROGRAMADO",IF($L34="NÃO","NÃO EXECUTADO","PROGRAMADO")))) -> PROGRAMADO | Q34: =IF($E34="","",IF($L34="SIM",IF($M34=$A34,"NO DIA","FORA DO DIA"),""))
A35: 46281 | B35: =IFERROR(IF($E35="","",VLOOKUP($E35,CAD_TAB,2,FALSE)),"") -> BERTIOGA | D35: 31 | E35: BER-0031 | F35: =IFERROR(IF($E35="","",VLOOKUP($E35,CAD_TAB,8,FALSE)),"") -> Vazamento no ramal não visível | G35: =IFERROR(IF($E35="","",VLOOKUP($E35,CAD_TAB,9,FALSE)),"") -> Rua Espírito Santo | H35: =IFERROR(IF($E35="","",VLOOKUP($E35,CAD_TAB,11,FALSE)),"") -> Vicente de Carvalho | I35: =IFERROR(IF($E35="","",VLOOKUP($E35,CAD_TAB,7,FALSE)),"") -> URGENTE | J35: =IFERROR(IF($E35="","",VLOOKUP($E35,CAD_TAB,6,FALSE)),"") -> 46284 | L35: SIM | M35: 46281 | P35: =IF($E35="","",IF($L35="SIM","EXECUTADO",IF($O35<>"","REPROGRAMADO",IF($L35="NÃO","NÃO EXECUTADO","PROGRAMADO")))) -> EXECUTADO | Q35: =IF($E35="","",IF($L35="SIM",IF($M35=$A35,"NO DIA","FORA DO DIA"),"")) -> NO DIA
A36: 46281 | B36: =IFERROR(IF($E36="","",VLOOKUP($E36,CAD_TAB,2,FALSE)),"") -> BERTIOGA | D36: 32 | E36: BER-0032 | F36: =IFERROR(IF($E36="","",VLOOKUP($E36,CAD_TAB,8,FALSE)),"") -> Vazamento cavalete não visível | G36: =IFERROR(IF($E36="","",VLOOKUP($E36,CAD_TAB,9,FALSE)),"") -> Rua Espírito Santo | H36: =IFERROR(IF($E36="","",VLOOKUP($E36,CAD_TAB,11,FALSE)),"") -> Vicente de Carvalho | I36: =IFERROR(IF($E36="","",VLOOKUP($E36,CAD_TAB,7,FALSE)),"") -> URGENTE | J36: =IFERROR(IF($E36="","",VLOOKUP($E36,CAD_TAB,6,FALSE)),"") -> 46284 | L36: SIM | M36: 46281 | P36: =IF($E36="","",IF($L36="SIM","EXECUTADO",IF($O36<>"","REPROGRAMADO",IF($L36="NÃO","NÃO EXECUTADO","PROGRAMADO")))) -> EXECUTADO | Q36: =IF($E36="","",IF($L36="SIM",IF($M36=$A36,"NO DIA","FORA DO DIA"),"")) -> NO DIA
A37: 46281 | B37: =IFERROR(IF($E37="","",VLOOKUP($E37,CAD_TAB,2,FALSE)),"") -> BERTIOGA | D37: 33 | E37: BER-0033 | F37: =IFERROR(IF($E37="","",VLOOKUP($E37,CAD_TAB,8,FALSE)),"") -> Vazamento no ramal não visível | G37: =IFERROR(IF($E37="","",VLOOKUP($E37,CAD_TAB,9,FALSE)),"") -> Rua Mario Silveira | H37: =IFERROR(IF($E37="","",VLOOKUP($E37,CAD_TAB,11,FALSE)),"") -> Vicente de Carvalho | I37: =IFERROR(IF($E37="","",VLOOKUP($E37,CAD_TAB,7,FALSE)),"") -> URGENTE | J37: =IFERROR(IF($E37="","",VLOOKUP($E37,CAD_TAB,6,FALSE)),"") -> 46284 | P37: =IF($E37="","",IF($L37="SIM","EXECUTADO",IF($O37<>"","REPROGRAMADO",IF($L37="NÃO","NÃO EXECUTADO","PROGRAMADO")))) -> PROGRAMADO | Q37: =IF($E37="","",IF($L37="SIM",IF($M37=$A37,"NO DIA","FORA DO DIA"),""))
A38: 46281 | B38: =IFERROR(IF($E38="","",VLOOKUP($E38,CAD_TAB,2,FALSE)),"") -> BERTIOGA | D38: 34 | E38: BER-0034 | F38: =IFERROR(IF($E38="","",VLOOKUP($E38,CAD_TAB,8,FALSE)),"") -> Vazamento no ramal não visível | G38: =IFERROR(IF($E38="","",VLOOKUP($E38,CAD_TAB,9,FALSE)),"") -> Rua Mario Silveira | H38: =IFERROR(IF($E38="","",VLOOKUP($E38,CAD_TAB,11,FALSE)),"") -> Vicente de Carvalho | I38: =IFERROR(IF($E38="","",VLOOKUP($E38,CAD_TAB,7,FALSE)),"") -> URGENTE | J38: =IFERROR(IF($E38="","",VLOOKUP($E38,CAD_TAB,6,FALSE)),"") -> 46284 | P38: =IF($E38="","",IF($L38="SIM","EXECUTADO",IF($O38<>"","REPROGRAMADO",IF($L38="NÃO","NÃO EXECUTADO","PROGRAMADO")))) -> PROGRAMADO | Q38: =IF($E38="","",IF($L38="SIM",IF($M38=$A38,"NO DIA","FORA DO DIA"),""))
A39: 46281 | B39: =IFERROR(IF($E39="","",VLOOKUP($E39,CAD_TAB,2,FALSE)),"") -> BERTIOGA | D39: 35 | E39: BER-0035 | F39: =IFERROR(IF($E39="","",VLOOKUP($E39,CAD_TAB,8,FALSE)),"") -> Vazamento no ramal não visível | G39: =IFERROR(IF($E39="","",VLOOKUP($E39,CAD_TAB,9,FALSE)),"") -> Rua Tambaú | H39: =IFERROR(IF($E39="","",VLOOKUP($E39,CAD_TAB,11,FALSE)),"") -> Vicente de Carvalho | I39: =IFERROR(IF($E39="","",VLOOKUP($E39,CAD_TAB,7,FALSE)),"") -> URGENTE | J39: =IFERROR(IF($E39="","",VLOOKUP($E39,CAD_TAB,6,FALSE)),"") -> 46284 | P39: =IF($E39="","",IF($L39="SIM","EXECUTADO",IF($O39<>"","REPROGRAMADO",IF($L39="NÃO","NÃO EXECUTADO","PROGRAMADO")))) -> PROGRAMADO | Q39: =IF($E39="","",IF($L39="SIM",IF($M39=$A39,"NO DIA","FORA DO DIA"),""))
A40: 46281 | B40: =IFERROR(IF($E40="","",VLOOKUP($E40,CAD_TAB,2,FALSE)),"") -> BERTIOGA | D40: 36 | E40: BER-0036 | F40: =IFERROR(IF($E40="","",VLOOKUP($E40,CAD_TAB,8,FALSE)),"") -> Vazamento de água não visível — rede | G40: =IFERROR(IF($E40="","",VLOOKUP($E40,CAD_TAB,9,FALSE)),"") -> Cazil Frazon | H40: =IFERROR(IF($E40="","",VLOOKUP($E40,CAD_TAB,11,FALSE)),"") -> Vicente de Carvalho | I40: =IFERROR(IF($E40="","",VLOOKUP($E40,CAD_TAB,7,FALSE)),"") -> URGENTE | J40: =IFERROR(IF($E40="","",VLOOKUP($E40,CAD_TAB,6,FALSE)),"") -> 46284 | P40: =IF($E40="","",IF($L40="SIM","EXECUTADO",IF($O40<>"","REPROGRAMADO",IF($L40="NÃO","NÃO EXECUTADO","PROGRAMADO")))) -> PROGRAMADO | Q40: =IF($E40="","",IF($L40="SIM",IF($M40=$A40,"NO DIA","FORA DO DIA"),""))
A41: 46281 | B41: =IFERROR(IF($E41="","",VLOOKUP($E41,CAD_TAB,2,FALSE)),"") -> BERTIOGA | D41: 37 | E41: BER-0037 | F41: =IFERROR(IF($E41="","",VLOOKUP($E41,CAD_TAB,8,FALSE)),"") -> Vazamento de água não visível — rede | G41: =IFERROR(IF($E41="","",VLOOKUP($E41,CAD_TAB,9,FALSE)),"") -> Rua Clemente da Mata Amorim | H41: =IFERROR(IF($E41="","",VLOOKUP($E41,CAD_TAB,11,FALSE)),"") -> Jardim Progresso | I41: =IFERROR(IF($E41="","",VLOOKUP($E41,CAD_TAB,7,FALSE)),"") -> URGENTE | J41: =IFERROR(IF($E41="","",VLOOKUP($E41,CAD_TAB,6,FALSE)),"") -> 46284 | P41: =IF($E41="","",IF($L41="SIM","EXECUTADO",IF($O41<>"","REPROGRAMADO",IF($L41="NÃO","NÃO EXECUTADO","PROGRAMADO")))) -> PROGRAMADO | Q41: =IF($E41="","",IF($L41="SIM",IF($M41=$A41,"NO DIA","FORA DO DIA"),""))
A42: 46281 | B42: =IFERROR(IF($E42="","",VLOOKUP($E42,CAD_TAB,2,FALSE)),"") -> BERTIOGA | D42: 38 | E42: BER-0038 | F42: =IFERROR(IF($E42="","",VLOOKUP($E42,CAD_TAB,8,FALSE)),"") -> Vazamento no ramal não visível | G42: =IFERROR(IF($E42="","",VLOOKUP($E42,CAD_TAB,9,FALSE)),"") -> Rua Clemente da Mata Amorim | H42: =IFERROR(IF($E42="","",VLOOKUP($E42,CAD_TAB,11,FALSE)),"") -> Jardim Progresso | I42: =IFERROR(IF($E42="","",VLOOKUP($E42,CAD_TAB,7,FALSE)),"") -> URGENTE | J42: =IFERROR(IF($E42="","",VLOOKUP($E42,CAD_TAB,6,FALSE)),"") -> 46284 | P42: =IF($E42="","",IF($L42="SIM","EXECUTADO",IF($O42<>"","REPROGRAMADO",IF($L42="NÃO","NÃO EXECUTADO","PROGRAMADO")))) -> PROGRAMADO | Q42: =IF($E42="","",IF($L42="SIM",IF($M42=$A42,"NO DIA","FORA DO DIA"),""))
A43: 46281 | B43: =IFERROR(IF($E43="","",VLOOKUP($E43,CAD_TAB,2,FALSE)),"") -> BERTIOGA | D43: 39 | E43: BER-0039 | F43: =IFERROR(IF($E43="","",VLOOKUP($E43,CAD_TAB,8,FALSE)),"") -> Vazamento cavalete não visível | G43: =IFERROR(IF($E43="","",VLOOKUP($E43,CAD_TAB,9,FALSE)),"") -> Rua Adão Pereira da Silva | H43: =IFERROR(IF($E43="","",VLOOKUP($E43,CAD_TAB,11,FALSE)),"") -> Jardim Progresso | I43: =IFERROR(IF($E43="","",VLOOKUP($E43,CAD_TAB,7,FALSE)),"") -> URGENTE | J43: =IFERROR(IF($E43="","",VLOOKUP($E43,CAD_TAB,6,FALSE)),"") -> 46284 | P43: =IF($E43="","",IF($L43="SIM","EXECUTADO",IF($O43<>"","REPROGRAMADO",IF($L43="NÃO","NÃO EXECUTADO","PROGRAMADO")))) -> PROGRAMADO | Q43: =IF($E43="","",IF($L43="SIM",IF($M43=$A43,"NO DIA","FORA DO DIA"),""))
A44: 46281 | B44: =IFERROR(IF($E44="","",VLOOKUP($E44,CAD_TAB,2,FALSE)),"") -> BERTIOGA | D44: 40 | E44: BER-0040 | F44: =IFERROR(IF($E44="","",VLOOKUP($E44,CAD_TAB,8,FALSE)),"") -> Vazamento no ramal não visível | G44: =IFERROR(IF($E44="","",VLOOKUP($E44,CAD_TAB,9,FALSE)),"") -> Rua Manoel Romero Rodrigues | H44: =IFERROR(IF($E44="","",VLOOKUP($E44,CAD_TAB,11,FALSE)),"") -> Jardim Progresso | I44: =IFERROR(IF($E44="","",VLOOKUP($E44,CAD_TAB,7,FALSE)),"") -> URGENTE | J44: =IFERROR(IF($E44="","",VLOOKUP($E44,CAD_TAB,6,FALSE)),"") -> 46284 | P44: =IF($E44="","",IF($L44="SIM","EXECUTADO",IF($O44<>"","REPROGRAMADO",IF($L44="NÃO","NÃO EXECUTADO","PROGRAMADO")))) -> PROGRAMADO | Q44: =IF($E44="","",IF($L44="SIM",IF($M44=$A44,"NO DIA","FORA DO DIA"),""))
A45: 46281 | B45: =IFERROR(IF($E45="","",VLOOKUP($E45,CAD_TAB,2,FALSE)),"") -> BERTIOGA | D45: 41 | E45: BER-0041 | F45: =IFERROR(IF($E45="","",VLOOKUP($E45,CAD_TAB,8,FALSE)),"") -> Vazamento no ramal não visível | G45: =IFERROR(IF($E45="","",VLOOKUP($E45,CAD_TAB,9,FALSE)),"") -> Rua Manoel Romero Rodrigues | H45: =IFERROR(IF($E45="","",VLOOKUP($E45,CAD_TAB,11,FALSE)),"") -> Jardim Progresso | I45: =IFERROR(IF($E45="","",VLOOKUP($E45,CAD_TAB,7,FALSE)),"") -> URGENTE | J45: =IFERROR(IF($E45="","",VLOOKUP($E45,CAD_TAB,6,FALSE)),"") -> 46284 | P45: =IF($E45="","",IF($L45="SIM","EXECUTADO",IF($O45<>"","REPROGRAMADO",IF($L45="NÃO","NÃO EXECUTADO","PROGRAMADO")))) -> PROGRAMADO | Q45: =IF($E45="","",IF($L45="SIM",IF($M45=$A45,"NO DIA","FORA DO DIA"),""))
A46: 46281 | B46: =IFERROR(IF($E46="","",VLOOKUP($E46,CAD_TAB,2,FALSE)),"") -> BERTIOGA | D46: 42 | E46: BER-0042 | F46: =IFERROR(IF($E46="","",VLOOKUP($E46,CAD_TAB,8,FALSE)),"") -> Vazamento de água não visível — rede | G46: =IFERROR(IF($E46="","",VLOOKUP($E46,CAD_TAB,9,FALSE)),"") -> Rua Dickson Rodrigues | H46: =IFERROR(IF($E46="","",VLOOKUP($E46,CAD_TAB,11,FALSE)),"") -> Jardim Progresso | I46: =IFERROR(IF($E46="","",VLOOKUP($E46,CAD_TAB,7,FALSE)),"") -> URGENTE | J46: =IFERROR(IF($E46="","",VLOOKUP($E46,CAD_TAB,6,FALSE)),"") -> 46284 | P46: =IF($E46="","",IF($L46="SIM","EXECUTADO",IF($O46<>"","REPROGRAMADO",IF($L46="NÃO","NÃO EXECUTADO","PROGRAMADO")))) -> PROGRAMADO | Q46: =IF($E46="","",IF($L46="SIM",IF($M46=$A46,"NO DIA","FORA DO DIA"),""))
A47: 46281 | B47: =IFERROR(IF($E47="","",VLOOKUP($E47,CAD_TAB,2,FALSE)),"") -> BERTIOGA | D47: 43 | E47: BER-0043 | F47: =IFERROR(IF($E47="","",VLOOKUP($E47,CAD_TAB,8,FALSE)),"") -> Vazamento no ramal não visível | G47: =IFERROR(IF($E47="","",VLOOKUP($E47,CAD_TAB,9,FALSE)),"") -> Rua Coronel João Akui | H47: =IFERROR(IF($E47="","",VLOOKUP($E47,CAD_TAB,11,FALSE)),"") -> Jardim Progresso | I47: =IFERROR(IF($E47="","",VLOOKUP($E47,CAD_TAB,7,FALSE)),"") -> URGENTE | J47: =IFERROR(IF($E47="","",VLOOKUP($E47,CAD_TAB,6,FALSE)),"") -> 46284 | P47: =IF($E47="","",IF($L47="SIM","EXECUTADO",IF($O47<>"","REPROGRAMADO",IF($L47="NÃO","NÃO EXECUTADO","PROGRAMADO")))) -> PROGRAMADO | Q47: =IF($E47="","",IF($L47="SIM",IF($M47=$A47,"NO DIA","FORA DO DIA"),""))
A48: 46281 | B48: =IFERROR(IF($E48="","",VLOOKUP($E48,CAD_TAB,2,FALSE)),"") -> BERTIOGA | D48: 44 | E48: BER-0044 | F48: =IFERROR(IF($E48="","",VLOOKUP($E48,CAD_TAB,8,FALSE)),"") -> Vazamento no ramal não visível | G48: =IFERROR(IF($E48="","",VLOOKUP($E48,CAD_TAB,9,FALSE)),"") -> Rua Miguel Seiad | H48: =IFERROR(IF($E48="","",VLOOKUP($E48,CAD_TAB,11,FALSE)),"") -> 0 | I48: =IFERROR(IF($E48="","",VLOOKUP($E48,CAD_TAB,7,FALSE)),"") -> URGENTE | J48: =IFERROR(IF($E48="","",VLOOKUP($E48,CAD_TAB,6,FALSE)),"") -> 46284 | L48: SIM | M48: 46281 | P48: =IF($E48="","",IF($L48="SIM","EXECUTADO",IF($O48<>"","REPROGRAMADO",IF($L48="NÃO","NÃO EXECUTADO","PROGRAMADO")))) -> EXECUTADO | Q48: =IF($E48="","",IF($L48="SIM",IF($M48=$A48,"NO DIA","FORA DO DIA"),"")) -> NO DIA
B49: =IFERROR(IF($E49="","",VLOOKUP($E49,CAD_TAB,2,FALSE)),"") | F49: =IFERROR(IF($E49="","",VLOOKUP($E49,CAD_TAB,8,FALSE)),"") | G49: =IFERROR(IF($E49="","",VLOOKUP($E49,CAD_TAB,9,FALSE)),"") | H49: =IFERROR(IF($E49="","",VLOOKUP($E49,CAD_TAB,11,FALSE)),"") | I49: =IFERROR(IF($E49="","",VLOOKUP($E49,CAD_TAB,7,FALSE)),"") | J49: =IFERROR(IF($E49="","",VLOOKUP($E49,CAD_TAB,6,FALSE)),"") | P49: =IF($E49="","",IF($L49="SIM","EXECUTADO",IF($O49<>"","REPROGRAMADO",IF($L49="NÃO","NÃO EXECUTADO","PROGRAMADO")))) | Q49: =IF($E49="","",IF($L49="SIM",IF($M49=$A49,"NO DIA","FORA DO DIA"),""))
B50: =IFERROR(IF($E50="","",VLOOKUP($E50,CAD_TAB,2,FALSE)),"") | F50: =IFERROR(IF($E50="","",VLOOKUP($E50,CAD_TAB,8,FALSE)),"") | G50: =IFERROR(IF($E50="","",VLOOKUP($E50,CAD_TAB,9,FALSE)),"") | H50: =IFERROR(IF($E50="","",VLOOKUP($E50,CAD_TAB,11,FALSE)),"") | I50: =IFERROR(IF($E50="","",VLOOKUP($E50,CAD_TAB,7,FALSE)),"") | J50: =IFERROR(IF($E50="","",VLOOKUP($E50,CAD_TAB,6,FALSE)),"") | P50: =IF($E50="","",IF($L50="SIM","EXECUTADO",IF($O50<>"","REPROGRAMADO",IF($L50="NÃO","NÃO EXECUTADO","PROGRAMADO")))) | Q50: =IF($E50="","",IF($L50="SIM",IF($M50=$A50,"NO DIA","FORA DO DIA"),""))
B51: =IFERROR(IF($E51="","",VLOOKUP($E51,CAD_TAB,2,FALSE)),"") | F51: =IFERROR(IF($E51="","",VLOOKUP($E51,CAD_TAB,8,FALSE)),"") | G51: =IFERROR(IF($E51="","",VLOOKUP($E51,CAD_TAB,9,FALSE)),"") | H51: =IFERROR(IF($E51="","",VLOOKUP($E51,CAD_TAB,11,FALSE)),"") | I51: =IFERROR(IF($E51="","",VLOOKUP($E51,CAD_TAB,7,FALSE)),"") | J51: =IFERROR(IF($E51="","",VLOOKUP($E51,CAD_TAB,6,FALSE)),"") | P51: =IF($E51="","",IF($L51="SIM","EXECUTADO",IF($O51<>"","REPROGRAMADO",IF($L51="NÃO","NÃO EXECUTADO","PROGRAMADO")))) | Q51: =IF($E51="","",IF($L51="SIM",IF($M51=$A51,"NO DIA","FORA DO DIA"),""))
B52: =IFERROR(IF($E52="","",VLOOKUP($E52,CAD_TAB,2,FALSE)),"") | F52: =IFERROR(IF($E52="","",VLOOKUP($E52,CAD_TAB,8,FALSE)),"") | G52: =IFERROR(IF($E52="","",VLOOKUP($E52,CAD_TAB,9,FALSE)),"") | H52: =IFERROR(IF($E52="","",VLOOKUP($E52,CAD_TAB,11,FALSE)),"") | I52: =IFERROR(IF($E52="","",VLOOKUP($E52,CAD_TAB,7,FALSE)),"") | J52: =IFERROR(IF($E52="","",VLOOKUP($E52,CAD_TAB,6,FALSE)),"") | P52: =IF($E52="","",IF($L52="SIM","EXECUTADO",IF($O52<>"","REPROGRAMADO",IF($L52="NÃO","NÃO EXECUTADO","PROGRAMADO")))) | Q52: =IF($E52="","",IF($L52="SIM",IF($M52=$A52,"NO DIA","FORA DO DIA"),""))
B53: =IFERROR(IF($E53="","",VLOOKUP($E53,CAD_TAB,2,FALSE)),"") | F53: =IFERROR(IF($E53="","",VLOOKUP($E53,CAD_TAB,8,FALSE)),"") | G53: =IFERROR(IF($E53="","",VLOOKUP($E53,CAD_TAB,9,FALSE)),"") | H53: =IFERROR(IF($E53="","",VLOOKUP($E53,CAD_TAB,11,FALSE)),"") | I53: =IFERROR(IF($E53="","",VLOOKUP($E53,CAD_TAB,7,FALSE)),"") | J53: =IFERROR(IF($E53="","",VLOOKUP($E53,CAD_TAB,6,FALSE)),"") | P53: =IF($E53="","",IF($L53="SIM","EXECUTADO",IF($O53<>"","REPROGRAMADO",IF($L53="NÃO","NÃO EXECUTADO","PROGRAMADO")))) | Q53: =IF($E53="","",IF($L53="SIM",IF($M53=$A53,"NO DIA","FORA DO DIA"),""))
B54: =IFERROR(IF($E54="","",VLOOKUP($E54,CAD_TAB,2,FALSE)),"") | F54: =IFERROR(IF($E54="","",VLOOKUP($E54,CAD_TAB,8,FALSE)),"") | G54: =IFERROR(IF($E54="","",VLOOKUP($E54,CAD_TAB,9,FALSE)),"") | H54: =IFERROR(IF($E54="","",VLOOKUP($E54,CAD_TAB,11,FALSE)),"") | I54: =IFERROR(IF($E54="","",VLOOKUP($E54,CAD_TAB,7,FALSE)),"") | J54: =IFERROR(IF($E54="","",VLOOKUP($E54,CAD_TAB,6,FALSE)),"") | P54: =IF($E54="","",IF($L54="SIM","EXECUTADO",IF($O54<>"","REPROGRAMADO",IF($L54="NÃO","NÃO EXECUTADO","PROGRAMADO")))) | Q54: =IF($E54="","",IF($L54="SIM",IF($M54=$A54,"NO DIA","FORA DO DIA"),""))
B55: =IFERROR(IF($E55="","",VLOOKUP($E55,CAD_TAB,2,FALSE)),"") | F55: =IFERROR(IF($E55="","",VLOOKUP($E55,CAD_TAB,8,FALSE)),"") | G55: =IFERROR(IF($E55="","",VLOOKUP($E55,CAD_TAB,9,FALSE)),"") | H55: =IFERROR(IF($E55="","",VLOOKUP($E55,CAD_TAB,11,FALSE)),"") | I55: =IFERROR(IF($E55="","",VLOOKUP($E55,CAD_TAB,7,FALSE)),"") | J55: =IFERROR(IF($E55="","",VLOOKUP($E55,CAD_TAB,6,FALSE)),"") | P55: =IF($E55="","",IF($L55="SIM","EXECUTADO",IF($O55<>"","REPROGRAMADO",IF($L55="NÃO","NÃO EXECUTADO","PROGRAMADO")))) | Q55: =IF($E55="","",IF($L55="SIM",IF($M55=$A55,"NO DIA","FORA DO DIA"),""))
B56: =IFERROR(IF($E56="","",VLOOKUP($E56,CAD_TAB,2,FALSE)),"") | F56: =IFERROR(IF($E56="","",VLOOKUP($E56,CAD_TAB,8,FALSE)),"") | G56: =IFERROR(IF($E56="","",VLOOKUP($E56,CAD_TAB,9,FALSE)),"") | H56: =IFERROR(IF($E56="","",VLOOKUP($E56,CAD_TAB,11,FALSE)),"") | I56: =IFERROR(IF($E56="","",VLOOKUP($E56,CAD_TAB,7,FALSE)),"") | J56: =IFERROR(IF($E56="","",VLOOKUP($E56,CAD_TAB,6,FALSE)),"") | P56: =IF($E56="","",IF($L56="SIM","EXECUTADO",IF($O56<>"","REPROGRAMADO",IF($L56="NÃO","NÃO EXECUTADO","PROGRAMADO")))) | Q56: =IF($E56="","",IF($L56="SIM",IF($M56=$A56,"NO DIA","FORA DO DIA"),""))
B57: =IFERROR(IF($E57="","",VLOOKUP($E57,CAD_TAB,2,FALSE)),"") | F57: =IFERROR(IF($E57="","",VLOOKUP($E57,CAD_TAB,8,FALSE)),"") | G57: =IFERROR(IF($E57="","",VLOOKUP($E57,CAD_TAB,9,FALSE)),"") | H57: =IFERROR(IF($E57="","",VLOOKUP($E57,CAD_TAB,11,FALSE)),"") | I57: =IFERROR(IF($E57="","",VLOOKUP($E57,CAD_TAB,7,FALSE)),"") | J57: =IFERROR(IF($E57="","",VLOOKUP($E57,CAD_TAB,6,FALSE)),"") | P57: =IF($E57="","",IF($L57="SIM","EXECUTADO",IF($O57<>"","REPROGRAMADO",IF($L57="NÃO","NÃO EXECUTADO","PROGRAMADO")))) | Q57: =IF($E57="","",IF($L57="SIM",IF($M57=$A57,"NO DIA","FORA DO DIA"),""))
B58: =IFERROR(IF($E58="","",VLOOKUP($E58,CAD_TAB,2,FALSE)),"") | F58: =IFERROR(IF($E58="","",VLOOKUP($E58,CAD_TAB,8,FALSE)),"") | G58: =IFERROR(IF($E58="","",VLOOKUP($E58,CAD_TAB,9,FALSE)),"") | H58: =IFERROR(IF($E58="","",VLOOKUP($E58,CAD_TAB,11,FALSE)),"") | I58: =IFERROR(IF($E58="","",VLOOKUP($E58,CAD_TAB,7,FALSE)),"") | J58: =IFERROR(IF($E58="","",VLOOKUP($E58,CAD_TAB,6,FALSE)),"") | P58: =IF($E58="","",IF($L58="SIM","EXECUTADO",IF($O58<>"","REPROGRAMADO",IF($L58="NÃO","NÃO EXECUTADO","PROGRAMADO")))) | Q58: =IF($E58="","",IF($L58="SIM",IF($M58=$A58,"NO DIA","FORA DO DIA"),""))
B59: =IFERROR(IF($E59="","",VLOOKUP($E59,CAD_TAB,2,FALSE)),"") | F59: =IFERROR(IF($E59="","",VLOOKUP($E59,CAD_TAB,8,FALSE)),"") | G59: =IFERROR(IF($E59="","",VLOOKUP($E59,CAD_TAB,9,FALSE)),"") | H59: =IFERROR(IF($E59="","",VLOOKUP($E59,CAD_TAB,11,FALSE)),"") | I59: =IFERROR(IF($E59="","",VLOOKUP($E59,CAD_TAB,7,FALSE)),"") | J59: =IFERROR(IF($E59="","",VLOOKUP($E59,CAD_TAB,6,FALSE)),"") | P59: =IF($E59="","",IF($L59="SIM","EXECUTADO",IF($O59<>"","REPROGRAMADO",IF($L59="NÃO","NÃO EXECUTADO","PROGRAMADO")))) | Q59: =IF($E59="","",IF($L59="SIM",IF($M59=$A59,"NO DIA","FORA DO DIA"),""))
B60: =IFERROR(IF($E60="","",VLOOKUP($E60,CAD_TAB,2,FALSE)),"") | F60: =IFERROR(IF($E60="","",VLOOKUP($E60,CAD_TAB,8,FALSE)),"") | G60: =IFERROR(IF($E60="","",VLOOKUP($E60,CAD_TAB,9,FALSE)),"") | H60: =IFERROR(IF($E60="","",VLOOKUP($E60,CAD_TAB,11,FALSE)),"") | I60: =IFERROR(IF($E60="","",VLOOKUP($E60,CAD_TAB,7,FALSE)),"") | J60: =IFERROR(IF($E60="","",VLOOKUP($E60,CAD_TAB,6,FALSE)),"") | P60: =IF($E60="","",IF($L60="SIM","EXECUTADO",IF($O60<>"","REPROGRAMADO",IF($L60="NÃO","NÃO EXECUTADO","PROGRAMADO")))) | Q60: =IF($E60="","",IF($L60="SIM",IF($M60=$A60,"NO DIA","FORA DO DIA"),""))
... B904: =IFERROR(IF($E904="","",VLOOKUP($E904,CAD_TAB,2,FALSE)),"") | F904: =IFERROR(IF($E904="","",VLOOKUP($E904,CAD_TAB,8,FALSE)),"") | G904: =IFERROR(IF($E904="","",VLOOKUP($E904,CAD_TAB,9,FALSE)),"") | H904: =IFERROR(IF($E904="","",VLOOKUP($E904,CAD_TAB,11,FALSE)),"") | I904: =IFERROR(IF($E904="","",VLOOKUP($E904,CAD_TAB,7,FALSE)),"") | J904: =IFERROR(IF($E904="","",VLOOKUP($E904,CAD_TAB,6,FALSE)),"") | P904: =IF($E904="","",IF($L904="SIM","EXECUTADO",IF($O904<>"","REPROGRAMADO",IF($L904="NÃO","NÃO EXECUTADO","PROGRAMADO")))) | Q904: =IF($E904="","",IF($L904="SIM",IF($M904=$A904,"NO DIA","FORA DO DIA"),""))

Sheet 05. ORDENS DE SERVIÇO
A1: ORDENS DE SERVIÇO — REGISTRO DE EXECUÇÃO (1 LINHA = 1 SERVIÇO CONCLUÍDO) | Y1: COMO PREENCHER ESTA ABA
A2: Abra a OS quando a equipe iniciar. Só entra em medição a OS com STATUS CONCLUÍDA, foto antes/depois e pavimento reposto. | Y2: Abre a OS quando a equipe COMEÇA o serviço.
Y3: 1 linha = 1 serviço.
A4: ID DO SERVIÇO | B4: CONTRATO | C4: Nº OS SABESP | D4: ENDEREÇO | E4: BAIRRO | F4: TIPO DE SERVIÇO | G4: EQUIPE | H4: ENCARREGADO | I4: DATA DE INÍCIO | J4: DATA DE CONCLUSÃO | K4: DIAS | L4: PROFUNDIDADE (m) | M4: EXTENSÃO (m) | N4: PAVIMENTO REPOSTO? | O4: FOTO ANTES | P4: FOTO DEPOIS | Q4: Nº DO RDO | R4: Nº ITENS MEDIDOS | S4: VALOR DA OS | T4: MÊS DE MEDIÇÃO | U4: STATUS DA OS | V4: PENDÊNCIA / OBSERVAÇÃO | Y4: A = ID do serviço (BER-0001) da aba 03
A5: BER-0001 | B5: =IFERROR(IF($A5="","",VLOOKUP($A5,CAD_TAB,2,FALSE)),"") -> BERTIOGA | C5: =IFERROR(IF($A5="","",VLOOKUP($A5,CAD_TAB,3,FALSE)),"") -> 0 | D5: =IFERROR(IF($A5="","",VLOOKUP($A5,CAD_TAB,9,FALSE)),"") -> Alameda Maua | E5: =IFERROR(IF($A5="","",VLOOKUP($A5,CAD_TAB,11,FALSE)),"") -> Boracéia | F5: =IFERROR(IF($A5="","",VLOOKUP($A5,CAD_TAB,8,FALSE)),"") -> Vazamento de água não visível — rede | I5: 46273 | J5: 46273 | K5: =IF(OR($I5="",$J5=""),"",$J5-$I5+1) -> 1 | R5: =IF($A5="","",COUNTIFS(MED_ID,$A5)) -> 1 | S5: =IF($A5="","",SUMIFS(MED_VLR,MED_ID,$A5)) -> 0 | T5: =IF($J5="","",EOMONTH($J5,0)) -> 46295 | U5: =IF($A5="","",IF($V5="CANCELADA","CANCELADA",IF($S5>0,"MEDIDA",IF($J5="","EM EXECUÇÃO",IF(OR($N5="NÃO",$O5="NÃO",$P5="NÃO"),"AGUARDANDO PAVIMENTO","CONCLUÍDA"))))) -> CONCLUÍDA | V5: Foi feito 2 sondagens de 4m de profundidade cada. Não foi encontrado nenhum vazamento | Y5: endereço, bairro e tipo vêm sozinhos
A6: BER-0002 | B6: =IFERROR(IF($A6="","",VLOOKUP($A6,CAD_TAB,2,FALSE)),"") -> BERTIOGA | C6: =IFERROR(IF($A6="","",VLOOKUP($A6,CAD_TAB,3,FALSE)),"") -> 0 | D6: =IFERROR(IF($A6="","",VLOOKUP($A6,CAD_TAB,9,FALSE)),"") -> Rua Francisco Chaves | E6: =IFERROR(IF($A6="","",VLOOKUP($A6,CAD_TAB,11,FALSE)),"") -> Jardim Vicente de Carvalho | F6: =IFERROR(IF($A6="","",VLOOKUP($A6,CAD_TAB,8,FALSE)),"") -> Vazamento de água não visível — rede | I6: 46268 | J6: 46268 | K6: =IF(OR($I6="",$J6=""),"",$J6-$I6+1) -> 1 | M6: 2 | N6: SIM | R6: =IF($A6="","",COUNTIFS(MED_ID,$A6)) -> 2 | S6: =IF($A6="","",SUMIFS(MED_VLR,MED_ID,$A6)) -> 924.97 | T6: =IF($J6="","",EOMONTH($J6,0)) -> 46295 | U6: =IF($A6="","",IF($V6="CANCELADA","CANCELADA",IF($S6>0,"MEDIDA",IF($J6="","EM EXECUÇÃO",IF(OR($N6="NÃO",$O6="NÃO",$P6="NÃO"),"AGUARDANDO PAVIMENTO","CONCLUÍDA"))))) -> MEDIDA | V6: Troca de ramal. Foi usado um T de serviço e 2m PEAD | Y6: G = equipe (menu)
A7: BER-0003 | B7: =IFERROR(IF($A7="","",VLOOKUP($A7,CAD_TAB,2,FALSE)),"") -> BERTIOGA | C7: =IFERROR(IF($A7="","",VLOOKUP($A7,CAD_TAB,3,FALSE)),"") -> 0 | D7: =IFERROR(IF($A7="","",VLOOKUP($A7,CAD_TAB,9,FALSE)),"") -> Alameda Agapanthos | E7: =IFERROR(IF($A7="","",VLOOKUP($A7,CAD_TAB,11,FALSE)),"") -> Boracéia | F7: =IFERROR(IF($A7="","",VLOOKUP($A7,CAD_TAB,8,FALSE)),"") -> Troca de ramal de água | I7: 46268 | J7: 46268 | K7: =IF(OR($I7="",$J7=""),"",$J7-$I7+1) -> 1 | M7: 2 | R7: =IF($A7="","",COUNTIFS(MED_ID,$A7)) -> 1 | S7: =IF($A7="","",SUMIFS(MED_VLR,MED_ID,$A7)) -> 785.07 | T7: =IF($J7="","",EOMONTH($J7,0)) -> 46295 | U7: =IF($A7="","",IF($V7="CANCELADA","CANCELADA",IF($S7>0,"MEDIDA",IF($J7="","EM EXECUÇÃO",IF(OR($N7="NÃO",$O7="NÃO",$P7="NÃO"),"AGUARDANDO PAVIMENTO","CONCLUÍDA"))))) -> MEDIDA | V7: Troca de ramal. Foi usado um T de serviço, 1 cotovelo de metal e 2m PEAD | Y7: H = encarregado (menu, vem da aba 08)
A8: BER-0004 | B8: =IFERROR(IF($A8="","",VLOOKUP($A8,CAD_TAB,2,FALSE)),"") -> BERTIOGA | C8: =IFERROR(IF($A8="","",VLOOKUP($A8,CAD_TAB,3,FALSE)),"") -> 0 | D8: =IFERROR(IF($A8="","",VLOOKUP($A8,CAD_TAB,9,FALSE)),"") -> Alameda Paranapiacaba | E8: =IFERROR(IF($A8="","",VLOOKUP($A8,CAD_TAB,11,FALSE)),"") -> Boracéia | F8: =IFERROR(IF($A8="","",VLOOKUP($A8,CAD_TAB,8,FALSE)),"") -> Vazamento de água não visível — ramal | I8: 46268 | J8: 46268 | K8: =IF(OR($I8="",$J8=""),"",$J8-$I8+1) -> 1 | M8: 10 | R8: =IF($A8="","",COUNTIFS(MED_ID,$A8)) -> 1 | S8: =IF($A8="","",SUMIFS(MED_VLR,MED_ID,$A8)) -> 785.07 | T8: =IF($J8="","",EOMONTH($J8,0)) -> 46295 | U8: =IF($A8="","",IF($V8="CANCELADA","CANCELADA",IF($S8>0,"MEDIDA",IF($J8="","EM EXECUÇÃO",IF(OR($N8="NÃO",$O8="NÃO",$P8="NÃO"),"AGUARDANDO PAVIMENTO","CONCLUÍDA"))))) -> MEDIDA | V8: Troca de ramal e uma supressão. Foi usado 10m PEAD e um T de 50 · Foi localizado um gato na mangueira da Sabesp, porem foi retirado | Y8: I = data que começou
A9: BER-0005 | B9: =IFERROR(IF($A9="","",VLOOKUP($A9,CAD_TAB,2,FALSE)),"") -> BERTIOGA | C9: =IFERROR(IF($A9="","",VLOOKUP($A9,CAD_TAB,3,FALSE)),"") -> 0 | D9: =IFERROR(IF($A9="","",VLOOKUP($A9,CAD_TAB,9,FALSE)),"") -> Alameda Rio Grande da Serra | E9: =IFERROR(IF($A9="","",VLOOKUP($A9,CAD_TAB,11,FALSE)),"") -> Boracéia | F9: =IFERROR(IF($A9="","",VLOOKUP($A9,CAD_TAB,8,FALSE)),"") -> Vazamento de água não visível — ramal | I9: 46268 | J9: 46268 | K9: =IF(OR($I9="",$J9=""),"",$J9-$I9+1) -> 1 | M9: 25 | R9: =IF($A9="","",COUNTIFS(MED_ID,$A9)) -> 2 | S9: =IF($A9="","",SUMIFS(MED_VLR,MED_ID,$A9)) -> 1086.54 | T9: =IF($J9="","",EOMONTH($J9,0)) -> 46295 | U9: =IF($A9="","",IF($V9="CANCELADA","CANCELADA",IF($S9>0,"MEDIDA",IF($J9="","EM EXECUÇÃO",IF(OR($N9="NÃO",$O9="NÃO",$P9="NÃO"),"AGUARDANDO PAVIMENTO","CONCLUÍDA"))))) -> MEDIDA | V9: Troca de ramal e 1 cavalete. Rede oposto de 50. Foi usado 1 T 50, 25m de PEAD, 1 adpt metal cotovelo, 1 registro e 30cm de cano pvc 3/4 | Y9: J = data que terminou
A10: BER-0006 | B10: =IFERROR(IF($A10="","",VLOOKUP($A10,CAD_TAB,2,FALSE)),"") -> BERTIOGA | C10: =IFERROR(IF($A10="","",VLOOKUP($A10,CAD_TAB,3,FALSE)),"") -> 0 | D10: =IFERROR(IF($A10="","",VLOOKUP($A10,CAD_TAB,9,FALSE)),"") -> Rua Prolongada Oswaldo Cruz | E10: =IFERROR(IF($A10="","",VLOOKUP($A10,CAD_TAB,11,FALSE)),"") -> Jardim Vicente de Carvalho | F10: =IFERROR(IF($A10="","",VLOOKUP($A10,CAD_TAB,8,FALSE)),"") -> Troca de ramal de água | I10: 46268 | J10: 46268 | K10: =IF(OR($I10="",$J10=""),"",$J10-$I10+1) -> 1 | M10: 4 | N10: SIM | R10: =IF($A10="","",COUNTIFS(MED_ID,$A10)) -> 2 | S10: =IF($A10="","",SUMIFS(MED_VLR,MED_ID,$A10)) -> 924.97 | T10: =IF($J10="","",EOMONTH($J10,0)) -> 46295 | U10: =IF($A10="","",IF($V10="CANCELADA","CANCELADA",IF($S10>0,"MEDIDA",IF($J10="","EM EXECUÇÃO",IF(OR($N10="NÃO",$O10="NÃO",$P10="NÃO"),"AGUARDANDO PAVIMENTO","CONCLUÍDA"))))) -> MEDIDA | V10: Troca de ramal e uma supressão. Foi usado o colar de 50 e 4m PEAD | Y10: L = profundidade em metros
A11: BER-0007 | B11: =IFERROR(IF($A11="","",VLOOKUP($A11,CAD_TAB,2,FALSE)),"") -> BERTIOGA | C11: =IFERROR(IF($A11="","",VLOOKUP($A11,CAD_TAB,3,FALSE)),"") -> 0 | D11: =IFERROR(IF($A11="","",VLOOKUP($A11,CAD_TAB,9,FALSE)),"") -> Rua Prolongada Oswaldo Cruz | E11: =IFERROR(IF($A11="","",VLOOKUP($A11,CAD_TAB,11,FALSE)),"") -> Jardim Vicente de Carvalho | F11: =IFERROR(IF($A11="","",VLOOKUP($A11,CAD_TAB,8,FALSE)),"") -> Troca de ramal de água | I11: 46268 | J11: 46268 | K11: =IF(OR($I11="",$J11=""),"",$J11-$I11+1) -> 1 | M11: 2 | R11: =IF($A11="","",COUNTIFS(MED_ID,$A11)) -> 2 | S11: =IF($A11="","",SUMIFS(MED_VLR,MED_ID,$A11)) -> 1871.61 | T11: =IF($J11="","",EOMONTH($J11,0)) -> 46295 | U11: =IF($A11="","",IF($V11="CANCELADA","CANCELADA",IF($S11>0,"MEDIDA",IF($J11="","EM EXECUÇÃO",IF(OR($N11="NÃO",$O11="NÃO",$P11="NÃO"),"AGUARDANDO PAVIMENTO","CONCLUÍDA"))))) -> MEDIDA | V11: Troca de ramal, troca na rede e uma troca no cavalete. Foi usado 1 T 50, 2m de PEAD, 1 cotovelo de metal, 3 cotovelos de plástico, 1 registro, 2 tubetes e 1 luva de 50
