Workbook

Sheet LEIA-ME
B2: FLUXO DE CAIXA PROJETADO — BERTIOGA + SANTOS (GLOBAL)
B3: Gerado em 25/08/2026 a partir de: Fluxo Trimestral Obra.xlsx (custos e tickets) · Adiantamento Bertioga.xlsx (mobilização) · tabelas de preços GJ/BT e Santos II · método do modelo Custo_Equipe_Rede_Esgoto (defasagem de recebimento e capital inicial).
B5: COMO USAR
B6: 1. Tudo se controla na aba PREMISSAS: cenário de produção (MÍNIMA / MÉDIA / BOA / ÓTIMA), defasagem de recebimento, imposto da nota (22%), tickets médios e mix água/esgoto de Santos.
B7: 2. Os custos vivem nas abas CUSTOS BERTIOGA e CUSTOS SANTOS. A seção 7 das PREMISSAS define QUEM PAGA cada bloco (consórcio × WCR) e se ele desconta da medição.
B8: 3. FCP SEMANAL e FCP MENSAL = FINANCEIRO (caixa da WCR). ECONÔMICO = margem real do contrato por competência. VIABILIDADE = produção necessária (visão econômica).
B9: 4. VIABILIDADE mostra quantos serviços por dia cada cidade precisa entregar em cada cenário. A aba AUX só faz conta — não precisa mexer.
B10: 5. Toda semana, lance a PRODUÇÃO REALIZADA na seção PLANEJADO × REALIZADO do FCP SEMANAL (células verdes). Medição, recebimento, FCP MENSAL e ECONÔMICO atualizam sozinhos; semana sem lançamento usa o planejado.
B12: LEGENDA DE CORES
B13: AZUL = valor editável (premissa) · PRETO = fórmula · VERDE = puxa de outra aba · FUNDO AMARELO = premissa crítica — confirme antes de decidir.
B15: Custo mensal GLOBAL da operação (todos os custos)
B16: Custos bancados pelo consórcio (descontados da medição) | C16: =PREMISSAS!$C$61 -> 466854.32
B17: Custos pagos pela WCR (caixa próprio) | C17: =PREMISSAS!$C$56 -> 40000
B18: Resultado econômico no horizonte (margem real) | C18: =ECONÔMICO!R17 -> 1172835.2
B19: Pior ponto do trimestre no caixa da WCR (FCP SEMANAL) | C19: ='FCP SEMANAL'!C42 -> -138227.95
B20: CAPITAL RECOMENDADO — WCR (necessidade máxima + contingência) | C20: ='FCP MENSAL'!C44 -> 204962.14
B22: AVISOS IMPORTANTES
B23: • A produção MÍNIMA aqui é maior que na sua planilha anterior: lá o empate não descontava o imposto da nota (22%). Ex.: Bertioga 8,98 → 11,5 serviços/dia. A linha cinza da VIABILIDADE mostra a referência antiga.
B24: • A medição fecha no fim do mês e é paga com a defasagem da PREMISSAS!C9. Até o primeiro recebimento a obra roda no caixa próprio — esse é o número do CAPITAL RECOMENDADO.
B25: • O kit ferramenta (R$ 28.800 por cidade) segue como custo MENSAL, igual à sua planilha. Se for compra única, mova para a mobilização nas PREMISSAS — o custo mensal cai e a viabilidade melhora.
B26: • Os preços de Santos foram transcritos de fotos; itens com dígito cortado estão marcados 'conferir' na aba PREÇOS SANTOS.
B27: • O 1º mês entra proporcional aos dias de obra (início em PREMISSAS!C6). A medição do 1º mês é parcial.
B28: • O pior ponto do caixa e o CAPITAL RECOMENDADO recalculam sozinhos quando você muda a defasagem, o cenário ou os custos nas PREMISSAS.
B29: • ECONÔMICO × FINANCEIRO: o consórcio banca folha, engenheiro e estrutura e DESCONTA da medição; a WCR paga só os indiretos e recebe o saldo. O ECONÔMICO mostra a margem real; o FINANCEIRO mostra o caixa da WCR. No 1º mês o desconto pode superar a medição parcial (líquido negativo = saldo devido ao consórcio, compensa em seguida).
B30: • Base do imposto (PREMISSAS C48): assumi 22% sobre a MEDIÇÃO CHEIA (conservador). Se a nota da WCR for só do valor líquido do desconto, troque para LÍQUIDA DO DESCONTO — entra bem mais caixa. Confirme com o contador.

Sheet PREMISSAS
B2: FLUXO DE CAIXA PROJETADO — BERTIOGA + SANTOS · PREMISSAS
B3: AZUL = valor editável · PRETO = fórmula · VERDE = puxa de outra aba · FUNDO AMARELO = premissa crítica
B5: 1. CALENDÁRIO E CONTRATO
B6: Início da obra / Semana 1 do fluxo | C6: 46258 | D6: data | E6: Segunda-feira. Primeira coluna do FCP SEMANAL.
B7: Fim da operação projetada | C7: 46599 | D7: data | E7: Último dia de obra no FCP MENSAL (~12 meses de operação). Edite para esticar ou encurtar.
B8: Dias por mês (convenção de rateio) | C8: 30 | D8: dias | E8: Mesma convenção da sua planilha: diário = mensal ÷ 30 · semana = 7 dias corridos.
B9: Defasagem de recebimento | C9: 20 | D9: dias | E9: A medição fecha no último dia do mês e é paga N dias depois (ex.: com N=20, agosto fecha 31/08 e paga 20/09).
B10: Imposto da nota | C10: 0.22 | D10: % | E10: Retenções + tributos sobre a medição bruta, pagos na data do recebimento — premissa da sua aba Custos.
B12: 2. CENÁRIO DE PRODUÇÃO
B13: Cenário adotado no fluxo | C13: ÓTIMA | D13: — | E13: Escolha: MÍNIMA, MÉDIA, BOA ou ÓTIMA. Todo o fluxo recalcula. MÍNIMA = empate real (cobre custo + imposto).
A14: MÍNIMA | B14: Margem do cenário MÍNIMA | C14: 0 | D14: % | E14: Empate: receita líquida = custo. Não sobra nada (nem recupera a mobilização).
A15: MÉDIA | B15: Margem do cenário MÉDIA | C15: 0.1 | D15: % | E15: Custo + 10% de margem.
A16: BOA | B16: Margem do cenário BOA | C16: 0.15 | D16: % | E16: Custo + 15% de margem.
A17: ÓTIMA | B17: Margem do cenário ÓTIMA | C17: 0.2 | D17: % | E17: Custo + 20% de margem.
B18: Margem do cenário adotado | C18: =INDEX(C14:C17,MATCH(C13,A14:A17,0)) -> 0.2 | D18: % | E18: Fórmula — não editar.
B20: 3. PREÇOS MÉDIOS POR SERVIÇO (ticket)
B21: Bertioga — ticket médio por serviço | C21: 881.2 | D21: R$/un | E21: Média adotada por você no Fluxo Trimestral (aba Custos). Tabela do contrato: aba PREÇOS BERTIOGA.
B22: Santos — ticket água | C22: 821.25 | D22: R$/un | E22: Idem. Tabela do contrato: aba PREÇOS SANTOS (coluna K50).
B23: Santos — ticket esgoto | C23: 1856.4 | D23: R$/un | E23: Idem.
B24: Santos — % dos serviços que são esgoto | C24: 0.5 | D24: % | E24: Mix da carteira. Muda o ticket ponderado e a produção necessária em unidades.
B25: Santos — ticket médio ponderado | C25: =C23*C24+C22*(1-C24) -> 1338.825 | D25: R$/un | E25: Fórmula — não editar.
B27: 4. CUSTOS MENSAIS (vêm das abas de custos)
B28: Bertioga — custo mensal total | C28: ='CUSTOS BERTIOGA'!F36 -> 237292.84 | D28: R$/mês | E28: Equipe + estrutura + engenheiro + indiretos. Detalhe na aba CUSTOS BERTIOGA.
B29: Santos — custo mensal total | C29: ='CUSTOS SANTOS'!F37 -> 269561.48 | D29: R$/mês | E29: Detalhe na aba CUSTOS SANTOS.
B30: GLOBAL — custo mensal total | C30: =C28+C29 -> 506854.32 | D30: R$/mês
B32: 5. MOBILIZAÇÃO — desembolsos iniciais (coluna “Anterior”)
B33: Bertioga — custos iniciais (Adiantamento) | C33: 13360 | D33: R$ | E33: 50% da mobilização total (carros eng.+empreiteiro 6.800 · alojamento 13.500 · casa 3.000 · alimentação ago+set 3.420 = 26.720), dividida meio a meio entre as cidades — como no FCP SEMANAL.
B34: Santos — custos iniciais | C34: 13360 | D34: R$ | E34: 50% da mobilização total, como no FCP SEMANAL.
B35: Total mobilização | C35: =SUM(C33:C34) -> 26720 | D35: R$
B37: 6. CAPITAL E RISCO
B38: Contingência sobre a necessidade máxima de caixa | C38: 0.15 | D38: % | E38: Atraso de medição, chuva, quebra, retrabalho. 15% é o mínimo prudente (modelo Custo_Equipe).
B39: Fator de custos do 1º mês (fração do custo mensal) | C39: 0.5 | D39: % | E39: Espelha o 0,5 do FCP SEMANAL para agosto (obra começa dia 24). Usado no FCP MENSAL e na sensibilidade.
B41: 7. QUEM PAGA O QUÊ — regime com o consórcio
B42: Folha das equipes — quem paga | C42: CONSÓRCIO | E42: Salários + encargos + benefícios das equipes.
B43: Engenheiro — quem paga | C43: CONSÓRCIO | E43: R$ 13.000/mês por cidade.
B44: Estrutura e locações — quem paga | C44: CONSÓRCIO | E44: Carros, caminhões, HR, alojamento, equipamentos, kit ferramenta.
B45: Custos indiretos — quem paga | C45: WCR | E45: R$ 20.000/mês por cidade — sai do caixa da WCR.
B46: Mobilização — quem paga | C46: CONSÓRCIO | E46: Adiantamento Bertioga (R$ 26.720) foi bancado pelo consórcio.
B47: O consórcio desconta da medição o que ele paga? | C47: SIM | E47: SIM = o que ele banca é abatido do valor que a WCR recebe.
B48: Base do imposto da nota | C48: MEDIÇÃO CHEIA | E48: MEDIÇÃO CHEIA = 22% sobre a medição toda (conservador). LÍQUIDA DO DESCONTO = 22% só sobre o que a WCR efetivamente fatura. Confirme com o contador.
B50: 8. CUSTOS PELO REGIME (fórmulas — não editar)
B51: Bertioga — custos bancados pelo consórcio | C51: =IF(C42="CONSÓRCIO",'CUSTOS BERTIOGA'!$H$22,0)+IF(C43="CONSÓRCIO",'CUSTOS BERTIOGA'!$F$26,0)+IF(C44="CONSÓRCIO",($C$28-'CUSTOS BERTIOGA'!$H$22-'CUSTOS BERTIOGA'!$F$26-'CUSTOS BERTIOGA'!$F$34),0)+IF(C45="CONSÓRCIO",'CUSTOS BERTIOGA'!$F$34,0) -> 217292.84
B52: Santos — custos bancados pelo consórcio | C52: =IF(C42="CONSÓRCIO",'CUSTOS SANTOS'!$H$23,0)+IF(C43="CONSÓRCIO",'CUSTOS SANTOS'!$F$27,0)+IF(C44="CONSÓRCIO",($C$29-'CUSTOS SANTOS'!$H$23-'CUSTOS SANTOS'!$F$27-'CUSTOS SANTOS'!$F$35),0)+IF(C45="CONSÓRCIO",'CUSTOS SANTOS'!$F$35,0) -> 249561.48
B53: GLOBAL — custos bancados pelo consórcio | C53: =C51+C52 -> 466854.32
B54: Bertioga — custos pagos pela WCR (caixa) | C54: =C28-C51 -> 20000
B55: Santos — custos pagos pela WCR (caixa) | C55: =C29-C52 -> 20000
B56: GLOBAL — custos pagos pela WCR (caixa) | C56: =C54+C55 -> 40000
B57: Mobilização paga pela WCR (caixa) | C57: =IF(C46="WCR",C35,0) -> 0
B58: Mobilização descontada pelo consórcio | C58: =IF(AND(C46="CONSÓRCIO",C47="SIM"),C35,0) -> 26720 | E58: Se o consórcio bancou e desconta, o valor é abatido no 1º recebimento.
B59: Desconto mensal efetivo — Bertioga | C59: =IF(C47="SIM",C51,0) -> 217292.84
B60: Desconto mensal efetivo — Santos | C60: =IF(C47="SIM",C52,0) -> 249561.48
B61: Desconto mensal efetivo — GLOBAL | C61: =C59+C60 -> 466854.32

Sheet FCP SEMANAL
B2: FCP SEMANAL — FINANCEIRO (CAIXA DA WCR)
B3: Só o que passa pela conta da WCR. Recebimento bruto nas semanas que você definiu (S1→S3, S2–S6→S7, S7–S11→S12); na mesma semana entra o DESCONTO do consórcio (folha, engenheiro, estrutura que ele banca) e o imposto. A WCR paga do bolso só os custos indiretos (dia 20 do mês seguinte). Visão de margem: aba ECONÔMICO.
N4: Cenário: | O4: =PREMISSAS!$C$13 -> ÓTIMA
C5: Anterior | D5: S1 | E5: S2 | F5: S3 | G5: S4 | H5: S5 | I5: S6 | J5: S7 | K5: S8 | L5: S9 | M5: S10 | N5: S11 | O5: S12 | P5: TOTAL
B6: início | D6: =PREMISSAS!$C$6 -> 46258 | E6: =D6+7 -> 46265 | F6: =E6+7 -> 46272 | G6: =F6+7 -> 46279 | H6: =G6+7 -> 46286 | I6: =H6+7 -> 46293 | J6: =I6+7 -> 46300 | K6: =J6+7 -> 46307 | L6: =K6+7 -> 46314 | ... O6: =N6+7 -> 46335
D7: a | E7: a | F7: a | G7: a | H7: a | I7: a | J7: a | K7: a | L7: a | M7: a | N7: a | O7: a
B8: fim | D8: =D6+6 -> 46264 | E8: =E6+6 -> 46271 | F8: =F6+6 -> 46278 | G8: =G6+6 -> 46285 | H8: =H6+6 -> 46292 | I8: =I6+6 -> 46299 | J8: =J6+6 -> 46306 | K8: =K6+6 -> 46313 | ... O8: =O6+6 -> 46341
B10: BERTIOGA
B11: Produção prevista (un) | D11: =PREMISSAS!$C$28*(1+PREMISSAS!$C$18)/(1-PREMISSAS!$C$10)/PREMISSAS!$C$21*7/PREMISSAS!$C$8 -> 96.665961 | E11: =PREMISSAS!$C$28*(1+PREMISSAS!$C$18)/(1-PREMISSAS!$C$10)/PREMISSAS!$C$21*7/PREMISSAS!$C$8 -> 96.665961 | F11: =PREMISSAS!$C$28*(1+PREMISSAS!$C$18)/(1-PREMISSAS!$C$10)/PREMISSAS!$C$21*7/PREMISSAS!$C$8 -> 96.665961 | G11: =PREMISSAS!$C$28*(1+PREMISSAS!$C$18)/(1-PREMISSAS!$C$10)/PREMISSAS!$C$21*7/PREMISSAS!$C$8 -> 96.665961 | H11: =PREMISSAS!$C$28*(1+PREMISSAS!$C$18)/(1-PREMISSAS!$C$10)/PREMISSAS!$C$21*7/PREMISSAS!$C$8 -> 96.665961 | I11: =PREMISSAS!$C$28*(1+PREMISSAS!$C$18)/(1-PREMISSAS!$C$10)/PREMISSAS!$C$21*7/PREMISSAS!$C$8 -> 96.665961 | J11: =PREMISSAS!$C$28*(1+PREMISSAS!$C$18)/(1-PREMISSAS!$C$10)/PREMISSAS!$C$21*7/PREMISSAS!$C$8 -> 96.665961 | K11: =PREMISSAS!$C$28*(1+PREMISSAS!$C$18)/(1-PREMISSAS!$C$10)/PREMISSAS!$C$21*7/PREMISSAS!$C$8 -> 96.665961 | ... O11: =PREMISSAS!$C$28*(1+PREMISSAS!$C$18)/(1-PREMISSAS!$C$10)/PREMISSAS!$C$21*7/PREMISSAS!$C$8 -> 96.665961 | P11: =SUM(C11:O11) -> 1159.9915
B12: Medição do período (REALIZADA se lançada; senão prevista) | D12: =IF(D$45<>"",D$45,D11)*PREMISSAS!$C$21 -> 85182.045 | E12: =IF(E$45<>"",E$45,E11)*PREMISSAS!$C$21 -> 85182.045 | F12: =IF(F$45<>"",F$45,F11)*PREMISSAS!$C$21 -> 85182.045 | G12: =IF(G$45<>"",G$45,G11)*PREMISSAS!$C$21 -> 85182.045 | H12: =IF(H$45<>"",H$45,H11)*PREMISSAS!$C$21 -> 85182.045 | I12: =IF(I$45<>"",I$45,I11)*PREMISSAS!$C$21 -> 85182.045 | J12: =IF(J$45<>"",J$45,J11)*PREMISSAS!$C$21 -> 85182.045 | K12: =IF(K$45<>"",K$45,K11)*PREMISSAS!$C$21 -> 85182.045 | ... O12: =IF(O$45<>"",O$45,O11)*PREMISSAS!$C$21 -> 85182.045 | P12: =SUM(C12:O12) -> 1022184.5
B13: (A) RECEBIMENTO BRUTO | C13: 0 | D13: =SUMPRODUCT((AUX!$C$8:$Q$8>=D$6)*(AUX!$C$8:$Q$8<=D$8)*AUX!$C$5:$Q$5) -> 0 | E13: =SUMPRODUCT((AUX!$C$8:$Q$8>=E$6)*(AUX!$C$8:$Q$8<=E$8)*AUX!$C$5:$Q$5) -> 0 | F13: =D12 -> 85182.045 | J13: =E12+F12+G12+H12+I12 -> 425910.23 | K13: =SUMPRODUCT((AUX!$C$8:$Q$8>=K$6)*(AUX!$C$8:$Q$8<=K$8)*AUX!$C$5:$Q$5) -> 0 | M13: =SUMPRODUCT((AUX!$C$8:$Q$8>=M$6)*(AUX!$C$8:$Q$8<=M$8)*AUX!$C$5:$Q$5) -> 0 | N13: =SUMPRODUCT((AUX!$C$8:$Q$8>=N$6)*(AUX!$C$8:$Q$8<=N$8)*AUX!$C$5:$Q$5) -> 0 | O13: =J12+K12+L12+M12+N12 -> 425910.23 | P13: =SUM(C13:O13) -> 937002.5
B14: (–) Imposto da nota | C14: =IF(PREMISSAS!$C$48="MEDIÇÃO CHEIA",C13,MAX(0,C13-C15))*PREMISSAS!$C$10 -> 0 | D14: =IF(PREMISSAS!$C$48="MEDIÇÃO CHEIA",D13,MAX(0,D13-D15))*PREMISSAS!$C$10 -> 0 | E14: =IF(PREMISSAS!$C$48="MEDIÇÃO CHEIA",E13,MAX(0,E13-E15))*PREMISSAS!$C$10 -> 0 | F14: =IF(PREMISSAS!$C$48="MEDIÇÃO CHEIA",F13,MAX(0,F13-F15))*PREMISSAS!$C$10 -> 18740.05 | G14: =IF(PREMISSAS!$C$48="MEDIÇÃO CHEIA",G13,MAX(0,G13-G15))*PREMISSAS!$C$10 -> 0 | H14: =IF(PREMISSAS!$C$48="MEDIÇÃO CHEIA",H13,MAX(0,H13-H15))*PREMISSAS!$C$10 -> 0 | I14: =IF(PREMISSAS!$C$48="MEDIÇÃO CHEIA",I13,MAX(0,I13-I15))*PREMISSAS!$C$10 -> 0 | J14: =IF(PREMISSAS!$C$48="MEDIÇÃO CHEIA",J13,MAX(0,J13-J15))*PREMISSAS!$C$10 -> 93700.25 | ... O14: =IF(PREMISSAS!$C$48="MEDIÇÃO CHEIA",O13,MAX(0,O13-O15))*PREMISSAS!$C$10 -> 93700.25 | P14: =SUM(C14:O14) -> 206140.55
B15: (–) Desconto do consórcio (custos que ele banca) | C15: 0 | D15: 0 | E15: 0 | F15: =PREMISSAS!$C$59*PREMISSAS!$C$39+PREMISSAS!$C$58*0.5 -> 122006.42 | G15: 0 | H15: 0 | I15: 0 | J15: =PREMISSAS!$C$59 -> 217292.84 | K15: 0 | L15: 0 | M15: 0 | N15: 0 | O15: =PREMISSAS!$C$59 -> 217292.84 | P15: =SUM(C15:O15) -> 556592.1
B16: (–) Custos pagos pela WCR (indiretos) | C16: 0 | D16: 0 | E16: 0 | F16: 0 | G16: =PREMISSAS!$C$54*PREMISSAS!$C$39 -> 10000 | H16: 0 | I16: 0 | J16: 0 | K16: 0 | L16: =PREMISSAS!$C$54 -> 20000 | M16: 0 | N16: 0 | O16: 0 | P16: =SUM(C16:O16) -> 30000
B17: (–) Outros desembolsos da WCR (edite se houver) | C17: 0 | D17: 0 | E17: 0 | F17: 0 | G17: 0 | H17: 0 | I17: 0 | J17: 0 | K17: 0 | L17: 0 | M17: 0 | N17: 0 | O17: 0 | P17: =SUM(C17:O17) -> 0
B18: (–) Mobilização paga pela WCR | C18: =PREMISSAS!$C$57*0.5 -> 0 | D18: 0 | E18: 0 | F18: 0 | G18: 0 | H18: 0 | I18: 0 | J18: 0 | K18: 0 | L18: 0 | M18: 0 | N18: 0 | O18: 0 | P18: =SUM(C18:O18) -> 0
B19: (B) TOTAL DE DESPESAS | C19: =SUM(C14:C18) -> 0 | D19: =SUM(D14:D18) -> 0 | E19: =SUM(E14:E18) -> 0 | F19: =SUM(F14:F18) -> 140746.47 | G19: =SUM(G14:G18) -> 10000 | H19: =SUM(H14:H18) -> 0 | I19: =SUM(I14:I18) -> 0 | J19: =SUM(J14:J18) -> 310993.09 | ... O19: =SUM(O14:O18) -> 310993.09 | P19: =SUM(C19:O19) -> 792732.65
B20: SALDO DO PERÍODO (A–B) | C20: =C13-C19 -> 0 | D20: =D13-D19 -> 0 | E20: =E13-E19 -> 0 | F20: =F13-F19 -> -55564.425 | G20: =G13-G19 -> -10000 | H20: =H13-H19 -> 0 | I20: =I13-I19 -> 0 | J20: =J13-J19 -> 114917.14 | ... O20: =O13-O19 -> 114917.14 | P20: =SUM(C20:O20) -> 144269.85
B21: SALDO ACUMULADO | C21: =C20 -> 0 | D21: =C21+D20 -> 0 | E21: =D21+E20 -> 0 | F21: =E21+F20 -> -55564.425 | G21: =F21+G20 -> -65564.425 | H21: =G21+H20 -> -65564.425 | I21: =H21+I20 -> -65564.425 | J21: =I21+J20 -> 49352.711 | K21: =J21+K20 -> 49352.711 | ... O21: =N21+O20 -> 144269.85 | P21: =O21 -> 144269.85
B23: SANTOS
B24: Produção prevista (un) | D24: =PREMISSAS!$C$29*(1+PREMISSAS!$C$18)/(1-PREMISSAS!$C$10)/PREMISSAS!$C$25*7/PREMISSAS!$C$8 -> 72.276556 | E24: =PREMISSAS!$C$29*(1+PREMISSAS!$C$18)/(1-PREMISSAS!$C$10)/PREMISSAS!$C$25*7/PREMISSAS!$C$8 -> 72.276556 | F24: =PREMISSAS!$C$29*(1+PREMISSAS!$C$18)/(1-PREMISSAS!$C$10)/PREMISSAS!$C$25*7/PREMISSAS!$C$8 -> 72.276556 | G24: =PREMISSAS!$C$29*(1+PREMISSAS!$C$18)/(1-PREMISSAS!$C$10)/PREMISSAS!$C$25*7/PREMISSAS!$C$8 -> 72.276556 | H24: =PREMISSAS!$C$29*(1+PREMISSAS!$C$18)/(1-PREMISSAS!$C$10)/PREMISSAS!$C$25*7/PREMISSAS!$C$8 -> 72.276556 | I24: =PREMISSAS!$C$29*(1+PREMISSAS!$C$18)/(1-PREMISSAS!$C$10)/PREMISSAS!$C$25*7/PREMISSAS!$C$8 -> 72.276556 | J24: =PREMISSAS!$C$29*(1+PREMISSAS!$C$18)/(1-PREMISSAS!$C$10)/PREMISSAS!$C$25*7/PREMISSAS!$C$8 -> 72.276556 | K24: =PREMISSAS!$C$29*(1+PREMISSAS!$C$18)/(1-PREMISSAS!$C$10)/PREMISSAS!$C$25*7/PREMISSAS!$C$8 -> 72.276556 | ... O24: =PREMISSAS!$C$29*(1+PREMISSAS!$C$18)/(1-PREMISSAS!$C$10)/PREMISSAS!$C$25*7/PREMISSAS!$C$8 -> 72.276556 | P24: =SUM(C24:O24) -> 867.31867
B25: Medição do período (REALIZADA se lançada; senão prevista) | D25: =IF(D$47<>"",D$47,D24)*PREMISSAS!$C$25 -> 96765.659 | E25: =IF(E$47<>"",E$47,E24)*PREMISSAS!$C$25 -> 96765.659 | F25: =IF(F$47<>"",F$47,F24)*PREMISSAS!$C$25 -> 96765.659 | G25: =IF(G$47<>"",G$47,G24)*PREMISSAS!$C$25 -> 96765.659 | H25: =IF(H$47<>"",H$47,H24)*PREMISSAS!$C$25 -> 96765.659 | I25: =IF(I$47<>"",I$47,I24)*PREMISSAS!$C$25 -> 96765.659 | J25: =IF(J$47<>"",J$47,J24)*PREMISSAS!$C$25 -> 96765.659 | K25: =IF(K$47<>"",K$47,K24)*PREMISSAS!$C$25 -> 96765.659 | ... O25: =IF(O$47<>"",O$47,O24)*PREMISSAS!$C$25 -> 96765.659 | P25: =SUM(C25:O25) -> 1161187.9
B26: (A) RECEBIMENTO BRUTO | C26: 0 | D26: =SUMPRODUCT((AUX!$C$8:$Q$8>=D$6)*(AUX!$C$8:$Q$8<=D$8)*AUX!$C$6:$Q$6) -> 0 | E26: =SUMPRODUCT((AUX!$C$8:$Q$8>=E$6)*(AUX!$C$8:$Q$8<=E$8)*AUX!$C$6:$Q$6) -> 0 | F26: =D25 -> 96765.659 | H26: =SUMPRODUCT((AUX!$C$8:$Q$8>=H$6)*(AUX!$C$8:$Q$8<=H$8)*AUX!$C$6:$Q$6) -> 0 | I26: {=SUMPRODUCT((AUX!$C$8:$Q$8>=I$6)*(AUX!$C$8:$Q$8<=I$8)*AUX!$C$6:$Q$6)} -> 0 | J26: =E25+F25+G25+H25+I25 -> 483828.3 | K26: {=SUMPRODUCT((AUX!$C$8:$Q$8>=K$6)*(AUX!$C$8:$Q$8<=K$8)*AUX!$C$6:$Q$6)} -> 0 | M26: =SUMPRODUCT((AUX!$C$8:$Q$8>=M$6)*(AUX!$C$8:$Q$8<=M$8)*AUX!$C$6:$Q$6) -> 0 | N26: =SUMPRODUCT((AUX!$C$8:$Q$8>=N$6)*(AUX!$C$8:$Q$8<=N$8)*AUX!$C$6:$Q$6) -> 0 | O26: =J25+K25+L25+M25+N25 -> 483828.3 | P26: =SUM(C26:O26) -> 1064422.3
B27: (–) Imposto da nota | C27: =IF(PREMISSAS!$C$48="MEDIÇÃO CHEIA",C26,MAX(0,C26-C28))*PREMISSAS!$C$10 -> 0 | D27: =IF(PREMISSAS!$C$48="MEDIÇÃO CHEIA",D26,MAX(0,D26-D28))*PREMISSAS!$C$10 -> 0 | E27: =IF(PREMISSAS!$C$48="MEDIÇÃO CHEIA",E26,MAX(0,E26-E28))*PREMISSAS!$C$10 -> 0 | F27: =IF(PREMISSAS!$C$48="MEDIÇÃO CHEIA",F26,MAX(0,F26-F28))*PREMISSAS!$C$10 -> 21288.445 | G27: =IF(PREMISSAS!$C$48="MEDIÇÃO CHEIA",G26,MAX(0,G26-G28))*PREMISSAS!$C$10 -> 0 | H27: =IF(PREMISSAS!$C$48="MEDIÇÃO CHEIA",H26,MAX(0,H26-H28))*PREMISSAS!$C$10 -> 0 | I27: =IF(PREMISSAS!$C$48="MEDIÇÃO CHEIA",I26,MAX(0,I26-I28))*PREMISSAS!$C$10 -> 0 | J27: =IF(PREMISSAS!$C$48="MEDIÇÃO CHEIA",J26,MAX(0,J26-J28))*PREMISSAS!$C$10 -> 106442.23 | ... O27: =IF(PREMISSAS!$C$48="MEDIÇÃO CHEIA",O26,MAX(0,O26-O28))*PREMISSAS!$C$10 -> 106442.23 | P27: =SUM(C27:O27) -> 234172.9
B28: (–) Desconto do consórcio (custos que ele banca) | C28: 0 | D28: 0 | E28: 0 | F28: =PREMISSAS!$C$60*PREMISSAS!$C$39+PREMISSAS!$C$58*0.5 -> 138140.74 | G28: 0 | H28: 0 | I28: 0 | J28: =PREMISSAS!$C$60 -> 249561.48 | K28: 0 | L28: 0 | M28: 0 | N28: 0 | O28: =PREMISSAS!$C$60 -> 249561.48 | P28: =SUM(C28:O28) -> 637263.7
B29: (–) Custos pagos pela WCR (indiretos) | C29: 0 | D29: 0 | E29: 0 | F29: 0 | G29: =PREMISSAS!$C$55*PREMISSAS!$C$39 -> 10000 | H29: 0 | I29: 0 | J29: 0 | K29: 0 | L29: =PREMISSAS!$C$55 -> 20000 | M29: 0 | N29: 0 | O29: 0 | P29: =SUM(C29:O29) -> 30000
B30: (–) Outros desembolsos da WCR (edite se houver) | C30: 0 | D30: 0 | E30: 0 | F30: 0 | G30: 0 | H30: 0 | I30: 0 | J30: 0 | K30: 0 | L30: 0 | M30: 0 | N30: 0 | O30: 0 | P30: =SUM(C30:O30) -> 0
B31: (–) Mobilização paga pela WCR | C31: =PREMISSAS!$C$57*0.5 -> 0 | D31: 0 | E31: 0 | F31: 0 | G31: 0 | H31: 0 | I31: 0 | J31: 0 | K31: 0 | L31: 0 | M31: 0 | N31: 0 | O31: 0 | P31: =SUM(C31:O31) -> 0
B32: (B) TOTAL DE DESPESAS | C32: =SUM(C27:C31) -> 0 | D32: =SUM(D27:D31) -> 0 | E32: =SUM(E27:E31) -> 0 | F32: =SUM(F27:F31) -> 159429.19 | G32: =SUM(G27:G31) -> 10000 | H32: =SUM(H27:H31) -> 0 | I32: =SUM(I27:I31) -> 0 | J32: =SUM(J27:J31) -> 356003.71 | ... O32: =SUM(O27:O31) -> 356003.71 | P32: =SUM(C32:O32) -> 901436.6
B33: SALDO DO PERÍODO (A–B) | C33: =C26-C32 -> 0 | D33: =D26-D32 -> 0 | E33: =E26-E32 -> 0 | F33: =F26-F32 -> -62663.526 | G33: =G26-G32 -> -10000 | H33: =H26-H32 -> 0 | I33: =I26-I32 -> 0 | J33: =J26-J32 -> 127824.59 | ... O33: =O26-O32 -> 127824.59 | P33: =SUM(C33:O33) -> 162985.66
B34: SALDO ACUMULADO | C34: =C33 -> 0 | D34: =C34+D33 -> 0 | E34: =D34+E33 -> 0 | F34: =E34+F33 -> -62663.526 | G34: =F34+G33 -> -72663.526 | H34: =G34+H33 -> -72663.526 | I34: =H34+I33 -> -72663.526 | J34: =I34+J33 -> 55161.066 | K34: =J34+K33 -> 55161.066 | ... O34: =N34+O33 -> 162985.66 | P34: =O34 -> 162985.66
B36: GLOBAL — BERTIOGA + SANTOS
B37: (A) RECEBIMENTO BRUTO | C37: =C13+C26 -> 0 | D37: =D13+D26 -> 0 | E37: =E13+E26 -> 0 | F37: =F13+F26 -> 181947.7 | G37: =G13+G26 -> 0 | H37: =H13+H26 -> 0 | I37: =I13+I26 -> 0 | J37: =J13+J26 -> 909738.52 | ... O37: =O13+O26 -> 909738.52 | P37: =SUM(C37:O37) -> 2001424.8
B38: (B) TOTAL DE DESPESAS | C38: =C19+C32 -> 0 | D38: =D19+D32 -> 0 | E38: =E19+E32 -> 0 | F38: =F19+F32 -> 300175.66 | G38: =G19+G32 -> 20000 | H38: =H19+H32 -> 0 | I38: =I19+I32 -> 0 | J38: =J19+J32 -> 666996.8 | ... O38: =O19+O32 -> 666996.8 | P38: =SUM(C38:O38) -> 1694169.2
B39: SALDO DO PERÍODO (A–B) | C39: =C37-C38 -> 0 | D39: =D37-D38 -> 0 | E39: =E37-E38 -> 0 | F39: =F37-F38 -> -118227.95 | G39: =G37-G38 -> -20000 | H39: =H37-H38 -> 0 | I39: =I37-I38 -> 0 | J39: =J37-J38 -> 242741.73 | ... O39: =O37-O38 -> 242741.73 | P39: =SUM(C39:O39) -> 307255.51
B40: SALDO ACUMULADO | C40: =C39 -> 0 | D40: =C40+D39 -> 0 | E40: =D40+E39 -> 0 | F40: =E40+F39 -> -118227.95 | G40: =F40+G39 -> -138227.95 | H40: =G40+H39 -> -138227.95 | I40: =H40+I39 -> -138227.95 | J40: =I40+J39 -> 104513.78 | K40: =J40+K39 -> 104513.78 | ... O40: =N40+O39 -> 307255.51 | P40: =O40 -> 307255.51
B42: PIOR PONTO DO TRIMESTRE (menor saldo acumulado) | C42: =MIN(C40:O40) -> -138227.95 | G42: É o caixa que a obra consome no trimestre antes de o dinheiro do cliente entrar. Capital de giro: ver FCP MENSAL.
B44: PLANEJADO × REALIZADO — lance aqui a PRODUÇÃO REALIZADA de cada semana (células verdes)
B45: BERTIOGA — produção REALIZADA (un) | P45: =SUM(D45:O45) -> 0
B46: BERTIOGA — % do planejado | D46: =IF(D45="","",D45/D11) | E46: =IF(E45="","",E45/E11) | F46: =IF(F45="","",F45/F11) | G46: =IF(G45="","",G45/G11) | H46: =IF(H45="","",H45/H11) | I46: =IF(I45="","",I45/I11) | J46: =IF(J45="","",J45/J11) | K46: =IF(K45="","",K45/K11) | ... O46: =IF(O45="","",O45/O11) | P46: =IF(P45=0,"",P45/SUM(D11:O11))
B47: SANTOS — produção REALIZADA (un) | P47: =SUM(D47:O47) -> 0
B48: SANTOS — % do planejado | D48: =IF(D47="","",D47/D24) | E48: =IF(E47="","",E47/E24) | F48: =IF(F47="","",F47/F24) | G48: =IF(G47="","",G47/G24) | H48: =IF(H47="","",H47/H24) | I48: =IF(I47="","",I47/I24) | J48: =IF(J47="","",J47/J24) | K48: =IF(K47="","",K47/K24) | ... O48: =IF(O47="","",O47/O24) | P48: =IF(P47=0,"",P47/SUM(D24:O24))
B49: GLOBAL — % do planejado (em R$) | D49: =IF(COUNT(D45,D47)=0,"",(D45*PREMISSAS!$C$21+D47*PREMISSAS!$C$25)/(D11*PREMISSAS!$C$21+D24*PREMISSAS!$C$25)) | E49: =IF(COUNT(E45,E47)=0,"",(E45*PREMISSAS!$C$21+E47*PREMISSAS!$C$25)/(E11*PREMISSAS!$C$21+E24*PREMISSAS!$C$25)) | F49: =IF(COUNT(F45,F47)=0,"",(F45*PREMISSAS!$C$21+F47*PREMISSAS!$C$25)/(F11*PREMISSAS!$C$21+F24*PREMISSAS!$C$25)) | G49: =IF(COUNT(G45,G47)=0,"",(G45*PREMISSAS!$C$21+G47*PREMISSAS!$C$25)/(G11*PREMISSAS!$C$21+G24*PREMISSAS!$C$25)) | H49: =IF(COUNT(H45,H47)=0,"",(H45*PREMISSAS!$C$21+H47*PREMISSAS!$C$25)/(H11*PREMISSAS!$C$21+H24*PREMISSAS!$C$25)) | I49: =IF(COUNT(I45,I47)=0,"",(I45*PREMISSAS!$C$21+I47*PREMISSAS!$C$25)/(I11*PREMISSAS!$C$21+I24*PREMISSAS!$C$25)) | J49: =IF(COUNT(J45,J47)=0,"",(J45*PREMISSAS!$C$21+J47*PREMISSAS!$C$25)/(J11*PREMISSAS!$C$21+J24*PREMISSAS!$C$25)) | K49: =IF(COUNT(K45,K47)=0,"",(K45*PREMISSAS!$C$21+K47*PREMISSAS!$C$25)/(K11*PREMISSAS!$C$21+K24*PREMISSAS!$C$25)) | ... O49: =IF(COUNT(O45,O47)=0,"",(O45*PREMISSAS!$C$21+O47*PREMISSAS!$C$25)/(O11*PREMISSAS!$C$21+O24*PREMISSAS!$C$25))
B50: Semana sem lançamento usa o PLANEJADO. Ao preencher, a medição (linhas 12/25), o recebimento, o FCP MENSAL e o ECONÔMICO atualizam sozinhos — agosto, setembro e outubro puxam daqui (S1 · S2–S6 · S7–S11); novembro em diante é projeção.

Sheet FCP MENSAL
B2: FCP MENSAL — FINANCEIRO (CAIXA DA WCR)
B3: Recebimento = medição do mês anterior (defasagem PREMISSAS!C9), menos o desconto do consórcio e o imposto. Desembolso = só o que a WCR paga (indiretos), no mês seguinte à competência. Margem real do contrato: aba ECONÔMICO.
P4: Cenário: | Q4: =PREMISSAS!$C$13 -> ÓTIMA
B5: Mês | C5: =DATE(YEAR(PREMISSAS!$C$6),MONTH(PREMISSAS!$C$6),1) -> 46235 | D5: =EDATE(C5,1) -> 46266 | E5: =EDATE(D5,1) -> 46296 | F5: =EDATE(E5,1) -> 46327 | G5: =EDATE(F5,1) -> 46357 | H5: =EDATE(G5,1) -> 46388 | I5: =EDATE(H5,1) -> 46419 | J5: =EDATE(I5,1) -> 46447 | K5: =EDATE(J5,1) -> 46478 | ... Q5: =EDATE(P5,1) -> 46661 | R5: TOTAL
B6: Dias de obra no mês | C6: =AUX!C4 -> 8 | D6: =AUX!D4 -> 30 | E6: =AUX!E4 -> 31 | F6: =AUX!F4 -> 30 | G6: =AUX!G4 -> 31 | H6: =AUX!H4 -> 31 | I6: =AUX!I4 -> 28 | J6: =AUX!J4 -> 31 | ... Q6: =AUX!Q4 -> 0 | R6: =SUM(C6:Q6) -> 342
B8: BERTIOGA
B9: Medição do mês (ago–out: FCP SEMANAL · depois: projeção) | C9: =AUX!C5 -> 85182.045 | D9: =AUX!D5 -> 425910.23 | E9: =AUX!E5 -> 425910.23 | F9: =AUX!F5 -> 365065.91 | G9: =AUX!G5 -> 377234.77 | H9: =AUX!H5 -> 377234.77 | I9: =AUX!I5 -> 340728.18 | J9: =AUX!J5 -> 377234.77 | ... Q9: =AUX!Q5 -> 0 | R9: =SUM(C9:Q9) -> 4259102.3
B10: Recebimento bruto (medição do mês anterior) | C10: =SUMPRODUCT((AUX!$C$8:$Q$8>=C$5)*(AUX!$C$8:$Q$8<=EOMONTH(C$5,0))*AUX!$C$5:$Q$5) -> 0 | D10: =SUMPRODUCT((AUX!$C$8:$Q$8>=D$5)*(AUX!$C$8:$Q$8<=EOMONTH(D$5,0))*AUX!$C$5:$Q$5) -> 85182.045 | E10: =SUMPRODUCT((AUX!$C$8:$Q$8>=E$5)*(AUX!$C$8:$Q$8<=EOMONTH(E$5,0))*AUX!$C$5:$Q$5) -> 425910.23 | F10: =SUMPRODUCT((AUX!$C$8:$Q$8>=F$5)*(AUX!$C$8:$Q$8<=EOMONTH(F$5,0))*AUX!$C$5:$Q$5) -> 425910.23 | G10: =SUMPRODUCT((AUX!$C$8:$Q$8>=G$5)*(AUX!$C$8:$Q$8<=EOMONTH(G$5,0))*AUX!$C$5:$Q$5) -> 365065.91 | H10: =SUMPRODUCT((AUX!$C$8:$Q$8>=H$5)*(AUX!$C$8:$Q$8<=EOMONTH(H$5,0))*AUX!$C$5:$Q$5) -> 377234.77 | I10: =SUMPRODUCT((AUX!$C$8:$Q$8>=I$5)*(AUX!$C$8:$Q$8<=EOMONTH(I$5,0))*AUX!$C$5:$Q$5) -> 377234.77 | J10: =SUMPRODUCT((AUX!$C$8:$Q$8>=J$5)*(AUX!$C$8:$Q$8<=EOMONTH(J$5,0))*AUX!$C$5:$Q$5) -> 340728.18 | ... Q10: =SUMPRODUCT((AUX!$C$8:$Q$8>=Q$5)*(AUX!$C$8:$Q$8<=EOMONTH(Q$5,0))*AUX!$C$5:$Q$5) -> 0 | R10: =SUM(C10:Q10) -> 4259102.3
B11: (–) Desconto do consórcio (custos bancados) | C11: 0 | D11: =PREMISSAS!$C$59*AUX!C$9/PREMISSAS!$C$8+IF(D$5=EDATE(DATE(YEAR(PREMISSAS!$C$6),MONTH(PREMISSAS!$C$6),1),1),PREMISSAS!$C$58*0.5,0) -> 122006.42 | E11: =PREMISSAS!$C$59*AUX!D$9/PREMISSAS!$C$8+IF(E$5=EDATE(DATE(YEAR(PREMISSAS!$C$6),MONTH(PREMISSAS!$C$6),1),1),PREMISSAS!$C$58*0.5,0) -> 217292.84 | F11: =PREMISSAS!$C$59*AUX!E$9/PREMISSAS!$C$8+IF(F$5=EDATE(DATE(YEAR(PREMISSAS!$C$6),MONTH(PREMISSAS!$C$6),1),1),PREMISSAS!$C$58*0.5,0) -> 224535.93 | G11: =PREMISSAS!$C$59*AUX!F$9/PREMISSAS!$C$8+IF(G$5=EDATE(DATE(YEAR(PREMISSAS!$C$6),MONTH(PREMISSAS!$C$6),1),1),PREMISSAS!$C$58*0.5,0) -> 217292.84 | H11: =PREMISSAS!$C$59*AUX!G$9/PREMISSAS!$C$8+IF(H$5=EDATE(DATE(YEAR(PREMISSAS!$C$6),MONTH(PREMISSAS!$C$6),1),1),PREMISSAS!$C$58*0.5,0) -> 224535.93 | I11: =PREMISSAS!$C$59*AUX!H$9/PREMISSAS!$C$8+IF(I$5=EDATE(DATE(YEAR(PREMISSAS!$C$6),MONTH(PREMISSAS!$C$6),1),1),PREMISSAS!$C$58*0.5,0) -> 224535.93 | J11: =PREMISSAS!$C$59*AUX!I$9/PREMISSAS!$C$8+IF(J$5=EDATE(DATE(YEAR(PREMISSAS!$C$6),MONTH(PREMISSAS!$C$6),1),1),PREMISSAS!$C$58*0.5,0) -> 202806.65 | K11: =PREMISSAS!$C$59*AUX!J$9/PREMISSAS!$C$8+IF(K$5=EDATE(DATE(YEAR(PREMISSAS!$C$6),MONTH(PREMISSAS!$C$6),1),1),PREMISSAS!$C$58*0.5,0) -> 224535.93 | ... Q11: =PREMISSAS!$C$59*AUX!P$9/PREMISSAS!$C$8+IF(Q$5=EDATE(DATE(YEAR(PREMISSAS!$C$6),MONTH(PREMISSAS!$C$6),1),1),PREMISSAS!$C$58*0.5,0) -> 0 | R11: =SUM(C11:Q11) -> 2541200
B12: (–) Imposto da nota | C12: =IF(PREMISSAS!$C$48="MEDIÇÃO CHEIA",C10,MAX(0,C10-C11))*PREMISSAS!$C$10 -> 0 | D12: =IF(PREMISSAS!$C$48="MEDIÇÃO CHEIA",D10,MAX(0,D10-D11))*PREMISSAS!$C$10 -> 18740.05 | E12: =IF(PREMISSAS!$C$48="MEDIÇÃO CHEIA",E10,MAX(0,E10-E11))*PREMISSAS!$C$10 -> 93700.25 | F12: =IF(PREMISSAS!$C$48="MEDIÇÃO CHEIA",F10,MAX(0,F10-F11))*PREMISSAS!$C$10 -> 93700.25 | G12: =IF(PREMISSAS!$C$48="MEDIÇÃO CHEIA",G10,MAX(0,G10-G11))*PREMISSAS!$C$10 -> 80314.5 | H12: =IF(PREMISSAS!$C$48="MEDIÇÃO CHEIA",H10,MAX(0,H10-H11))*PREMISSAS!$C$10 -> 82991.65 | I12: =IF(PREMISSAS!$C$48="MEDIÇÃO CHEIA",I10,MAX(0,I10-I11))*PREMISSAS!$C$10 -> 82991.65 | J12: =IF(PREMISSAS!$C$48="MEDIÇÃO CHEIA",J10,MAX(0,J10-J11))*PREMISSAS!$C$10 -> 74960.2 | ... Q12: =IF(PREMISSAS!$C$48="MEDIÇÃO CHEIA",Q10,MAX(0,Q10-Q11))*PREMISSAS!$C$10 -> 0 | R12: =SUM(C12:Q12) -> 937002.5
B13: ENTRA NO CAIXA DA WCR | C13: =C10-C11-C12 -> 0 | D13: =D10-D11-D12 -> -55564.425 | E13: =E10-E11-E12 -> 114917.14 | F13: =F10-F11-F12 -> 107674.04 | G13: =G10-G11-G12 -> 67458.568 | H13: =H10-H11-H12 -> 69707.187 | I13: =I10-I11-I12 -> 69707.187 | J13: =J10-J11-J12 -> 62961.33 | ... Q13: =Q10-Q11-Q12 -> 0 | R13: =SUM(C13:Q13) -> 780899.72
B14: (–) Sai do caixa da WCR (indiretos do mês ant.) | C14: =IF(C$5=DATE(YEAR(PREMISSAS!$C$6),MONTH(PREMISSAS!$C$6),1),PREMISSAS!$C$57*0.5,0) -> 0 | D14: =PREMISSAS!$C$54*AUX!C$9/PREMISSAS!$C$8 -> 10000 | E14: =PREMISSAS!$C$54*AUX!D$9/PREMISSAS!$C$8 -> 20000 | F14: =PREMISSAS!$C$54*AUX!E$9/PREMISSAS!$C$8 -> 20666.667 | G14: =PREMISSAS!$C$54*AUX!F$9/PREMISSAS!$C$8 -> 20000 | H14: =PREMISSAS!$C$54*AUX!G$9/PREMISSAS!$C$8 -> 20666.667 | I14: =PREMISSAS!$C$54*AUX!H$9/PREMISSAS!$C$8 -> 20666.667 | J14: =PREMISSAS!$C$54*AUX!I$9/PREMISSAS!$C$8 -> 18666.667 | K14: =PREMISSAS!$C$54*AUX!J$9/PREMISSAS!$C$8 -> 20666.667 | ... Q14: =PREMISSAS!$C$54*AUX!P$9/PREMISSAS!$C$8 -> 0 | R14: =SUM(C14:Q14) -> 232666.67
B15: Saldo do mês | C15: =C13-C14 -> 0 | D15: =D13-D14 -> -65564.425 | E15: =E13-E14 -> 94917.136 | F15: =F13-F14 -> 87007.375 | G15: =G13-G14 -> 47458.568 | H15: =H13-H14 -> 49040.52 | I15: =I13-I14 -> 49040.52 | J15: =J13-J14 -> 44294.663 | ... Q15: =Q13-Q14 -> 0 | R15: =SUM(C15:Q15) -> 548233.05
B16: CAIXA ACUMULADO — antes do recebimento | C16: =-C14 -> 0 | D16: =C17-D14 -> -10000 | E16: =D17-E14 -> -85564.425 | F16: =E17-F14 -> 8686.0445 | G16: =F17-G14 -> 96360.086 | H16: =G17-H14 -> 143151.99 | I16: =H17-I14 -> 192192.51 | J16: =I17-J14 -> 243233.03 | K16: =J17-K14 -> 285527.69 | ... Q16: =P17-Q14 -> 548233.05 | R16: =MIN(C16:Q16) -> -85564.425
B17: CAIXA ACUMULADO — após o recebimento | C17: =C16+C13 -> 0 | D17: =D16+D13 -> -65564.425 | E17: =E16+E13 -> 29352.711 | F17: =F16+F13 -> 116360.09 | G17: =G16+G13 -> 163818.65 | H17: =H16+H13 -> 212859.17 | I17: =I16+I13 -> 261899.69 | J17: =J16+J13 -> 306194.36 | ... Q17: =Q16+Q13 -> 548233.05 | R17: =Q17 -> 548233.05
B19: SANTOS
B20: Medição do mês (ago–out: FCP SEMANAL · depois: projeção) | C20: =AUX!C6 -> 96765.659 | D20: =AUX!D6 -> 483828.3 | E20: =AUX!E6 -> 483828.3 | F20: =AUX!F6 -> 414709.97 | G20: =AUX!G6 -> 428533.63 | H20: =AUX!H6 -> 428533.63 | I20: =AUX!I6 -> 387062.64 | J20: =AUX!J6 -> 428533.63 | ... Q20: =AUX!Q6 -> 0 | R20: =SUM(C20:Q20) -> 4838283
B21: Recebimento bruto (medição do mês anterior) | C21: =SUMPRODUCT((AUX!$C$8:$Q$8>=C$5)*(AUX!$C$8:$Q$8<=EOMONTH(C$5,0))*AUX!$C$6:$Q$6) -> 0 | D21: =SUMPRODUCT((AUX!$C$8:$Q$8>=D$5)*(AUX!$C$8:$Q$8<=EOMONTH(D$5,0))*AUX!$C$6:$Q$6) -> 96765.659 | E21: =SUMPRODUCT((AUX!$C$8:$Q$8>=E$5)*(AUX!$C$8:$Q$8<=EOMONTH(E$5,0))*AUX!$C$6:$Q$6) -> 483828.3 | F21: =SUMPRODUCT((AUX!$C$8:$Q$8>=F$5)*(AUX!$C$8:$Q$8<=EOMONTH(F$5,0))*AUX!$C$6:$Q$6) -> 483828.3 | G21: =SUMPRODUCT((AUX!$C$8:$Q$8>=G$5)*(AUX!$C$8:$Q$8<=EOMONTH(G$5,0))*AUX!$C$6:$Q$6) -> 414709.97 | H21: =SUMPRODUCT((AUX!$C$8:$Q$8>=H$5)*(AUX!$C$8:$Q$8<=EOMONTH(H$5,0))*AUX!$C$6:$Q$6) -> 428533.63 | I21: =SUMPRODUCT((AUX!$C$8:$Q$8>=I$5)*(AUX!$C$8:$Q$8<=EOMONTH(I$5,0))*AUX!$C$6:$Q$6) -> 428533.63 | J21: =SUMPRODUCT((AUX!$C$8:$Q$8>=J$5)*(AUX!$C$8:$Q$8<=EOMONTH(J$5,0))*AUX!$C$6:$Q$6) -> 387062.64 | ... Q21: =SUMPRODUCT((AUX!$C$8:$Q$8>=Q$5)*(AUX!$C$8:$Q$8<=EOMONTH(Q$5,0))*AUX!$C$6:$Q$6) -> 0 | R21: =SUM(C21:Q21) -> 4838283
B22: (–) Desconto do consórcio (custos bancados) | C22: 0 | D22: =PREMISSAS!$C$60*AUX!C$9/PREMISSAS!$C$8+IF(D$5=EDATE(DATE(YEAR(PREMISSAS!$C$6),MONTH(PREMISSAS!$C$6),1),1),PREMISSAS!$C$58*0.5,0) -> 138140.74 | E22: =PREMISSAS!$C$60*AUX!D$9/PREMISSAS!$C$8+IF(E$5=EDATE(DATE(YEAR(PREMISSAS!$C$6),MONTH(PREMISSAS!$C$6),1),1),PREMISSAS!$C$58*0.5,0) -> 249561.48 | F22: =PREMISSAS!$C$60*AUX!E$9/PREMISSAS!$C$8+IF(F$5=EDATE(DATE(YEAR(PREMISSAS!$C$6),MONTH(PREMISSAS!$C$6),1),1),PREMISSAS!$C$58*0.5,0) -> 257880.2 | G22: =PREMISSAS!$C$60*AUX!F$9/PREMISSAS!$C$8+IF(G$5=EDATE(DATE(YEAR(PREMISSAS!$C$6),MONTH(PREMISSAS!$C$6),1),1),PREMISSAS!$C$58*0.5,0) -> 249561.48 | H22: =PREMISSAS!$C$60*AUX!G$9/PREMISSAS!$C$8+IF(H$5=EDATE(DATE(YEAR(PREMISSAS!$C$6),MONTH(PREMISSAS!$C$6),1),1),PREMISSAS!$C$58*0.5,0) -> 257880.2 | I22: =PREMISSAS!$C$60*AUX!H$9/PREMISSAS!$C$8+IF(I$5=EDATE(DATE(YEAR(PREMISSAS!$C$6),MONTH(PREMISSAS!$C$6),1),1),PREMISSAS!$C$58*0.5,0) -> 257880.2 | J22: =PREMISSAS!$C$60*AUX!I$9/PREMISSAS!$C$8+IF(J$5=EDATE(DATE(YEAR(PREMISSAS!$C$6),MONTH(PREMISSAS!$C$6),1),1),PREMISSAS!$C$58*0.5,0) -> 232924.05 | K22: =PREMISSAS!$C$60*AUX!J$9/PREMISSAS!$C$8+IF(K$5=EDATE(DATE(YEAR(PREMISSAS!$C$6),MONTH(PREMISSAS!$C$6),1),1),PREMISSAS!$C$58*0.5,0) -> 257880.2 | ... Q22: =PREMISSAS!$C$60*AUX!P$9/PREMISSAS!$C$8+IF(Q$5=EDATE(DATE(YEAR(PREMISSAS!$C$6),MONTH(PREMISSAS!$C$6),1),1),PREMISSAS!$C$58*0.5,0) -> 0 | R22: =SUM(C22:Q22) -> 2916591.9
B23: (–) Imposto da nota | C23: =IF(PREMISSAS!$C$48="MEDIÇÃO CHEIA",C21,MAX(0,C21-C22))*PREMISSAS!$C$10 -> 0 | D23: =IF(PREMISSAS!$C$48="MEDIÇÃO CHEIA",D21,MAX(0,D21-D22))*PREMISSAS!$C$10 -> 21288.445 | E23: =IF(PREMISSAS!$C$48="MEDIÇÃO CHEIA",E21,MAX(0,E21-E22))*PREMISSAS!$C$10 -> 106442.23 | F23: =IF(PREMISSAS!$C$48="MEDIÇÃO CHEIA",F21,MAX(0,F21-F22))*PREMISSAS!$C$10 -> 106442.23 | G23: =IF(PREMISSAS!$C$48="MEDIÇÃO CHEIA",G21,MAX(0,G21-G22))*PREMISSAS!$C$10 -> 91236.193 | H23: =IF(PREMISSAS!$C$48="MEDIÇÃO CHEIA",H21,MAX(0,H21-H22))*PREMISSAS!$C$10 -> 94277.4 | I23: =IF(PREMISSAS!$C$48="MEDIÇÃO CHEIA",I21,MAX(0,I21-I22))*PREMISSAS!$C$10 -> 94277.4 | J23: =IF(PREMISSAS!$C$48="MEDIÇÃO CHEIA",J21,MAX(0,J21-J22))*PREMISSAS!$C$10 -> 85153.78 | ... Q23: =IF(PREMISSAS!$C$48="MEDIÇÃO CHEIA",Q21,MAX(0,Q21-Q22))*PREMISSAS!$C$10 -> 0 | R23: =SUM(C23:Q23) -> 1064422.3
B24: ENTRA NO CAIXA DA WCR | C24: =C21-C22-C23 -> 0 | D24: =D21-D22-D23 -> -62663.526 | E24: =E21-E22-E23 -> 127824.59 | F24: =F21-F22-F23 -> 119505.88 | G24: =G21-G22-G23 -> 73912.296 | H24: =H21-H22-H23 -> 76376.039 | I24: =I21-I22-I23 -> 76376.039 | J24: =J21-J22-J23 -> 68984.81 | ... Q24: =Q21-Q22-Q23 -> 0 | R24: =SUM(C24:Q24) -> 857268.84
B25: (–) Sai do caixa da WCR (indiretos do mês ant.) | C25: =IF(C$5=DATE(YEAR(PREMISSAS!$C$6),MONTH(PREMISSAS!$C$6),1),PREMISSAS!$C$57*0.5,0) -> 0 | D25: =PREMISSAS!$C$55*AUX!C$9/PREMISSAS!$C$8 -> 10000 | E25: =PREMISSAS!$C$55*AUX!D$9/PREMISSAS!$C$8 -> 20000 | F25: =PREMISSAS!$C$55*AUX!E$9/PREMISSAS!$C$8 -> 20666.667 | G25: =PREMISSAS!$C$55*AUX!F$9/PREMISSAS!$C$8 -> 20000 | H25: =PREMISSAS!$C$55*AUX!G$9/PREMISSAS!$C$8 -> 20666.667 | I25: =PREMISSAS!$C$55*AUX!H$9/PREMISSAS!$C$8 -> 20666.667 | J25: =PREMISSAS!$C$55*AUX!I$9/PREMISSAS!$C$8 -> 18666.667 | K25: =PREMISSAS!$C$55*AUX!J$9/PREMISSAS!$C$8 -> 20666.667 | ... Q25: =PREMISSAS!$C$55*AUX!P$9/PREMISSAS!$C$8 -> 0 | R25: =SUM(C25:Q25) -> 232666.67
B26: Saldo do mês | C26: =C24-C25 -> 0 | D26: =D24-D25 -> -72663.526 | E26: =E24-E25 -> 107824.59 | F26: =F24-F25 -> 98839.209 | G26: =G24-G25 -> 53912.296 | H26: =H24-H25 -> 55709.373 | I26: =I24-I25 -> 55709.373 | J26: =J24-J25 -> 50318.143 | ... Q26: =Q24-Q25 -> 0 | R26: =SUM(C26:Q26) -> 624602.17
B27: CAIXA ACUMULADO — antes do recebimento | C27: =-C25 -> 0 | D27: =C28-D25 -> -10000 | E27: =D28-E25 -> -92663.526 | F27: =E28-F25 -> 14494.4 | G27: =F28-G25 -> 114000.28 | H27: =G28-H25 -> 167245.91 | I27: =H28-I25 -> 222955.28 | J27: =I28-J25 -> 280664.65 | K27: =J28-K25 -> 328982.79 | ... Q27: =P28-Q25 -> 624602.17 | R27: =MIN(C27:Q27) -> -92663.526
B28: CAIXA ACUMULADO — após o recebimento | C28: =C27+C24 -> 0 | D28: =D27+D24 -> -72663.526 | E28: =E27+E24 -> 35161.066 | F28: =F27+F24 -> 134000.28 | G28: =G27+G24 -> 187912.57 | H28: =H27+H24 -> 243621.94 | I28: =I27+I24 -> 299331.32 | J28: =J27+J24 -> 349649.46 | ... Q28: =Q27+Q24 -> 624602.17 | R28: =Q28 -> 624602.17
B30: GLOBAL — BERTIOGA + SANTOS
B31: Medição bruta (ago–out: FCP SEMANAL · depois: projeção) | C31: =C9+C20 -> 181947.7 | D31: =D9+D20 -> 909738.52 | E31: =E9+E20 -> 909738.52 | F31: =F9+F20 -> 779775.88 | G31: =G9+G20 -> 805768.41 | H31: =H9+H20 -> 805768.41 | I31: =I9+I20 -> 727790.82 | J31: =J9+J20 -> 805768.41 | ... Q31: =Q9+Q20 -> 0 | R31: =SUM(C31:Q31) -> 9097385.2
B32: Recebimento bruto | C32: =C10+C21 -> 0 | D32: =D10+D21 -> 181947.7 | E32: =E10+E21 -> 909738.52 | F32: =F10+F21 -> 909738.52 | G32: =G10+G21 -> 779775.88 | H32: =H10+H21 -> 805768.41 | I32: =I10+I21 -> 805768.41 | J32: =J10+J21 -> 727790.82 | ... Q32: =Q10+Q21 -> 0 | R32: =SUM(C32:Q32) -> 9097385.2
B33: (–) Desconto do consórcio | C33: =C11+C22 -> 0 | D33: =D11+D22 -> 260147.16 | E33: =E11+E22 -> 466854.32 | F33: =F11+F22 -> 482416.13 | G33: =G11+G22 -> 466854.32 | H33: =H11+H22 -> 482416.13 | I33: =I11+I22 -> 482416.13 | J33: =J11+J22 -> 435730.7 | ... Q33: =Q11+Q22 -> 0 | R33: =SUM(C33:Q33) -> 5457791.9
B34: (–) Imposto da nota | C34: =C12+C23 -> 0 | D34: =D12+D23 -> 40028.495 | E34: =E12+E23 -> 200142.48 | F34: =F12+F23 -> 200142.48 | G34: =G12+G23 -> 171550.69 | H34: =H12+H23 -> 177269.05 | I34: =I12+I23 -> 177269.05 | J34: =J12+J23 -> 160113.98 | ... Q34: =Q12+Q23 -> 0 | R34: =SUM(C34:Q34) -> 2001424.8
B35: ENTRA NO CAIXA DA WCR | C35: =C13+C24 -> 0 | D35: =D13+D24 -> -118227.95 | E35: =E13+E24 -> 242741.73 | F35: =F13+F24 -> 227179.92 | G35: =G13+G24 -> 141370.86 | H35: =H13+H24 -> 146083.23 | I35: =I13+I24 -> 146083.23 | J35: =J13+J24 -> 131946.14 | ... Q35: =Q13+Q24 -> 0 | R35: =SUM(C35:Q35) -> 1638168.6
B36: (–) Sai do caixa da WCR | C36: =C14+C25 -> 0 | D36: =D14+D25 -> 20000 | E36: =E14+E25 -> 40000 | F36: =F14+F25 -> 41333.333 | G36: =G14+G25 -> 40000 | H36: =H14+H25 -> 41333.333 | I36: =I14+I25 -> 41333.333 | J36: =J14+J25 -> 37333.333 | ... Q36: =Q14+Q25 -> 0 | R36: =SUM(C36:Q36) -> 465333.33
B37: Saldo do mês | C37: =C35-C36 -> 0 | D37: =D35-D36 -> -138227.95 | E37: =E35-E36 -> 202741.73 | F37: =F35-F36 -> 185846.58 | G37: =G35-G36 -> 101370.86 | H37: =H35-H36 -> 104749.89 | I37: =I35-I36 -> 104749.89 | J37: =J35-J36 -> 94612.806 | ... Q37: =Q35-Q36 -> 0 | R37: =SUM(C37:Q37) -> 1172835.2
B38: CAIXA ACUMULADO — antes do recebimento | C38: =-C36 -> 0 | D38: =C39-D36 -> -20000 | E38: =D39-E36 -> -178227.95 | F38: =E39-F36 -> 23180.444 | G38: =F39-G36 -> 210360.36 | H38: =G39-H36 -> 310397.89 | I38: =H39-I36 -> 415147.79 | J38: =I39-J36 -> 523897.68 | K38: =J39-K36 -> 614510.48 | ... Q38: =P39-Q36 -> 1172835.2 | R38: =MIN(C38:Q38) -> -178227.95
B39: CAIXA ACUMULADO — após o recebimento | C39: =C38+C35 -> 0 | D39: =D38+D35 -> -138227.95 | E39: =E38+E35 -> 64513.778 | F39: =F38+F35 -> 250360.36 | G39: =G38+G35 -> 351731.23 | H39: =H38+H35 -> 456481.12 | I39: =I38+I35 -> 561231.01 | J39: =J38+J35 -> 655843.82 | ... Q39: =Q38+Q35 -> 1172835.2 | R39: =Q39 -> 1172835.2
B41: CAPITAL NECESSÁRIO E RESULTADO DE CAIXA — cenário adotado
B42: Necessidade máxima de caixa da WCR (pior ponto) | C42: =MAX(0,-MIN(C38:Q38)) -> 178227.95 | F42: Com o consórcio bancando folha, engenheiro e estrutura, a WCR só financia os indiretos e o descasamento do 1º mês. No começo o desconto pode ser maior que a medição parcial (agosto): o líquido fica negativo — é saldo devido ao consórcio, compensa no mês seguinte.
B43: Contingência (premissa) | C43: =C42*PREMISSAS!$C$38 -> 26734.193
B44: CAPITAL RECOMENDADO — WCR | C44: =C42+C43 -> 204962.14
B45: Resultado de caixa no fim do horizonte | C45: =Q39 -> 1172835.2
B46: Confere com o resultado ECONÔMICO acumulado | C46: =ECONÔMICO!Q18 -> 1172835.2 | F46: Os dois fecham no mesmo número — a diferença entre econômico e financeiro é só o caminho (quem banca e quando).
B48: SENSIBILIDADE — caixa da WCR por cenário
B49: CENÁRIO | C49: MARGEM | D49: ENTRA/MÊS (cheio) | E49: NECESSIDADE MÁX. | F49: CAPITAL RECOM. | G49: RESULTADO FINAL
B50: MÍNIMA | C50: =PREMISSAS!C14 -> 0 | D50: =PREMISSAS!$C$30*(1+C50)/(1-PREMISSAS!$C$10)*(1-IF(PREMISSAS!$C$48="MEDIÇÃO CHEIA",PREMISSAS!$C$10,0))-PREMISSAS!$C$61-IF(PREMISSAS!$C$48="LÍQUIDA DO DESCONTO",(PREMISSAS!$C$30*(1+C50)/(1-PREMISSAS!$C$10)-PREMISSAS!$C$61)*PREMISSAS!$C$10,0) -> 40000 | E50: =AUX!S14 -> 186319.34 | F50: =E50*(1+PREMISSAS!$C$38) -> 214267.24 | G50: =AUX!S15 -> -144986.01 | H50: =IF(B50=PREMISSAS!$C$13,"◀ adotado","")
B51: MÉDIA | C51: =PREMISSAS!C15 -> 0.1 | D51: =PREMISSAS!$C$30*(1+C51)/(1-PREMISSAS!$C$10)*(1-IF(PREMISSAS!$C$48="MEDIÇÃO CHEIA",PREMISSAS!$C$10,0))-PREMISSAS!$C$61-IF(PREMISSAS!$C$48="LÍQUIDA DO DESCONTO",(PREMISSAS!$C$30*(1+C51)/(1-PREMISSAS!$C$10)-PREMISSAS!$C$61)*PREMISSAS!$C$10,0) -> 90685.432 | E51: =AUX!S20 -> 171469.89 | F51: =E51*(1+PREMISSAS!$C$38) -> 197190.38 | G51: =AUX!S21 -> 432827.92 | H51: =IF(B51=PREMISSAS!$C$13,"◀ adotado","")
B52: BOA | C52: =PREMISSAS!C16 -> 0.15 | D52: =PREMISSAS!$C$30*(1+C52)/(1-PREMISSAS!$C$10)*(1-IF(PREMISSAS!$C$48="MEDIÇÃO CHEIA",PREMISSAS!$C$10,0))-PREMISSAS!$C$61-IF(PREMISSAS!$C$48="LÍQUIDA DO DESCONTO",(PREMISSAS!$C$30*(1+C52)/(1-PREMISSAS!$C$10)-PREMISSAS!$C$61)*PREMISSAS!$C$10,0) -> 116028.15 | E52: =AUX!S26 -> 164711.84 | F52: =E52*(1+PREMISSAS!$C$38) -> 189418.61 | G52: =AUX!S27 -> 721734.88 | H52: =IF(B52=PREMISSAS!$C$13,"◀ adotado","")
B53: ÓTIMA | C53: =PREMISSAS!C17 -> 0.2 | D53: =PREMISSAS!$C$30*(1+C53)/(1-PREMISSAS!$C$10)*(1-IF(PREMISSAS!$C$48="MEDIÇÃO CHEIA",PREMISSAS!$C$10,0))-PREMISSAS!$C$61-IF(PREMISSAS!$C$48="LÍQUIDA DO DESCONTO",(PREMISSAS!$C$30*(1+C53)/(1-PREMISSAS!$C$10)-PREMISSAS!$C$61)*PREMISSAS!$C$10,0) -> 141370.86 | E53: =AUX!S32 -> 157953.78 | F53: =E53*(1+PREMISSAS!$C$38) -> 181646.84 | G53: =AUX!S33 -> 1010641.8 | H53: =IF(B53=PREMISSAS!$C$13,"◀ adotado","") -> ◀ adotado
B55: Caixa da WCR: como quase todo o custo é bancado pelo consórcio e descontado, o capital necessário fica pequeno em todos os cenários. Na MÍNIMA o que entra empata com os indiretos e o resultado final fica negativo no descasamento do 1º mês.

Sheet ECONÔMICO
B2: ECONÔMICO — RESULTADO DO CONTRATO (COMPETÊNCIA)
B3: A margem real da operação, mês a mês, com TODOS os custos — inclusive os que o consórcio banca. Estilo do DRE Se Liga na Rede. O caixa da WCR está no FCP MENSAL / FCP SEMANAL.
P4: Cenário: | Q4: =PREMISSAS!$C$13 -> ÓTIMA
B5: Mês | C5: =DATE(YEAR(PREMISSAS!$C$6),MONTH(PREMISSAS!$C$6),1) -> 46235 | D5: =EDATE(C5,1) -> 46266 | E5: =EDATE(D5,1) -> 46296 | F5: =EDATE(E5,1) -> 46327 | G5: =EDATE(F5,1) -> 46357 | H5: =EDATE(G5,1) -> 46388 | I5: =EDATE(H5,1) -> 46419 | J5: =EDATE(I5,1) -> 46447 | K5: =EDATE(J5,1) -> 46478 | ... Q5: =EDATE(P5,1) -> 46661 | R5: TOTAL
B6: Dias de obra no mês | C6: =AUX!C4 -> 8 | D6: =AUX!D4 -> 30 | E6: =AUX!E4 -> 31 | F6: =AUX!F4 -> 30 | G6: =AUX!G4 -> 31 | H6: =AUX!H4 -> 31 | I6: =AUX!I4 -> 28 | J6: =AUX!J4 -> 31 | ... Q6: =AUX!Q4 -> 0 | R6: =SUM(C6:Q6) -> 342
B9: Medição bruta (ago–out: FCP SEMANAL · depois: projeção) | C9: =AUX!C7 -> 181947.7 | D9: =AUX!D7 -> 909738.52 | E9: =AUX!E7 -> 909738.52 | F9: =AUX!F7 -> 779775.88 | G9: =AUX!G7 -> 805768.41 | H9: =AUX!H7 -> 805768.41 | I9: =AUX!I7 -> 727790.82 | J9: =AUX!J7 -> 805768.41 | ... Q9: =AUX!Q7 -> 0 | R9: =SUM(C9:Q9) -> 9097385.2
B10: (–) Imposto da nota | C10: =IF(PREMISSAS!$C$48="MEDIÇÃO CHEIA",C9,MAX(0,C9-PREMISSAS!$C$61*AUX!C$9/PREMISSAS!$C$8))*PREMISSAS!$C$10 -> 40028.495 | D10: =IF(PREMISSAS!$C$48="MEDIÇÃO CHEIA",D9,MAX(0,D9-PREMISSAS!$C$61*AUX!D$9/PREMISSAS!$C$8))*PREMISSAS!$C$10 -> 200142.48 | E10: =IF(PREMISSAS!$C$48="MEDIÇÃO CHEIA",E9,MAX(0,E9-PREMISSAS!$C$61*AUX!E$9/PREMISSAS!$C$8))*PREMISSAS!$C$10 -> 200142.48 | F10: =IF(PREMISSAS!$C$48="MEDIÇÃO CHEIA",F9,MAX(0,F9-PREMISSAS!$C$61*AUX!F$9/PREMISSAS!$C$8))*PREMISSAS!$C$10 -> 171550.69 | G10: =IF(PREMISSAS!$C$48="MEDIÇÃO CHEIA",G9,MAX(0,G9-PREMISSAS!$C$61*AUX!G$9/PREMISSAS!$C$8))*PREMISSAS!$C$10 -> 177269.05 | H10: =IF(PREMISSAS!$C$48="MEDIÇÃO CHEIA",H9,MAX(0,H9-PREMISSAS!$C$61*AUX!H$9/PREMISSAS!$C$8))*PREMISSAS!$C$10 -> 177269.05 | I10: =IF(PREMISSAS!$C$48="MEDIÇÃO CHEIA",I9,MAX(0,I9-PREMISSAS!$C$61*AUX!I$9/PREMISSAS!$C$8))*PREMISSAS!$C$10 -> 160113.98 | J10: =IF(PREMISSAS!$C$48="MEDIÇÃO CHEIA",J9,MAX(0,J9-PREMISSAS!$C$61*AUX!J$9/PREMISSAS!$C$8))*PREMISSAS!$C$10 -> 177269.05 | ... Q10: =IF(PREMISSAS!$C$48="MEDIÇÃO CHEIA",Q9,MAX(0,Q9-PREMISSAS!$C$61*AUX!Q$9/PREMISSAS!$C$8))*PREMISSAS!$C$10 -> 0 | R10: =SUM(C10:Q10) -> 2001424.8
B11: (=) Medição líquida de imposto | C11: =C9-C10 -> 141919.21 | D11: =D9-D10 -> 709596.05 | E11: =E9-E10 -> 709596.05 | F11: =F9-F10 -> 608225.18 | G11: =G9-G10 -> 628499.36 | H11: =H9-H10 -> 628499.36 | I11: =I9-I10 -> 567676.84 | J11: =J9-J10 -> 628499.36 | ... Q11: =Q9-Q10 -> 0 | R11: =SUM(C11:Q11) -> 7095960.5
B12: (–) Folha das equipes | C12: =('CUSTOS BERTIOGA'!$H$22+'CUSTOS SANTOS'!$H$23)*AUX!C$9/PREMISSAS!$C$8 -> 113377.16 | D12: =('CUSTOS BERTIOGA'!$H$22+'CUSTOS SANTOS'!$H$23)*AUX!D$9/PREMISSAS!$C$8 -> 226754.32 | E12: =('CUSTOS BERTIOGA'!$H$22+'CUSTOS SANTOS'!$H$23)*AUX!E$9/PREMISSAS!$C$8 -> 234312.8 | F12: =('CUSTOS BERTIOGA'!$H$22+'CUSTOS SANTOS'!$H$23)*AUX!F$9/PREMISSAS!$C$8 -> 226754.32 | G12: =('CUSTOS BERTIOGA'!$H$22+'CUSTOS SANTOS'!$H$23)*AUX!G$9/PREMISSAS!$C$8 -> 234312.8 | H12: =('CUSTOS BERTIOGA'!$H$22+'CUSTOS SANTOS'!$H$23)*AUX!H$9/PREMISSAS!$C$8 -> 234312.8 | I12: =('CUSTOS BERTIOGA'!$H$22+'CUSTOS SANTOS'!$H$23)*AUX!I$9/PREMISSAS!$C$8 -> 211637.37 | J12: =('CUSTOS BERTIOGA'!$H$22+'CUSTOS SANTOS'!$H$23)*AUX!J$9/PREMISSAS!$C$8 -> 234312.8 | ... Q12: =('CUSTOS BERTIOGA'!$H$22+'CUSTOS SANTOS'!$H$23)*AUX!Q$9/PREMISSAS!$C$8 -> 0 | R12: =SUM(C12:Q12) -> 2637908.6
B13: (–) Engenheiro | C13: =('CUSTOS BERTIOGA'!$F$26+'CUSTOS SANTOS'!$F$27)*AUX!C$9/PREMISSAS!$C$8 -> 13000 | D13: =('CUSTOS BERTIOGA'!$F$26+'CUSTOS SANTOS'!$F$27)*AUX!D$9/PREMISSAS!$C$8 -> 26000 | E13: =('CUSTOS BERTIOGA'!$F$26+'CUSTOS SANTOS'!$F$27)*AUX!E$9/PREMISSAS!$C$8 -> 26866.667 | F13: =('CUSTOS BERTIOGA'!$F$26+'CUSTOS SANTOS'!$F$27)*AUX!F$9/PREMISSAS!$C$8 -> 26000 | G13: =('CUSTOS BERTIOGA'!$F$26+'CUSTOS SANTOS'!$F$27)*AUX!G$9/PREMISSAS!$C$8 -> 26866.667 | H13: =('CUSTOS BERTIOGA'!$F$26+'CUSTOS SANTOS'!$F$27)*AUX!H$9/PREMISSAS!$C$8 -> 26866.667 | I13: =('CUSTOS BERTIOGA'!$F$26+'CUSTOS SANTOS'!$F$27)*AUX!I$9/PREMISSAS!$C$8 -> 24266.667 | J13: =('CUSTOS BERTIOGA'!$F$26+'CUSTOS SANTOS'!$F$27)*AUX!J$9/PREMISSAS!$C$8 -> 26866.667 | ... Q13: =('CUSTOS BERTIOGA'!$F$26+'CUSTOS SANTOS'!$F$27)*AUX!Q$9/PREMISSAS!$C$8 -> 0 | R13: =SUM(C13:Q13) -> 302466.67
B14: (–) Estrutura e locações | C14: =(PREMISSAS!$C$30-'CUSTOS BERTIOGA'!$H$22-'CUSTOS SANTOS'!$H$23-'CUSTOS BERTIOGA'!$F$26-'CUSTOS SANTOS'!$F$27-'CUSTOS BERTIOGA'!$F$34-'CUSTOS SANTOS'!$F$35)*AUX!C$9/PREMISSAS!$C$8 -> 107050 | D14: =(PREMISSAS!$C$30-'CUSTOS BERTIOGA'!$H$22-'CUSTOS SANTOS'!$H$23-'CUSTOS BERTIOGA'!$F$26-'CUSTOS SANTOS'!$F$27-'CUSTOS BERTIOGA'!$F$34-'CUSTOS SANTOS'!$F$35)*AUX!D$9/PREMISSAS!$C$8 -> 214100 | E14: =(PREMISSAS!$C$30-'CUSTOS BERTIOGA'!$H$22-'CUSTOS SANTOS'!$H$23-'CUSTOS BERTIOGA'!$F$26-'CUSTOS SANTOS'!$F$27-'CUSTOS BERTIOGA'!$F$34-'CUSTOS SANTOS'!$F$35)*AUX!E$9/PREMISSAS!$C$8 -> 221236.67 | F14: =(PREMISSAS!$C$30-'CUSTOS BERTIOGA'!$H$22-'CUSTOS SANTOS'!$H$23-'CUSTOS BERTIOGA'!$F$26-'CUSTOS SANTOS'!$F$27-'CUSTOS BERTIOGA'!$F$34-'CUSTOS SANTOS'!$F$35)*AUX!F$9/PREMISSAS!$C$8 -> 214100 | G14: =(PREMISSAS!$C$30-'CUSTOS BERTIOGA'!$H$22-'CUSTOS SANTOS'!$H$23-'CUSTOS BERTIOGA'!$F$26-'CUSTOS SANTOS'!$F$27-'CUSTOS BERTIOGA'!$F$34-'CUSTOS SANTOS'!$F$35)*AUX!G$9/PREMISSAS!$C$8 -> 221236.67 | H14: =(PREMISSAS!$C$30-'CUSTOS BERTIOGA'!$H$22-'CUSTOS SANTOS'!$H$23-'CUSTOS BERTIOGA'!$F$26-'CUSTOS SANTOS'!$F$27-'CUSTOS BERTIOGA'!$F$34-'CUSTOS SANTOS'!$F$35)*AUX!H$9/PREMISSAS!$C$8 -> 221236.67 | I14: =(PREMISSAS!$C$30-'CUSTOS BERTIOGA'!$H$22-'CUSTOS SANTOS'!$H$23-'CUSTOS BERTIOGA'!$F$26-'CUSTOS SANTOS'!$F$27-'CUSTOS BERTIOGA'!$F$34-'CUSTOS SANTOS'!$F$35)*AUX!I$9/PREMISSAS!$C$8 -> 199826.67 | J14: =(PREMISSAS!$C$30-'CUSTOS BERTIOGA'!$H$22-'CUSTOS SANTOS'!$H$23-'CUSTOS BERTIOGA'!$F$26-'CUSTOS SANTOS'!$F$27-'CUSTOS BERTIOGA'!$F$34-'CUSTOS SANTOS'!$F$35)*AUX!J$9/PREMISSAS!$C$8 -> 221236.67 | ... Q14: =(PREMISSAS!$C$30-'CUSTOS BERTIOGA'!$H$22-'CUSTOS SANTOS'!$H$23-'CUSTOS BERTIOGA'!$F$26-'CUSTOS SANTOS'!$F$27-'CUSTOS BERTIOGA'!$F$34-'CUSTOS SANTOS'!$F$35)*AUX!Q$9/PREMISSAS!$C$8 -> 0 | R14: =SUM(C14:Q14) -> 2490696.7
B15: (–) Custos indiretos | C15: =('CUSTOS BERTIOGA'!$F$34+'CUSTOS SANTOS'!$F$35)*AUX!C$9/PREMISSAS!$C$8 -> 20000 | D15: =('CUSTOS BERTIOGA'!$F$34+'CUSTOS SANTOS'!$F$35)*AUX!D$9/PREMISSAS!$C$8 -> 40000 | E15: =('CUSTOS BERTIOGA'!$F$34+'CUSTOS SANTOS'!$F$35)*AUX!E$9/PREMISSAS!$C$8 -> 41333.333 | F15: =('CUSTOS BERTIOGA'!$F$34+'CUSTOS SANTOS'!$F$35)*AUX!F$9/PREMISSAS!$C$8 -> 40000 | G15: =('CUSTOS BERTIOGA'!$F$34+'CUSTOS SANTOS'!$F$35)*AUX!G$9/PREMISSAS!$C$8 -> 41333.333 | H15: =('CUSTOS BERTIOGA'!$F$34+'CUSTOS SANTOS'!$F$35)*AUX!H$9/PREMISSAS!$C$8 -> 41333.333 | I15: =('CUSTOS BERTIOGA'!$F$34+'CUSTOS SANTOS'!$F$35)*AUX!I$9/PREMISSAS!$C$8 -> 37333.333 | J15: =('CUSTOS BERTIOGA'!$F$34+'CUSTOS SANTOS'!$F$35)*AUX!J$9/PREMISSAS!$C$8 -> 41333.333 | ... Q15: =('CUSTOS BERTIOGA'!$F$34+'CUSTOS SANTOS'!$F$35)*AUX!Q$9/PREMISSAS!$C$8 -> 0 | R15: =SUM(C15:Q15) -> 465333.33
B16: (–) Mobilização / custos iniciais | C16: =IF(C$5=DATE(YEAR(PREMISSAS!$C$6),MONTH(PREMISSAS!$C$6),1),PREMISSAS!$C$35,0) -> 26720 | D16: =IF(D$5=DATE(YEAR(PREMISSAS!$C$6),MONTH(PREMISSAS!$C$6),1),PREMISSAS!$C$35,0) -> 0 | E16: =IF(E$5=DATE(YEAR(PREMISSAS!$C$6),MONTH(PREMISSAS!$C$6),1),PREMISSAS!$C$35,0) -> 0 | F16: =IF(F$5=DATE(YEAR(PREMISSAS!$C$6),MONTH(PREMISSAS!$C$6),1),PREMISSAS!$C$35,0) -> 0 | G16: =IF(G$5=DATE(YEAR(PREMISSAS!$C$6),MONTH(PREMISSAS!$C$6),1),PREMISSAS!$C$35,0) -> 0 | H16: =IF(H$5=DATE(YEAR(PREMISSAS!$C$6),MONTH(PREMISSAS!$C$6),1),PREMISSAS!$C$35,0) -> 0 | I16: =IF(I$5=DATE(YEAR(PREMISSAS!$C$6),MONTH(PREMISSAS!$C$6),1),PREMISSAS!$C$35,0) -> 0 | J16: =IF(J$5=DATE(YEAR(PREMISSAS!$C$6),MONTH(PREMISSAS!$C$6),1),PREMISSAS!$C$35,0) -> 0 | ... Q16: =IF(Q$5=DATE(YEAR(PREMISSAS!$C$6),MONTH(PREMISSAS!$C$6),1),PREMISSAS!$C$35,0) -> 0 | R16: =SUM(C16:Q16) -> 26720
B17: (=) RESULTADO ECONÔMICO DO MÊS | C17: =C11-C12-C13-C14-C15-C16 -> -138227.95 | D17: =D11-D12-D13-D14-D15-D16 -> 202741.73 | E17: =E11-E12-E13-E14-E15-E16 -> 185846.58 | F17: =F11-F12-F13-F14-F15-F16 -> 101370.86 | G17: =G11-G12-G13-G14-G15-G16 -> 104749.89 | H17: =H11-H12-H13-H14-H15-H16 -> 104749.89 | I17: =I11-I12-I13-I14-I15-I16 -> 94612.806 | J17: =J11-J12-J13-J14-J15-J16 -> 104749.89 | ... Q17: =Q11-Q12-Q13-Q14-Q15-Q16 -> 0 | R17: =SUM(C17:Q17) -> 1172835.2
B18: RESULTADO ACUMULADO | C18: =C17 -> -138227.95 | D18: =C18+D17 -> 64513.778 | E18: =D18+E17 -> 250360.36 | F18: =E18+F17 -> 351731.23 | G18: =F18+G17 -> 456481.12 | H18: =G18+H17 -> 561231.01 | I18: =H18+I17 -> 655843.82 | J18: =I18+J17 -> 760593.71 | K18: =J18+K17 -> 861964.57 | ... Q18: =P18+Q17 -> 1172835.2 | R18: =Q18 -> 1172835.2
B19: Margem do mês (% da medição) | C19: =IFERROR(C17/C9,0) -> -0.75971253 | D19: =IFERROR(D17/D9,0) -> 0.22285714 | E19: =IFERROR(E17/E9,0) -> 0.20428571 | F19: =IFERROR(F17/F9,0) -> 0.13 | G19: =IFERROR(G17/G9,0) -> 0.13 | H19: =IFERROR(H17/H9,0) -> 0.13 | I19: =IFERROR(I17/I9,0) -> 0.13 | J19: =IFERROR(J17/J9,0) -> 0.13 | ... R19: =IFERROR(R17/R9,0) -> 0.12892004
B21: RESUMO
B22: Resultado econômico do contrato no horizonte | C22: =R17 -> 1172835.2
B23: Margem sobre a medição | C23: =R19 -> 0.12892004
B24: O resultado econômico e o resultado de caixa do FCP MENSAL fecham no mesmo número no fim do horizonte. No dia a dia eles diferem: o consórcio financia folha/estrutura e desconta da medição; a WCR só gira os indiretos.

Sheet VIABILIDADE
B2: VIABILIDADE — produção necessária por cenário
B3: MÍNIMA = empate real: cobre custo + imposto da nota. Sua planilha anterior não descontava o imposto — a linha cinza mostra aquela referência.
B4: BERTIOGA
B5: Custo mensal: | C5: =PREMISSAS!$C$28 -> 237292.84 | E5: Ticket médio: | F5: =PREMISSAS!$C$21 -> 881.2
B6: CENÁRIO | C6: MARGEM | D6: RECEITA LÍQUIDA /MÊS | E6: MEDIÇÃO BRUTA /MÊS | F6: SERVIÇOS /MÊS | G6: SERVIÇOS /SEMANA | H6: SERVIÇOS /DIA
B7: MÍNIMA | C7: =PREMISSAS!C14 -> 0 | D7: =PREMISSAS!$C$28*(1+C7) -> 237292.84 | E7: =D7/(1-PREMISSAS!$C$10) -> 304221.59 | F7: =E7/PREMISSAS!$C$21 -> 345.23558 | G7: =F7*7/PREMISSAS!$C$8 -> 80.554968 | H7: =F7/PREMISSAS!$C$8 -> 11.507853 | I7: =IF(B7=PREMISSAS!$C$13,"◀ adotado","")
B8: MÉDIA | C8: =PREMISSAS!C15 -> 0.1 | D8: =PREMISSAS!$C$28*(1+C8) -> 261022.12 | E8: =D8/(1-PREMISSAS!$C$10) -> 334643.75 | F8: =E8/PREMISSAS!$C$21 -> 379.75913 | G8: =F8*7/PREMISSAS!$C$8 -> 88.610465 | H8: =F8/PREMISSAS!$C$8 -> 12.658638 | I8: =IF(B8=PREMISSAS!$C$13,"◀ adotado","")
B9: BOA | C9: =PREMISSAS!C16 -> 0.15 | D9: =PREMISSAS!$C$28*(1+C9) -> 272886.77 | E9: =D9/(1-PREMISSAS!$C$10) -> 349854.83 | F9: =E9/PREMISSAS!$C$21 -> 397.02091 | G9: =F9*7/PREMISSAS!$C$8 -> 92.638213 | H9: =F9/PREMISSAS!$C$8 -> 13.23403 | I9: =IF(B9=PREMISSAS!$C$13,"◀ adotado","")
B10: ÓTIMA | C10: =PREMISSAS!C17 -> 0.2 | D10: =PREMISSAS!$C$28*(1+C10) -> 284751.41 | E10: =D10/(1-PREMISSAS!$C$10) -> 365065.91 | F10: =E10/PREMISSAS!$C$21 -> 414.28269 | G10: =F10*7/PREMISSAS!$C$8 -> 96.665961 | H10: =F10/PREMISSAS!$C$8 -> 13.809423 | I10: =IF(B10=PREMISSAS!$C$13,"◀ adotado","") -> ◀ adotado
B11: Referência: mínima da sua planilha anterior (sem imposto) | F11: =PREMISSAS!$C$28/PREMISSAS!$C$21 -> 269.28375 | G11: =F11*7/PREMISSAS!$C$8 -> 62.832875 | H11: =F11/PREMISSAS!$C$8 -> 8.976125
B13: SANTOS (mix água/esgoto da premissa)
B14: Custo mensal: | C14: =PREMISSAS!$C$29 -> 269561.48 | E14: Ticket médio: | F14: =PREMISSAS!$C$25 -> 1338.825
B15: CENÁRIO | C15: MARGEM | D15: RECEITA LÍQUIDA /MÊS | E15: MEDIÇÃO BRUTA /MÊS | F15: SERVIÇOS /MÊS | G15: SERVIÇOS /SEMANA | H15: SERVIÇOS /DIA | J15: ÁGUA /DIA | K15: ESGOTO /DIA
B16: MÍNIMA | C16: =PREMISSAS!C14 -> 0 | D16: =PREMISSAS!$C$29*(1+C16) -> 269561.48 | E16: =D16/(1-PREMISSAS!$C$10) -> 345591.64 | F16: =E16/PREMISSAS!$C$25 -> 258.13056 | G16: =F16*7/PREMISSAS!$C$8 -> 60.230463 | H16: =F16/PREMISSAS!$C$8 -> 8.6043519 | I16: =IF(B16=PREMISSAS!$C$13,"◀ adotado","") | J16: =H16*(1-PREMISSAS!$C$24) -> 4.3021759 | K16: =H16*PREMISSAS!$C$24 -> 4.3021759
B17: MÉDIA | C17: =PREMISSAS!C15 -> 0.1 | D17: =PREMISSAS!$C$29*(1+C17) -> 296517.63 | E17: =D17/(1-PREMISSAS!$C$10) -> 380150.81 | F17: =E17/PREMISSAS!$C$25 -> 283.94361 | G17: =F17*7/PREMISSAS!$C$8 -> 66.253509 | H17: =F17/PREMISSAS!$C$8 -> 9.464787 | I17: =IF(B17=PREMISSAS!$C$13,"◀ adotado","") | J17: =H17*(1-PREMISSAS!$C$24) -> 4.7323935 | K17: =H17*PREMISSAS!$C$24 -> 4.7323935
B18: BOA | C18: =PREMISSAS!C16 -> 0.15 | D18: =PREMISSAS!$C$29*(1+C18) -> 309995.7 | E18: =D18/(1-PREMISSAS!$C$10) -> 397430.39 | F18: =E18/PREMISSAS!$C$25 -> 296.85014 | G18: =F18*7/PREMISSAS!$C$8 -> 69.265032 | H18: =F18/PREMISSAS!$C$8 -> 9.8950046 | I18: =IF(B18=PREMISSAS!$C$13,"◀ adotado","") | J18: =H18*(1-PREMISSAS!$C$24) -> 4.9475023 | K18: =H18*PREMISSAS!$C$24 -> 4.9475023
B19: ÓTIMA | C19: =PREMISSAS!C17 -> 0.2 | D19: =PREMISSAS!$C$29*(1+C19) -> 323473.78 | E19: =D19/(1-PREMISSAS!$C$10) -> 414709.97 | F19: =E19/PREMISSAS!$C$25 -> 309.75667 | G19: =F19*7/PREMISSAS!$C$8 -> 72.276556 | H19: =F19/PREMISSAS!$C$8 -> 10.325222 | I19: =IF(B19=PREMISSAS!$C$13,"◀ adotado","") -> ◀ adotado | J19: =H19*(1-PREMISSAS!$C$24) -> 5.1626111 | K19: =H19*PREMISSAS!$C$24 -> 5.1626111
B20: Referência antiga (sem imposto) — se fosse SÓ ÁGUA | F20: =PREMISSAS!$C$29/PREMISSAS!$C$22 -> 328.23316 | G20: =F20*7/PREMISSAS!$C$8 -> 76.587737 | H20: =F20/PREMISSAS!$C$8 -> 10.941105
B21: Referência antiga (sem imposto) — se fosse SÓ ESGOTO | F21: =PREMISSAS!$C$29/PREMISSAS!$C$23 -> 145.20657 | G21: =F21*7/PREMISSAS!$C$8 -> 33.881533 | H21: =F21/PREMISSAS!$C$8 -> 4.8402191
B22: GLOBAL — BERTIOGA + SANTOS (em R$)
B23: CENÁRIO | C23: MARGEM | D23: RECEITA LÍQUIDA /MÊS | E23: MEDIÇÃO BRUTA /MÊS
B24: MÍNIMA | C24: =PREMISSAS!C14 -> 0 | D24: =PREMISSAS!$C$30*(1+C24) -> 506854.32 | E24: =D24/(1-PREMISSAS!$C$10) -> 649813.23 | F24: =IF(B24=PREMISSAS!$C$13,"◀ adotado","")
B25: MÉDIA | C25: =PREMISSAS!C15 -> 0.1 | D25: =PREMISSAS!$C$30*(1+C25) -> 557539.75 | E25: =D25/(1-PREMISSAS!$C$10) -> 714794.55 | F25: =IF(B25=PREMISSAS!$C$13,"◀ adotado","")
B26: BOA | C26: =PREMISSAS!C16 -> 0.15 | D26: =PREMISSAS!$C$30*(1+C26) -> 582882.47 | E26: =D26/(1-PREMISSAS!$C$10) -> 747285.22 | F26: =IF(B26=PREMISSAS!$C$13,"◀ adotado","")
B27: ÓTIMA | C27: =PREMISSAS!C17 -> 0.2 | D27: =PREMISSAS!$C$30*(1+C27) -> 608225.18 | E27: =D27/(1-PREMISSAS!$C$10) -> 779775.88 | F27: =IF(B27=PREMISSAS!$C$13,"◀ adotado","") -> ◀ adotado
B29: Produção em unidades não soma entre cidades (tickets diferentes) — acompanhe unidades por cidade, R$ no global.

Sheet CUSTOS BERTIOGA
B2: CUSTOS — BERTIOGA
B3: Fonte: Fluxo Trimestral Obra.xlsx · aba Custos (18/08/2026) — edite os valores em azul
B5: EQUIPE — QUADRO NOMINAL
B6: EQUIPE | C6: NOME | D6: CARGO | E6: SALÁRIO | F6: ENCARGOS | G6: BENEFÍCIOS | H6: TOTAL / MÊS
B7: A | C7: Lenildo Lourenco da Silva | D7: Ajudante Geral | E7: 2951 | F7: 1712 | G7: 1679 | H7: =E7+F7+G7 -> 6342
B8: A | C8: Edivan dos Santos | D8: Encanador Motorizado | E8: 3932 | F8: 2281 | G8: 1679 | H8: =E8+F8+G8 -> 7892
B9: A | C9: Marcelo dos Santos Marciano | D9: Ajudante Geral | E9: 2951 | F9: 1712 | G9: 1679 | H9: =E9+F9+G9 -> 6342
B10: B | C10: Junior Sabino | D10: Lider de Equipe | E10: 3908 | F10: 2267 | G10: 1679 | H10: =E10+F10+G10 -> 7854
B11: B | C11: Bruno Carvalho Dias | D11: Ajudante Geral | E11: 2951 | F11: 1712 | G11: 1679 | H11: =E11+F11+G11 -> 6342
B12: B | C12: Jerailson Lourenco Santos da S | D12: Encanador | E12: 3633 | F12: 2107 | G12: 1679 | H12: =E12+F12+G12 -> 7419
B13: C | C13: Egmar de Almeida Pinto | D13: Ajudante Geral | E13: 2951 | F13: 1712 | G13: 1679 | H13: =E13+F13+G13 -> 6342
B14: C | C14: Oziel | D14: Encanador | E14: 3633 | F14: 2107 | G14: 1679 | H14: =E14+F14+G14 -> 7419
B15: C | C15: Rafael Nunes de Godoy | D15: Ajudante Geral | E15: 2951 | F15: 1712 | G15: 1679 | H15: =E15+F15+G15 -> 6342
B16: C | C16: Rafael Santos Cruz | D16: Operador de Retroescavadeira | E16: 3947 | F16: 2289 | G16: 1679 | H16: =E16+F16+G16 -> 7915
B17: D | C17: Jose Henrique | D17: Ajudante Geral | E17: 2951 | F17: 1712 | G17: 1679 | H17: =E17+F17+G17 -> 6342
B18: D | C18: Arnaldo de Araujo Bastos | D18: Encanador Motorizado | E18: 3932 | F18: 2281 | G18: 1679 | H18: =E18+F18+G18 -> 7892
B19: D | C19: Kaique Tavares da Silva | D19: Encanador | E19: 3633 | F19: 2107 | G19: 1679 | H19: =E19+F19+G19 -> 7419
B20: — | D20: Programador | E20: 2548 | F20: 1477.84 | G20: 1679 | H20: =E20+F20+G20 -> 5704.84
B21: — | C21: Sergio Rodrigues da Silva | D21: Encarregado de Obras | E21: 4713 | F21: 2734 | G21: 1679 | H21: =E21+F21+G21 -> 9126
B22: TOTAL | C22: 15 pessoas | E22: =SUM(E7:E21) -> 51585 | F22: =SUM(F7:F21) -> 29922.84 | G22: =SUM(G7:G21) -> 25185 | H22: =SUM(H7:H21) -> 106692.84
B24: CUSTOS GERAIS DA OBRA (R$/MÊS)
B25: ITEM | D25: QNT | E25: VALOR UNIT. | F25: TOTAL MÊS
B26: Salário engenheiro | D26: 1 | E26: 13000 | F26: =D26*E26 -> 13000
B27: Kit ferramenta equipes | D27: 4 | E27: 7200 | F27: =D27*E27 -> 28800 | H27: mantido como custo mensal, igual à sua planilha
B28: Carro engenheiro | D28: 1 | E28: 3400 | F28: =D28*E28 -> 3400
B29: Carro encarregado | D29: 1 | E29: 3500 | F29: =D29*E29 -> 3500
B30: Caminhão 3/4 + munck | D30: 1 | E30: 25000 | F30: =D30*E30 -> 25000
B31: HR CAMINHÃO TIPO HR | D31: 3 | E31: 3500 | F31: =D31*E31 -> 10500
B32: Alojamento | D32: 1 | E32: 13500 | F32: =D32*E32 -> 13500
B33: Equipamentos leves | D33: 1 | E33: 12900 | F33: =D33*E33 -> 12900
B34: Custos indiretos | D34: 1 | E34: 20000 | F34: =D34*E34 -> 20000
B35: Equipe (folha + encargos + benefícios) | D35: 1 | E35: =H22 -> 106692.84 | F35: =D35*E35 -> 106692.84
B36: TOTAL MENSAL — BERTIOGA | F36: =SUM(F26:F35) -> 237292.84
B38: TOTAL SEMANAL (7 dias) | F38: =F36*7/PREMISSAS!$C$8 -> 55368.329
B39: TOTAL QUINZENAL (15 dias) | F39: =F36/2 -> 118646.42
B40: TOTAL DIÁRIO | F40: =F36/PREMISSAS!$C$8 -> 7909.7613

Sheet CUSTOS SANTOS
B2: CUSTOS — SANTOS
B3: Fonte: Fluxo Trimestral Obra.xlsx · aba Custos (18/08/2026) — edite os valores em azul
B5: EQUIPE — QUADRO NOMINAL
B6: EQUIPE | C6: NOME | D6: CARGO | E6: SALÁRIO | F6: ENCARGOS | G6: BENEFÍCIOS | H6: TOTAL / MÊS
B7: A | C7: Ricardo Dantas da Silva Junior | D7: Ajudante Geral | E7: 2951 | F7: 1712 | G7: 1679 | H7: =E7+F7+G7 -> 6342
B8: A | C8: Jean Estevam de Oliveira | D8: Encanador Motorizado | E8: 3932 | F8: 2281 | G8: 1679 | H8: =E8+F8+G8 -> 7892
B9: A | C9: Renato Santos Araujo | D9: Pedreiro | E9: 3633 | F9: 2107 | G9: 1679 | H9: =E9+F9+G9 -> 7419
B10: B | C10: Paulo Alberto da Silva de Paula | D10: Pedreiro | E10: 3633 | F10: 2107 | G10: 1679 | H10: =E10+F10+G10 -> 7419
B11: B | C11: Kaua dos Santos Nunes Rodrigues | D11: Ajudante Geral | E11: 2951 | F11: 1712 | G11: 1679 | H11: =E11+F11+G11 -> 6342
B12: B | C12: Marcelo da Silva Nogueira | D12: Encanador Motorizado | E12: 3932 | F12: 2281 | G12: 1679 | H12: =E12+F12+G12 -> 7892
B13: C | C13: Jeferson Silva de Paiva | D13: Encanador | E13: 3633 | F13: 2107 | G13: 1679 | H13: =E13+F13+G13 -> 7419
B14: C | C14: Danilo Fernando Salgado | D14: Pedreiro Motorizado | E14: 3932 | F14: 2281 | G14: 1679 | H14: =E14+F14+G14 -> 7892
B15: C | C15: Rian Teixeira da Silva | D15: Ajudante Geral | E15: 2951 | F15: 1712 | G15: 1679 | H15: =E15+F15+G15 -> 6342
B16: C | C16: Rogério Soares da Silva | D16: Operador de Retroescavadeira | E16: 4979 | F16: 2887.82 | G16: 1679 | H16: =E16+F16+G16 -> 9545.82
B17: D | C17: Hernandes Araújo de Oliveira | D17: Encanador | E17: 3633 | F17: 2107 | G17: 1679 | H17: =E17+F17+G17 -> 7419
B18: D | C18: Alex | D18: Encanador | E18: 3633 | F18: 2107 | G18: 1679 | H18: =E18+F18+G18 -> 7419
... B22: — | C22: Sidnei Jose dos Santos | D22: Encarregado de Obras | E22: 4713 | F22: 2734 | G22: 1679 | H22: =E22+F22+G22 -> 9126
B23: TOTAL | C23: 16 pessoas | E23: =SUM(E7:E22) -> 58984 | F23: =SUM(F7:F22) -> 34213.48 | G23: =SUM(G7:G22) -> 26864 | H23: =SUM(H7:H22) -> 120061.48
B25: CUSTOS GERAIS DA OBRA (R$/MÊS)
B26: ITEM | D26: QNT | E26: VALOR UNIT. | F26: TOTAL MÊS
B27: Salário engenheiro | D27: 1 | E27: 13000 | F27: =D27*E27 -> 13000
B28: Kit ferramenta equipes | D28: 4 | E28: 7200 | F28: =D28*E28 -> 28800 | H28: mantido como custo mensal, igual à sua planilha
B29: Carro engenheiro | D29: 1 | E29: 3400 | F29: =D29*E29 -> 3400
B30: Carro encarregado | D30: 1 | E30: 3400 | F30: =D30*E30 -> 3400
B31: Caminhão 3/4 + munck | D31: 2 | E31: 25000 | F31: =D31*E31 -> 50000
B32: HR (horas de máquina) | D32: 2 | E32: 6000 | F32: =D32*E32 -> 12000
B33: Alojamento | D33: 1 | E33: 6000 | F33: =D33*E33 -> 6000
B34: Equipamentos leves | D34: 1 | E34: 12900 | F34: =D34*E34 -> 12900
B35: Custos indiretos | D35: 1 | E35: 20000 | F35: =D35*E35 -> 20000
B36: Equipe (folha + encargos + benefícios) | D36: 1 | E36: =H23 -> 120061.48 | F36: =D36*E36 -> 120061.48
B37: TOTAL MENSAL — SANTOS | F37: =SUM(F27:F36) -> 269561.48
B39: TOTAL SEMANAL (7 dias) | F39: =F37*7/PREMISSAS!$C$8 -> 62897.679
B40: TOTAL QUINZENAL (15 dias) | F40: =F37/2 -> 134780.74
B41: TOTAL DIÁRIO | F41: =F37/PREMISSAS!$C$8 -> 8985.3827

Sheet AUX
B2: AUX — medições, datas de pagamento e cenários (cálculo; não precisa editar)
B3: Mês (1º dia) | C3: =DATE(YEAR(PREMISSAS!$C$6),MONTH(PREMISSAS!$C$6),1) -> 46235 | D3: =EDATE(C3,1) -> 46266 | E3: =EDATE(D3,1) -> 46296 | F3: =EDATE(E3,1) -> 46327 | G3: =EDATE(F3,1) -> 46357 | H3: =EDATE(G3,1) -> 46388 | I3: =EDATE(H3,1) -> 46419 | J3: =EDATE(I3,1) -> 46447 | K3: =EDATE(J3,1) -> 46478 | ... Q3: =EDATE(P3,1) -> 46661
B4: Dias de obra no mês | C4: =MAX(0,MIN(EOMONTH(C3,0),PREMISSAS!$C$7)-MAX(C3,PREMISSAS!$C$6)+1) -> 8 | D4: =MAX(0,MIN(EOMONTH(D3,0),PREMISSAS!$C$7)-MAX(D3,PREMISSAS!$C$6)+1) -> 30 | E4: =MAX(0,MIN(EOMONTH(E3,0),PREMISSAS!$C$7)-MAX(E3,PREMISSAS!$C$6)+1) -> 31 | F4: =MAX(0,MIN(EOMONTH(F3,0),PREMISSAS!$C$7)-MAX(F3,PREMISSAS!$C$6)+1) -> 30 | G4: =MAX(0,MIN(EOMONTH(G3,0),PREMISSAS!$C$7)-MAX(G3,PREMISSAS!$C$6)+1) -> 31 | H4: =MAX(0,MIN(EOMONTH(H3,0),PREMISSAS!$C$7)-MAX(H3,PREMISSAS!$C$6)+1) -> 31 | I4: =MAX(0,MIN(EOMONTH(I3,0),PREMISSAS!$C$7)-MAX(I3,PREMISSAS!$C$6)+1) -> 28 | J4: =MAX(0,MIN(EOMONTH(J3,0),PREMISSAS!$C$7)-MAX(J3,PREMISSAS!$C$6)+1) -> 31 | ... Q4: =MAX(0,MIN(EOMONTH(Q3,0),PREMISSAS!$C$7)-MAX(Q3,PREMISSAS!$C$6)+1) -> 0
B5: Medição bruta BERTIOGA (ago–out: FCP SEMANAL · depois: projeção) | C5: ='FCP SEMANAL'!D12 -> 85182.045 | D5: =SUM('FCP SEMANAL'!E12:I12) -> 425910.23 | E5: =SUM('FCP SEMANAL'!J12:N12) -> 425910.23 | F5: =PREMISSAS!$C$28*(1+PREMISSAS!$C$18)/(1-PREMISSAS!$C$10)*F4/PREMISSAS!$C$8 -> 365065.91 | G5: =PREMISSAS!$C$28*(1+PREMISSAS!$C$18)/(1-PREMISSAS!$C$10)*G4/PREMISSAS!$C$8 -> 377234.77 | H5: =PREMISSAS!$C$28*(1+PREMISSAS!$C$18)/(1-PREMISSAS!$C$10)*H4/PREMISSAS!$C$8 -> 377234.77 | I5: =PREMISSAS!$C$28*(1+PREMISSAS!$C$18)/(1-PREMISSAS!$C$10)*I4/PREMISSAS!$C$8 -> 340728.18 | J5: =PREMISSAS!$C$28*(1+PREMISSAS!$C$18)/(1-PREMISSAS!$C$10)*J4/PREMISSAS!$C$8 -> 377234.77 | K5: =PREMISSAS!$C$28*(1+PREMISSAS!$C$18)/(1-PREMISSAS!$C$10)*K4/PREMISSAS!$C$8 -> 365065.91 | L5: =PREMISSAS!$C$28*(1+PREMISSAS!$C$18)/(1-PREMISSAS!$C$10)*L4/PREMISSAS!$C$8 -> 377234.77 | M5: =PREMISSAS!$C$28*(1+PREMISSAS!$C$18)/(1-PREMISSAS!$C$10)*M4/PREMISSAS!$C$8 -> 365065.91 | ... Q5: =PREMISSAS!$C$28*(1+PREMISSAS!$C$18)/(1-PREMISSAS!$C$10)*Q4/PREMISSAS!$C$8 -> 0
B6: Medição bruta SANTOS (ago–out: FCP SEMANAL · depois: projeção) | C6: ='FCP SEMANAL'!D25 -> 96765.659 | D6: =SUM('FCP SEMANAL'!E25:I25) -> 483828.3 | E6: =SUM('FCP SEMANAL'!J25:N25) -> 483828.3 | F6: =PREMISSAS!$C$29*(1+PREMISSAS!$C$18)/(1-PREMISSAS!$C$10)*F4/PREMISSAS!$C$8 -> 414709.97 | G6: =PREMISSAS!$C$29*(1+PREMISSAS!$C$18)/(1-PREMISSAS!$C$10)*G4/PREMISSAS!$C$8 -> 428533.63 | H6: =PREMISSAS!$C$29*(1+PREMISSAS!$C$18)/(1-PREMISSAS!$C$10)*H4/PREMISSAS!$C$8 -> 428533.63 | I6: =PREMISSAS!$C$29*(1+PREMISSAS!$C$18)/(1-PREMISSAS!$C$10)*I4/PREMISSAS!$C$8 -> 387062.64 | J6: =PREMISSAS!$C$29*(1+PREMISSAS!$C$18)/(1-PREMISSAS!$C$10)*J4/PREMISSAS!$C$8 -> 428533.63 | K6: =PREMISSAS!$C$29*(1+PREMISSAS!$C$18)/(1-PREMISSAS!$C$10)*K4/PREMISSAS!$C$8 -> 414709.97 | L6: =PREMISSAS!$C$29*(1+PREMISSAS!$C$18)/(1-PREMISSAS!$C$10)*L4/PREMISSAS!$C$8 -> 428533.63 | M6: =PREMISSAS!$C$29*(1+PREMISSAS!$C$18)/(1-PREMISSAS!$C$10)*M4/PREMISSAS!$C$8 -> 414709.97 | ... Q6: =PREMISSAS!$C$29*(1+PREMISSAS!$C$18)/(1-PREMISSAS!$C$10)*Q4/PREMISSAS!$C$8 -> 0
B7: Medição bruta GLOBAL | C7: =C5+C6 -> 181947.7 | D7: =D5+D6 -> 909738.52 | E7: =E5+E6 -> 909738.52 | F7: =F5+F6 -> 779775.88 | G7: =G5+G6 -> 805768.41 | H7: =H5+H6 -> 805768.41 | I7: =I5+I6 -> 727790.82 | J7: =J5+J6 -> 805768.41 | ... Q7: =Q5+Q6 -> 0
B8: Data de pagamento da medição | C8: =EOMONTH(C3,0)+PREMISSAS!$C$9 -> 46285 | D8: =EOMONTH(D3,0)+PREMISSAS!$C$9 -> 46315 | E8: =EOMONTH(E3,0)+PREMISSAS!$C$9 -> 46346 | F8: =EOMONTH(F3,0)+PREMISSAS!$C$9 -> 46376 | G8: =EOMONTH(G3,0)+PREMISSAS!$C$9 -> 46407 | H8: =EOMONTH(H3,0)+PREMISSAS!$C$9 -> 46438 | I8: =EOMONTH(I3,0)+PREMISSAS!$C$9 -> 46466 | J8: =EOMONTH(J3,0)+PREMISSAS!$C$9 -> 46497 | ... Q8: =EOMONTH(Q3,0)+PREMISSAS!$C$9 -> 46711
B9: Dias equivalentes p/ custo (1º mês = fator × 30) | C9: =IF(C3=DATE(YEAR(PREMISSAS!$C$6),MONTH(PREMISSAS!$C$6),1),PREMISSAS!$C$39*PREMISSAS!$C$8,C4) -> 15 | D9: =IF(D3=DATE(YEAR(PREMISSAS!$C$6),MONTH(PREMISSAS!$C$6),1),PREMISSAS!$C$39*PREMISSAS!$C$8,D4) -> 30 | E9: =IF(E3=DATE(YEAR(PREMISSAS!$C$6),MONTH(PREMISSAS!$C$6),1),PREMISSAS!$C$39*PREMISSAS!$C$8,E4) -> 31 | F9: =IF(F3=DATE(YEAR(PREMISSAS!$C$6),MONTH(PREMISSAS!$C$6),1),PREMISSAS!$C$39*PREMISSAS!$C$8,F4) -> 30 | G9: =IF(G3=DATE(YEAR(PREMISSAS!$C$6),MONTH(PREMISSAS!$C$6),1),PREMISSAS!$C$39*PREMISSAS!$C$8,G4) -> 31 | H9: =IF(H3=DATE(YEAR(PREMISSAS!$C$6),MONTH(PREMISSAS!$C$6),1),PREMISSAS!$C$39*PREMISSAS!$C$8,H4) -> 31 | I9: =IF(I3=DATE(YEAR(PREMISSAS!$C$6),MONTH(PREMISSAS!$C$6),1),PREMISSAS!$C$39*PREMISSAS!$C$8,I4) -> 28 | J9: =IF(J3=DATE(YEAR(PREMISSAS!$C$6),MONTH(PREMISSAS!$C$6),1),PREMISSAS!$C$39*PREMISSAS!$C$8,J4) -> 31 | ... Q9: =IF(Q3=DATE(YEAR(PREMISSAS!$C$6),MONTH(PREMISSAS!$C$6),1),PREMISSAS!$C$39*PREMISSAS!$C$8,Q4) -> 0
B10: GRADE DE CENÁRIOS — CAIXA DA WCR (capital e resultado por cenário)
B11: MÍNIMA — medição bruta global | C11: =PREMISSAS!$C$30*(1+PREMISSAS!$C$14)/(1-PREMISSAS!$C$10)*C$4/PREMISSAS!$C$8 -> 173283.53 | D11: =PREMISSAS!$C$30*(1+PREMISSAS!$C$14)/(1-PREMISSAS!$C$10)*D$4/PREMISSAS!$C$8 -> 649813.23 | E11: =PREMISSAS!$C$30*(1+PREMISSAS!$C$14)/(1-PREMISSAS!$C$10)*E$4/PREMISSAS!$C$8 -> 671473.67 | F11: =PREMISSAS!$C$30*(1+PREMISSAS!$C$14)/(1-PREMISSAS!$C$10)*F$4/PREMISSAS!$C$8 -> 649813.23 | G11: =PREMISSAS!$C$30*(1+PREMISSAS!$C$14)/(1-PREMISSAS!$C$10)*G$4/PREMISSAS!$C$8 -> 671473.67 | H11: =PREMISSAS!$C$30*(1+PREMISSAS!$C$14)/(1-PREMISSAS!$C$10)*H$4/PREMISSAS!$C$8 -> 671473.67 | I11: =PREMISSAS!$C$30*(1+PREMISSAS!$C$14)/(1-PREMISSAS!$C$10)*I$4/PREMISSAS!$C$8 -> 606492.35 | J11: =PREMISSAS!$C$30*(1+PREMISSAS!$C$14)/(1-PREMISSAS!$C$10)*J$4/PREMISSAS!$C$8 -> 671473.67 | ... Q11: =PREMISSAS!$C$30*(1+PREMISSAS!$C$14)/(1-PREMISSAS!$C$10)*Q$4/PREMISSAS!$C$8 -> 0
B12: entra no caixa WCR (receb − desconto − imposto) | C12: =SUMPRODUCT((AUX!$C$8:$Q$8>=C$3)*(AUX!$C$8:$Q$8<=EOMONTH(C$3,0))*$C$11:$Q$11)-0-IF(PREMISSAS!$C$48="MEDIÇÃO CHEIA",SUMPRODUCT((AUX!$C$8:$Q$8>=C$3)*(AUX!$C$8:$Q$8<=EOMONTH(C$3,0))*$C$11:$Q$11),MAX(0,SUMPRODUCT((AUX!$C$8:$Q$8>=C$3)*(AUX!$C$8:$Q$8<=EOMONTH(C$3,0))*$C$11:$Q$11)-0))*PREMISSAS!$C$10 -> 0 | D12: =SUMPRODUCT((AUX!$C$8:$Q$8>=D$3)*(AUX!$C$8:$Q$8<=EOMONTH(D$3,0))*$C$11:$Q$11)-(PREMISSAS!$C$61*C$9/PREMISSAS!$C$8+IF(D$3=EDATE(DATE(YEAR(PREMISSAS!$C$6),MONTH(PREMISSAS!$C$6),1),1),PREMISSAS!$C$58,0))-IF(PREMISSAS!$C$48="MEDIÇÃO CHEIA",SUMPRODUCT((AUX!$C$8:$Q$8>=D$3)*(AUX!$C$8:$Q$8<=EOMONTH(D$3,0))*$C$11:$Q$11),MAX(0,SUMPRODUCT((AUX!$C$8:$Q$8>=D$3)*(AUX!$C$8:$Q$8<=EOMONTH(D$3,0))*$C$11:$Q$11)-(PREMISSAS!$C$61*C$9/PREMISSAS!$C$8+IF(D$3=EDATE(DATE(YEAR(PREMISSAS!$C$6),MONTH(PREMISSAS!$C$6),1),1),PREMISSAS!$C$58,0))))*PREMISSAS!$C$10 -> -124986.01 | E12: =SUMPRODUCT((AUX!$C$8:$Q$8>=E$3)*(AUX!$C$8:$Q$8<=EOMONTH(E$3,0))*$C$11:$Q$11)-(PREMISSAS!$C$61*D$9/PREMISSAS!$C$8+IF(E$3=EDATE(DATE(YEAR(PREMISSAS!$C$6),MONTH(PREMISSAS!$C$6),1),1),PREMISSAS!$C$58,0))-IF(PREMISSAS!$C$48="MEDIÇÃO CHEIA",SUMPRODUCT((AUX!$C$8:$Q$8>=E$3)*(AUX!$C$8:$Q$8<=EOMONTH(E$3,0))*$C$11:$Q$11),MAX(0,SUMPRODUCT((AUX!$C$8:$Q$8>=E$3)*(AUX!$C$8:$Q$8<=EOMONTH(E$3,0))*$C$11:$Q$11)-(PREMISSAS!$C$61*D$9/PREMISSAS!$C$8+IF(E$3=EDATE(DATE(YEAR(PREMISSAS!$C$6),MONTH(PREMISSAS!$C$6),1),1),PREMISSAS!$C$58,0))))*PREMISSAS!$C$10 -> 40000 | F12: =SUMPRODUCT((AUX!$C$8:$Q$8>=F$3)*(AUX!$C$8:$Q$8<=EOMONTH(F$3,0))*$C$11:$Q$11)-(PREMISSAS!$C$61*E$9/PREMISSAS!$C$8+IF(F$3=EDATE(DATE(YEAR(PREMISSAS!$C$6),MONTH(PREMISSAS!$C$6),1),1),PREMISSAS!$C$58,0))-IF(PREMISSAS!$C$48="MEDIÇÃO CHEIA",SUMPRODUCT((AUX!$C$8:$Q$8>=F$3)*(AUX!$C$8:$Q$8<=EOMONTH(F$3,0))*$C$11:$Q$11),MAX(0,SUMPRODUCT((AUX!$C$8:$Q$8>=F$3)*(AUX!$C$8:$Q$8<=EOMONTH(F$3,0))*$C$11:$Q$11)-(PREMISSAS!$C$61*E$9/PREMISSAS!$C$8+IF(F$3=EDATE(DATE(YEAR(PREMISSAS!$C$6),MONTH(PREMISSAS!$C$6),1),1),PREMISSAS!$C$58,0))))*PREMISSAS!$C$10 -> 41333.333 | G12: =SUMPRODUCT((AUX!$C$8:$Q$8>=G$3)*(AUX!$C$8:$Q$8<=EOMONTH(G$3,0))*$C$11:$Q$11)-(PREMISSAS!$C$61*F$9/PREMISSAS!$C$8+IF(G$3=EDATE(DATE(YEAR(PREMISSAS!$C$6),MONTH(PREMISSAS!$C$6),1),1),PREMISSAS!$C$58,0))-IF(PREMISSAS!$C$48="MEDIÇÃO CHEIA",SUMPRODUCT((AUX!$C$8:$Q$8>=G$3)*(AUX!$C$8:$Q$8<=EOMONTH(G$3,0))*$C$11:$Q$11),MAX(0,SUMPRODUCT((AUX!$C$8:$Q$8>=G$3)*(AUX!$C$8:$Q$8<=EOMONTH(G$3,0))*$C$11:$Q$11)-(PREMISSAS!$C$61*F$9/PREMISSAS!$C$8+IF(G$3=EDATE(DATE(YEAR(PREMISSAS!$C$6),MONTH(PREMISSAS!$C$6),1),1),PREMISSAS!$C$58,0))))*PREMISSAS!$C$10 -> 40000 | H12: =SUMPRODUCT((AUX!$C$8:$Q$8>=H$3)*(AUX!$C$8:$Q$8<=EOMONTH(H$3,0))*$C$11:$Q$11)-(PREMISSAS!$C$61*G$9/PREMISSAS!$C$8+IF(H$3=EDATE(DATE(YEAR(PREMISSAS!$C$6),MONTH(PREMISSAS!$C$6),1),1),PREMISSAS!$C$58,0))-IF(PREMISSAS!$C$48="MEDIÇÃO CHEIA",SUMPRODUCT((AUX!$C$8:$Q$8>=H$3)*(AUX!$C$8:$Q$8<=EOMONTH(H$3,0))*$C$11:$Q$11),MAX(0,SUMPRODUCT((AUX!$C$8:$Q$8>=H$3)*(AUX!$C$8:$Q$8<=EOMONTH(H$3,0))*$C$11:$Q$11)-(PREMISSAS!$C$61*G$9/PREMISSAS!$C$8+IF(H$3=EDATE(DATE(YEAR(PREMISSAS!$C$6),MONTH(PREMISSAS!$C$6),1),1),PREMISSAS!$C$58,0))))*PREMISSAS!$C$10 -> 41333.333 | I12: =SUMPRODUCT((AUX!$C$8:$Q$8>=I$3)*(AUX!$C$8:$Q$8<=EOMONTH(I$3,0))*$C$11:$Q$11)-(PREMISSAS!$C$61*H$9/PREMISSAS!$C$8+IF(I$3=EDATE(DATE(YEAR(PREMISSAS!$C$6),MONTH(PREMISSAS!$C$6),1),1),PREMISSAS!$C$58,0))-IF(PREMISSAS!$C$48="MEDIÇÃO CHEIA",SUMPRODUCT((AUX!$C$8:$Q$8>=I$3)*(AUX!$C$8:$Q$8<=EOMONTH(I$3,0))*$C$11:$Q$11),MAX(0,SUMPRODUCT((AUX!$C$8:$Q$8>=I$3)*(AUX!$C$8:$Q$8<=EOMONTH(I$3,0))*$C$11:$Q$11)-(PREMISSAS!$C$61*H$9/PREMISSAS!$C$8+IF(I$3=EDATE(DATE(YEAR(PREMISSAS!$C$6),MONTH(PREMISSAS!$C$6),1),1),PREMISSAS!$C$58,0))))*PREMISSAS!$C$10 -> 41333.333 | J12: =SUMPRODUCT((AUX!$C$8:$Q$8>=J$3)*(AUX!$C$8:$Q$8<=EOMONTH(J$3,0))*$C$11:$Q$11)-(PREMISSAS!$C$61*I$9/PREMISSAS!$C$8+IF(J$3=EDATE(DATE(YEAR(PREMISSAS!$C$6),MONTH(PREMISSAS!$C$6),1),1),PREMISSAS!$C$58,0))-IF(PREMISSAS!$C$48="MEDIÇÃO CHEIA",SUMPRODUCT((AUX!$C$8:$Q$8>=J$3)*(AUX!$C$8:$Q$8<=EOMONTH(J$3,0))*$C$11:$Q$11),MAX(0,SUMPRODUCT((AUX!$C$8:$Q$8>=J$3)*(AUX!$C$8:$Q$8<=EOMONTH(J$3,0))*$C$11:$Q$11)-(PREMISSAS!$C$61*I$9/PREMISSAS!$C$8+IF(J$3=EDATE(DATE(YEAR(PREMISSAS!$C$6),MONTH(PREMISSAS!$C$6),1),1),PREMISSAS!$C$58,0))))*PREMISSAS!$C$10 -> 37333.333 | K12: =SUMPRODUCT((AUX!$C$8:$Q$8>=K$3)*(AUX!$C$8:$Q$8<=EOMONTH(K$3,0))*$C$11:$Q$11)-(PREMISSAS!$C$61*J$9/PREMISSAS!$C$8+IF(K$3=EDATE(DATE(YEAR(PREMISSAS!$C$6),MONTH(PREMISSAS!$C$6),1),1),PREMISSAS!$C$58,0))-IF(PREMISSAS!$C$48="MEDIÇÃO CHEIA",SUMPRODUCT((AUX!$C$8:$Q$8>=K$3)*(AUX!$C$8:$Q$8<=EOMONTH(K$3,0))*$C$11:$Q$11),MAX(0,SUMPRODUCT((AUX!$C$8:$Q$8>=K$3)*(AUX!$C$8:$Q$8<=EOMONTH(K$3,0))*$C$11:$Q$11)-(PREMISSAS!$C$61*J$9/PREMISSAS!$C$8+IF(K$3=EDATE(DATE(YEAR(PREMISSAS!$C$6),MONTH(PREMISSAS!$C$6),1),1),PREMISSAS!$C$58,0))))*PREMISSAS!$C$10 -> 41333.333 | ... Q12: =SUMPRODUCT((AUX!$C$8:$Q$8>=Q$3)*(AUX!$C$8:$Q$8<=EOMONTH(Q$3,0))*$C$11:$Q$11)-(PREMISSAS!$C$61*P$9/PREMISSAS!$C$8+IF(Q$3=EDATE(DATE(YEAR(PREMISSAS!$C$6),MONTH(PREMISSAS!$C$6),1),1),PREMISSAS!$C$58,0))-IF(PREMISSAS!$C$48="MEDIÇÃO CHEIA",SUMPRODUCT((AUX!$C$8:$Q$8>=Q$3)*(AUX!$C$8:$Q$8<=EOMONTH(Q$3,0))*$C$11:$Q$11),MAX(0,SUMPRODUCT((AUX!$C$8:$Q$8>=Q$3)*(AUX!$C$8:$Q$8<=EOMONTH(Q$3,0))*$C$11:$Q$11)-(PREMISSAS!$C$61*P$9/PREMISSAS!$C$8+IF(Q$3=EDATE(DATE(YEAR(PREMISSAS!$C$6),MONTH(PREMISSAS!$C$6),1),1),PREMISSAS!$C$58,0))))*PREMISSAS!$C$10 -> 0
B13: sai do caixa WCR (indiretos mês ant. + mob WCR) | C13: =IF(C$3=DATE(YEAR(PREMISSAS!$C$6),MONTH(PREMISSAS!$C$6),1),PREMISSAS!$C$57,0) -> 0 | D13: =PREMISSAS!$C$56*C$9/PREMISSAS!$C$8 -> 20000 | E13: =PREMISSAS!$C$56*D$9/PREMISSAS!$C$8 -> 40000 | F13: =PREMISSAS!$C$56*E$9/PREMISSAS!$C$8 -> 41333.333 | G13: =PREMISSAS!$C$56*F$9/PREMISSAS!$C$8 -> 40000 | H13: =PREMISSAS!$C$56*G$9/PREMISSAS!$C$8 -> 41333.333 | I13: =PREMISSAS!$C$56*H$9/PREMISSAS!$C$8 -> 41333.333 | J13: =PREMISSAS!$C$56*I$9/PREMISSAS!$C$8 -> 37333.333 | K13: =PREMISSAS!$C$56*J$9/PREMISSAS!$C$8 -> 41333.333 | ... Q13: =PREMISSAS!$C$56*P$9/PREMISSAS!$C$8 -> 0
B14: caixa acumulado ANTES do recebimento | C14: =-C13 -> 0 | D14: =C15-D13 -> -20000 | E14: =D15-E13 -> -184986.01 | F14: =E15-F13 -> -186319.34 | G14: =F15-G13 -> -184986.01 | H14: =G15-H13 -> -186319.34 | I14: =H15-I13 -> -186319.34 | J14: =I15-J13 -> -182319.34 | K14: =J15-K13 -> -186319.34 | ... Q14: =P15-Q13 -> -144986.01 | S14: =MAX(0,-MIN(C14:Q14)) -> 186319.34
B15: caixa acumulado APÓS o recebimento | C15: =C14+C12 -> 0 | D15: =D14+D12 -> -144986.01 | E15: =E14+E12 -> -144986.01 | F15: =F14+F12 -> -144986.01 | G15: =G14+G12 -> -144986.01 | H15: =H14+H12 -> -144986.01 | I15: =I14+I12 -> -144986.01 | J15: =J14+J12 -> -144986.01 | ... Q15: =Q14+Q12 -> -144986.01 | S15: =Q15 -> -144986.01
B17: MÉDIA — medição bruta global | C17: =PREMISSAS!$C$30*(1+PREMISSAS!$C$15)/(1-PREMISSAS!$C$10)*C$4/PREMISSAS!$C$8 -> 190611.88 | D17: =PREMISSAS!$C$30*(1+PREMISSAS!$C$15)/(1-PREMISSAS!$C$10)*D$4/PREMISSAS!$C$8 -> 714794.55 | E17: =PREMISSAS!$C$30*(1+PREMISSAS!$C$15)/(1-PREMISSAS!$C$10)*E$4/PREMISSAS!$C$8 -> 738621.04 | F17: =PREMISSAS!$C$30*(1+PREMISSAS!$C$15)/(1-PREMISSAS!$C$10)*F$4/PREMISSAS!$C$8 -> 714794.55 | G17: =PREMISSAS!$C$30*(1+PREMISSAS!$C$15)/(1-PREMISSAS!$C$10)*G$4/PREMISSAS!$C$8 -> 738621.04 | H17: =PREMISSAS!$C$30*(1+PREMISSAS!$C$15)/(1-PREMISSAS!$C$10)*H$4/PREMISSAS!$C$8 -> 738621.04 | I17: =PREMISSAS!$C$30*(1+PREMISSAS!$C$15)/(1-PREMISSAS!$C$10)*I$4/PREMISSAS!$C$8 -> 667141.58 | J17: =PREMISSAS!$C$30*(1+PREMISSAS!$C$15)/(1-PREMISSAS!$C$10)*J$4/PREMISSAS!$C$8 -> 738621.04 | ... Q17: =PREMISSAS!$C$30*(1+PREMISSAS!$C$15)/(1-PREMISSAS!$C$10)*Q$4/PREMISSAS!$C$8 -> 0
B18: entra no caixa WCR (receb − desconto − imposto) | C18: =SUMPRODUCT((AUX!$C$8:$Q$8>=C$3)*(AUX!$C$8:$Q$8<=EOMONTH(C$3,0))*$C$17:$Q$17)-0-IF(PREMISSAS!$C$48="MEDIÇÃO CHEIA",SUMPRODUCT((AUX!$C$8:$Q$8>=C$3)*(AUX!$C$8:$Q$8<=EOMONTH(C$3,0))*$C$17:$Q$17),MAX(0,SUMPRODUCT((AUX!$C$8:$Q$8>=C$3)*(AUX!$C$8:$Q$8<=EOMONTH(C$3,0))*$C$17:$Q$17)-0))*PREMISSAS!$C$10 -> 0 | D18: =SUMPRODUCT((AUX!$C$8:$Q$8>=D$3)*(AUX!$C$8:$Q$8<=EOMONTH(D$3,0))*$C$17:$Q$17)-(PREMISSAS!$C$61*C$9/PREMISSAS!$C$8+IF(D$3=EDATE(DATE(YEAR(PREMISSAS!$C$6),MONTH(PREMISSAS!$C$6),1),1),PREMISSAS!$C$58,0))-IF(PREMISSAS!$C$48="MEDIÇÃO CHEIA",SUMPRODUCT((AUX!$C$8:$Q$8>=D$3)*(AUX!$C$8:$Q$8<=EOMONTH(D$3,0))*$C$17:$Q$17),MAX(0,SUMPRODUCT((AUX!$C$8:$Q$8>=D$3)*(AUX!$C$8:$Q$8<=EOMONTH(D$3,0))*$C$17:$Q$17)-(PREMISSAS!$C$61*C$9/PREMISSAS!$C$8+IF(D$3=EDATE(DATE(YEAR(PREMISSAS!$C$6),MONTH(PREMISSAS!$C$6),1),1),PREMISSAS!$C$58,0))))*PREMISSAS!$C$10 -> -111469.89 | E18: =SUMPRODUCT((AUX!$C$8:$Q$8>=E$3)*(AUX!$C$8:$Q$8<=EOMONTH(E$3,0))*$C$17:$Q$17)-(PREMISSAS!$C$61*D$9/PREMISSAS!$C$8+IF(E$3=EDATE(DATE(YEAR(PREMISSAS!$C$6),MONTH(PREMISSAS!$C$6),1),1),PREMISSAS!$C$58,0))-IF(PREMISSAS!$C$48="MEDIÇÃO CHEIA",SUMPRODUCT((AUX!$C$8:$Q$8>=E$3)*(AUX!$C$8:$Q$8<=EOMONTH(E$3,0))*$C$17:$Q$17),MAX(0,SUMPRODUCT((AUX!$C$8:$Q$8>=E$3)*(AUX!$C$8:$Q$8<=EOMONTH(E$3,0))*$C$17:$Q$17)-(PREMISSAS!$C$61*D$9/PREMISSAS!$C$8+IF(E$3=EDATE(DATE(YEAR(PREMISSAS!$C$6),MONTH(PREMISSAS!$C$6),1),1),PREMISSAS!$C$58,0))))*PREMISSAS!$C$10 -> 90685.432 | F18: =SUMPRODUCT((AUX!$C$8:$Q$8>=F$3)*(AUX!$C$8:$Q$8<=EOMONTH(F$3,0))*$C$17:$Q$17)-(PREMISSAS!$C$61*E$9/PREMISSAS!$C$8+IF(F$3=EDATE(DATE(YEAR(PREMISSAS!$C$6),MONTH(PREMISSAS!$C$6),1),1),PREMISSAS!$C$58,0))-IF(PREMISSAS!$C$48="MEDIÇÃO CHEIA",SUMPRODUCT((AUX!$C$8:$Q$8>=F$3)*(AUX!$C$8:$Q$8<=EOMONTH(F$3,0))*$C$17:$Q$17),MAX(0,SUMPRODUCT((AUX!$C$8:$Q$8>=F$3)*(AUX!$C$8:$Q$8<=EOMONTH(F$3,0))*$C$17:$Q$17)-(PREMISSAS!$C$61*E$9/PREMISSAS!$C$8+IF(F$3=EDATE(DATE(YEAR(PREMISSAS!$C$6),MONTH(PREMISSAS!$C$6),1),1),PREMISSAS!$C$58,0))))*PREMISSAS!$C$10 -> 93708.28 | G18: =SUMPRODUCT((AUX!$C$8:$Q$8>=G$3)*(AUX!$C$8:$Q$8<=EOMONTH(G$3,0))*$C$17:$Q$17)-(PREMISSAS!$C$61*F$9/PREMISSAS!$C$8+IF(G$3=EDATE(DATE(YEAR(PREMISSAS!$C$6),MONTH(PREMISSAS!$C$6),1),1),PREMISSAS!$C$58,0))-IF(PREMISSAS!$C$48="MEDIÇÃO CHEIA",SUMPRODUCT((AUX!$C$8:$Q$8>=G$3)*(AUX!$C$8:$Q$8<=EOMONTH(G$3,0))*$C$17:$Q$17),MAX(0,SUMPRODUCT((AUX!$C$8:$Q$8>=G$3)*(AUX!$C$8:$Q$8<=EOMONTH(G$3,0))*$C$17:$Q$17)-(PREMISSAS!$C$61*F$9/PREMISSAS!$C$8+IF(G$3=EDATE(DATE(YEAR(PREMISSAS!$C$6),MONTH(PREMISSAS!$C$6),1),1),PREMISSAS!$C$58,0))))*PREMISSAS!$C$10 -> 90685.432 | H18: =SUMPRODUCT((AUX!$C$8:$Q$8>=H$3)*(AUX!$C$8:$Q$8<=EOMONTH(H$3,0))*$C$17:$Q$17)-(PREMISSAS!$C$61*G$9/PREMISSAS!$C$8+IF(H$3=EDATE(DATE(YEAR(PREMISSAS!$C$6),MONTH(PREMISSAS!$C$6),1),1),PREMISSAS!$C$58,0))-IF(PREMISSAS!$C$48="MEDIÇÃO CHEIA",SUMPRODUCT((AUX!$C$8:$Q$8>=H$3)*(AUX!$C$8:$Q$8<=EOMONTH(H$3,0))*$C$17:$Q$17),MAX(0,SUMPRODUCT((AUX!$C$8:$Q$8>=H$3)*(AUX!$C$8:$Q$8<=EOMONTH(H$3,0))*$C$17:$Q$17)-(PREMISSAS!$C$61*G$9/PREMISSAS!$C$8+IF(H$3=EDATE(DATE(YEAR(PREMISSAS!$C$6),MONTH(PREMISSAS!$C$6),1),1),PREMISSAS!$C$58,0))))*PREMISSAS!$C$10 -> 93708.28 | I18: =SUMPRODUCT((AUX!$C$8:$Q$8>=I$3)*(AUX!$C$8:$Q$8<=EOMONTH(I$3,0))*$C$17:$Q$17)-(PREMISSAS!$C$61*H$9/PREMISSAS!$C$8+IF(I$3=EDATE(DATE(YEAR(PREMISSAS!$C$6),MONTH(PREMISSAS!$C$6),1),1),PREMISSAS!$C$58,0))-IF(PREMISSAS!$C$48="MEDIÇÃO CHEIA",SUMPRODUCT((AUX!$C$8:$Q$8>=I$3)*(AUX!$C$8:$Q$8<=EOMONTH(I$3,0))*$C$17:$Q$17),MAX(0,SUMPRODUCT((AUX!$C$8:$Q$8>=I$3)*(AUX!$C$8:$Q$8<=EOMONTH(I$3,0))*$C$17:$Q$17)-(PREMISSAS!$C$61*H$9/PREMISSAS!$C$8+IF(I$3=EDATE(DATE(YEAR(PREMISSAS!$C$6),MONTH(PREMISSAS!$C$6),1),1),PREMISSAS!$C$58,0))))*PREMISSAS!$C$10 -> 93708.28 | J18: =SUMPRODUCT((AUX!$C$8:$Q$8>=J$3)*(AUX!$C$8:$Q$8<=EOMONTH(J$3,0))*$C$17:$Q$17)-(PREMISSAS!$C$61*I$9/PREMISSAS!$C$8+IF(J$3=EDATE(DATE(YEAR(PREMISSAS!$C$6),MONTH(PREMISSAS!$C$6),1),1),PREMISSAS!$C$58,0))-IF(PREMISSAS!$C$48="MEDIÇÃO CHEIA",SUMPRODUCT((AUX!$C$8:$Q$8>=J$3)*(AUX!$C$8:$Q$8<=EOMONTH(J$3,0))*$C$17:$Q$17),MAX(0,SUMPRODUCT((AUX!$C$8:$Q$8>=J$3)*(AUX!$C$8:$Q$8<=EOMONTH(J$3,0))*$C$17:$Q$17)-(PREMISSAS!$C$61*I$9/PREMISSAS!$C$8+IF(J$3=EDATE(DATE(YEAR(PREMISSAS!$C$6),MONTH(PREMISSAS!$C$6),1),1),PREMISSAS!$C$58,0))))*PREMISSAS!$C$10 -> 84639.737 | K18: =SUMPRODUCT((AUX!$C$8:$Q$8>=K$3)*(AUX!$C$8:$Q$8<=EOMONTH(K$3,0))*$C$17:$Q$17)-(PREMISSAS!$C$61*J$9/PREMISSAS!$C$8+IF(K$3=EDATE(DATE(YEAR(PREMISSAS!$C$6),MONTH(PREMISSAS!$C$6),1),1),PREMISSAS!$C$58,0))-IF(PREMISSAS!$C$48="MEDIÇÃO CHEIA",SUMPRODUCT((AUX!$C$8:$Q$8>=K$3)*(AUX!$C$8:$Q$8<=EOMONTH(K$3,0))*$C$17:$Q$17),MAX(0,SUMPRODUCT((AUX!$C$8:$Q$8>=K$3)*(AUX!$C$8:$Q$8<=EOMONTH(K$3,0))*$C$17:$Q$17)-(PREMISSAS!$C$61*J$9/PREMISSAS!$C$8+IF(K$3=EDATE(DATE(YEAR(PREMISSAS!$C$6),MONTH(PREMISSAS!$C$6),1),1),PREMISSAS!$C$58,0))))*PREMISSAS!$C$10 -> 93708.28 | ... Q18: =SUMPRODUCT((AUX!$C$8:$Q$8>=Q$3)*(AUX!$C$8:$Q$8<=EOMONTH(Q$3,0))*$C$17:$Q$17)-(PREMISSAS!$C$61*P$9/PREMISSAS!$C$8+IF(Q$3=EDATE(DATE(YEAR(PREMISSAS!$C$6),MONTH(PREMISSAS!$C$6),1),1),PREMISSAS!$C$58,0))-IF(PREMISSAS!$C$48="MEDIÇÃO CHEIA",SUMPRODUCT((AUX!$C$8:$Q$8>=Q$3)*(AUX!$C$8:$Q$8<=EOMONTH(Q$3,0))*$C$17:$Q$17),MAX(0,SUMPRODUCT((AUX!$C$8:$Q$8>=Q$3)*(AUX!$C$8:$Q$8<=EOMONTH(Q$3,0))*$C$17:$Q$17)-(PREMISSAS!$C$61*P$9/PREMISSAS!$C$8+IF(Q$3=EDATE(DATE(YEAR(PREMISSAS!$C$6),MONTH(PREMISSAS!$C$6),1),1),PREMISSAS!$C$58,0))))*PREMISSAS!$C$10 -> 0
B19: sai do caixa WCR (indiretos mês ant. + mob WCR) | C19: =IF(C$3=DATE(YEAR(PREMISSAS!$C$6),MONTH(PREMISSAS!$C$6),1),PREMISSAS!$C$57,0) -> 0 | D19: =PREMISSAS!$C$56*C$9/PREMISSAS!$C$8 -> 20000 | E19: =PREMISSAS!$C$56*D$9/PREMISSAS!$C$8 -> 40000 | F19: =PREMISSAS!$C$56*E$9/PREMISSAS!$C$8 -> 41333.333 | G19: =PREMISSAS!$C$56*F$9/PREMISSAS!$C$8 -> 40000 | H19: =PREMISSAS!$C$56*G$9/PREMISSAS!$C$8 -> 41333.333 | I19: =PREMISSAS!$C$56*H$9/PREMISSAS!$C$8 -> 41333.333 | J19: =PREMISSAS!$C$56*I$9/PREMISSAS!$C$8 -> 37333.333 | K19: =PREMISSAS!$C$56*J$9/PREMISSAS!$C$8 -> 41333.333 | ... Q19: =PREMISSAS!$C$56*P$9/PREMISSAS!$C$8 -> 0
B20: caixa acumulado ANTES do recebimento | C20: =-C19 -> 0 | D20: =C21-D19 -> -20000 | E20: =D21-E19 -> -171469.89 | F20: =E21-F19 -> -122117.79 | G20: =F21-G19 -> -68409.514 | H20: =G21-H19 -> -19057.416 | I20: =H21-I19 -> 33317.531 | J20: =I21-J19 -> 89692.477 | K20: =J21-K19 -> 132998.88 | ... Q20: =P21-Q19 -> 432827.92 | S20: =MAX(0,-MIN(C20:Q20)) -> 171469.89
B21: caixa acumulado APÓS o recebimento | C21: =C20+C18 -> 0 | D21: =D20+D18 -> -131469.89 | E21: =E20+E18 -> -80784.461 | F21: =F20+F18 -> -28409.514 | G21: =G20+G18 -> 22275.918 | H21: =H20+H18 -> 74650.864 | I21: =I20+I18 -> 127025.81 | J21: =J20+J18 -> 174332.21 | ... Q21: =Q20+Q18 -> 432827.92 | S21: =Q21 -> 432827.92
B23: BOA — medição bruta global | C23: =PREMISSAS!$C$30*(1+PREMISSAS!$C$16)/(1-PREMISSAS!$C$10)*C$4/PREMISSAS!$C$8 -> 199276.06 | D23: =PREMISSAS!$C$30*(1+PREMISSAS!$C$16)/(1-PREMISSAS!$C$10)*D$4/PREMISSAS!$C$8 -> 747285.22 | E23: =PREMISSAS!$C$30*(1+PREMISSAS!$C$16)/(1-PREMISSAS!$C$10)*E$4/PREMISSAS!$C$8 -> 772194.72 | F23: =PREMISSAS!$C$30*(1+PREMISSAS!$C$16)/(1-PREMISSAS!$C$10)*F$4/PREMISSAS!$C$8 -> 747285.22 | G23: =PREMISSAS!$C$30*(1+PREMISSAS!$C$16)/(1-PREMISSAS!$C$10)*G$4/PREMISSAS!$C$8 -> 772194.72 | H23: =PREMISSAS!$C$30*(1+PREMISSAS!$C$16)/(1-PREMISSAS!$C$10)*H$4/PREMISSAS!$C$8 -> 772194.72 | I23: =PREMISSAS!$C$30*(1+PREMISSAS!$C$16)/(1-PREMISSAS!$C$10)*I$4/PREMISSAS!$C$8 -> 697466.2 | J23: =PREMISSAS!$C$30*(1+PREMISSAS!$C$16)/(1-PREMISSAS!$C$10)*J$4/PREMISSAS!$C$8 -> 772194.72 | ... Q23: =PREMISSAS!$C$30*(1+PREMISSAS!$C$16)/(1-PREMISSAS!$C$10)*Q$4/PREMISSAS!$C$8 -> 0
B24: entra no caixa WCR (receb − desconto − imposto) | C24: =SUMPRODUCT((AUX!$C$8:$Q$8>=C$3)*(AUX!$C$8:$Q$8<=EOMONTH(C$3,0))*$C$23:$Q$23)-0-IF(PREMISSAS!$C$48="MEDIÇÃO CHEIA",SUMPRODUCT((AUX!$C$8:$Q$8>=C$3)*(AUX!$C$8:$Q$8<=EOMONTH(C$3,0))*$C$23:$Q$23),MAX(0,SUMPRODUCT((AUX!$C$8:$Q$8>=C$3)*(AUX!$C$8:$Q$8<=EOMONTH(C$3,0))*$C$23:$Q$23)-0))*PREMISSAS!$C$10 -> 0 | D24: =SUMPRODUCT((AUX!$C$8:$Q$8>=D$3)*(AUX!$C$8:$Q$8<=EOMONTH(D$3,0))*$C$23:$Q$23)-(PREMISSAS!$C$61*C$9/PREMISSAS!$C$8+IF(D$3=EDATE(DATE(YEAR(PREMISSAS!$C$6),MONTH(PREMISSAS!$C$6),1),1),PREMISSAS!$C$58,0))-IF(PREMISSAS!$C$48="MEDIÇÃO CHEIA",SUMPRODUCT((AUX!$C$8:$Q$8>=D$3)*(AUX!$C$8:$Q$8<=EOMONTH(D$3,0))*$C$23:$Q$23),MAX(0,SUMPRODUCT((AUX!$C$8:$Q$8>=D$3)*(AUX!$C$8:$Q$8<=EOMONTH(D$3,0))*$C$23:$Q$23)-(PREMISSAS!$C$61*C$9/PREMISSAS!$C$8+IF(D$3=EDATE(DATE(YEAR(PREMISSAS!$C$6),MONTH(PREMISSAS!$C$6),1),1),PREMISSAS!$C$58,0))))*PREMISSAS!$C$10 -> -104711.84 | E24: =SUMPRODUCT((AUX!$C$8:$Q$8>=E$3)*(AUX!$C$8:$Q$8<=EOMONTH(E$3,0))*$C$23:$Q$23)-(PREMISSAS!$C$61*D$9/PREMISSAS!$C$8+IF(E$3=EDATE(DATE(YEAR(PREMISSAS!$C$6),MONTH(PREMISSAS!$C$6),1),1),PREMISSAS!$C$58,0))-IF(PREMISSAS!$C$48="MEDIÇÃO CHEIA",SUMPRODUCT((AUX!$C$8:$Q$8>=E$3)*(AUX!$C$8:$Q$8<=EOMONTH(E$3,0))*$C$23:$Q$23),MAX(0,SUMPRODUCT((AUX!$C$8:$Q$8>=E$3)*(AUX!$C$8:$Q$8<=EOMONTH(E$3,0))*$C$23:$Q$23)-(PREMISSAS!$C$61*D$9/PREMISSAS!$C$8+IF(E$3=EDATE(DATE(YEAR(PREMISSAS!$C$6),MONTH(PREMISSAS!$C$6),1),1),PREMISSAS!$C$58,0))))*PREMISSAS!$C$10 -> 116028.15 | F24: =SUMPRODUCT((AUX!$C$8:$Q$8>=F$3)*(AUX!$C$8:$Q$8<=EOMONTH(F$3,0))*$C$23:$Q$23)-(PREMISSAS!$C$61*E$9/PREMISSAS!$C$8+IF(F$3=EDATE(DATE(YEAR(PREMISSAS!$C$6),MONTH(PREMISSAS!$C$6),1),1),PREMISSAS!$C$58,0))-IF(PREMISSAS!$C$48="MEDIÇÃO CHEIA",SUMPRODUCT((AUX!$C$8:$Q$8>=F$3)*(AUX!$C$8:$Q$8<=EOMONTH(F$3,0))*$C$23:$Q$23),MAX(0,SUMPRODUCT((AUX!$C$8:$Q$8>=F$3)*(AUX!$C$8:$Q$8<=EOMONTH(F$3,0))*$C$23:$Q$23)-(PREMISSAS!$C$61*E$9/PREMISSAS!$C$8+IF(F$3=EDATE(DATE(YEAR(PREMISSAS!$C$6),MONTH(PREMISSAS!$C$6),1),1),PREMISSAS!$C$58,0))))*PREMISSAS!$C$10 -> 119895.75 | G24: =SUMPRODUCT((AUX!$C$8:$Q$8>=G$3)*(AUX!$C$8:$Q$8<=EOMONTH(G$3,0))*$C$23:$Q$23)-(PREMISSAS!$C$61*F$9/PREMISSAS!$C$8+IF(G$3=EDATE(DATE(YEAR(PREMISSAS!$C$6),MONTH(PREMISSAS!$C$6),1),1),PREMISSAS!$C$58,0))-IF(PREMISSAS!$C$48="MEDIÇÃO CHEIA",SUMPRODUCT((AUX!$C$8:$Q$8>=G$3)*(AUX!$C$8:$Q$8<=EOMONTH(G$3,0))*$C$23:$Q$23),MAX(0,SUMPRODUCT((AUX!$C$8:$Q$8>=G$3)*(AUX!$C$8:$Q$8<=EOMONTH(G$3,0))*$C$23:$Q$23)-(PREMISSAS!$C$61*F$9/PREMISSAS!$C$8+IF(G$3=EDATE(DATE(YEAR(PREMISSAS!$C$6),MONTH(PREMISSAS!$C$6),1),1),PREMISSAS!$C$58,0))))*PREMISSAS!$C$10 -> 116028.15 | H24: =SUMPRODUCT((AUX!$C$8:$Q$8>=H$3)*(AUX!$C$8:$Q$8<=EOMONTH(H$3,0))*$C$23:$Q$23)-(PREMISSAS!$C$61*G$9/PREMISSAS!$C$8+IF(H$3=EDATE(DATE(YEAR(PREMISSAS!$C$6),MONTH(PREMISSAS!$C$6),1),1),PREMISSAS!$C$58,0))-IF(PREMISSAS!$C$48="MEDIÇÃO CHEIA",SUMPRODUCT((AUX!$C$8:$Q$8>=H$3)*(AUX!$C$8:$Q$8<=EOMONTH(H$3,0))*$C$23:$Q$23),MAX(0,SUMPRODUCT((AUX!$C$8:$Q$8>=H$3)*(AUX!$C$8:$Q$8<=EOMONTH(H$3,0))*$C$23:$Q$23)-(PREMISSAS!$C$61*G$9/PREMISSAS!$C$8+IF(H$3=EDATE(DATE(YEAR(PREMISSAS!$C$6),MONTH(PREMISSAS!$C$6),1),1),PREMISSAS!$C$58,0))))*PREMISSAS!$C$10 -> 119895.75 | I24: =SUMPRODUCT((AUX!$C$8:$Q$8>=I$3)*(AUX!$C$8:$Q$8<=EOMONTH(I$3,0))*$C$23:$Q$23)-(PREMISSAS!$C$61*H$9/PREMISSAS!$C$8+IF(I$3=EDATE(DATE(YEAR(PREMISSAS!$C$6),MONTH(PREMISSAS!$C$6),1),1),PREMISSAS!$C$58,0))-IF(PREMISSAS!$C$48="MEDIÇÃO CHEIA",SUMPRODUCT((AUX!$C$8:$Q$8>=I$3)*(AUX!$C$8:$Q$8<=EOMONTH(I$3,0))*$C$23:$Q$23),MAX(0,SUMPRODUCT((AUX!$C$8:$Q$8>=I$3)*(AUX!$C$8:$Q$8<=EOMONTH(I$3,0))*$C$23:$Q$23)-(PREMISSAS!$C$61*H$9/PREMISSAS!$C$8+IF(I$3=EDATE(DATE(YEAR(PREMISSAS!$C$6),MONTH(PREMISSAS!$C$6),1),1),PREMISSAS!$C$58,0))))*PREMISSAS!$C$10 -> 119895.75 | J24: =SUMPRODUCT((AUX!$C$8:$Q$8>=J$3)*(AUX!$C$8:$Q$8<=EOMONTH(J$3,0))*$C$23:$Q$23)-(PREMISSAS!$C$61*I$9/PREMISSAS!$C$8+IF(J$3=EDATE(DATE(YEAR(PREMISSAS!$C$6),MONTH(PREMISSAS!$C$6),1),1),PREMISSAS!$C$58,0))-IF(PREMISSAS!$C$48="MEDIÇÃO CHEIA",SUMPRODUCT((AUX!$C$8:$Q$8>=J$3)*(AUX!$C$8:$Q$8<=EOMONTH(J$3,0))*$C$23:$Q$23),MAX(0,SUMPRODUCT((AUX!$C$8:$Q$8>=J$3)*(AUX!$C$8:$Q$8<=EOMONTH(J$3,0))*$C$23:$Q$23)-(PREMISSAS!$C$61*I$9/PREMISSAS!$C$8+IF(J$3=EDATE(DATE(YEAR(PREMISSAS!$C$6),MONTH(PREMISSAS!$C$6),1),1),PREMISSAS!$C$58,0))))*PREMISSAS!$C$10 -> 108292.94 | K24: =SUMPRODUCT((AUX!$C$8:$Q$8>=K$3)*(AUX!$C$8:$Q$8<=EOMONTH(K$3,0))*$C$23:$Q$23)-(PREMISSAS!$C$61*J$9/PREMISSAS!$C$8+IF(K$3=EDATE(DATE(YEAR(PREMISSAS!$C$6),MONTH(PREMISSAS!$C$6),1),1),PREMISSAS!$C$58,0))-IF(PREMISSAS!$C$48="MEDIÇÃO CHEIA",SUMPRODUCT((AUX!$C$8:$Q$8>=K$3)*(AUX!$C$8:$Q$8<=EOMONTH(K$3,0))*$C$23:$Q$23),MAX(0,SUMPRODUCT((AUX!$C$8:$Q$8>=K$3)*(AUX!$C$8:$Q$8<=EOMONTH(K$3,0))*$C$23:$Q$23)-(PREMISSAS!$C$61*J$9/PREMISSAS!$C$8+IF(K$3=EDATE(DATE(YEAR(PREMISSAS!$C$6),MONTH(PREMISSAS!$C$6),1),1),PREMISSAS!$C$58,0))))*PREMISSAS!$C$10 -> 119895.75 | ... Q24: =SUMPRODUCT((AUX!$C$8:$Q$8>=Q$3)*(AUX!$C$8:$Q$8<=EOMONTH(Q$3,0))*$C$23:$Q$23)-(PREMISSAS!$C$61*P$9/PREMISSAS!$C$8+IF(Q$3=EDATE(DATE(YEAR(PREMISSAS!$C$6),MONTH(PREMISSAS!$C$6),1),1),PREMISSAS!$C$58,0))-IF(PREMISSAS!$C$48="MEDIÇÃO CHEIA",SUMPRODUCT((AUX!$C$8:$Q$8>=Q$3)*(AUX!$C$8:$Q$8<=EOMONTH(Q$3,0))*$C$23:$Q$23),MAX(0,SUMPRODUCT((AUX!$C$8:$Q$8>=Q$3)*(AUX!$C$8:$Q$8<=EOMONTH(Q$3,0))*$C$23:$Q$23)-(PREMISSAS!$C$61*P$9/PREMISSAS!$C$8+IF(Q$3=EDATE(DATE(YEAR(PREMISSAS!$C$6),MONTH(PREMISSAS!$C$6),1),1),PREMISSAS!$C$58,0))))*PREMISSAS!$C$10 -> 0
B25: sai do caixa WCR (indiretos mês ant. + mob WCR) | C25: =IF(C$3=DATE(YEAR(PREMISSAS!$C$6),MONTH(PREMISSAS!$C$6),1),PREMISSAS!$C$57,0) -> 0 | D25: =PREMISSAS!$C$56*C$9/PREMISSAS!$C$8 -> 20000 | E25: =PREMISSAS!$C$56*D$9/PREMISSAS!$C$8 -> 40000 | F25: =PREMISSAS!$C$56*E$9/PREMISSAS!$C$8 -> 41333.333 | G25: =PREMISSAS!$C$56*F$9/PREMISSAS!$C$8 -> 40000 | H25: =PREMISSAS!$C$56*G$9/PREMISSAS!$C$8 -> 41333.333 | I25: =PREMISSAS!$C$56*H$9/PREMISSAS!$C$8 -> 41333.333 | J25: =PREMISSAS!$C$56*I$9/PREMISSAS!$C$8 -> 37333.333 | K25: =PREMISSAS!$C$56*J$9/PREMISSAS!$C$8 -> 41333.333 | ... Q25: =PREMISSAS!$C$56*P$9/PREMISSAS!$C$8 -> 0
B26: caixa acumulado ANTES do recebimento | C26: =-C25 -> 0 | D26: =C27-D25 -> -20000 | E26: =D27-E25 -> -164711.84 | F26: =E27-F25 -> -90017.021 | G26: =F27-G25 -> -10121.268 | H26: =G27-H25 -> 64573.547 | I26: =H27-I25 -> 143135.97 | J26: =I27-J25 -> 225698.39 | K26: =J27-K25 -> 292657.99 | ... Q26: =P27-Q25 -> 721734.88 | S26: =MAX(0,-MIN(C26:Q26)) -> 164711.84
B27: caixa acumulado APÓS o recebimento | C27: =C26+C24 -> 0 | D27: =D26+D24 -> -124711.84 | E27: =E26+E24 -> -48683.687 | F27: =F26+F24 -> 29878.732 | G27: =G26+G24 -> 105906.88 | H27: =H26+H24 -> 184469.3 | I27: =I26+I24 -> 263031.72 | J27: =J26+J24 -> 333991.32 | ... Q27: =Q26+Q24 -> 721734.88 | S27: =Q27 -> 721734.88
B29: ÓTIMA — medição bruta global | C29: =PREMISSAS!$C$30*(1+PREMISSAS!$C$17)/(1-PREMISSAS!$C$10)*C$4/PREMISSAS!$C$8 -> 207940.23 | D29: =PREMISSAS!$C$30*(1+PREMISSAS!$C$17)/(1-PREMISSAS!$C$10)*D$4/PREMISSAS!$C$8 -> 779775.88 | E29: =PREMISSAS!$C$30*(1+PREMISSAS!$C$17)/(1-PREMISSAS!$C$10)*E$4/PREMISSAS!$C$8 -> 805768.41 | F29: =PREMISSAS!$C$30*(1+PREMISSAS!$C$17)/(1-PREMISSAS!$C$10)*F$4/PREMISSAS!$C$8 -> 779775.88 | G29: =PREMISSAS!$C$30*(1+PREMISSAS!$C$17)/(1-PREMISSAS!$C$10)*G$4/PREMISSAS!$C$8 -> 805768.41 | H29: =PREMISSAS!$C$30*(1+PREMISSAS!$C$17)/(1-PREMISSAS!$C$10)*H$4/PREMISSAS!$C$8 -> 805768.41 | I29: =PREMISSAS!$C$30*(1+PREMISSAS!$C$17)/(1-PREMISSAS!$C$10)*I$4/PREMISSAS!$C$8 -> 727790.82 | J29: =PREMISSAS!$C$30*(1+PREMISSAS!$C$17)/(1-PREMISSAS!$C$10)*J$4/PREMISSAS!$C$8 -> 805768.41 | ... Q29: =PREMISSAS!$C$30*(1+PREMISSAS!$C$17)/(1-PREMISSAS!$C$10)*Q$4/PREMISSAS!$C$8 -> 0
B30: entra no caixa WCR (receb − desconto − imposto) | C30: =SUMPRODUCT((AUX!$C$8:$Q$8>=C$3)*(AUX!$C$8:$Q$8<=EOMONTH(C$3,0))*$C$29:$Q$29)-0-IF(PREMISSAS!$C$48="MEDIÇÃO CHEIA",SUMPRODUCT((AUX!$C$8:$Q$8>=C$3)*(AUX!$C$8:$Q$8<=EOMONTH(C$3,0))*$C$29:$Q$29),MAX(0,SUMPRODUCT((AUX!$C$8:$Q$8>=C$3)*(AUX!$C$8:$Q$8<=EOMONTH(C$3,0))*$C$29:$Q$29)-0))*PREMISSAS!$C$10 -> 0 | D30: =SUMPRODUCT((AUX!$C$8:$Q$8>=D$3)*(AUX!$C$8:$Q$8<=EOMONTH(D$3,0))*$C$29:$Q$29)-(PREMISSAS!$C$61*C$9/PREMISSAS!$C$8+IF(D$3=EDATE(DATE(YEAR(PREMISSAS!$C$6),MONTH(PREMISSAS!$C$6),1),1),PREMISSAS!$C$58,0))-IF(PREMISSAS!$C$48="MEDIÇÃO CHEIA",SUMPRODUCT((AUX!$C$8:$Q$8>=D$3)*(AUX!$C$8:$Q$8<=EOMONTH(D$3,0))*$C$29:$Q$29),MAX(0,SUMPRODUCT((AUX!$C$8:$Q$8>=D$3)*(AUX!$C$8:$Q$8<=EOMONTH(D$3,0))*$C$29:$Q$29)-(PREMISSAS!$C$61*C$9/PREMISSAS!$C$8+IF(D$3=EDATE(DATE(YEAR(PREMISSAS!$C$6),MONTH(PREMISSAS!$C$6),1),1),PREMISSAS!$C$58,0))))*PREMISSAS!$C$10 -> -97953.778 | E30: =SUMPRODUCT((AUX!$C$8:$Q$8>=E$3)*(AUX!$C$8:$Q$8<=EOMONTH(E$3,0))*$C$29:$Q$29)-(PREMISSAS!$C$61*D$9/PREMISSAS!$C$8+IF(E$3=EDATE(DATE(YEAR(PREMISSAS!$C$6),MONTH(PREMISSAS!$C$6),1),1),PREMISSAS!$C$58,0))-IF(PREMISSAS!$C$48="MEDIÇÃO CHEIA",SUMPRODUCT((AUX!$C$8:$Q$8>=E$3)*(AUX!$C$8:$Q$8<=EOMONTH(E$3,0))*$C$29:$Q$29),MAX(0,SUMPRODUCT((AUX!$C$8:$Q$8>=E$3)*(AUX!$C$8:$Q$8<=EOMONTH(E$3,0))*$C$29:$Q$29)-(PREMISSAS!$C$61*D$9/PREMISSAS!$C$8+IF(E$3=EDATE(DATE(YEAR(PREMISSAS!$C$6),MONTH(PREMISSAS!$C$6),1),1),PREMISSAS!$C$58,0))))*PREMISSAS!$C$10 -> 141370.86 | F30: =SUMPRODUCT((AUX!$C$8:$Q$8>=F$3)*(AUX!$C$8:$Q$8<=EOMONTH(F$3,0))*$C$29:$Q$29)-(PREMISSAS!$C$61*E$9/PREMISSAS!$C$8+IF(F$3=EDATE(DATE(YEAR(PREMISSAS!$C$6),MONTH(PREMISSAS!$C$6),1),1),PREMISSAS!$C$58,0))-IF(PREMISSAS!$C$48="MEDIÇÃO CHEIA",SUMPRODUCT((AUX!$C$8:$Q$8>=F$3)*(AUX!$C$8:$Q$8<=EOMONTH(F$3,0))*$C$29:$Q$29),MAX(0,SUMPRODUCT((AUX!$C$8:$Q$8>=F$3)*(AUX!$C$8:$Q$8<=EOMONTH(F$3,0))*$C$29:$Q$29)-(PREMISSAS!$C$61*E$9/PREMISSAS!$C$8+IF(F$3=EDATE(DATE(YEAR(PREMISSAS!$C$6),MONTH(PREMISSAS!$C$6),1),1),PREMISSAS!$C$58,0))))*PREMISSAS!$C$10 -> 146083.23 | G30: =SUMPRODUCT((AUX!$C$8:$Q$8>=G$3)*(AUX!$C$8:$Q$8<=EOMONTH(G$3,0))*$C$29:$Q$29)-(PREMISSAS!$C$61*F$9/PREMISSAS!$C$8+IF(G$3=EDATE(DATE(YEAR(PREMISSAS!$C$6),MONTH(PREMISSAS!$C$6),1),1),PREMISSAS!$C$58,0))-IF(PREMISSAS!$C$48="MEDIÇÃO CHEIA",SUMPRODUCT((AUX!$C$8:$Q$8>=G$3)*(AUX!$C$8:$Q$8<=EOMONTH(G$3,0))*$C$29:$Q$29),MAX(0,SUMPRODUCT((AUX!$C$8:$Q$8>=G$3)*(AUX!$C$8:$Q$8<=EOMONTH(G$3,0))*$C$29:$Q$29)-(PREMISSAS!$C$61*F$9/PREMISSAS!$C$8+IF(G$3=EDATE(DATE(YEAR(PREMISSAS!$C$6),MONTH(PREMISSAS!$C$6),1),1),PREMISSAS!$C$58,0))))*PREMISSAS!$C$10 -> 141370.86 | H30: =SUMPRODUCT((AUX!$C$8:$Q$8>=H$3)*(AUX!$C$8:$Q$8<=EOMONTH(H$3,0))*$C$29:$Q$29)-(PREMISSAS!$C$61*G$9/PREMISSAS!$C$8+IF(H$3=EDATE(DATE(YEAR(PREMISSAS!$C$6),MONTH(PREMISSAS!$C$6),1),1),PREMISSAS!$C$58,0))-IF(PREMISSAS!$C$48="MEDIÇÃO CHEIA",SUMPRODUCT((AUX!$C$8:$Q$8>=H$3)*(AUX!$C$8:$Q$8<=EOMONTH(H$3,0))*$C$29:$Q$29),MAX(0,SUMPRODUCT((AUX!$C$8:$Q$8>=H$3)*(AUX!$C$8:$Q$8<=EOMONTH(H$3,0))*$C$29:$Q$29)-(PREMISSAS!$C$61*G$9/PREMISSAS!$C$8+IF(H$3=EDATE(DATE(YEAR(PREMISSAS!$C$6),MONTH(PREMISSAS!$C$6),1),1),PREMISSAS!$C$58,0))))*PREMISSAS!$C$10 -> 146083.23 | I30: =SUMPRODUCT((AUX!$C$8:$Q$8>=I$3)*(AUX!$C$8:$Q$8<=EOMONTH(I$3,0))*$C$29:$Q$29)-(PREMISSAS!$C$61*H$9/PREMISSAS!$C$8+IF(I$3=EDATE(DATE(YEAR(PREMISSAS!$C$6),MONTH(PREMISSAS!$C$6),1),1),PREMISSAS!$C$58,0))-IF(PREMISSAS!$C$48="MEDIÇÃO CHEIA",SUMPRODUCT((AUX!$C$8:$Q$8>=I$3)*(AUX!$C$8:$Q$8<=EOMONTH(I$3,0))*$C$29:$Q$29),MAX(0,SUMPRODUCT((AUX!$C$8:$Q$8>=I$3)*(AUX!$C$8:$Q$8<=EOMONTH(I$3,0))*$C$29:$Q$29)-(PREMISSAS!$C$61*H$9/PREMISSAS!$C$8+IF(I$3=EDATE(DATE(YEAR(PREMISSAS!$C$6),MONTH(PREMISSAS!$C$6),1),1),PREMISSAS!$C$58,0))))*PREMISSAS!$C$10 -> 146083.23 | J30: =SUMPRODUCT((AUX!$C$8:$Q$8>=J$3)*(AUX!$C$8:$Q$8<=EOMONTH(J$3,0))*$C$29:$Q$29)-(PREMISSAS!$C$61*I$9/PREMISSAS!$C$8+IF(J$3=EDATE(DATE(YEAR(PREMISSAS!$C$6),MONTH(PREMISSAS!$C$6),1),1),PREMISSAS!$C$58,0))-IF(PREMISSAS!$C$48="MEDIÇÃO CHEIA",SUMPRODUCT((AUX!$C$8:$Q$8>=J$3)*(AUX!$C$8:$Q$8<=EOMONTH(J$3,0))*$C$29:$Q$29),MAX(0,SUMPRODUCT((AUX!$C$8:$Q$8>=J$3)*(AUX!$C$8:$Q$8<=EOMONTH(J$3,0))*$C$29:$Q$29)-(PREMISSAS!$C$61*I$9/PREMISSAS!$C$8+IF(J$3=EDATE(DATE(YEAR(PREMISSAS!$C$6),MONTH(PREMISSAS!$C$6),1),1),PREMISSAS!$C$58,0))))*PREMISSAS!$C$10 -> 131946.14 | K30: =SUMPRODUCT((AUX!$C$8:$Q$8>=K$3)*(AUX!$C$8:$Q$8<=EOMONTH(K$3,0))*$C$29:$Q$29)-(PREMISSAS!$C$61*J$9/PREMISSAS!$C$8+IF(K$3=EDATE(DATE(YEAR(PREMISSAS!$C$6),MONTH(PREMISSAS!$C$6),1),1),PREMISSAS!$C$58,0))-IF(PREMISSAS!$C$48="MEDIÇÃO CHEIA",SUMPRODUCT((AUX!$C$8:$Q$8>=K$3)*(AUX!$C$8:$Q$8<=EOMONTH(K$3,0))*$C$29:$Q$29),MAX(0,SUMPRODUCT((AUX!$C$8:$Q$8>=K$3)*(AUX!$C$8:$Q$8<=EOMONTH(K$3,0))*$C$29:$Q$29)-(PREMISSAS!$C$61*J$9/PREMISSAS!$C$8+IF(K$3=EDATE(DATE(YEAR(PREMISSAS!$C$6),MONTH(PREMISSAS!$C$6),1),1),PREMISSAS!$C$58,0))))*PREMISSAS!$C$10 -> 146083.23 | ... Q30: =SUMPRODUCT((AUX!$C$8:$Q$8>=Q$3)*(AUX!$C$8:$Q$8<=EOMONTH(Q$3,0))*$C$29:$Q$29)-(PREMISSAS!$C$61*P$9/PREMISSAS!$C$8+IF(Q$3=EDATE(DATE(YEAR(PREMISSAS!$C$6),MONTH(PREMISSAS!$C$6),1),1),PREMISSAS!$C$58,0))-IF(PREMISSAS!$C$48="MEDIÇÃO CHEIA",SUMPRODUCT((AUX!$C$8:$Q$8>=Q$3)*(AUX!$C$8:$Q$8<=EOMONTH(Q$3,0))*$C$29:$Q$29),MAX(0,SUMPRODUCT((AUX!$C$8:$Q$8>=Q$3)*(AUX!$C$8:$Q$8<=EOMONTH(Q$3,0))*$C$29:$Q$29)-(PREMISSAS!$C$61*P$9/PREMISSAS!$C$8+IF(Q$3=EDATE(DATE(YEAR(PREMISSAS!$C$6),MONTH(PREMISSAS!$C$6),1),1),PREMISSAS!$C$58,0))))*PREMISSAS!$C$10 -> 0
B31: sai do caixa WCR (indiretos mês ant. + mob WCR) | C31: =IF(C$3=DATE(YEAR(PREMISSAS!$C$6),MONTH(PREMISSAS!$C$6),1),PREMISSAS!$C$57,0) -> 0 | D31: =PREMISSAS!$C$56*C$9/PREMISSAS!$C$8 -> 20000 | E31: =PREMISSAS!$C$56*D$9/PREMISSAS!$C$8 -> 40000 | F31: =PREMISSAS!$C$56*E$9/PREMISSAS!$C$8 -> 41333.333 | G31: =PREMISSAS!$C$56*F$9/PREMISSAS!$C$8 -> 40000 | H31: =PREMISSAS!$C$56*G$9/PREMISSAS!$C$8 -> 41333.333 | I31: =PREMISSAS!$C$56*H$9/PREMISSAS!$C$8 -> 41333.333 | J31: =PREMISSAS!$C$56*I$9/PREMISSAS!$C$8 -> 37333.333 | K31: =PREMISSAS!$C$56*J$9/PREMISSAS!$C$8 -> 41333.333 | ... Q31: =PREMISSAS!$C$56*P$9/PREMISSAS!$C$8 -> 0
B32: caixa acumulado ANTES do recebimento | C32: =-C31 -> 0 | D32: =C33-D31 -> -20000 | E32: =D33-E31 -> -157953.78 | F32: =E33-F31 -> -57916.247 | G32: =F33-G31 -> 48166.979 | H32: =G33-H31 -> 148204.51 | I32: =H33-I31 -> 252954.4 | J32: =I33-J31 -> 361704.3 | K32: =J33-K31 -> 452317.1 | ... Q32: =P33-Q31 -> 1010641.8 | S32: =MAX(0,-MIN(C32:Q32)) -> 157953.78
B33: caixa acumulado APÓS o recebimento | C33: =C32+C30 -> 0 | D33: =D32+D30 -> -117953.78 | E33: =E32+E30 -> -16582.914 | F33: =F32+F30 -> 88166.979 | G33: =G32+G30 -> 189537.84 | H33: =H32+H30 -> 294287.74 | I33: =I32+I30 -> 399037.63 | J33: =J32+J30 -> 493650.44 | ... Q33: =Q32+Q30 -> 1010641.8 | S33: =Q33 -> 1010641.8

Sheet PREÇOS BERTIOGA
B2: PREÇOS DO CONTRATO — BERTIOGA / GUARUJÁ (GLOBAL GJ BT)
B3: Fonte: Valores Unitários Trocas e Ligações Global GJ BT.xlsx (enviado 25/08/2026).
B4: DESCRIÇÃO | C4: N. PREÇO | D4: UN | E4: R$ UNIT.
B5: EXECUÇÃO DE LIGAÇÃO DE ÁGUA SUCESSIVA -
B6: LAG PA SUCES S/REP SF | C6: 72000033 | D6: un | E6: 60.9462
B7: LAG TA SUCES S/REP SF | C7: 72000034 | D7: un | E7: 151.8069
B8: LAG EX SUCES S/REP SF | C8: 72000035 | D8: un | E8: 202.3896
B9: LAG TO SUCES S/REP SF | C9: 72000036 | D9: un | E9: 282.6712
B10: LAG PO SUCES S/REP SF | C10: 72000037 | D10: un | E10: 338.9036
B11: ADC INST CV SF | C11: 72000229 | D11: un | E11: 193.795
B12: LAG PA SUCES S/REP | C12: 72000057 | D12: un | E12: 436.7811
B13: LAG TA SUCES S/REP | C13: 72000058 | D13: un | E13: 500.8731
B14: LAG EX SUCES S/REP | C14: 72000059 | D14: un | E14: 637.5047
B15: LAG TO SUCES S/REP | C15: 72000060 | D15: un | E15: 654.591
B16: LAG PO SUCES S/REP | C16: 72000061 | D16: un | E16: 704.5906
B17: ADC INST CV | C17: 72000224 | D17: un | E17: 311.3901
... B27: LPB MND LAG SUCES COMPX C | C27: 72001105 | D27: un | E27: 76.0578
B28: EXECUÇÃO DE LIGAÇÃO DE ÁGUA AVULSA
B29: LAG ATE 32MM PA AVUL S/REP SF | C29: 72000052 | D29: un | E29: 702.8462
B30: LAG ATE 32MM TA AVUL S/REP SF | C30: 72000053 | D30: un | E30: 787.4986
B31: LAG ATE 32MM EX AVUL S/REP SF | C31: 72000054 | D31: un | E31: 798.504
B32: LAG ATE 32MM TO AVUL S/REP SF | C32: 72000055 | D32: un | E32: 803.4628
B33: LAG ATE 32MM PO AVUL S/REP SF | C33: 72000056 | D33: un | E33: 840.7175
B34: LAG ATE 32MM PA AVUL S/REP | C34: 72000028 | D34: un | E34: 806.246
B35: LAG ATE 32MM TA AVUL S/REP | C35: 72000029 | D35: un | E35: 864.5462
B36: LAG ATE 32MM EX AVUL S/REP | C36: 72000030 | D36: un | E36: 909.6507
B37: LAG ATE 32MM TO AVUL S/REP | C37: 72000031 | D37: un | E37: 1002.3048
B38: LAG ATE 32MM PO AVUL S/REP | C38: 72000032 | D38: un | E38: 1034.1009
B39: LAG DN50 HD30 SF | C39: 72000076 | D39: un | E39: 501.5297
B40: LAG DN50 HD300 SF | C40: 72000077 | D40: un | E40: 460.355
... B64: INSTAL CAIXA PARA UMAP | C64: 72000223 | D64: un | E64: 81.095
B65: EXECUÇÃO DE TROCA DE LIGAÇÃO DE ÁGUA
B66: TRA ATE 32MM CORR PA S/REP SF | C66: 72000043 | D66: un | E66: 722.4952
B67: TRA ATE 32MM CORR TA S/REP SF | C67: 72000044 | D67: un | E67: 785.0682
B68: TRA ATE 32MM CORR EX S/REP SF | C68: 72000045 | D68: un | E68: 786.8518
B69: TRA ATE 32MM CORR TO S/REP SF | C69: 72000046 | D69: un | E69: 820.9803
B70: TRA ATE 32MM CORR PO S/REP SF | C70: 72000047 | D70: un | E70: 841.6044
B71: TRA ATE 32MM CORR PA S/REP | C71: 72000067 | D71: un | E71: 885.9592
B72: TRA ATE 32MM CORR TA S/REP | C72: 72000068 | D72: un | E72: 960.4441
B73: TRA ATE 32MM CORR EX S/REP | C73: 72000069 | D73: un | E73: 1022.7574
B74: TRA ATE 32MM CORR TO S/REP | C74: 72000070 | D74: un | E74: 1079.5925
B75: TRA ATE 32MM CORR PO S/REP | C75: 72000071 | D75: un | E75: 1144.6351
B76: LRP CIM TRA CORR | C76: 72000141 | D76: un | E76: 139.895
B77: LRP ESP TRA CORR | C77: 72000142 | D77: un | E77: 242.9665
... B108: LPB MND TRA PREV COMPX C | C108: 72001111 | D108: un | E108: 68.796
B109: EXECUÇÃO DE SERVIÇOS GERAIS EM CAVALETE
B110: TCV SF | C110: 72000226 | D110: un | E110: 301.4725
B111: ADC TCV SF | C111: 72000230 | D111: un | E111: 193.795
B112: ADIC TROCA PREVENT REGIST CAV DN 20MM SF | C112: 72001002 | D112: un | E112: 10.5595
B113: SUBST CV POR UMA C/REP PASS | C113: 72000215 | D113: un | E113: 404.495
B114: SUBST CV POR UMA S/REP | C114: 72000214 | D114: un | E114: 330.995
B115: ADC INST CX UMA | C115: 72000222 | D115: un | E115: 67.7425
B116: INST CX UMA | C116: 72000213 | D116: un | E116: 118.6976
B117: INST CX UMA COM CONSTRUCAO DE MURETA | C117: 72000212 | D117: un | E117: 313.3697
B118: INSTAL CAIXA PARA UMAP | C118: 72000216 | D118: un | E118: 104.0025
B119: INSTAL CAIXA PARA UMAP | C119: 72000223 | D119: un | E119: 81.095
B120: TCV | C120: 72000204 | D120: un | E120: 355.495
B121: ADC TCV | C121: 72000217 | D121: un | E121: 338.051
... B124: FORNEC CAIXA UMAP | C124: 72000890 | D124: un | E124: 291.648
B125: EXECUÇÃO DE LIGAÇÃO DE ESGOTO SUCESSIVA
B126: LESG CER/PVC PA SUCES S/REP SF | C126: 72000479 | D126: un | E126: 390.0057
B127: LESG CER/PVC TA SUCES S/REP SF | C127: 72000480 | D127: un | E127: 423.4041
B128: LESG CER/PVC EX SUCES S/REP SF | C128: 72000481 | D128: un | E128: 432.2584
B129: LESG CER/PVC TO SUCES S/REP SF | C129: 72000482 | D129: un | E129: 460.5608
B130: LESG CER/PVC PO SUCES S/REP SF | C130: 72000483 | D130: un | E130: 493.9886
B131: LESG PVC PA SUCES S/REP | C131: 72000511 | D131: un | E131: 650.9503
B132: LESG PVC TA SUCES S/REP | C132: 72000512 | D132: un | E132: 798.1806
B133: LESG PVC EX SUCES S/REP | C133: 72000513 | D133: un | E133: 811.8467
B134: LESG PVC TO SUCES S/REP | C134: 72000514 | D134: un | E134: 863.6152
B135: LESG PVC PO SUCES S/REP | C135: 72000515 | D135: un | E135: 977.6431
B136: LRP CIM LESG SUCES | C136: 72000571 | D136: un | E136: 139.895
B137: LRP ESP LESG SUCES | C137: 72000572 | D137: un | E137: 240.5361
... B140: LPB TO LESG SUCES COMPX C | C140: 72001207 | D140: un | E140: 255.4566
B141: EXECUÇÃO DE LIGAÇÃO DE ESGOTO AVULSA
B142: LESG CER/PVC ATE 2M PA AVUL S/REP SF | C142: 72000005 | D142: un | E142: 596.7906
B143: LESG CER/PVC ATE 2M TA AVUL S/REP SF | C143: 72000468 | D143: un | E143: 1119.552
B144: LESG CER/PVC ATE 2M EX AVUL S/REP SF | C144: 72000469 | D144: un | E144: 1173.109
B145: LESG CER/PVC ATE 2M TO AVUL S/REP SF | C145: 72000470 | D145: un | E145: 1177.7444
B146: LESG CER/PVC ATE 2M PO AVUL S/REP SF | C146: 72000471 | D146: un | E146: 1240.1949
B147: LESG CER/PVC DE 2 A 4M PA AVUL S/REP SF | C147: 72000472 | D147: un | E147: 768.2612
B148: LESG CER/PVC DE 2 A 4M TA AVUL S/REP SF | C148: 72000473 | D148: un | E148: 1387.3517
B149: LESG CER/PVC DE 2 A 4M EX AVUL S/REP SF | C149: 72000474 | D149: un | E149: 1400.8757
B150: LESG CER/PVC DE 2 A 4M TO AVUL S/REP SF | C150: 72000475 | D150: un | E150: 1387.4889
B151: LESG CER/PVC DE 2 A 4M PO AVUL S/REP SF | C151: 72000476 | D151: un | E151: 1438.101
B152: LESG PVC ATE 2M PA AVUL S/REP | C152: 72000499 | D152: un | E152: 893.7355
B153: LESG PVC ATE 2M TA AVUL S/REP | C153: 72000500 | D153: un | E153: 1227.793
... B177: INST DE CXA DE INSPEÇÃO ESG 45x45x60 CM | C177: 72000907 | D177: un | E177: 237.895
B178: EXECUÇÃO DE TROCA DE LIGAÇÃO DE ESGOTO
B179: TRE CER/PVC ATE 2M CORR PA S/REP SF | C179: 72000484 | D179: un | E179: 770.2065
B180: TRE CER/PVC ATE 2M CORR TA S/REP SF | C180: 72000485 | D180: un | E180: 1278.4345
B181: TRE CER/PVC ATE 2M CORR EX S/REP SF | C181: 72000486 | D181: un | E181: 1257.536
B182: TRE CER/PVC ATE 2M CORR TO S/REP SF | C182: 72000487 | D182: un | E182: 1305.2767
B183: TRE CER/PVC ATE 2M CORR PO S/REP SF | C183: 72000488 | D183: un | E183: 1317.1641
B184: TRE CER/PVC DE 2 A 3M CORR PA S/REP SF | C184: 72000489 | D184: un | E184: 964.516
B185: TRE CER/PVC DE 2 A 3M CORR TA S/REP SF | C185: 72000490 | D185: un | E185: 1302.3024
B186: TRE CER/PVC DE 2 A 3M CORR EX S/REP SF | C186: 72000491 | D186: un | E186: 1364.7284
B187: TRE CER/PVC DE 2 A 3M CORR TO S/REP SF | C187: 72000492 | D187: un | E187: 1376.4394
B188: TRE CER/PVC DE 2 A 3M CORR PO S/REP SF | C188: 72000493 | D188: un | E188: 1456.8827
B189: TRE CER/PVC DE 3 A 4M CORR PA S/REP SF | C189: 72000494 | D189: un | E189: 1079.2054
B190: TRE CER/PVC DE 3 A 4M CORR TA S/REP SF | C190: 72000495 | D190: un | E190: 1474.5668
...

Sheet PREÇOS SANTOS
B2: PREÇOS DO CONTRATO — CONSÓRCIO GLOBAL SANTOS II
B3: Transcrito das fotos enviadas em 25/08/2026 (Planilhas de Preços Contratuais). Água = coluna K50. Itens marcados 'conferir' tiveram dígitos cortados na foto.
B4: SERVIÇOS DE ESGOTO
B5: ITEM | C5: DESCRIÇÃO | D5: N. PREÇO | E5: UN | F5: R$ UNIT. | G5: OBS
B6: 2090501 | C6: CONST PI ATE 2M S/REP | D6: 72000759 | E6: un | F6: 1597.75
B7: 2220501 | C7: CONST PI ATE 2M S/REP | D7: 72000759 | E7: un | F7: 1597.75
B8: 2090502 | C8: CONST PI DE 2 A 3M S/REP | D8: 72000760 | E8: un | F8: 1762.75
B9: 2220502 | C9: CONST PI DE 2 A 3M S/REP | D9: 72000760 | E9: un | F9: 1762.75
B10: 2090508 | C10: CPV DIAM = 1,20M - DE 2 A 3M - S/REP | D10: 72000748 | E10: un | F10: 2992.75
B11: 2220508 | C11: CPV DIAM = 1,20M - DE 2 A 3M - S/REP | D11: 72000748 | E11: un | F11: 2992.75
B12: 2090509 | C12: CPV DIAM = 1,20M - DE 3 A 4M - S/REP | D12: 72000749 | E12: un | F12: 3712.75
B13: 2220509 | C13: CPV DIAM = 1,20M - DE 3 A 4M - S/REP | D13: 72000749 | E13: un | F13: 3712.75
B14: 2090510 | C14: CPV DIAM = 1,20M - DE 4 A 5M - S/REP | D14: 72000750 | E14: un | F14: 4297.75
B15: 2220510 | C15: CPV DIAM = 1,20M - DE 4 A 5M - S/REP | D15: 72000750 | E15: un | F15: 4297.75
B16: 2090507 | C16: CPV DIAM = 1,20M - PROF ATE 2M S/REP | D16: 72000747 | E16: un | F16: 2097.75
B17: 2220507 | C17: CPV DIAM = 1,20M - PROF ATE 2M S/REP | D17: 72000747 | E17: un | F17: 2097.75
... B29: 2240309 | C29: LPB ATE 2M TA TRE COMPX A | D29: 72001184 | E29: un | F29: 296.4
B30: 2240308 | C30: LPB ATE 2M TA TRE COMPX B | D30: 72001185 | E30: un | F30: 280.7 | G30: foto cortada — conferir centavos
B31: 2240307 | C31: LPB ATE 2M TA TRE COMPX C | D31: 72001186 | E31: un | F31: 729.3 | G31: foto cortada — conferir centavos
B32: 2240345 | C32: LPB ATE 2M TO TRE COMPX A | D32: 72001214 | E32: un | F32: 621.1 | G32: foto cortada — conferir centavos
B33: 2240344 | C33: LPB ATE 2M TO TRE COMPX B | D33: 72001215 | E33: un | F33: 589.3 | G33: foto cortada — conferir centavos
B34: 2240343 | C34: LPB ATE 2M TO TRE COMPX C | D34: 72001216 | E34: un | F34: 1540.4 | G34: foto cortada — conferir centavos
B35: 1090115 | C35: SUBST PI POR PLAST ATE 2M S/REP | D35: 72000767 | E35: un | F35: 3967 | G35: foto cortada — conferir centavos
B36: 1090110 | C36: REC PI DE 2 A 3M S/REP | D36: 72000762 | E36: un | F36: 3261 | G36: foto cortada — conferir centavos
B37: 1090109 | C37: REC PI ATE 2M S/REP | D37: 72000761 | E37: un | F37: 2394 | G37: foto cortada — conferir centavos
B38: 2090605 | C38: LPB CPV DIAM = 1,20M COMPX A | D38: 72001060 | E38: un | F38: 275 | G38: foto cortada — conferir centavos
B39: 2220605 | C39: LPB CPV DIAM = 1,20M COMPX A | D39: 72001060 | E39: un | F39: 275 | G39: foto cortada — conferir centavos
B40: 2090604 | C40: LPB CPV DIAM = 1,20M COMPX B | D40: 72001061 | E40: un | F40: 223 | G40: foto cortada — conferir centavos
B41: 2220604 | C41: LPB CPV DIAM = 1,20M COMPX B | D41: 72001061 | E41: un | F41: 223 | G41: foto cortada — conferir centavos
... B52: 2240349 | C52: LPB DE 2 A 3M TO TRE COMPX C | D52: 72001219 | E52: un | F52: 2132.3 | G52: foto cortada — conferir centavos
B53: 2240339 | C53: LPB DE 3 A 4M EX TRE COMPX A | D53: 72001092 | E53: un | F53: 1084.13
B54: 2240338 | C54: LPB DE 3 A 4M EX TRE COMPX B | D54: 72001093 | E54: un | F54: 1051.78
B55: 2240337 | C55: LPB DE 3 A 4M EX TRE COMPX C | D55: 72001094 | E55: un | F55: 2743.13
B56: 2240321 | C56: LPB DE 3 A 4M TA TRE COMPX A | D56: 72001190 | E56: un | F56: 894.67
B57: 2240320 | C57: LPB DE 3 A 4M TA TRE COMPX B | D57: 72001191 | E57: un | F57: 871.78
B58: 2240319 | C58: LPB DE 3 A 4M TA TRE COMPX C | D58: 72001192 | E58: un | F58: 2270
B59: 2240357 | C59: LPB DE 3 A 4M TO TRE COMPX A | D59: 72001220 | E59: un | F59: 1273.6
B60: 2240356 | C60: LPB DE 3 A 4M TO TRE COMPX B | D60: 72001221 | E60: un | F60: 1231.8
B61: 2240355 | C61: LPB DE 3 A 4M TO TRE COMPX C | D61: 72001222 | E61: un | F61: 3216.27
B62: 1090116 | C62: SUBST PV POR PLAST ATE 2M S/REP | D62: 72000768 | E62: un | F62: 5164.44
B63: 1090117 | C63: SUBST PV POR PLAST DE 2 A 3M S/REP | D63: 72000769 | E63: un | F63: 8472.55
B64: 1090118 | C64: SUBST PV POR PLAST DE 3 A 4M S/REP | D64: 72000770 | E64: un | F64: 11566.33
... B97: 2240112 | C97: TRE CER/PVC DE 3 A 4M CORR TA S/REP SF | D97: 72000495 | E97: un | F97: 1240.13
B98: 2240115 | C98: TRE CER/PVC DE 3 A 4M CORR TO S/REP SF | D98: 72000498 | E98: un | F98: 1347.75 | G98: impresso repete TO (provável PO)
B99: 2240114 | C99: TRE CER/PVC DE 3 A 4M CORR TO S/REP SF | D99: 72000497 | E99: un | F99: 1315.13
B100: 2240203 | C100: TRE PVC ATE 2M CORR EX S/REP | D100: 72000518 | E100: un | F100: 1725
B101: 2240201 | C101: TRE PVC ATE 2M CORR PA S/REP | D101: 72000516 | E101: un | F101: 689.14
B102: 2240205 | C102: TRE PVC ATE 2M CORR PO S/REP | D102: 72000520 | E102: un | F102: 1492.75
B103: 2240202 | C103: TRE PVC ATE 2M CORR TA S/REP | D103: 72000517 | E103: un | F103: 1660
B104: 2240204 | C104: TRE PVC ATE 2M CORR TO S/REP | D104: 72000519 | E104: un | F104: 1342.95
B105: 2240208 | C105: TRE PVC DE 2 A 3M CORR EX S/REP | D105: 72000523 | E105: un | F105: 1945
B106: 2240206 | C106: TRE PVC DE 2 A 3M CORR PA S/REP | D106: 72000521 | E106: un | F106: 757.75
B107: 2240210 | C107: TRE PVC DE 2 A 3M CORR PO S/REP | D107: 72000525 | E107: un | F107: 1737.95
B108: 2240207 | C108: TRE PVC DE 2 A 3M CORR TA S/REP | D108: 72000522 | E108: un | F108: 1925
B109: 2240209 | C109: TRE PVC DE 2 A 3M CORR TO S/REP | D109: 72000524 | E109: un | F109: 1552.75
B110: 2240213 | C110: TRE PVC DE 3 A 4M CORR EX S/REP | D110: 72000528 | E110: un | F110: 1487.75
... B136: 2140524 | C136: LPB MAIS DE 2M TA LESG COMPX B | D136: 72001173 | E136: un | F136: 1479.6
B137: 2130302 | C137: LRP ESP LESG SUCES | D137: 72000572 | E137: un | F137: 1001.29 | G137: item repetido no impresso com preço diferente (247,93 na pág. 2) — conferir
B138: 2130201 | C138: LESG PVC PA SUCES S/REP | D138: 72000511 | E138: un | F138: 1242.9
B139: 2130202 | C139: LESG PVC TA SUCES S/REP | D139: 72000512 | E139: un | F139: 1502.53
B140: 2130203 | C140: LESG PVC EX SUCES S/REP | D140: 72000513 | E140: un | F140: 1567.75
B141: 2130204 | C141: LESG PVC TO SUCES S/REP | D141: 72000514 | E141: un | F141: 1625.1
B142: 2130205 | C142: LESG PVC PO SUCES S/REP | D142: 72000515 | E142: un | F142: 456.33
B143: 2130303 | C143: LPB TA LESG SUCES COMPX C | D143: 72001177 | E143: un | F143: 62.94
B144: 2130304 | C144: LPB TA LESG SUCES COMPX B | D144: 72001176 | E144: un | F144: 30.72
B145: 2130305 | C145: LPB TA LESG SUCES COMPX A | D145: 72001175 | E145: un | F145: 38.82
B146: 2130309 | C146: LPB EX LESG SUCES COMPX C | D146: 72001077 | E146: un | F146: 138.44
B147: 2130315 | C147: LPB TO LESG SUCES COMPX C | D147: 72001207 | E147: un | F147: 213.94
B148: 2130316 | C148: LPB TO LESG SUCES COMPX B | D148: 72001206 | E148: un | F148: 101.1
B149: 2130317 | C149: LPB TO LESG SUCES COMPX A | D149: 72001205 | E149: un | F149: 125.39
... B158: 2140209 | C158: LESG PVC DE 2 A 4M TO AVUL S/REP | D158: 72000507 | E158: un | F158: 783.88
B160: SERVIÇOS DE ÁGUA (coluna K50)
B161: ITEM | C161: DESCRIÇÃO | D161: N. PREÇO | E161: UN | F161: R$ UNIT. | G161: OBS
B162: 2060101 | C162: LAG PA SUCES S/REP SF | D162: 72000033 | E162: un | F162: 56.9
B163: 2060102 | C163: LAG TA SUCES S/REP SF | D163: 72000034 | E163: un | F163: 141.72
B164: 2060103 | C164: LAG EX SUCES S/REP SF | D164: 72000035 | E164: un | F164: 188.94
B165: 2060104 | C165: LAG TO SUCES S/REP SF | D165: 72000036 | E165: un | F165: 263.88
B166: 2060105 | C166: LAG PO SUCES S/REP SF | D166: 72000037 | E166: un | F166: 316.38
B167: 2060201 | C167: LAG PA SUCES S/REP | D167: 72000057 | E167: un | F167: 407.75
B168: 2060202 | C168: LAG TA SUCES S/REP | D168: 72000058 | E168: un | F168: 467.58
B169: 2060203 | C169: LAG EX SUCES S/REP | D169: 72000059 | E169: un | F169: 595.13
B170: 2060204 | C170: LAG TO SUCES S/REP | D170: 72000060 | E170: un | F170: 611.08
B171: 2060205 | C171: LAG PO SUCES S/REP | D171: 72000061 | E171: un | F171: 657.75
B172: 1030501 | C172: LRP CIM SUPR RELIGACAO DE LIGACAO | D172: 72001230 | E172: un | F172: 7.81
B173: 2060303 | C173: LPB TA LAG SUCES COMPX C | D173: 72001180 | E173: un | F173: 69.59
... B226: 2190601 | C226: LRP CIM TRA PREV | D226: 72000121 | E226: un | F226: 142.75
B227: 2190101 | C227: TRA ATE 32MM CORR PA S/REP SF | D227: 72000044 | E227: un | F227: 845 | G227: impresso mostra mesmo N.Preço da linha seguinte — conferir (provável 72000043)
B228: 2190102 | C228: TRA ATE 32MM CORR TA S/REP SF | D228: 72000044 | E228: un | F228: 1025
B229: 2190103 | C229: TRA ATE 32MM CORR EX S/REP SF | D229: 72000045 | E229: un | F229: 661.75
B230: 2190104 | C230: TRA ATE 32MM CORR TO S/REP SF | D230: 72000046 | E230: un | F230: 690.45
B231: 2190105 | C231: TRA ATE 32MM CORR PO S/REP SF | D231: 72000047 | E231: un | F231: 707.8
B232: 2190201 | C232: TRA ATE 32MM CORR PA S/REP | D232: 72000067 | E232: un | F232: 987.5
B233: 2190202 | C233: TRA ATE 32MM CORR TA S/REP | D233: 72000068 | E233: un | F233: 1175
B234: 2190203 | C234: TRA ATE 32MM CORR EX S/REP | D234: 72000069 | E234: un | F234: 860.15
B235: 2190204 | C235: TRA ATE 32MM CORR TO S/REP | D235: 72000070 | E235: un | F235: 907.95
B236: 2190205 | C236: TRA ATE 32MM CORR PO S/REP | D236: 72000071 | E236: un | F236: 962.65
B237: 2190602 | C237: LRP ESP TRA PREV | D237: 72000122 | E237: un | F237: 247.93
B238: 2190303 | C238: LPB TA TRA CORR COMPX C | D238: 72001183 | E238: un | F238: 204.45
B239: 2190304 | C239: LPB TA TRA CORR COMPX B | D239: 72001182 | E239: un | F239: 87.3
... B307: 1030301 | C307: SUPR TMD AG S/REP SF | D307: 72000238 | E307: un | F307: 427.95
